Workbook
Name ____ML1: '[1]Material List '!$M$4:$M$5
Name ___ph1: [2]NPV!$B$40
Name __aoc1: '[4]01'!$H$43
Name __aoc10: #N/A
Name __aoc11: #REF!
Name __aoc2: '[4]02'!$H$24
Name __aoc3: '[4]03'!$H$21
Name __aoc4: '[4]04'!$H$33
Name __aoc7: #REF!
Name __aoc8: #REF!
Name __aoc9: #REF!
Name __ph1: [2]NPV!$B$40
Name __vut02533: #REF!
Name __xlnm.Print_Area: "$#REF!.$A$2:$I$161"
Name __xlnm.Print_Area_1: #REF!
Name __xlnm.Print_Area_10: #REF!
Name __xlnm.Print_Area_11: #REF!
Name __xlnm.Print_Area_12: #REF!
Name __xlnm.Print_Area_13: #REF!
Name __xlnm.Print_Area_14: #REF!
Name __xlnm.Print_Area_15: #REF!
Name __xlnm.Print_Area_16: #REF!
Name __xlnm.Print_Area_17: #REF!
Name __xlnm.Print_Area_18: #REF!
Name __xlnm.Print_Area_19: #REF!
Name __xlnm.Print_Area_2: #REF!
Name __xlnm.Print_Area_20: #REF!
Name __xlnm.Print_Area_22: #REF!
Name __xlnm.Print_Area_25: #REF!
Name __xlnm.Print_Area_26: #REF!
Name __xlnm.Print_Area_27: #REF!
Name __xlnm.Print_Area_3: #REF!
Name __xlnm.Print_Area_4: #REF!
Name __xlnm.Print_Area_5: #REF!
Name __xlnm.Print_Area_6: #REF!
Name __xlnm.Print_Area_8: #REF!
Name __xlnm.Print_Area_9: #REF!
Name __xlnm.Print_Titles: #N/A
Name __xlnm.Print_Titles_1: "$'Soft landscape'.$A$4:$AMJ$5"
Name __xlnm.Print_Titles_10: #REF!
Name __xlnm.Print_Titles_11: #REF!
Name __xlnm.Print_Titles_12: #REF!
Name __xlnm.Print_Titles_14: #REF!
Name __xlnm.Print_Titles_15: #REF!
Name __xlnm.Print_Titles_16: #REF!
Name __xlnm.Print_Titles_17: #REF!
Name __xlnm.Print_Titles_18: #REF!
Name __xlnm.Print_Titles_19: #REF!
Name __xlnm.Print_Titles_2: #REF!
Name __xlnm.Print_Titles_20: #REF!
Name __xlnm.Print_Titles_22: #REF!
Name __xlnm.Print_Titles_23: #REF!
Name __xlnm.Print_Titles_24: #REF!
Name __xlnm.Print_Titles_27: #REF!
Name __xlnm.Print_Titles_3: #REF!
Name __xlnm.Print_Titles_4: #REF!
Name __xlnm.Print_Titles_5: #REF!
Name __xlnm.Print_Titles_6: #REF!
Name __xlnm.Print_Titles_7: #REF!
Name __xlnm.Print_Titles_8: #REF!

Sheet Budget Tower-E
A1: OMAXE AANANDA, ALLAHABAD
A2: SUMMARY OF COST OF CIVIL WORK
A4: S.No. | B4: Description of Items | C4: Amount (Rs.) | D4: COST PER SQFT
D5: 259280 | E5: Salable Area
A6: A | B6: BUILDING WORK
A7: I. | B7: EARTH WORK & P.C.C. | C7: =+D7*$D$5 -> 4667040 | D7: 18
A9: II. | B9: R.C.C. | C9: =+D9*$D$5 -> 53152400 | D9: 205
A11: III. | B11: SHUTTERING | C11: =+D11*$D$5 -> 16075360 | D11: 62
A13: IV. | B13: STEEL REINFORCEMENT | C13: =+D13*$D$5 -> 84266000 | D13: 325
A15: V. | B15: BRICK WORK | C15: =+D15*$D$5 -> 29817200 | D15: 115
A17: VI | B17: WOOD WORK | C17: =+D17*$D$5 -> 32410000 | D17: 125
A19: VII. | B19: STEEL WORK | C19: =+D19*$D$5 -> 4634291.3 | D19: 17.873694
A21: VIII. | B21: FLOORING | C21: =+D21*$D$5 -> 30595040 | D21: 118
A23: IX. | B23: ROOFING | C23: =+D23*$D$5 -> 1555680 | D23: 6
A25: X. | B25: FINISHING | C25: =+D25*$D$5 -> 45374000 | D25: 175
A27: XI | B27: SPECIAL FEATURES (AC, Gyser, RO, Modular Kitchen, Dish Washer, Cup board, Home Theater) | C27: 66327503 | D27: =+C27/$D$5 -> 255.81419
A29: XII. | B29: MISCELLANEOUS | C29: =+D29*$D$5 -> 2312777.6 | D29: 8.92
A31: XIII. | B31: ENTRY AND ELEVATION | C31: =+D31*$D$5 -> 7778400 | D31: 30
B33: TOTAL OF CIVIL WORK Rs. = | C33: =SUM(C7:C32) -> 3.7896569e+08 | D33: =SUM(D7:D32) -> 1461.6079
A35: B | B35: OTHER WORK
A36: I. | B36: INTERNAL ELECTRICAL | C36: =+D36*$D$5 -> 18149600 | D36: 70
A38: II. | B38: PLUMBING WORK | C38: =+D38*$D$5 -> 18149600 | D38: 70
A40: III. | B40: LIFT | C40: =+D40*$D$5 -> 12964000 | D40: 50
A42: IV. | B42: EXTERNAL DEVELOPMENT | C42: =+D42*$D$5 -> 12964000 | D42: 50
A44: V. | B44: FIRE FIGHTING | C44: =+D44*$D$5 -> 7778400 | D44: 30
A46: VI. | B46: MECHANICAL VENT | C46: =+D46*$D$5 -> 0 | D46: 0
A48: VII. | B48: CLUB | C48: =+D48*$D$5 -> 12964000 | D48: 50
B50: TOTAL AMOUNT | C50: =SUM(C36:C48) -> 82969600 | D50: =SUM(D36:D48) -> 320
A52: C | B52: EXTERNAL DEVELOPMENT
A54: a | B54: ROAD WORK | D54: =C54/$D$5 -> 0
D55: =C55/$D$5 -> 0
A56: b | B56: SEWER AND STORM LINE WORK | D56: =C56/$D$5 -> 0
D57: =C57/$D$5 -> 0
A58: c | B58: UGT | D58: =C58/$D$5 -> 0
D59: =C59/$D$5 -> 0
A60: d | B60: STP | D60: =C60/$D$5 -> 0
D61: =C61/$D$5 -> 0
A62: e | B62: BOUNDARY WALL | D62: =C62/$D$5 -> 0
D63: =C63/$D$5 -> 0
A64: f | B64: DG/LT/PANEL ROOM | D64: =C64/$D$5 -> 0
D65: =C65/$D$5 -> 0
A66: g | B66: MAIN GATE | D66: =C66/$D$5 -> 0
D67: =C67/$D$5 -> 0
A68: h | B68: WATER BODY/PATHWAYS/GUARD WALL/HARVESTING/HORTICULTURE/INTERNAL BOUNDARY/MISCELLANEOUS WORK | D68: =C68/$D$5 -> 0
D69: =C69/$D$5 -> 0
A70: i | B70: WATER SUPPLY WORK | D70: =C70/$D$5 -> 0
D71: =C71/$D$5 -> 0
A72: j | B72: EXTERNAL ELECTRIFICATION | D72: =C72/$D$5 -> 0
B75: TOATL AMOUNT (EXTERNAL DEVELOPMENT) | C75: =SUM(C54:C74) -> 0 | D75: =C75/D5 -> 0
B78: TOTAL(A+B) = (WITH OUT ESCALATION) | C78: =+C50+C33 -> 4.6193529e+08
A80: C | B80: EXTRA PARKINGS FOR ANANDA(Basement+Ground) | C80: 92610518
B82: GROSS TOTAL(A+B+C) | C82: =C78+C80 -> 5.5454581e+08 | D82: =C82/D5 -> 2138.7913 | E82: Per sqft

Sheet Schedule-Tower-E
B3: Tower-E Estimated Budget | E3: Schedule of Work
B4: S.No. | C4: Description | D4: Amount | E4: Months
B5: A | C5: Building Work | E5: 45619 | F5: 45649 | G5: 45680 | H5: 45711 | I5: 45739 | J5: 45770 | K5: 45800 | L5: 45831 | M5: 45861 | N5: 45892 | O5: 45923 | P5: 45953 | Q5: 45984 | R5: 46014 | S5: 46045 | T5: 46076 | U5: 46104 | V5: 46135 | W5: 46165 | X5: 46196 | Y5: 46226 | Z5: 46257 | AA5: 46288 | AB5: 46318 | AC5: 46349 | AD5: 46379 | AE5: 46410 | AF5: 46441 | AG5: 46469 | AH5: 46500 | AI5: 46530 | AJ5: 46561 | AK5: 46591 | AL5: 46622 | AM5: 46653 | AN5: 46683 | AO5: 46714 | AP5: 46744 | AQ5: 46775 | AR5: 46806 | AS5: 46835 | AT5: 46866 | AU5: 46896 | AV5: 46927 | AW5: 46957
B6: 1 | C6: Earthwork & PCC (including other works over existing structure) | D6: =+'Budget Tower-E'!C7 -> 4667040 | E6: =+D6/5 -> 933408 | F6: =+E6 -> 933408 | G6: =+F6 -> 933408 | H6: =+G6 -> 933408 | I6: =+H6 -> 933408 | AY6: =SUM(E6:AW6) -> 4667040
B7: 2 | C7: RCC | D7: =+'Budget Tower-E'!C9 -> 53152400 | G7: =+D7/17 -> 3126611.8 | H7: =G7 -> 3126611.8 | I7: =H7 -> 3126611.8 | J7: =I7 -> 3126611.8 | K7: =J7 -> 3126611.8 | L7: =K7 -> 3126611.8 | M7: =L7 -> 3126611.8 | N7: =M7 -> 3126611.8 | O7: =N7 -> 3126611.8 | ... W7: =V7 -> 3126611.8 | AY7: =SUM(E7:AW7) -> 53152400
B8: 3 | C8: Shuttering | D8: =+'Budget Tower-E'!C11 -> 16075360 | G8: =+D8/17 -> 945609.41 | H8: =G8 -> 945609.41 | I8: =H8 -> 945609.41 | J8: =I8 -> 945609.41 | K8: =J8 -> 945609.41 | L8: =K8 -> 945609.41 | M8: =L8 -> 945609.41 | N8: =M8 -> 945609.41 | O8: =N8 -> 945609.41 | ... W8: =V8 -> 945609.41 | AY8: =SUM(E8:AW8) -> 16075360
B9: 4 | C9: Steel | D9: =+'Budget Tower-E'!C13 -> 84266000 | G9: =+D9/17 -> 4956823.5 | H9: =G9 -> 4956823.5 | I9: =H9 -> 4956823.5 | J9: =+I9 -> 4956823.5 | K9: =+J9 -> 4956823.5 | L9: =+K9 -> 4956823.5 | M9: =+L9 -> 4956823.5 | N9: =+M9 -> 4956823.5 | O9: =+N9 -> 4956823.5 | P9: =+O9 -> 4956823.5 | Q9: =+P9 -> 4956823.5 | ... W9: =+V9 -> 4956823.5 | AY9: =SUM(E9:AW9) -> 84266000
B10: 5 | C10: Brickwork | D10: =+'Budget Tower-E'!C15 -> 29817200 | N10: =+D10/20 -> 1490860 | O10: =+N10 -> 1490860 | P10: =+O10 -> 1490860 | Q10: =+P10 -> 1490860 | R10: =+Q10 -> 1490860 | S10: =+R10 -> 1490860 | T10: =+S10 -> 1490860 | U10: =+T10 -> 1490860 | V10: =+U10 -> 1490860 | ... AG10: =+AF10 -> 1490860 | AY10: =SUM(E10:AW10) -> 29817200
B11: 6 | C11: UPVC & Woodwork etc. | D11: =+'Budget Tower-E'!C17 -> 32410000 | AA11: =+AB11 -> 1543333.3 | AB11: =+AC11 -> 1543333.3 | AC11: =+AD11 -> 1543333.3 | AD11: =+AE11 -> 1543333.3 | AE11: =+AF11 -> 1543333.3 | AF11: =+AG11 -> 1543333.3 | AG11: =+AH11 -> 1543333.3 | AH11: =+D11/21 -> 1543333.3 | AI11: =+AH11 -> 1543333.3 | AJ11: =+AI11 -> 1543333.3 | AK11: =+AJ11 -> 1543333.3 | AL11: =+AK11 -> 1543333.3 | AM11: =+AL11 -> 1543333.3 | AN11: =+AM11 -> 1543333.3 | AO11: =+AN11 -> 1543333.3 | AP11: =+AO11 -> 1543333.3 | ... AU11: =+AT11 -> 1543333.3 | AY11: =SUM(E11:AW11) -> 32410000
B12: 7 | C12: MS Work | D12: =+'Budget Tower-E'!C19 -> 4634291.3 | V12: =+D12/20 -> 231714.57 | W12: =+V12 -> 231714.57 | X12: =+W12 -> 231714.57 | Y12: =+X12 -> 231714.57 | Z12: =+Y12 -> 231714.57 | AA12: =+Z12 -> 231714.57 | AB12: =+AA12 -> 231714.57 | AC12: =+AB12 -> 231714.57 | AD12: =+AC12 -> 231714.57 | ... AO12: =+AN12 -> 231714.57 | AY12: =SUM(E12:AW12) -> 4634291.3
B13: 8 | C13: Flooring Work | D13: =+'Budget Tower-E'!C21 -> 30595040 | Y13: =+Z13 -> 1223801.6 | Z13: =+AA13 -> 1223801.6 | AA13: =+D13/25 -> 1223801.6 | AB13: =+AA13 -> 1223801.6 | AC13: =+AB13 -> 1223801.6 | AD13: =+AC13 -> 1223801.6 | AE13: =+AD13 -> 1223801.6 | AF13: =+AE13 -> 1223801.6 | AG13: =+AF13 -> 1223801.6 | AH13: =+AG13 -> 1223801.6 | AI13: =+AH13 -> 1223801.6 | ... AW13: =+AV13 -> 1223801.6 | AY13: =SUM(E13:AW13) -> 30595040
B14: 9 | C14: Roofing Work | D14: =+'Budget Tower-E'!C23 -> 1555680 | AN14: =+AO14 -> 388920 | AO14: =+AP14 -> 388920 | AP14: =+AQ14 -> 388920 | AQ14: =+D14/4 -> 388920 | AY14: =SUM(E14:AW14) -> 1555680
B15: 10 | C15: Finishing Work | D15: =+'Budget Tower-E'!C25 -> 45374000 | U15: =+D15/25 -> 1814960 | V15: =+U15 -> 1814960 | W15: =+V15 -> 1814960 | X15: =+W15 -> 1814960 | Y15: =+X15 -> 1814960 | Z15: =+Y15 -> 1814960 | AA15: =+Z15 -> 1814960 | AB15: =+AA15 -> 1814960 | AC15: =+AB15 -> 1814960 | ... AS15: =+AR15 -> 1814960 | AY15: =SUM(E15:AW15) -> 45374000
B16: 11 | C16: =+'Budget Tower-E'!B27 -> SPECIAL FEATURES (AC, Gyser, RO, Modular Kitchen, Dish Washer, Cup board, Home Theater) | D16: =+'Budget Tower-E'!C27 -> 66327503 | AD16: =+AE16 -> 3316375.2 | AE16: =+AF16 -> 3316375.2 | AF16: =+AG16 -> 3316375.2 | AG16: =+AH16 -> 3316375.2 | AH16: =+AI16 -> 3316375.2 | AI16: =+AJ16 -> 3316375.2 | AJ16: =+AK16 -> 3316375.2 | AK16: =+AL16 -> 3316375.2 | ... AV16: =+AW16 -> 3316375.2 | AW16: =+D16/20 -> 3316375.2 | AY16: =SUM(E16:AW16) -> 66327503
B17: 12 | C17: Miscellaneous | D17: =+'Budget Tower-E'!C29 -> 2312777.6 | AC17: =+D17/8 -> 289097.2 | AD17: =+AC17 -> 289097.2 | AE17: =+AD17 -> 289097.2 | AF17: =+AE17 -> 289097.2 | AG17: =+AF17 -> 289097.2 | AH17: =+AG17 -> 289097.2 | AI17: =+AH17 -> 289097.2 | AJ17: =+AI17 -> 289097.2 | AW17: =N17 -> 0 | AY17: =SUM(E17:AW17) -> 2312777.6
B18: 13 | C18: =+'Budget Tower-E'!B31 -> ENTRY AND ELEVATION | D18: =+'Budget Tower-E'!C31 -> 7778400 | U18: =+D18/8 -> 972300 | V18: =+U18 -> 972300 | W18: =+V18 -> 972300 | X18: =+W18 -> 972300 | Y18: =+X18 -> 972300 | Z18: =+Y18 -> 972300 | AA18: =+Z18 -> 972300 | AB18: =+AA18 -> 972300 | AY18: =SUM(E18:AW18) -> 7778400
C19: Total of Civil Work(i) | D19: =SUM(D6:D18) -> 3.7896569e+08 | E19: =SUM(E6:E18) -> 933408 | F19: =SUM(F6:F18) -> 933408 | G19: =SUM(G6:G18) -> 9962452.7 | H19: =SUM(H6:H18) -> 9962452.7 | I19: =SUM(I6:I18) -> 9962452.7 | J19: =SUM(J6:J18) -> 9029044.7 | K19: =SUM(K6:K18) -> 9029044.7 | ... AW19: =SUM(AW6:AW18) -> 4540176.8 | AY19: =SUM(E19:AW19) -> 3.7896569e+08
D20: =+D19/10000000 -> 37.896569 | E20: =+E19/10000000 -> 0.0933408 | F20: =+F19/10000000 -> 0.0933408 | G20: =+G19/10000000 -> 0.99624527 | H20: =+H19/10000000 -> 0.99624527 | I20: =+I19/10000000 -> 0.99624527 | J20: =+J19/10000000 -> 0.90290447 | K20: =+K19/10000000 -> 0.90290447 | ... AW20: =+AW19/10000000 -> 0.45401768 | AY20: =+AY19/10000000 -> 37.896569
B21: B | C21: Other Work
B22: 1 | C22: Electrical Work-Internal | D22: =+'Budget Tower-E'!C36 -> 18149600 | S22: =+D22/25 -> 725984 | T22: =+S22 -> 725984 | U22: =+T22 -> 725984 | V22: =+U22 -> 725984 | W22: =+V22 -> 725984 | X22: =+W22 -> 725984 | Y22: =+X22 -> 725984 | Z22: =+Y22 -> 725984 | AA22: =+Z22 -> 725984 | ... AQ22: =+AP22 -> 725984 | AY22: =SUM(E22:AW22) -> 18149600
B23: 2 | C23: Plumbing work- Internal | D23: =+'Budget Tower-E'!C38 -> 18149600 | X23: =+D23/15 -> 1209973.3 | Y23: =+X23 -> 1209973.3 | Z23: =+Y23 -> 1209973.3 | AA23: =+Z23 -> 1209973.3 | AB23: =+AA23 -> 1209973.3 | AC23: =+AB23 -> 1209973.3 | AD23: =+AC23 -> 1209973.3 | AE23: =+AD23 -> 1209973.3 | AF23: =+AE23 -> 1209973.3 | ... AL23: =+AK23 -> 1209973.3 | AY23: =SUM(E23:AW23) -> 18149600
B24: 3 | C24: Fire fighting | D24: =+'Budget Tower-E'!C44 -> 7778400 | AH24: =+D24/8 -> 972300 | AI24: =+AH24 -> 972300 | AJ24: =+AI24 -> 972300 | AK24: =+AJ24 -> 972300 | AL24: =+AK24 -> 972300 | AM24: =+AL24 -> 972300 | AN24: =+AM24 -> 972300 | AO24: =+AN24 -> 972300 | AY24: =SUM(E24:AW24) -> 7778400
B25: 4 | C25: Lift | D25: =+'Budget Tower-E'!C40 -> 12964000 | AH25: =+D25/8 -> 1620500 | AI25: =+AH25 -> 1620500 | AJ25: =+AI25 -> 1620500 | AK25: =+AJ25 -> 1620500 | AL25: =+AK25 -> 1620500 | AM25: =+AL25 -> 1620500 | AN25: =+AM25 -> 1620500 | AO25: =+AN25 -> 1620500 | AY25: =SUM(E25:AW25) -> 12964000
B26: 5 | C26: External Development | D26: =+'Budget Tower-E'!C42 -> 12964000 | X26: =+D26/15 -> 864266.67 | Y26: =+X26 -> 864266.67 | Z26: =+Y26 -> 864266.67 | AA26: =+Z26 -> 864266.67 | AB26: =+AA26 -> 864266.67 | AC26: =+AB26 -> 864266.67 | AD26: =+AC26 -> 864266.67 | AE26: =+AD26 -> 864266.67 | AF26: =+AE26 -> 864266.67 | ... AL26: =+AK26 -> 864266.67 | AY26: =SUM(E26:AW26) -> 12964000
B27: 6 | C27: =+'Budget Tower-E'!B48 -> CLUB | D27: =+'Budget Tower-E'!C48 -> 12964000 | AK27: =+D27/10 -> 1296400 | AL27: =+AK27 -> 1296400 | AM27: =+AL27 -> 1296400 | AN27: =+AM27 -> 1296400 | AO27: =+AN27 -> 1296400 | AP27: =+AO27 -> 1296400 | AQ27: =+AP27 -> 1296400 | AR27: =+AQ27 -> 1296400 | AS27: =+AR27 -> 1296400 | AT27: =+AS27 -> 1296400
C28: Total of Other works(ii) | D28: =SUM(D22:D27) -> 82969600 | E28: =SUM(E22:E27) -> 0 | F28: =SUM(F22:F27) -> 0 | G28: =SUM(G22:G27) -> 0 | H28: =SUM(H22:H27) -> 0 | I28: =SUM(I22:I27) -> 0 | J28: =SUM(J22:J27) -> 0 | K28: =SUM(K22:K27) -> 0 | ... AW28: =SUM(AW22:AW27) -> 0 | AY28: =SUM(E28:AW28) -> 82969600
D29: =+D28/10^7 -> 8.29696 | E29: =+E28/10^7 -> 0 | F29: =+F28/10^7 -> 0 | G29: =+G28/10^7 -> 0 | H29: =+H28/10^7 -> 0 | I29: =+I28/10^7 -> 0 | J29: =+J28/10^7 -> 0 | K29: =+K28/10^7 -> 0 | ... AW29: =+AW28/10^7 -> 0 | AY29: =+AY28/10^7 -> 8.29696
B30: C | C30: Extra Parking work(Basement+Ground) | D30: ='Budget Tower-E'!C80 -> 92610518 | G30: =D30/8 -> 11576315 | H30: =G30 -> 11576315 | I30: =H30 -> 11576315 | J30: =I30 -> 11576315 | K30: =J30 -> 11576315 | L30: =K30 -> 11576315 | M30: =L30 -> 11576315 | N30: =M30 -> 11576315 | AY30: =SUM(E30:AW30) -> 92610518
D31: =+D30/10000000 -> 9.2610518 | G31: 0.779375 | H31: 0.779375 | I31: 0.779375 | J31: 0.779375 | K31: 0.779375 | L31: 0.779375 | M31: 0.779375 | N31: 0.779375
C32: Total of Civil,Other Works & Parkings(A+B+C) | D32: =D19+D28+D30 -> 5.5454581e+08 | E32: =E19+E28+E30 -> 933408 | F32: =F19+F28+F30 -> 933408 | G32: =G19+G28+G30 -> 21538767 | H32: =H19+H28+H30 -> 21538767 | I32: =I19+I28+I30 -> 21538767 | J32: =J19+J28+J30 -> 20605359 | K32: =K19+K28+K30 -> 20605359 | ... AW32: =AW19+AW28+AW30 -> 4540176.8 | AY32: =AY19+AY28+AY30 -> 5.5454581e+08
C34: Gross Total --(Rs.) | D34: =D32 -> 5.5454581e+08 | E34: =E32 -> 933408 | F34: =F32 -> 933408 | G34: =G32 -> 21538767 | H34: =H32 -> 21538767 | I34: =I32 -> 21538767 | J34: =J32 -> 20605359 | K34: =K32 -> 20605359 | ... AW34: =AW32 -> 4540176.8 | AY34: =AY32 -> 5.5454581e+08
C35: Gross Total --(Cr.) | D35: =D34/10^7 -> 55.454581 | E35: =E34/10^7 -> 0.0933408 | F35: =F34/10^7 -> 0.0933408 | G35: =G34/10^7 -> 2.1538767 | H35: =H34/10^7 -> 2.1538767 | I35: =I34/10^7 -> 2.1538767 | J35: =J34/10^7 -> 2.0605359 | K35: =K34/10^7 -> 2.0605359 | ... AW35: =AW34/10^7 -> 0.45401768 | AY35: =AY34/10^7 -> 55.454581

Sheet BOQ
A1: BOQ of Civil & Structure Works (Stilt + 14) Tower-E - Prayagraj
A2: S.No. | B2: Description | C2: Unit | D2: Qty | E2: Rate | F2: Amount
B3: General Notes - The following notes shall apply to all Sections and Bills contained in this Bill of Quantities:
A4: 1 | B4: The quantities, classes and kinds of work set out in this Bill of Quantities are provisional. They do not purport to or represent the final quantities, classes or kinds of work eventually required to be done.
A5: 2 | B5: This Bill of Quantities is not intended for and shall not be used for ordering purposes.
A6: 3 | B6: This Bill of Quantities is to be read in conjunction with the Drawings, Specifications & Preambles to Work Sections which shall be construed as being complementary to one another. Any discrepancy shall be dealt in accordance with the Conditions of Contract.
A7: 4 | B7: Works shall be executed at all heights / depths, levels, floors and locations all complete as per Drawings, Specifications and to the complete satisfaction of the Engineer-In-Charge.
A8: 5 | B8: Unless otherwise specified, mode and method of measurement shall be in accordance with IS:1200.
A9: 6 | B9: Contractor should strictly follow the Site Safety Manual and provide & install all the safety measures required as per Manual.
A10: 7 | B10: The description of an item shall be deemed to include all preambles, headings, sub-headings and references to other documents. The detailed description of work and materials, given in the Specification are not necessarily repeated in the Bill of Quantities.
A11: 8 | B11: The Preamble to the Bills of Quantities must be read with the Drawings, Conditions of Contract and the Specification and the tenderer shall be deemed to have examined the Drawings, Specifications, Conditions of Contract and to have acquainted himself with the Works to be done and the way in which they are to be carried out. This preamble to the Bills of Quantities shall form part of the Contract.
A12: 9 | B12: Providing and maintaining Field Laboratory in a satisfactory manner till the completion of work to ensure site control on quality of materials and the works and shall strictly comply with provision of Indian/ International Standards at no extra cost. All other regular tests including requisite materials shall be carried out as directed either at approved laboratory or at site at no extra cost.
A13: 10 | B13: The Tenderers are requested to inspect the site and obtain for themselves at their own expense all necessary information and particulars to enable them to submit the tender.
A14: 11 | B14: The dimensions shown in the drawings shall have to be verified by the contractor at site before execution of the items and necessary allowance's have to be made as per the actual dimensions available at site.
A15: 12 | B15: For the items of works having Basic rate of material, price adjustment will be made only on the actual quantity measured. Wastage shall be to Contractors account. Basic rate indicates landed cost at site including transportation charges, loading-unloading as applicable.
... A30: 27 | B30: Keeping the site clear, clean, and meeting the hygiene standards- Cost of providing and maintaining the workers toilets shall be covered in the scope of contractor. As per safety norms mentioned elsewhere.
B32: EARTH WORK
A33: 1.1. | B33: Earth work in excavation in foundation trenches, column pits, plinth beam, under grade/ raft slab etc. by mechanical and/or manual means up to a depth of 1.5 mtr in soil from existing excavated soil level, stacking/spreading the excavated material within site premises (within a stretch of 1500 M) as per direction of Project Manager including dressing of bottom, sides strutting, timbering, shoring, trimming of sides, all leads and lifts, bailing or pumping out the water from the excavated areas collected from any source including subsoil water and keeping the excavated surface dry for subsequent works incidentals, etc. complete with ramming of bottom, surface preparation as per specifications to receive the PCC. | C33: CUM | D33: 1000 | F33: =$D33*E33 -> 0
B34: Excavation shall be payable only for vertical cut up to the outer edge of foundation lean concrete as indicated in drawings for all depths. Cost of extra excavation required for working space, supporting side shuttering of foundations and retaining walls, planking, dewatering, strutting etc. and that required for making slopes for stability of excavation shall be deemed to be included in the rate quoted. This item is not for Mass Excavation.
A35: 1.2. | B35: Prepare the surface for PCC by manual excavation upto 30 cm depth including dressing the surface, ramming the bottom, disposal and spreading of the surplus earth at the specified location within premises including proper levelling, watering and consolidation complete as directed by E I C. (The item shall be measured as per plan area of PCC, Working space shall not be taken into measurement, deemed to be included into rates) (This item is only applicable if excavation item is not being executed by contractor and excavation already done by client for the location) | C35: SQM | D35: 1500 | F35: =$D35*E35 -> 0
A36: 1.3. | B36: Filling available excavated earth in trenches, plinth, sides of foundations etc. in layers not exceeding 20cm in depth: consolidating each deposited layer by ramming and watering, lead within the premises and upto any depth. (Compacted Volume shall be payable as per drawing) - Actual volume shall be paid incase excavation is done by Client. | C36: CUM | D36: 2400 | F36: =$D36*E36 -> 0
B37: Total of Earthwork | F37: =SUBTOTAL(9,F33:F36) -> 0
A39: 2 | B39: CONCRETE WORK
B40: Rates for all cement concrete items plain and reinforced described below shall include work from Basement Level to top of last roof including roof of machine room, mumty, over head water tanks and parapets above at all floors and for all heights. The contractor should provide full time sufficient pipes with accessories and pumps based on the site requirement for pumping and laying of concrete as directed by the EIC. The rate inclusive of standard rigid pipe line and its supports, lifting, laying charges, etc., at all heights and levels. No additional payment shall be payable to the contractor on account of using or change in any size of coarse aggregate in PCC/ RCC work at any stage during currency of works. (This section covers cast in situ structural and architectural as well.)
A41: 2.1 | B41: Plain Cement Concrete: Providing and laying plain cement concrete of specified grade as bed concrete under foundation, bases for rafts, underground water tank, building machine equipments, column footing, under floor landings, below road and pathways, cill, coping, screeding at roof to required slope and other locations as called for laid, consolidated and cured etc. complete including finishing the top surface to receive the next course / layer as per specification and drawing. (Shuttering shall be paid in Item No.3.1.1) M10 Grade (Basic Rate of PCC - Rs. 4200/cum) without pump | C41: CUM | D41: 100 | F41: =$D41*E41 -> 0
A42: 2.2. | B42: Providing and laying cement concrete 1:2:4 (1 cement : 2 coarse sand : 4 graded stone aggregate 20mm nominal size) for ledge wall below balcony railings, band, mullion, lintel etc. (Shuttering shall be paid separately in respective item) as per drawing and as directed by the Project Manager. | C42: CUM | D42: 50 | F42: =$D42*E42 -> 0
A43: 2.3. | B43: Providing and laying damp proof course 40mm thick including shttering with cement concrete 1:2:4 (1 cement : 2 coarse sand : 4 graded stone aggregate 20mm nominal size) including mixing of water proofing compound @ 2% of cement content and applying two layers of bitumen @ 1.70 Kg/Sqm of grade 85/25 and as directed by the Project Manager. | C43: SQM | D43: 200 | F43: =$D43*E43 -> 0
A45: 2.4. | B45: RCC WORK
B46: Providing & Laying RMC M-25 Grade as per approved design mix concrete (strictly controlled conditions) with flyash (as per approved design mix) with automatic batching plant machine mixed and machine vibrated RCC with melamine based plasticisers etc., upto any level, including finishing the exposed surface, fixing/ removal of pockets, fixing of sleeves and inserts (sleeves provided by client), curing etc complete, as per drawing (including all size and shape like circular, semi-circular, oval etc.) and as directed for all lead and lift, excluding cost of centering, shuttering and steel reinforcement but including cost of making shear keys and provision of construction / contraction / control joints in various locations. Checking from Client should not be considered as final and any defects arising during or after casting should be borne & bear by contractor at his own cost. This is inclusive of leaving shuttering & centring for pour strip, slab in slope, RCC members in curved, etc., nothing is payable extra on this account. RMC (M-25) Basic Rate - Rs. 5200/cum without pump excluding GST
A47: 2.4.1. | B47: Foundation, column footings, raft slab, raft beams, plinth beam, lift pits, sump pits, pedestals / bases of column, column upto plinth, swimming pool, Retaining wall foundations, grade slab etc. | C47: CUM | D47: 2080 | F47: =$D47*E47 -> 0
A48: 2.4.2. | B48: Suspended floors, roofs, balconies, shelves/ counters, stair waist slabs, folded plate stairs and landings, swimming pool slab, lintel and floor beams, landing beams, girders (deep beams), RCC bands, swimming pool beam, cantilever projections, coping, cills, slab of tank etc at all levels.
A49: 2.4.2.1. | B49: Stilt Floor level to 7th Floor level | C49: CUM | D49: 2200 | F49: =$D49*E49 -> 0
A50: 2.4.2.2. | B50: 7th Floor level to to Terrace Including OHT, Mumty, Machine Room, Parapet | C50: CUM | D50: 2440 | F50: =$D50*E50 -> 0
A51: 2.4.2.3. | B51: All type of Moulding, Bands, Elevation/Architectural Features as per drawing and as directed by EIC. at all level | C51: CUM | D51: 70 | F51: =$D51*E51 -> 0
A53: 2.5. | B53: Columns, Wall, pillars, piers, abutments, posts and struts, offset and projection of columns, water tank walls, lift walls, Retaining Wall, swimming pool, Parapets, planters, vertical projection of pergolas, wall and ramp walls etc. at all levels.
A54: 2.5.1. | B54: Stilt Floor level to 7th Floor level | C54: CUM | D54: 860 | F54: =$D54*E54 -> 0
A55: 2.5.2. | B55: 7th Floor level to to Terrace Including OHT, Mumty, Machine Room, Parapet | C55: CUM | D55: 950 | F55: =$D55*E55 -> 0
A56: 2.5.3. | B56: All type of Moulding, Bands, Elevation/Architectural Features as per drawing and as directed by EIC. at all level | C56: CUM | D56: 30 | F56: =$D56*E56 -> 0
A57: 2.5.4. | B57: Finishing vaccum dewatering continuous concrete flooring 100-150 mm thick with specified grade concrete including necessary formwork in required level, vibrating concrete both by poker vibrators / leveling vaccum processing of the concrete and planning the surface by skin powered floater trowels with broom/plain finish including groove cutting & filling etc. complete. (Concrete shall be paid in the respective items above). | C57: SQM | D57: 1625 | F57: =$D57*E57 -> 0
B59: Total of RCC Work | F59: =SUBTOTAL(9,F41:F58) -> 0
A61: 3 | B61: CENTRING AND SHUTTERING
B62: Providing and fixing plywood or steel plate shuttering and centring for structural concrete work in locations called for including strutting, propping, bracing, bolting, wedging, casing, striking, removal etc. complete for any size, section, thickness. Props shall consist of well designed steel pipes adequately braced (wooden ballies as props shall not be permitted). The item to include centering and shuttering at all heights and levels. Allow for forming grooves, drip course, chamfers, cut-outs, openings etc. where called for and for dressing with approved shuttering oil to prevent adhesion. Unexposed concrete surfaces subsequently left untreated (in the condition obtained on removal of form work) shall not constitute exposed concrete work and shall be measured under this item only Irregular shapes with sides (like circular, semi-circular, oval etc.) which may not be perpendicular to each other for shapes not conforming to rectangle or square, and circular shuttering shall not be paid separately. Joints of soffits of the slab shall be made clean after concreting and de-shuttering. (quoted rate to include all staging upto 3.50 mtr height). Note:- Contractor shall take necessary precautions such as watertight shuttering. This is inclusive of RCC members, leaving shuttering & centring for pour strip, slab in slope, RCC members in curved (in plan), etc., nothing is payable extra on this account.
A63: 3.1.1. | B63: Foundation, column footings, raft slab, raft beams, plinth beam, lift pits, sump pits, pedestals / bases of column, column up to plinth, swimming pool, Retaining wall foundations, grade slab etc. | C63: SQM | D63: 2150 | F63: =$D63*E63 -> 0
A64: 3.1.2. | B64: Suspended floors, roofs, balconies, shelves/ counters, stair waist slabs, folded plate stairs and landings, swimming pool slab, lintel and floor beams, landing beams, girders (deep beams), RCC bands, swimming pool beam, cantilever projections, coping, cills, slab of tank etc at all levels.
A65: 3.1.2.1. | B65: Stilt Floor level to 7th Floor level | C65: SQM | D65: 17600 | F65: =$D65*E65 -> 0
A66: 3.1.2.2. | B66: 7th Floor level to to Terrace Including OHT, Mumty, Machine Room, Parapet | C66: SQM | D66: 18800 | F66: =$D66*E66 -> 0
A67: 3.1.2..3 | B67: All type of Moulding, Bands, Elevation/Architectural Features as per drawing and as directed by EIC. at all level | C67: SQM | D67: 400 | F67: =$D67*E67 -> 0
A69: 3.2. | B69: Columns, Wall, pillars, piers, abutments, posts and struts, offset and projection of columns, water tank walls, lift walls, Retaining Wall, swimming pool, Parapets, planters, vertical projection of pergolas, wall and ramp walls etc. at all levels.
A70: 3.2.1. | B70: Stilt Floor level to 7th Floor level | C70: SQM | D70: 7825 | F70: =$D70*E70 -> 0
A71: 3.2.2. | B71: 7th Floor level to to Terrace Including OHT, Mumty, Machine Room, Parapet | C71: SQM | D71: 8200 | F71: =$D71*E71 -> 0
A72: 3.2.3. | B72: All type of Moulding, Bands, Elevation/Architectural Features as per drawing and as directed by EIC. at all level | C72: SQM | D72: 150 | F72: =$D72*E72 -> 0
A74: 3.3. | B74: Extra for additional height in centring, shuttering where ever required with adequate bracing, propping etc. including cost of de-shuttering and decentring at all levels, over and above height of 3.50 mtr (Plan area to be measured and shall be paid proportionately on actual height) – for every 1.0 mtr. height | C74: SQM | D74: 1000 | F74: =$D74*E74 -> 0
B75: Total of Shuttering | F75: =SUBTOTAL(9,F63:F74) -> 0
A77: 4 | B77: REINFORCEMENT
B78: Receiving, laying and fixing in position steel reinforcement in all reinforced concrete work, including straightening, cutting, removal of loose rust by wire brush and coating with cement slurry, bending, hoisting, laying in position to the shape and profile required at all levels and heights as per drawing and design and/ or as directed, binding with double folded steel wire as approved by EIC etc. complete. (Contractor shall prepare BBS and submit to EIC for approval prior to cutting, bending & laying of steel bars and payments shall be released as per approved BBS complete in all respect as per direction and approval of EIC Rate shall include cost of 18 gauge GI binding wire, cover blocks as per Indian Standards, unloading the steel & moving to the steel yard, moving site to site within project etc) (Only Steel reinforcement shall be provided by the owner free of cost at one point)
A79: 4.1. | B79: Thermomechanically Treated Reinforcement (TMT) or High yield strength Deformed (Tor steel) bars of all size & grades.
A80: 4.1.1. | B80: Up to Stilt Floor Level | C80: MT | D80: 150 | F80: =$D80*E80 -> 0
A81: 4.1.2. | B81: Stilt Floor level to to Terrace Including OHT, Mumty, Machine Room, Parapet) | C81: MT | D81: 805 | F81: =$D81*E81 -> 0
A82: 4.1.3. | B82: All type of Moulding, Bands, Elevation/Architectural Features as per drawing and as directed by EIC. at all level | C82: MT | D82: 10 | F82: =$D82*E82 -> 0
B83: Total of Reinforcement | F83: =SUBTOTAL(9,F79:F82) -> 0
A85: 5 | B85: MASONARY WORK
B86: (Quoted Rates are for all heights, all depths, all levels, including basement to roof (mumty) & all leads and lifts, including curved or circular including elevation masonary work) (Basic Rate of Brick @ Rs. 7/No. FOR at site without GST)
A87: 5.1. | B87: Brick work in Sub Structure (Up to Stilt Floor level):
B88: Providing and laying 230mm thick brick masonry using 1st quality burnt clay FPS bricks in Sub-Structure laid in cement mortar 1:6 (1 cement : 6 coarse sand) mix, joints finished, flush/ raked to 6mm depth including scaffolding, curing complete as per specification and drawing or as directed by Project Manager. | C88: CUM | D88: 100 | F88: =$D88*E88 -> 0
A89: 5.2. | B89: Brick work in Sub Structure (Up to Stilt Floor level):
B90: Providing and laying of 115 mm thick brick work with 1st quality burnt clay FPS bricks in sub-superstructure laid in cement mortar 1:4 (1 cement : 4 coarse sand) mix, joints finished, including placing hoop iron as per specification at every third course, scaffolding, curing complete in all respect as per direction of EIC. (Hoop iron shall be provided by client free of cost) (Items of RCC bands like shuttering, concrete and reinforcement to be paid in respective items). | C90: SQM | D90: 1000 | F90: =$D90*E90 -> 0
A91: 5.3. | B91: Brick work in Super Structure (Above Stilt FLoor level)
A92: 5.3.1 | B92: Providing and laying 230mm thick brick masonry using 1st quality burnt clay FPS bricks in Super-Structure laid in cement mortar 1:6 (1 cement : 6 coarse sand) mix, joints finished, flush/ raked to 6mm depth including scaffolding, curing complete as per specification and drawing or as directed by Project Manager.
A93: (a) | B93: Stilt Floor level to 7th Floor level | C93: CUM | D93: 1185 | F93: =$D93*E93 -> 0
A94: (b) | B94: 7th Floor level to to Terrace Including OHT, Mumty, Machine Room, Parapet | C94: CUM | D94: 1355 | F94: =$D94*E94 -> 0
A95: 5.4. | B95: Brick work in Super Structure (Above Stilt FLoor level)
A96: 5.4.1 | B96: Providing and laying of 115 mm thick brick work with 1st quality burnt clay FPS bricks in Super-Superstructure laid in cement mortar 1:4 (1 cement : 4 coarse sand) mix, joints finished, including placing hoop iron as per specification at every third course, scaffolding, curing complete in all respect as per direction of EIC. (Hoop iron shall be provided by client free of cost) (Items of RCC bands like shuttering, concrete and reinforcement to be paid in respective items).
A97: (a) | B97: Stilt Floor level to 7th Floor level | C97: SQM | D97: 7100 | F97: =$D97*E97 -> 0
A98: (b) | B98: 7th Floor level to to Terrace Including OHT, Mumty, Machine Room, Parapet | C98: SQM | D98: 8155 | F98: =$D98*E98 -> 0
A99: 5.8. | B99: Brick work in staircase steps:
B100: Providing and laying and constructing brickwork in staircase steps using 1st quality burnt clay FPS bricks in cement mortar 1:3 (1 cement : 3 coarse sand) at all heights and levels including cutting, chamfering scaffolding, curing, complete as per specification. | C100: CUM | D100: 40 | F100: =$D100*E100 -> 0
B101: Total of Masonary Work | F101: =SUBTOTAL(9,F87:F100) -> 0
A103: 6 | B103: FINISHING WORKS (PLASTER)
B104: (Quoted Rate shall be for all heights, depths, levels, leads and lifts and to include providing and fixing chicken wire mesh in junction RCC and brick / AAC Block walls and at all chased for electrical conduits & plumbing pipes etc. for internal and external plaster works including minor chipping of RCC, brickwork surface).
A106: 6.1. | B106: Internal Plaster Super-Structure:
B107: Wall Plaster: Providing and applying 12 to 15mm thick plaster to masonry and RCC walls, columns etc. in cement mortar 1:5 (1 cement : 5 screened coarse sand) finished smooth including hacking the surfaces, steel scaffolding, curing, making grooves at desired location etc. complete for all levels as per approved drawing.
A108: (a) | B108: Stilt Floor level to 7th Floor level | C108: SQM | D108: 19970 | F108: =$D108*E108 -> 0
A109: (b) | B109: 7th Floor level to to Terrace Including OHT, Mumty, Machine Room, Parapet | C109: SQM | D109: 22825 | F109: =$D109*E109 -> 0
A110: 6.2. | B110: Internal Plaster Super-Structure:
B111: Ceiling Plaster: Providing and applying 6-10mm thick plaster to RCC slab, beam in cement mortar 1:4 (1 cement : 4 screened coarse sand) finished smooth including hacking the surfaces, steel scaffolding, curing, making grooves at desired location etc. complete for all levels as per approved drawing.
A112: (a) | B112: Stilt Floor level to 7th Floor level | C112: SQM | D112: 9135 | F112: =$D112*E112 -> 0
A113: (b) | B113: 7th Floor level to to Terrace Including OHT, Mumty, Machine Room, Parapet | C113: SQM | D113: 10440 | F113: =$D113*E113 -> 0
A114: 6.3 | B114: Double Layer External Plaster: Providing and applying 20 mm thick external cement plaster in two coats under layer 12 mm thick cement plaster 1:5 (1 cement : 5 screened coarse sand) finished with a top layer 8mm thick cement plaster 1:4 (1 cement : 4 screened coarse sand) including making of grooves, bands, drip coarse, design etc. as shown in drawing, steel scaffolding, curing, providing & mixing water proofing compound (CICO) in both layers as per manufacturer specification etc. complete as per approved drawing. | C114: SQM | D114: 19200 | F114: =$D114*E114 -> 0
A115: 6.4 | B115: Single Layer (Shaft Plaster): Providing and applying 12-15 mm thick external cement plaster in single coat finished with cement plaster 1:4 (1 cement : 4 screened coarse sand) including making of grooves, bands, drip coarse as shown in drawing, steel scaffolding, curing, providing & mixing water proofing compound (CICO) as per manufacturer specification etc. complete as per approved drawing. | C115: SQM | D115: 1000 | F115: =$D115*E115 -> 0
B116: Total of Finishing Work (Plaster) | F116: =SUBTOTAL(9,F105:F115) -> 0
A118: 7 | B118: STRUCTURE STEEL
B119: NOTES: The rates quoted by contractor for items under this head shall be inclusive of the following:-
A120: (i) | B120: Fabrication, cutting, bending to required size and shape, drilling, punching, counter-sinking, welding, grinding, filling etc. finishing, erecting and fixing in position at all heights and depths with all leads and lift.
A121: (ii) | B121: M.S. ladders and MS Railings in staircases, balconies and at any other place etc shall be fixed by welding the railing to steel reinforcement of slabs/beams/columns/staircase etc to make it absolutely rigid. The rate includes cutting of RCC required if any and making good the same after welding of the railing. Subsequently, the same shall be embedded in cement concrete of specified grade.
A122: (iii) | B122: M.S. grills/weld mesh etc. shall be fixed to masonry/concrete jambs of floor by means of required size and number of M.S. lugs grouted/ embeded in cement concrete block 1:2:4 or fixed by means of suitable counter sunk screw with rawal plugs or fixed by dash fastener of required dia and depth.
A123: (iv) | B123: The accessories such as M.S. hold-fasts / dash fasteners, lugs screws, rawal plug, G.I. pipe pieces, grouting in C.C. block 1:2:4 etc. shall not be paid separately. This shall be included in rate of items.
A124: (v) | B124: All steel work shall be painted with one coat of red oxide primer of approved make.
A125: (vi) | B125: No extra shall be paid for transport of fabricated items from one place to another place.
A126: (vii) | B126: Cost of all erection fasteners shall be borne by the contractor.
A127: (viii) | B127: All Welding work should be done as per IS:814.
...

Sheet Sheet6
A1: S. No. | B1: DESCRIPTION OF ITEMS | C1: UNIT | D1: BOQ DETAIL
D2: QUANTITY | E2: RATE | F2: AMOUNT
A3: S.H.-I | B3: MAIN WORK
A4: 1 | B4: EARTH WORK IN EXCAVATION
A5: 1.1 | B5: A) ALL KINDS OF SOIL, LIFT UPTO 3 M | C5: CUM
A6: 1.3 | B6: FILLING OF EARTH | C6: CUM
A8: 2 | B8: REINFORCED CEMENT CONCRETE
B9: PROVIDING & LAYING RMC DESIGN MIX CONCRETE
A10: 2.1 | B10: FOUNDATION, RAFTS, FOOTINGS, BASES OF COLUMNS, IN M-25 GRADE | C10: CUM
A11: 2.2 | B11: IN SUSPENDED FLOORS, ROOFS,BEAMS, LANDING, CHAJJAS, CANTILEVERS, BALCONIES,
B12: M25 GRADE | C12: CUM
A13: 2.3 | B13: IN PLINTH BEAMS, LANDING BEAM CANTILEVERS BEAM ETC ON PLINTH LVL.
B14: M25 GRADE | C14: CUM
A15: 2.4 | B15: IN GRADE SLAB FOR FLOORING AT GROUND FLOOR LVL.
B16: M25 GRADE | C16: CUM
A17: 2.5 | B17: IN STAIRCASE ETC. IN M-25 GRADE CONCRETE ALL WORK .
B18: M25 GRADE | C18: CUM
A19: 2.6 | B19: IN SHEAR WALLS, LIFT WALLS, RETAINING WALL | C19: CUM
B20: M25 GRADE | C20: CUM
B21: M30 GRADE | C21: CUM
A22: 2.7 | B22: IN COLUMNS, PILLARS & PIERS, POSTS, STRUTS
B23: M25 GRADE | C23: CUM
B24: M30 GRADE | C24: CUM
A25: 2.8 | B25: IN WALLS (ANY THICKNESS) AND BASE SLAB AND COVER SLAB OF OVERHEAD TANKS ETC., IN M-25 GRADE | C25: CUM
A26: 2.9 | B26: EXTRA OVER 5TH FLOOR LEVEL TO 8TH FLOOR | C26: CUM
A27: 2.1 | B27: EXTRA OVER 9TH FLOOR LEVEL TO 12TH FLOOR | C27: CUM
A28: 2.11 | B28: EXTRA OVER 13TH FLOOR LEVEL TO 16TH FLOOR | C28: CUM
A29: 2.12 | B29: RCC IN KITCHEN COUNTER INCLUDING SHUTTERING REINFORCEMENT COMPLETE IN FLAT | C29: NOS
A30: 2.13 | B30: RCC IN LINTEL OF AVG SIZE 100X125X1200MM INCLUDING SHUTTERING REINFORCEMENT COMPLETE | C30: NOS
A31: 2.14 | B31: RCC IN LEDGE WALL/CONCRET BLOCK OF COMPLETE | C31: CUM
A34: 3 | B34: P/F SHUTTERING WORK
A35: 3.1 | B35: FOUNDATIONS, RAFT, FOOTINGS, | C35: Sqm
A36: 3.2 | B36: OUTER SHEAR WALLS, LIFT WALLS, | C36: Sqm
A37: 3.3 | B37: PLINTH BEAM, LANDING BEAM, AT PLINTH LVL. | C37: Sqm
A38: 3.4 | B38: STAIRCASE, TIE-BEAMS, ETC UP TO ANY HEIGHT. | C38: Sqm
A39: 3.5 | B39: SUSPENDED/FLAT FLOOR, ROOFS AND BEAM, LANDINGS, CANTILEVER SLABS, CHAJJAS, | C39: Sqm
A40: 3.6 | B40: COLUMNS, PILLARS, PIERS, POSTS, STRUTS | C40: Sqm
A41: 3.7 | B41: ABOVE TERRACE WORK WALLS | C41: Sqm
A42: 3.7 | B42: ABOVE TERRACE WORK WALLS | C42: Sqm
A44: 4 | B44: P/F REINFORCEMENT WORK
A45: 4.1 | B45: LAYING OF REINFORCEMENT STEEL OF HIGH YEILD STRENGTH . ( BASIC RATE RS. 40/- PER KGS. ) | C45: MT
A46: 4.2 | B46: ADJUSTMENT UPTO MONTH OF JAN 19. ( INSTRUCTED BY C.GUPTA SIR)
A47: 4.3 | B47: June-19 Closing as per ERP was 14 MT BUT PHY Balance at site found 75 mt, So same qty reverse from ERP as well as in Client also. ( INSTRUCTED BY SK PANDEY SIR)
A50: 5 | B50: BRICK MASONRY
A51: 5.1 | B51: P/L 230 MM THICK BRICK WORK WITH FIRST QUALITY FLY ASH BRICKS IN SUPER STRUCTURE ABOVE PLINTH | C51: Cum
A52: 5.2 | B52: P/L 115 MM TH. MASONRY WITH FIRST QUALITY FLY ASH BRICKS IN SUPER STRUCTURE ABOVE PLINTH LVL | C52: Sqm
A53: 5.3 | B53: P/L 200 MM THICK WORK WITH FIRST QUALITY AAC BLOCK IN SUPER STRUCTURE ABOVE PLINTH LVL | C53: Cum
A54: 5.4 | B54: P/L 100 MM TH. MASONRY WITH FIRST QUALITY AAC BLOCK BRICKS IN SUPER STRUCTURE ABOVE PLINTH LVL | C54: Sqm
A55: 5.5 | B55: BRICK WORK IN STAIRCASE FOR STAIRCASE STEP MAKING IN THE RATIO 1:6 | C55: Nos.
A56: 5.6 | B56: FOR 230MM THICK BRICK WORK
A57: 5.6a | B57: EXTRA OVER 5TH FLOOR LVL TO 8TH FLOOR LVL | C57: CUM
A58: 5.6b | B58: EXTRA OVER 9TH FLOOR LVL TO 12TH FLOOR LVL | C58: CUM
A59: 5.6c | B59: EXTRA OVER 13TH FLOOR LVL AND ABOVE LVL | C59: CUM
A60: 5.7 | B60: FOR 115MM THICK BRICK WORK
A61: 5.7a | B61: EXTRA OVER 5TH FLOOR LVL TO 8TH FLOOR LVL | C61: SQM
A62: 5.7b | B62: EXTRA OVER 9TH FLOOR LVL TO 12TH FLOOR LVL | C62: SQM
A63: 5.7c | B63: EXTRA OVER 13TH FLOOR LVL AND ABOVE LVL | C63: SQM
A64: 5.8 | B64: P/L VERTICAL/HORIZONTAL BAND I/C SHUTTEING WORK. | C64: CUM
A65: 5.9 | B65: P/L REINFORCEMENT WORK IN RCC BAND AS PER SPECIFICATION. | C65: MT
B66: CC BLOCK CASTING | C66: CUM
A68: 6 | B68: WOOD WORK & ALUMINIUM WORK
A69: 6.1 | B69: PROVIDING WOOD WORK IN FRAMES OF DOORS, WINDOWS AND OTHER FRAMES,
B70: A) USING RED MIRANDI WOOD. | C70: Rmt
A71: 6.2 | B71: PROVIDING AND FIXING 35 MM THICK SKIN MOULDED DOORS SHUTTER, | C71: Sqm
A72: 6.3 | B72: PROVIDING AND FIXING 35 MM THICK WELL SEASONED HARDWOOD FRAME WOODEN PANELLED SHUTTER POLISH, | C72: Sqm
A73: 6.4 | B73: PROVIDING AND FIXING TAPERED HARD WOOD MOULDING 35 MM WIDE AND 12 MM ON ONE SIDE AND 6 MM ON OTHER SIDE THICKNESS | C73: Mtrs.
A74: 6.5 | B74: PROVIDING AND FIXING OF STRUCTURE GLAZZING IN ELEVATION OF TOWER AS PER APPROVED DETAIL. | C74: Sqm
A75: 6.6 | B75: PROVIDING AND FIXING OF FIRE HYDRANT CABINATE DOOR IN SHAFT AREA AS PER APPROVED DESIGN. | C75: Nos
A76: 6.7 | B76: SUPPLYING & FIXING UPVC DOOR AND WINDOWS WITH ALL ACCESORIESA AS PER DRAWINGS (BASIC RATE - RS 400 PER SQFT. ) | C76: Sqm
A77: 6.8 | B77: SUPPLYING & FIXING ALUMINIUM WINDOWS WITH ALL ACCESORIES AS PER DRAWINGS IN MAIN STAIRCASE (TOWER -A) | C77: Sft
A78: 6.9 | B78: SUPPLYING & FIXING ALUMINIUM WINDOWS WITH ALL ACCESORIESS AS PER DRAWINGS IN FIRE STAIRCASE (TOWER -A) | C78: Sft
A80: 7 | B80: STEEL WORK
A81: 7.1 | B81: PROVIDING AND FIXING M.S. STAIRCASE RAILING WITH M S HANDRAIL, BALCONY RAILING | C81: Kg.
A83: 8 | B83: FLOORING
A84: 8.1 | B84: PROVIDING AND LAYING VITRIFIED TILES OF MINIMUM THICKNESS 10 MM IN FLOORING & SKIRTING.(BASIC RATE OF VITRIFIED TILES @ RS. 400/- PER SQM INCLUDING FREIGHT BUT EXCLUDING TAXES) | C84: Sqm
A85: 8.2 | B85: PROVIDING AND LAYING FIRST CLASS CERAMIC TILES OF REQUIRED SIZE THICKNESS 8 MM IN FLOORING ON 20 MM AVERAGE THICK. (BASIC RATE OF CEREMIC TILES @ RS. 320 /- PER SQM INCLUDING FREIGHT BUT EXCLUDING TAXES) | C85: Sqm
A86: 8.3 | B86: PROVIDING AND LAYING FIRST CLASS GLAZED/ CERAMIC TILES OF REQUIRED SIZE OF MINIMUM THICKNESS 5 MM IN SKIRTING AND DADO ON 12 MM THICK CEMENT PLASTER. (BASIC RATE OF CEREMIC TILES @ RS.320/- PER SQM INCLUDING FREIGHT BUT EXCLUDING TAXES) | C86: Sqm
A87: 8.4 | B87: PROVIDING AND FIXING PRE POLISHED GRANITE 18 - 20 M M THICK IN STAIR CASE ON RISER AND TREADS AND SKIRTING . (BASIC RATE OF STONE @ RS. 1000/ - PER SQM INCLUDING FREIGHT BUT EXCLUDING TAXES.) | C87: SQM
A88: 8.5 | B88: PROVIDING AND FIXING GRANITE 18 - 20 M M THICK IN LIFT FACIA AS PER APPROVED DESIGN, . (BASIC RATE OF STONE @ RS. 1500/ - PER SQM INCLUDING FREIGHT BUT EXCLUDING TAXES.) | C88: SQM
A89: 8.6 | B89: PROVIDING AND FIXING 18 MM THICK GRANITE STONE SLABS AS APPROVED ON KITCHEN PLATFORM COUNTER (BASIC RATE OF STONE @ RS. 1600/- PER SQM INCLUDING FREIGHT BUT EXCLUDING TAXES.) | C89: Sqm
A90: 8.7 | B90: IPS FLOORING 1:2:4 OF THICKNESS 100MM FOR CUP BOARD | C90: Sqm
A91: 8.8 | B91: PROVIDING AND LAYING FIRST CLASS GLAZED TILE FOR WATER TANK INCLUDING REQUIRED WATERPROOFING PLASTER | C91: Sqm
A92: 8.9 | B92: WATER PROOFING OF WATER TANK WITH INJECTION GROUTING INCLUDING TWO OR MORE COAT WATER PROOFING | C92: Sqm
A93: 8.1 | B93: SAND FILLING UNDER FLAT VITRIFIED FLOOR TILES | C93: CUM
A94: 8.11 | B94: PCC (1:4:8) (FOR BELOW TOILET & BALCONY FL TILES) | C94: CUM
A95: 8.12 | B95: GRANITE IN CORIDOR-18MM THICK | C95: SQMT
A97: 9 | B97: ROOFING
A98: 9.1 | B98: PROVIDING AND LAYING BRICK COBA WATER PROOFING TREATMENT ON TERRACE 120 MM THICK (AVERAGE) | C98: SQM
A99: 9.2 | B99: MAKING KHURRAS 45 X 45 CM WITH AVERAGE MINIMUM THICKNESS OF 5 CM CEMENT CONCRETE 1:2:4 | C99: NOS
A101: 10 | B101: FINISHING WORK
A102: 10.1 | B102: P/L 12 MM THICK CEMENT PLASTER IN CEMENT MORTAR 1:6 (1 CEMENT : 0 FINE SAND AND 6 COARSE SAND) . | C102: Sqm
A103: 10.2 | B103: P/L 20 MM CEMENT PLASTER IN TWO COATS, UNDER LAYER 12MM TH.IN CEMENT MORTAR 1:6 | C103: Sqm
A104: 10.3 | B104: POP CORNICE | C104: Rmt
A105: 10.4 | B105: DISTEMPERING WITH OIL BOUND WASHABLE DISTEMPER OF APPROVED BRAND AND MANUFACTURER | C105: Sqm
A106: 10.5 | B106: Texture Paint with Primer | C106: Sqmt
B107: Superfine with Primer | C107: Sqmt
A108: 10.6 | B108: POLISH ON INTERNAL DOOR SHUTTERS | C108: Sqm
A109: 10.7 | B109: ENAMEL PAINT | C109: Sqm
A110: 10.8 | B110: P/L UPTO 50 MM THICK CEMENT ROUGH PLASTER IN CEMENT MORTAR 1:6 (1 CEMENT : 0 FINE SAND AND 6 COARSE SAND) . | C110: Sqm
A112: 11 | B112: MISCELLANEOUS
...

Sheet Summary
A1: S. No. | B1: Description | C1: Unit | D1: QTY
A2: 1 | B2: Excavation upto 3 Mtr. | C2: CUM | D2: =1532.83*2.5 -> 3832.075 | F2: =4000 -> 4000 | G2: =F2-1600 -> 2400
A3: 2 | B3: PCC | C3: CUM | D3: =+#REF!+#REF!+#REF! -> #REF!
A4: 3 | B4: RCC M-25 | C4: CUM | D4: =+#REF!-Summary!D3-Summary!D5 -> #REF!
A5: 4 | B5: RCC M-30 | C5: CUM | D5: =+#REF!+#REF!+#REF!+#REF!+#REF!+#REF!+#REF!+#REF!+#REF!+#REF!+#REF!+#REF!+#REF! -> #REF!
A6: 5 | B6: RCC in Ladge Wall | C6: CUM | D6: =+#REF! -> #REF!
A7: 6 | B7: Shuttering | C7: SQM
A8: 6.1 | B8: RAFT | C8: SQM | D8: =+#REF! -> #REF!
A9: 6.2 | B9: COLUMN | C9: SQM | D9: =+#REF!+#REF! -> #REF!
A10: 6.3 | B10: SHEAR WALL | C10: SQM | D10: =+#REF!+#REF! -> #REF!
A11: 6.4 | B11: STAIR CASE | C11: SQM | D11: =+#REF!+#REF! -> #REF!
A12: 6.5 | B12: PLINTH BEAM | C12: SQM | D12: =+#REF! -> #REF!
A13: 6.6 | B13: Slab | C13: SQM | D13: =+#REF! -> #REF!
A14: 7 | B14: Steel | C14: MT | D14: =+#REF! -> #REF!
A15: 8 | B15: DPC | C15: CUM | D15: =(#REF!+#REF!)*15 -> #REF!
A16: 9 | B16: Brick Work 115mm | C16: SQM | D16: =+#REF!*15 -> #REF!
A17: 10 | B17: Brick Work 230mm | C17: CUM | D17: =+#REF!*15 -> #REF!
A18: 11 | B18: Internal Wall Plaster | C18: SQM | D18: =+#REF!*15 -> #REF!
A19: 12 | B19: Internal Ceiling Plaster | C19: SQM | D19: =+#REF!*15 -> #REF!
A20: 13 | B20: External Plaster | C20: SQM | D20: =+#REF!+#REF! -> #REF!

Sheet Sheet2
B7: 259280 | D7: =1598*15 -> 23970 | E7: =1500*15 -> 22500
B8: =+B7/10.764 -> 24087.7 | D8: =+D7*10.764 -> 258013.08 | E8: =+E7*10.764 -> 242190
B9: =+B8/15 -> 1605.8466 | D9: =1600*15*10.764 -> 258336
B11: =1605*10.764*15 -> 259143.3
B12: =0.847*15*10.764 -> 136.75662 | C12: =+B12/15 -> 9.117108
B13: =+B12*900 -> 123080.96 | C13: =+C12*900 -> 8205.3972 | D13: =+B11*900 -> 2.3322897e+08
D14: =+D13/10000000 -> 23.322897
F18: 230mm Wall
F19: Flat No.2
F20: Bed Room-1 | G20: 6 | H20: 1 | I20: 3.165 | J20: =3-0.5 -> 2.5 | K20: =+PRODUCT(G20:J20) -> 47.475
G21: 6 | H21: -1 | I21: 2.065 | J21: =3-0.5 -> 2.5 | K21: =+PRODUCT(G21:J21) -> -30.975
G22: 6 | H22: 1 | I22: 0.985 | J22: =3-0.5 -> 2.5 | K22: =+PRODUCT(G22:J22) -> 14.775
F23: Bed Room-2 | G23: 6 | H23: 1 | I23: 2.165 | J23: =3-0.5 -> 2.5 | K23: =+PRODUCT(G23:J23) -> 32.475
G24: 6 | H24: -1 | I24: 2.065 | J24: =3-0.5 -> 2.5 | K24: =+PRODUCT(G24:J24) -> -30.975
F25: Bed Room-3 | G25: 6 | H25: 1 | I25: 3.55 | J25: =3-0.5 -> 2.5 | K25: =+PRODUCT(G25:J25) -> 53.25
G26: 6 | H26: 1 | I26: 1.92 | J26: =3-0.5 -> 2.5 | K26: =+PRODUCT(G26:J26) -> 28.8
G27: 6 | H27: -1 | I27: 1.5 | J27: 1.5 | K27: =+PRODUCT(G27:J27) -> -13.5
F28: Toilet Wall | G28: 6 | H28: 1 | I28: 2.58 | J28: =3-0.5 -> 2.5 | K28: =+PRODUCT(G28:J28) -> 38.7
G29: 6 | H29: -2 | I29: 0.55 | J29: 1 | K29: =+PRODUCT(G29:J29) -> -6.6
G30: 6 | H30: 1 | I30: 2.3 | J30: =3-0.35 -> 2.65 | K30: =+PRODUCT(G30:J30) -> 36.57
F31: Drawing Room | G31: 6 | H31: 1 | I31: 3.19 | J31: =3-0.5 -> 2.5 | K31: =+PRODUCT(G31:J31) -> 47.85
G32: 6 | H32: -1 | I32: 2.45 | J32: =3-0.5 -> 2.5 | K32: =+PRODUCT(G32:J32) -> -36.75
F33: Kitchen | G33: 6 | H33: 1 | I33: 0.415 | J33: =3-0.35 -> 2.65 | K33: =+PRODUCT(G33:J33) -> 6.5985
F34: Entry Wall | G34: 6 | H34: 1 | I34: 1.515 | J34: =3-0.125 -> 2.875 | K34: =+PRODUCT(G34:J34) -> 26.13375
G35: 6 | H35: -1 | I35: 1.2 | J35: 2.4 | K35: =+PRODUCT(G35:J35) -> -17.28
F36: Toilet Wall | G36: 6 | H36: 1 | I36: 0.515 | J36: =3-0.5 -> 2.5 | K36: =+PRODUCT(G36:J36) -> 7.725
F37: Toilet Wall | G37: 6 | H37: 1 | I37: 1.81 | J37: =3-0.5 -> 2.5 | K37: =+PRODUCT(G37:J37) -> 27.15
F38: Kitchen Common Wall for Flat 2 & 3 | G38: 2 | H38: 1 | I38: 4.735 | J38: =3-0.35 -> 2.65 | K38: =+PRODUCT(G38:J38) -> 25.0955
F39: Drawing Room Common Wall for Flat 1 & 2 | G39: 2 | H39: 1 | I39: 1.5 | J39: =3-0.45 -> 2.55 | K39: =+PRODUCT(G39:J39) -> 7.65
G40: 2 | H40: 1 | I40: 5.245 | J40: =3-0.45 -> 2.55 | K40: =+PRODUCT(G40:J40) -> 26.7495
G41: 2 | H41: 1 | I41: 1.075 | J41: =3-0.125 -> 2.875 | K41: =+PRODUCT(G41:J41) -> 6.18125
F42: Drawing Room Common Wall for Flat 3 | G42: 2 | H42: 1 | I42: 2.57 | J42: =3-0.5 -> 2.5 | K42: =+PRODUCT(G42:J42) -> 12.85
F43: Flat No.4
F44: Bed Room-1 | G44: 2 | H44: 1 | I44: 3.025 | J44: =3-0.5 -> 2.5 | K44: =+PRODUCT(G44:J44) -> 15.125
G45: 2 | H45: -1 | I45: 2.065 | J45: =3-0.5 -> 2.5 | K45: =+PRODUCT(G45:J45) -> -10.325
G46: 2 | H46: 1 | I46: 3.8 | J46: =3-0.5 -> 2.5 | K46: =+PRODUCT(G46:J46) -> 19
G47: 2 | H47: -1 | I47: 0.55 | J47: 1 | K47: =+PRODUCT(G47:J47) -> -1.1
F48: Bed Room-2 | G48: 2 | H48: 1 | I48: 2.8 | J48: =3-0.5 -> 2.5 | K48: =+PRODUCT(G48:J48) -> 14
G49: 2 | H49: -1 | I49: 2.065 | J49: =3-0.5 -> 2.5 | K49: =+PRODUCT(G49:J49) -> -10.325
F50: Living Room | G50: 2 | H50: 1 | I50: 3.3 | J50: =3-0.5 -> 2.5 | K50: =+PRODUCT(G50:J50) -> 16.5
G51: 2 | H51: -1 | I51: 2.45 | J51: =3-0.5 -> 2.5 | K51: =+PRODUCT(G51:J51) -> -12.25
G52: 2 | H52: 1 | I52: 1.99 | J52: =3-0.45 -> 2.55 | K52: =+PRODUCT(G52:J52) -> 10.149
G53: 2 | H53: 1 | I53: 3.43 | J53: =3-0.45 -> 2.55 | K53: =+PRODUCT(G53:J53) -> 17.493
F54: Entry Wall | G54: 2 | H54: 1 | I54: 1.5 | J54: =3-0.45 -> 2.55 | K54: =+PRODUCT(G54:J54) -> 7.65
G55: 2 | H55: -1 | I55: 1.2 | J55: 2.4 | K55: =+PRODUCT(G55:J55) -> -5.76
F56: Bed Room-3 | G56: 2 | H56: 1 | I56: 3.115 | J56: =3-0.5 -> 2.5 | K56: =+PRODUCT(G56:J56) -> 15.575
G57: 2 | H57: 1 | I57: 1.785 | J57: =3-0.5 -> 2.5 | K57: =+PRODUCT(G57:J57) -> 8.925
G58: 2 | H58: -1 | I58: 1.5 | J58: 1.5 | K58: =+PRODUCT(G58:J58) -> -4.5
F59: Toilet Wall | G59: 2 | H59: 1 | I59: 1.915 | J59: =3-0.45 -> 2.55 | K59: =+PRODUCT(G59:J59) -> 9.7665
G60: 2 | H60: 1 | I60: 2.04 | J60: =3-0.35 -> 2.65 | K60: =+PRODUCT(G60:J60) -> 10.812
F61: Flat No.5
F62: Living Room | G62: 4 | H62: 1 | I62: 2.93 | J62: =3-0.5 -> 2.5 | K62: =+PRODUCT(G62:J62) -> 29.3
G63: 4 | H63: -1 | I63: 2.05 | J63: =3-0.5 -> 2.5 | K63: =+PRODUCT(G63:J63) -> -20.5
G64: 4 | H64: 1 | I64: 0.415 | J64: =3-0.5 -> 2.5 | K64: =+PRODUCT(G64:J64) -> 4.15
F65: Kitchen cum Bed Room-2 | G65: 4 | H65: 1 | I65: 4.69 | J65: =3-0.5 -> 2.5 | K65: =+PRODUCT(G65:J65) -> 46.9
F66: Bed Room-3 | G66: 4 | H66: 1 | I66: 3.05 | J66: =3-0.5 -> 2.5 | K66: =+PRODUCT(G66:J66) -> 30.5
G67: 4 | H67: -1 | I67: 2.45 | J67: =3-0.5 -> 2.5 | K67: =+PRODUCT(G67:J67) -> -24.5
F68: Toilet Wall | G68: 4 | H68: 1 | I68: 1.6 | J68: =3-0.5 -> 2.5 | K68: =+PRODUCT(G68:J68) -> 16
G69: 4 | H69: -1 | I69: 0.55 | J69: 1 | K69: =+PRODUCT(G69:J69) -> -2.2
F70: Open to Sky Wall | G70: 4 | H70: 1 | I70: 3.35 | J70: 2.5 | K70: =+PRODUCT(G70:J70) -> 33.5
G71: 4 | H71: 1 | I71: 0.6 | J71: 2.5 | K71: =+PRODUCT(G71:J71) -> 6
G72: 4 | H72: 1 | I72: 1.385 | J72: 2.5 | K72: =+PRODUCT(G72:J72) -> 13.85
G73: 4 | H73: -1 | I73: 0.55 | J73: 1 | K73: =+PRODUCT(G73:J73) -> -2.2
F74: Entry Wall | G74: 4 | H74: 1 | I74: 1.57 | J74: =3-0.45 -> 2.55 | K74: =+PRODUCT(G74:J74) -> 16.014
G75: 4 | H75: -1 | I75: 1.2 | J75: 2.4 | K75: =+PRODUCT(G75:J75) -> -11.52
F76: Common Wall of Flat 5 & 8 | G76: 2 | H76: 1 | I76: 5.28 | J76: 2.5 | K76: =+PRODUCT(G76:J76) -> 26.4
F77: Common Wall of Flat 5 & 6 | G77: 2 | H77: 1 | I77: 2.41 | J77: 2.5 | K77: =+PRODUCT(G77:J77) -> 12.05
F78: Common Wall of Flat 5 & 6 | G78: 2 | H78: 1 | I78: 6.79 | J78: 2.5 | K78: =+PRODUCT(G78:J78) -> 33.95
F79: Flat No.11 & 12
F80: Bed Room-1 | G80: 2 | H80: 1 | I80: 3.43 | J80: 2.5 | K80: =+PRODUCT(G80:J80) -> 17.15
F81: Main Staircase | G81: 2 | H81: 1 | I81: 2.55 | J81: 2.5 | K81: =+PRODUCT(G81:J81) -> 12.75
G82: 2 | H82: 1 | I82: 3.53 | J82: 2.5 | K82: =+PRODUCT(G82:J82) -> 17.65
G83: 2 | H83: -1 | I83: 1.55 | J83: 1 | K83: =+PRODUCT(G83:J83) -> -3.1
F84: Fire Staircase | G84: 2 | H84: 1 | I84: 3.2 | J84: 2.5 | K84: =+PRODUCT(G84:J84) -> 16
G85: 2 | H85: 1 | I85: 2.76 | J85: 2.5 | K85: =+PRODUCT(G85:J85) -> 13.8
G86: 2 | H86: 1 | I86: 3.2 | J86: 2.5 | K86: =+PRODUCT(G86:J86) -> 16
G87: 2 | H87: -1 | I87: 1.8 | J87: 1 | K87: =+PRODUCT(G87:J87) -> -3.6
F88: Lift | G88: 4 | H88: 2 | I88: 1.9 | J88: 2.5 | K88: =+PRODUCT(G88:J88) -> 38
G89: 4 | H89: -1 | I89: 0.9 | J89: 2.1 | K89: =+PRODUCT(G89:J89) -> -7.56
K91: =SUM(K19:K90) -> 735.468
