Workbook
Name \0: #REF!
Name \0: #REF!
Name \B: #REF!
Name \B: #REF!
Name \C: #REF!
Name \C: #REF!
Name \G: #REF!
Name \I: #REF!
Name \M: #REF!
Name \O: #REF!
Name \P: #REF!
Name \Q: #REF!
Name \R: #REF!
Name \S: #REF!
Name __aoc10: #N/A
Name __aoc11: #REF!
Name __aoc11: #REF!
Name __aoc11: #REF!
Name __aoc7: #REF!
Name __aoc7: #REF!
Name __aoc7: #REF!
Name __aoc8: #REF!
Name __aoc8: #REF!
Name __aoc9: #REF!
Name __aoc9: #REF!
Name __ERA1: #REF!
Name __ERA1: #REF!
Name __ERA10: #REF!
Name __ERA10: #REF!
Name __ERA11: #REF!
Name __ERA11: #REF!
Name __ERA2: #REF!
Name __ERA3: #REF!
Name __ERA5: #REF!
Name __ERA5: #REF!
Name __ERA9: #REF!
Name __ERA9: #REF!
Name __HED1: #REF!
Name __HED1: #REF!
Name __HED2: #REF!
Name __HED2: #REF!
Name __vut02533: #REF!
Name __vut02533: #REF!
Name __vut02533: #REF!
Name __xlnm.Print_Area: "$#REF!.$A$2:$I$161"
Name __xlnm.Print_Area_1: #REF!
Name __xlnm.Print_Area_1: #REF!
Name __xlnm.Print_Area_1: #REF!
Name __xlnm.Print_Area_10: #REF!
Name __xlnm.Print_Area_10: #REF!
Name __xlnm.Print_Area_11: #REF!
Name __xlnm.Print_Area_11: #REF!
Name __xlnm.Print_Area_12: #REF!
Name __xlnm.Print_Area_12: #REF!
Name __xlnm.Print_Area_13: #REF!
Name __xlnm.Print_Area_13: #REF!
Name __xlnm.Print_Area_14: #REF!
Name __xlnm.Print_Area_14: #REF!
Name __xlnm.Print_Area_15: #REF!
Name __xlnm.Print_Area_15: #REF!

Sheet TOP SHEET
A1: OMAXE LTD. | F1: Tracker NO | G1: Office NO
A2: NAME OF PROJECT : OMAXE ANANDA TOWER-E (Location: Tower-E STILT + 14 FLOORS) | E2: CONTRACT VALUE ; | G2: =+ABSTRACT!F109 -> 162074375
A3: NATURE OF WORK : CIVIL STRUCTURE WORK | E3: PROGRESS OF WORK: | G3: =D11/G2 -> 0.11625374
A4: NAME OF THE CONTRACTOR :- M/s MARCO-ENTERPRISES | E4: VENDOR CODE:
A5: WORK ORDER NO. & DATE : OPRL/ATE/11094106758 (14 FEB, 2025) | E5: DATE OF START: 01.MAY.2025
A6: THIS R/A BILL NO. & DATE : 8TH RA BILL, DATE 12-02-2026 | E6: COMPLETION PERIOD : Upto 31-Aug-2026 (18 Months)
A7: PERIOD OF BILL :- FROM 01-02-2026 TO 12-02-2026 | E7: GST No. : 09BLDPK5228HIZ2
A8: ERP PROJECT CODE : 127018 | E8: PAN NO. : BLDPK5228H
A9: DATE OF BILL REC. AT SITE :- | C9: DATE OF BILL RECEIVED AT H.O. :- | E9: DATE OF BILL CHECKING AT H.O. :-
A10: S.NO. | B10: PARTICULARS | C10: CLAIMED BY CONTRACTOR | D10: GROSS AMT | E10: PREVIOUS AMT. | F10: THIS BILL AMT | G10: REMARKS
A11: 1 | B11: WORK DONE(CIVIL) | D11: =ABSTRACT!M109 -> 18841753 | E11: 16826127 | F11: =+D11-E11 -> 2015626
A12: 2 | B12: WORK DONE(ELECT/ PLUMBING)
A13: 3 | B13: DIFF. OF CEMENT
A14: 4 | B14: RATE DIFF OF TILES
B15: TOTAL (A) | D15: =SUM(D11:D14) -> 18841753 | E15: =SUM(E11:E14) -> 16826127 | F15: =SUM(F11:F14) -> 2015626
A16: 5 | B16: Add GST 18% On (A) | D16: =D15*18% -> 3391515.5 | E16: =E15*18% -> 3028702.8 | F16: =F15*18% -> 362812.67
B17: TOTAL (B) | D17: =D16+D15 -> 22233268 | E17: =E16+E15 -> 19854830 | F17: =F16+F15 -> 2378438.6
B18: ADVANCES
A21: 7.1 | B21: Add Mobilization Advance | D21: =+F21+E21 -> 6000000 | E21: 6000000
A22: 7.2 | B22: Recover Mobilization Advance | D22: =-(E21*G3)/80% -> -871903.07 | E22: -778629.88 | F22: =+D22-E22 -> -93273.194
B23: TOTAL (C) | D23: =SUM(D17:D22) -> 27361365 | E23: =SUM(E17:E22) -> 25076200 | F23: =SUM(F17:F22) -> 2285165.4
B24: DEDUCTIONS
A25: 8 | B25: SECURITY @ 5 % (ON TOTAL A) | D25: =ROUND(D15*5%,0) -> 942088 | E25: =ROUND(E15*5%,0) -> 841306 | F25: =ROUND(F15*5%,0) -> 100781
A26: 9 | B26: TDS @ 1% (ON TOTAL A) | D26: =ROUND((D15+D19+D20+D21+D22)*1%,0) -> 239698 | E26: =ROUND((E15+E19+E20+E21+E22)*1%,0) -> 220475 | F26: =+D26-E26 -> 19223
B27: TOTAL DEDUCTION (C) | D27: =SUM(D25:D26) -> 1181786 | E27: =SUM(E25:E26) -> 1061781 | F27: =SUM(F25:F26) -> 120004
A28: 11 | B28: NET PAYABLE AMOUNT (D) | D28: =D23-D27 -> 26179579 | E28: =E23-E27 -> 24014419 | F28: =F23-F27 -> 2165161.4
B29: NOW PAYABLE | F29: =F28 -> 2165161.4
B30: PREPARED BY
C31: PRIYANK BARANWAL
C32: MANAGER (BILLING)
C33: 9988294677
B34: ACCOUNT (SITE) | E34: PREVIOUS RA BILL NO:-
C35: ANUP SINGH | E35: PREVIOUS RA GROSS AMOUNT:-
C36: DY. MANAGER
C37: 9315403180
B38: PROJECT INCHARGE {CPC/PC/ASST V.P./SR GM /GM}
E39: S K PANDEY
E40: G.M. - PROJECT
E41: 9711800470
B42: HO BILL MONITORING
C43: UPENDER SINGH | E43: GAURAV MAHESHWARI
C44: CHIEF MANAGER | E44: G.M.-HO BILLING

Sheet ABSTRACT
A1: OMAXE PANCHAM REALCON PVT. LTD.
B2: =+'TOP SHEET'!A5 -> WORK ORDER NO. & DATE : OPRL/ATE/11094106758 (14 FEB, 2025) | J2: =+'TOP SHEET'!A8 -> ERP PROJECT CODE : 127018
B3: =+'TOP SHEET'!A6 -> THIS R/A BILL NO. & DATE : 8TH RA BILL, DATE 12-02-2026 | J3: =+'TOP SHEET'!A9 -> DATE OF BILL REC. AT SITE :-
B4: =+'TOP SHEET'!A3 -> NATURE OF WORK : CIVIL STRUCTURE WORK | J4: =+'TOP SHEET'!A7 -> PERIOD OF BILL :- FROM 01-02-2026 TO 12-02-2026
A5: ABSTRACT OF COST
A6: S.No. | B6: DESCRIPTION OF ITEM | C6: Unit | D6: AS PER W.O. (R0) | H6: Qty | K6: Amount | N6: Executed %
D7: Qty | E7: Rate | F7: Amount | G7: Part Rate | H7: Prev. Bill | I7: This Bill | J7: UpTo Date | K7: Prev. Bill | L7: This Bill | M7: UpTo Date
A8: 1 | B8: EARTH WORK
A9: 1.1. | B9: Earth work in excavation in foundation trenches, column pits, plinth beam, under grade/ raft slab etc. by mechanical and/or manual means up to a depth of 1.5 mtr in soil from existing excavated soil level, stacking/spreading the excavated material within site premises (within a stretch of 1500 M) as per direction of Project Manager including dressing of bottom, sides strutting, timbering, shoring, trimming of sides, all leads and lifts, bailing or pumping out the water from the excavated areas collected from any source including subsoil water and keeping the excavated surface dry for subsequent works incidentals, etc. complete with ramming of bottom, surface preparation as per specifications to receive the PCC. | C9: CUM | D9: 1000 | E9: 120 | F9: =$D9*E9 -> 120000 | I9: =J9-H9 -> 0 | L9: =M9-K9 -> 0 | M9: =E9*J9 -> 0 | N9: =J9/D9 -> 0
B10: Excavation shall be payable only for vertical cut up to the outer edge of foundation lean concrete as indicated in drawings for all depths. Cost of extra excavation required for working space, supporting side shuttering of foundations and retaining walls, planking, dewatering, strutting etc. and that required for making slopes for stability of excavation shall be deemed to be included in the rate quoted. This item is not for Mass Excavation. | L10: =M10-K10 -> 0 | M10: =E10*J10 -> 0
A11: 1.2. | B11: Prepare the surface for PCC by manual excavation upto 30 cm depth including dressing the surface, ramming the bottom, disposal and spreading of the surplus earth at the specified location within premises including proper levelling, watering and consolidation complete as directed by E I C. (The item shall be measured as per plan area of PCC, Working space shall not be taken into measurement, deemed to be included into rates) (This item is only applicable if excavation item is not being executed by contractor and excavation already done by client for the location) | C11: SQM | D11: 1500 | E11: 65 | F11: =$D11*E11 -> 97500 | G11: =+E11 -> 65 | H11: 1881.385 | I11: =J11-H11 -> 0 | J11: ='EARTH WORK MB'!I78 -> 1881.385 | K11: 122290.02 | L11: =M11-K11 -> 0 | M11: =G11*J11 -> 122290.02 | N11: =J11/D11 -> 1.2542566
A12: 1.3. | B12: Filling available excavated earth in trenches, plinth, sides of foundations etc. in layers not exceeding 20cm in depth: consolidating each deposited layer by ramming and watering, lead within the premises and upto any depth. (Compacted Volume shall be payable as per drawing) - Actual volume shall be paid incase excavation is done by Client. | C12: CUM | D12: 2400 | E12: 100 | F12: =$D12*E12 -> 240000 | G12: 100 | H12: 4725.3991 | I12: =J12-H12 -> 0 | J12: ='EARTH WORK MB'!I86 -> 4725.3991 | K12: 472539.91 | L12: =M12-K12 -> 0 | M12: =G12*J12 -> 472539.91 | N12: =J12/D12 -> 1.9689163
B13: Total of Earthwork | F13: =SUBTOTAL(9,F9:F12) -> 457500
A15: 2 | B15: CONCRETE WORK
B16: Rates for all cement concrete items plain and reinforced described below shall include work from Basement Level to top of last roof including roof of machine room, mumty, over head water tanks and parapets above at all floors and for all heights. The contractor should provide full time sufficient pipes with accessories and pumps based on the site requirement for pumping and laying of concrete as directed by the EIC. The rate inclusive of standard rigid pipe line and its supports, lifting, laying charges, etc., at all heights and levels. No additional payment shall be payable to the contractor on account of using or change in any size of coarse aggregate in PCC/ RCC work at any stage during currency of works. (This section covers cast in situ structural and architectural as well.)
A17: 2.1 | B17: Plain Cement Concrete: Providing and laying plain cement concrete of specified grade as bed concrete under foundation, bases for rafts, underground water tank, building machine equipments, column footing, under floor landings, below road and pathways, cill, coping, screeding at roof to required slope and other locations as called for laid, consolidated and cured etc. complete including finishing the top surface to receive the next course / layer as per specification and drawing. (Shuttering shall be paid in Item No.3.1.1) M10 Grade (Basic Rate of PCC - Rs. 4200/cum) without pump | C17: CUM | D17: 100 | E17: 5550 | F17: =$D17*E17 -> 555000 | G17: 5550 | H17: 79.466655 | I17: =J17-H17 -> 0 | J17: ='CONCRETE SUMMARY'!M6 -> 79.466655 | K17: 441039.94 | L17: =M17-K17 -> 0 | M17: =G17*J17 -> 441039.94 | N17: =J17/D17 -> 0.79466655
A18: 2.2. | B18: Providing and laying cement concrete 1:2:4 (1 cement : 2 coarse sand : 4 graded stone aggregate 20mm nominal size) for ledge wall below balcony railings, band, mullion, lintel etc. (Shuttering shall be paid separately in respective item) as per drawing and as directed by the Project Manager. | C18: CUM | D18: 50 | E18: 5750 | F18: =$D18*E18 -> 287500 | I18: =J18-H18 -> 0 | J18: ='CONCRETE SUMMARY'!M7 -> 0 | L18: =M18-K18 -> 0 | M18: =E18*J18 -> 0 | N18: =J18/D18 -> 0
A19: 2.3. | B19: Providing and laying damp proof course 40mm thick including shttering with cement concrete 1:2:4 (1 cement : 2 coarse sand : 4 graded stone aggregate 20mm nominal size) including mixing of water proofing compound @ 2% of cement content and applying two layers of bitumen @ 1.70 Kg/Sqm of grade 85/25 and as directed by the Project Manager. | C19: SQM | D19: 200 | E19: 480 | F19: =$D19*E19 -> 96000 | I19: =J19-H19 -> 0 | J19: ='CONCRETE SUMMARY'!M8 -> 0 | L19: =M19-K19 -> 0 | M19: =E19*J19 -> 0 | N19: =J19/D19 -> 0
A21: 2.4. | B21: RCC WORK
B22: Providing & Laying RMC M-25 Grade as per approved design mix concrete (strictly controlled conditions) with flyash (as per approved design mix) with automatic batching plant machine mixed and machine vibrated RCC with melamine based plasticisers etc., upto any level, including finishing the exposed surface, fixing/ removal of pockets, fixing of sleeves and inserts (sleeves provided by client), curing etc complete, as per drawing (including all size and shape like circular, semi-circular, oval etc.) and as directed for all lead and lift, excluding cost of centering, shuttering and steel reinforcement but including cost of making shear keys and provision of construction / contraction / control joints in various locations. Checking from Client should not be considered as final and any defects arising during or after casting should be borne & bear by contractor at his own cost. This is inclusive of leaving shuttering & centring for pour strip, slab in slope, RCC members in curved, etc., nothing is payable extra on this account. RMC (M-25) Basic Rate - Rs. 5200/cum without pump excluding GST
A23: 2.4.1. | B23: Foundation, column footings, raft slab, raft beams, plinth beam, lift pits, sump pits, pedestals / bases of column, column upto plinth, swimming pool, Retaining wall foundations, grade slab etc. | C23: CUM | D23: 2080 | E23: 6600 | F23: =$D23*E23 -> 13728000 | G23: =+E23 -> 6600 | H23: 1686.5471 | I23: =J23-H23 -> 0 | J23: ='CONCRETE SUMMARY'!M12 -> 1686.5471 | K23: 11131211 | L23: =M23-K23 -> 0 | M23: =G23*J23 -> 11131211 | N23: =J23/D23 -> 0.81083997
A24: 2.4.2. | B24: Suspended floors, roofs, balconies, shelves/ counters, stair waist slabs, folded plate stairs and landings, swimming pool slab, lintel and floor beams, landing beams, girders (deep beams), RCC bands, swimming pool beam, cantilever projections, coping, cills, slab of tank etc at all levels.
A25: 2.4.2.1. | B25: Stilt Floor level to 7th Floor level | C25: CUM | D25: 2200 | E25: 6550 | F25: =$D25*E25 -> 14410000 | H25: 138.41397 | I25: =J25-H25 -> 169.17264 | J25: ='CONCRETE SUMMARY'!M14 -> 307.58661 | K25: 906611.53 | L25: =M25-K25 -> 1108080.8 | M25: =E25*J25 -> 2014692.3 | N25: =J25/D25 -> 0.1398121
A26: 2.4.2.2. | B26: 7th Floor level to to Terrace Including OHT, Mumty, Machine Room, Parapet | C26: CUM | D26: 2440 | E26: 6750 | F26: =$D26*E26 -> 16470000 | I26: =J26-H26 -> 0 | J26: ='CONCRETE SUMMARY'!M15 -> 0 | L26: =M26-K26 -> 0 | M26: =E26*J26 -> 0 | N26: =J26/D26 -> 0
A27: 2.4.2.3. | B27: All type of Moulding, Bands, Elevation/Architectural Features as per drawing and as directed by EIC. at all level | C27: CUM | D27: 70 | E27: 7300 | F27: =$D27*E27 -> 511000 | I27: =J27-H27 -> 0 | J27: ='CONCRETE SUMMARY'!M16 -> 0 | L27: =M27-K27 -> 0 | M27: =E27*J27 -> 0 | N27: =J27/D27 -> 0
A29: 2.5. | B29: Columns, Wall, pillars, piers, abutments, posts and struts, offset and projection of columns, water tank walls, lift walls, Retaining Wall, swimming pool, Parapets, planters, vertical projection of pergolas, wall and ramp walls etc. at all levels.
A30: 2.5.1. | B30: Stilt Floor level to 7th Floor level | C30: CUM | D30: 860 | E30: 6850 | F30: =$D30*E30 -> 5891000 | G30: 6850 | H30: 93.874382 | I30: =J30-H30 -> 0 | J30: ='CONCRETE SUMMARY'!M19 -> 93.874382 | K30: 643039.52 | L30: =M30-K30 -> 0 | M30: =G30*J30 -> 643039.52 | N30: =J30/D30 -> 0.10915626
A31: 2.5.2. | B31: 7th Floor level to to Terrace Including OHT, Mumty, Machine Room, Parapet | C31: CUM | D31: 950 | E31: 7050 | F31: =$D31*E31 -> 6697500 | I31: =J31-H31 -> 0 | J31: ='CONCRETE SUMMARY'!M20 -> 0 | L31: =M31-K31 -> 0 | M31: =E31*J31 -> 0 | N31: =J31/D31 -> 0
A32: 2.5.3. | B32: All type of Moulding, Bands, Elevation/Architectural Features as per drawing and as directed by EIC. at all level | C32: CUM | D32: 30 | E32: 7650 | F32: =$D32*E32 -> 229500 | I32: =J32-H32 -> 0 | J32: ='CONCRETE SUMMARY'!M21 -> 0 | L32: =M32-K32 -> 0 | M32: =E32*J32 -> 0 | N32: =J32/D32 -> 0
A33: 2.5.4. | B33: Finishing vaccum dewatering continuous concrete flooring 100-150 mm thick with specified grade concrete including necessary formwork in required level, vibrating concrete both by poker vibrators / leveling vaccum processing of the concrete and planning the surface by skin powered floater trowels with broom/plain finish including groove cutting & filling etc. complete. (Concrete shall be paid in the respective items above). | C33: SQM | D33: 1625 | E33: 100 | F33: =$D33*E33 -> 162500 | J33: ='CONCRETE SUMMARY'!M22 -> 0
B35: Total of RCC Work | F35: =SUBTOTAL(9,F17:F34) -> 59038000
A37: 3 | B37: CENTRING AND SHUTTERING
B38: Providing and fixing plywood or steel plate shuttering and centring for structural concrete work in locations called for including strutting, propping, bracing, bolting, wedging, casing, striking, removal etc. complete for any size, section, thickness. Props shall consist of well designed steel pipes adequately braced (wooden ballies as props shall not be permitted). The item to include centering and shuttering at all heights and levels. Allow for forming grooves, drip course, chamfers, cut-outs, openings etc. where called for and for dressing with approved shuttering oil to prevent adhesion. Unexposed concrete surfaces subsequently left untreated (in the condition obtained on removal of form work) shall not constitute exposed concrete work and shall be measured under this item only Irregular shapes with sides (like circular, semi-circular, oval etc.) which may not be perpendicular to each other for shapes not conforming to rectangle or square, and circular shuttering shall not be paid separately. Joints of soffits of the slab shall be made clean after concreting and de-shuttering. (quoted rate to include all staging upto 3.50 mtr height). Note:- Contractor shall take necessary precautions such as watertight shuttering. This is inclusive of RCC members, leaving shuttering & centring for pour strip, slab in slope, RCC members in curved (in plan), etc., nothing is payable extra on this account.
A39: 3.1.1. | B39: Foundation, column footings, raft slab, raft beams, plinth beam, lift pits, sump pits, pedestals / bases of column, column up to plinth, swimming pool, Retaining wall foundations, grade slab etc. | C39: SQM | D39: 2150 | E39: 360 | F39: =$D39*E39 -> 774000 | G39: =+E39 -> 360 | H39: 1645.4974 | I39: =J39-H39 -> 0 | J39: ='SHUTT. WORK SUMMARY'!M5 -> 1645.4974 | K39: 592379.05 | L39: =M39-K39 -> 0 | M39: =G39*J39 -> 592379.05 | N39: =J39/D39 -> 0.7653476
A40: 3.1.2. | B40: Suspended floors, roofs, balconies, shelves/ counters, stair waist slabs, folded plate stairs and landings, swimming pool slab, lintel and floor beams, landing beams, girders (deep beams), RCC bands, swimming pool beam, cantilever projections, coping, cills, slab of tank etc at all levels.
A41: 3.1.2.1. | B41: Stilt Floor level to 7th Floor level | C41: SQM | D41: 17600 | E41: 465 | F41: =$D41*E41 -> 8184000 | H41: 1016.4427 | I41: =J41-H41 -> 1375.1872 | J41: ='SHUTT. WORK SUMMARY'!M7 -> 2391.6299 | K41: 472645.86 | L41: =M41-K41 -> 639462.04 | M41: =E41*J41 -> 1112107.9 | N41: =J41/D41 -> 0.13588806
A42: 3.1.2.2. | B42: 7th Floor level to to Terrace Including OHT, Mumty, Machine Room, Parapet | C42: SQM | D42: 18800 | E42: 485 | F42: =$D42*E42 -> 9118000 | I42: =J42-H42 -> 0 | J42: ='SHUTT. WORK SUMMARY'!M8 -> 0 | L42: =M42-K42 -> 0 | M42: =E42*J42 -> 0 | N42: =J42/D42 -> 0
A43: 3.1.2..3 | B43: All type of Moulding, Bands, Elevation/Architectural Features as per drawing and as directed by EIC. at all level | C43: SQM | D43: 400 | E43: 550 | F43: =$D43*E43 -> 220000 | I43: =J43-H43 -> 0 | J43: ='SHUTT. WORK SUMMARY'!M9 -> 0 | L43: =M43-K43 -> 0 | M43: =E43*J43 -> 0 | N43: =J43/D43 -> 0
L44: =M44-K44 -> 0 | M44: =E44*J44 -> 0
A45: 3.2. | B45: Columns, Wall, pillars, piers, abutments, posts and struts, offset and projection of columns, water tank walls, lift walls, Retaining Wall, swimming pool, Parapets, planters, vertical projection of pergolas, wall and ramp walls etc. at all levels.
A46: 3.2.1. | B46: Stilt Floor level to 7th Floor level | C46: SQM | D46: 7825 | E46: 465 | F46: =$D46*E46 -> 3638625 | H46: 998.109 | I46: =J46-H46 -> 0 | J46: ='SHUTT. WORK SUMMARY'!M12 -> 998.109 | K46: 464120.68 | L46: =M46-K46 -> 0 | M46: =E46*J46 -> 464120.68 | N46: =J46/D46 -> 0.12755387
A47: 3.2.2. | B47: 7th Floor level to to Terrace Including OHT, Mumty, Machine Room, Parapet | C47: SQM | D47: 8200 | E47: 485 | F47: =$D47*E47 -> 3977000 | I47: =J47-H47 -> 0 | J47: ='SHUTT. WORK SUMMARY'!M13 -> 0 | L47: =M47-K47 -> 0 | M47: =E47*J47 -> 0 | N47: =J47/D47 -> 0
A48: 3.2.3. | B48: All type of Moulding, Bands, Elevation/Architectural Features as per drawing and as directed by EIC. at all level | C48: SQM | D48: 150 | E48: 550 | F48: =$D48*E48 -> 82500 | I48: =J48-H48 -> 0 | J48: ='SHUTT. WORK SUMMARY'!M14 -> 0 | L48: =M48-K48 -> 0 | M48: =E48*J48 -> 0 | N48: =J48/D48 -> 0
A50: 3.3. | B50: Extra for additional height in centring, shuttering where ever required with adequate bracing, propping etc. including cost of de-shuttering and decentring at all levels, over and above height of 3.50 mtr (Plan area to be measured and shall be paid proportionately on actual height) – for every 1.0 mtr. height | C50: SQM | D50: 1000 | E50: 115 | F50: =$D50*E50 -> 115000 | I50: =J50-H50 -> 0 | J50: ='SHUTT. WORK SUMMARY'!M16 -> 0 | L50: =M50-K50 -> 0 | M50: =E50*J50 -> 0 | N50: =J50/D50 -> 0
B51: Total of Shuttering | F51: =SUBTOTAL(9,F39:F50) -> 26109125
A53: 4 | B53: REINFORCEMENT
B54: Receiving, laying and fixing in position steel reinforcement in all reinforced concrete work, including straightening, cutting, removal of loose rust by wire brush and coating with cement slurry, bending, hoisting, laying in position to the shape and profile required at all levels and heights as per drawing and design and/ or as directed, binding with double folded steel wire as approved by EIC etc. complete. (Contractor shall prepare BBS and submit to EIC for approval prior to cutting, bending & laying of steel bars and payments shall be released as per approved BBS complete in all respect as per direction and approval of EIC Rate shall include cost of 18 gauge GI binding wire, cover blocks as per Indian Standards, unloading the steel & moving to the steel yard, moving site to site within project etc) (Only Steel reinforcement shall be provided by the owner free of cost at one point)
A55: 4.1. | B55: Thermomechanically Treated Reinforcement (TMT) or High yield strength Deformed (Tor steel) bars of all size & grades.
A56: 4.1.1. | B56: Up to Stilt Floor Level | C56: MT | D56: 150 | E56: 8500 | F56: =$D56*E56 -> 1275000 | G56: 8500 | H56: 132.1686 | I56: =J56-H56 -> 0 | J56: ='TMT SUMMARY'!M15/1000 -> 132.1686 | K56: 1123433.1 | L56: =M56-K56 -> 0 | M56: =G56*J56 -> 1123433.1 | N56: =J56/D56 -> 0.88112399
A57: 4.1.2. | B57: Stilt Floor level to to Terrace Including OHT, Mumty, Machine Room, Parapet) | C57: MT | D57: 805 | E57: 9400 | F57: =$D57*E57 -> 7567000 | G57: 9400 | H57: 43.346352 | I57: =J57-H57 -> 28.519484 | J57: ='TMT SUMMARY'!M22/1000 -> 71.865836 | K57: 407455.71 | L57: =M57-K57 -> 268083.15 | M57: =E57*J57 -> 675538.86 | N57: =J57/D57 -> 0.08927433
A58: 4.1.3. | B58: All type of Moulding, Bands, Elevation/Architectural Features as per drawing and as directed by EIC. at all level | C58: MT | D58: 10 | E58: 11000 | F58: =$D58*E58 -> 110000 | H58: 0 | I58: =J58-H58 -> 0 | J58: 0 | K58: 0 | L58: =M58-K58 -> 0 | M58: =E58*J58 -> 0 | N58: =J58/D58 -> 0
B59: Total of Reinforcement | F59: =SUBTOTAL(9,F55:F58) -> 8952000
A61: 5 | B61: MASONARY WORK
B62: (Quoted Rates are for all heights, all depths, all levels, including basement to roof (mumty) & all leads and lifts, including curved or circular including elevation masonary work) (Basic Rate of Brick @ Rs. 7/No. FOR at site without GST)
A63: 5.1. | B63: Brick work in Sub Structure (Up to Stilt Floor level):
B64: Providing and laying 230mm thick brick masonry using 1st quality burnt clay FPS bricks in Sub-Structure laid in cement mortar 1:6 (1 cement : 6 coarse sand) mix, joints finished, flush/ raked to 6mm depth including scaffolding, curing complete as per specification and drawing or as directed by Project Manager. | C64: CUM | D64: 100 | E64: 6000 | F64: =$D64*E64 -> 600000 | I64: =J64-H64 -> 0 | J64: ='BRICK WORK SUMMARY'!J7 -> 0 | L64: =M64-K64 -> 0 | M64: =E64*J64 -> 0 | N64: =J64/D64 -> 0
A65: 5.2. | B65: Brick work in Sub Structure (Up to Stilt Floor level):
B66: Providing and laying of 115 mm thick brick work with 1st quality burnt clay FPS bricks in sub-superstructure laid in cement mortar 1:4 (1 cement : 4 coarse sand) mix, joints finished, including placing hoop iron as per specification at every third course, scaffolding, curing complete in all respect as per direction of EIC. (Hoop iron shall be provided by client free of cost) (Items of RCC bands like shuttering, concrete and reinforcement to be paid in respective items). | C66: SQM | D66: 1000 | E66: 800 | F66: =$D66*E66 -> 800000 | G66: =+E66*0.7 -> 560 | H66: 88.1435 | I66: =J66-H66 -> 0 | J66: ='BRICK WORK SUMMARY'!J9 -> 88.1435 | K66: 49360.36 | L66: =M66-K66 -> 0 | M66: =G66*J66 -> 49360.36 | N66: =J66/D66 -> 0.0881435
A67: 5.3. | B67: Brick work in Super Structure (Above Stilt FLoor level)
A68: 5.3.1 | B68: Providing and laying 230mm thick brick masonry using 1st quality burnt clay FPS bricks in Super-Structure laid in cement mortar 1:6 (1 cement : 6 coarse sand) mix, joints finished, flush/ raked to 6mm depth including scaffolding, curing complete as per specification and drawing or as directed by Project Manager. | L68: =M68-K68 -> 0 | M68: =E68*J68 -> 0
A69: (a) | B69: Stilt Floor level to 7th Floor level | C69: CUM | D69: 1185 | E69: 6300 | F69: =$D69*E69 -> 7465500 | I69: =J69-H69 -> 0 | J69: ='BRICK WORK SUMMARY'!J12 -> 0 | L69: =M69-K69 -> 0 | M69: =E69*J69 -> 0 | N69: =J69/D69 -> 0
A70: (b) | B70: 7th Floor level to to Terrace Including OHT, Mumty, Machine Room, Parapet | C70: CUM | D70: 1355 | E70: 6500 | F70: =$D70*E70 -> 8807500 | I70: =J70-H70 -> 0 | J70: ='BRICK WORK SUMMARY'!J13 -> 0 | L70: =M70-K70 -> 0 | M70: =E70*J70 -> 0 | N70: =J70/D70 -> 0
A71: 5.4. | B71: Brick work in Super Structure (Above Stilt FLoor level)
A72: 5.4.1 | B72: Providing and laying of 115 mm thick brick work with 1st quality burnt clay FPS bricks in Super-Superstructure laid in cement mortar 1:4 (1 cement : 4 coarse sand) mix, joints finished, including placing hoop iron as per specification at every third course, scaffolding, curing complete in all respect as per direction of EIC. (Hoop iron shall be provided by client free of cost) (Items of RCC bands like shuttering, concrete and reinforcement to be paid in respective items).
A73: (a) | B73: Stilt Floor level to 7th Floor level | C73: SQM | D73: 7100 | E73: 875 | F73: =$D73*E73 -> 6212500 | I73: =J73-H73 -> 0 | J73: ='BRICK WORK SUMMARY'!J16 -> 0 | L73: =M73-K73 -> 0 | M73: =E73*J73 -> 0 | N73: =J73/D73 -> 0
A74: (b) | B74: 7th Floor level to to Terrace Including OHT, Mumty, Machine Room, Parapet | C74: SQM | D74: 8155 | E74: 915 | F74: =$D74*E74 -> 7461825 | I74: =J74-H74 -> 0 | J74: ='BRICK WORK SUMMARY'!J17 -> 0 | L74: =M74-K74 -> 0 | M74: =E74*J74 -> 0 | N74: =J74/D74 -> 0
A75: 5.8. | B75: Brick work in staircase steps:
B76: Providing and laying and constructing brickwork in staircase steps using 1st quality burnt clay FPS bricks in cement mortar 1:3 (1 cement : 3 coarse sand) at all heights and levels including cutting, chamfering scaffolding, curing, complete as per specification. | C76: CUM | D76: 40 | E76: 7000 | F76: =$D76*E76 -> 280000 | I76: =J76-H76 -> 0 | J76: ='BRICK WORK SUMMARY'!J19 -> 0 | L76: =M76-K76 -> 0 | M76: =E76*J76 -> 0 | N76: =J76/D76 -> 0
B77: Total of Masonary Work | F77: =SUBTOTAL(9,F63:F76) -> 31627325
A79: 6 | B79: FINISHING WORKS (PLASTER)
B80: (Quoted Rate shall be for all heights, depths, levels, leads and lifts and to include providing and fixing chicken wire mesh in junction RCC and brick / AAC Block walls and at all chased for electrical conduits & plumbing pipes etc. for internal and external plaster works including minor chipping of RCC, brickwork surface).
A82: 6.1. | B82: Internal Plaster Super-Structure:
B83: Wall Plaster: Providing and applying 12 to 15mm thick plaster to masonry and RCC walls, columns etc. in cement mortar 1:5 (1 cement : 5 screened coarse sand) finished smooth including hacking the surfaces, steel scaffolding, curing, making grooves at desired location etc. complete for all levels as per approved drawing.
A84: (a) | B84: Stilt Floor level to 7th Floor level | C84: SQM | D84: 19970 | E84: 265 | F84: =$D84*E84 -> 5292050 | I84: =J84-H84 -> 0 | L84: =M84-K84 -> 0 | M84: =E84*J84 -> 0 | N84: =J84/D84 -> 0
A85: (b) | B85: 7th Floor level to to Terrace Including OHT, Mumty, Machine Room, Parapet | C85: SQM | D85: 22825 | E85: 280 | F85: =$D85*E85 -> 6391000 | I85: =J85-H85 -> 0 | L85: =M85-K85 -> 0 | M85: =E85*J85 -> 0 | N85: =J85/D85 -> 0
A86: 6.2. | B86: Internal Plaster Super-Structure:
B87: Ceiling Plaster: Providing and applying 6-10mm thick plaster to RCC slab, beam in cement mortar 1:4 (1 cement : 4 screened coarse sand) finished smooth including hacking the surfaces, steel scaffolding, curing, making grooves at desired location etc. complete for all levels as per approved drawing.
A88: (a) | B88: Stilt Floor level to 7th Floor level | C88: SQM | D88: 9135 | E88: 255 | F88: =$D88*E88 -> 2329425 | I88: =J88-H88 -> 0 | L88: =M88-K88 -> 0 | M88: =E88*J88 -> 0 | N88: =J88/D88 -> 0
A89: (b) | B89: 7th Floor level to to Terrace Including OHT, Mumty, Machine Room, Parapet | C89: SQM | D89: 10440 | E89: 270 | F89: =$D89*E89 -> 2818800 | I89: =J89-H89 -> 0 | L89: =M89-K89 -> 0 | M89: =E89*J89 -> 0 | N89: =J89/D89 -> 0
A90: 6.3 | B90: Double Layer External Plaster: Providing and applying 20 mm thick external cement plaster in two coats under layer 12 mm thick cement plaster 1:5 (1 cement : 5 screened coarse sand) finished with a top layer 8mm thick cement plaster 1:4 (1 cement : 4 screened coarse sand) including making of grooves, bands, drip coarse, design etc. as shown in drawing, steel scaffolding, curing, providing & mixing water proofing compound (CICO) in both layers as per manufacturer specification etc. complete as per approved drawing. | C90: SQM | D90: 19200 | E90: 480 | F90: =$D90*E90 -> 9216000 | I90: =J90-H90 -> 0 | N90: =J90/D90 -> 0
A91: 6.4 | B91: Single Layer (Shaft Plaster): Providing and applying 12-15 mm thick external cement plaster in single coat finished with cement plaster 1:4 (1 cement : 4 screened coarse sand) including making of grooves, bands, drip coarse as shown in drawing, steel scaffolding, curing, providing & mixing water proofing compound (CICO) as per manufacturer specification etc. complete as per approved drawing. | C91: SQM | D91: 1000 | E91: 380 | F91: =$D91*E91 -> 380000 | I91: =J91-H91 -> 0 | L91: =M91-K91 -> 0 | M91: =E91*J91 -> 0 | N91: =J91/D91 -> 0
B92: Total of Finishing Work (Plaster) | F92: =SUBTOTAL(9,F81:F91) -> 26427275
A94: 7 | B94: STRUCTURE STEEL
A95: 7.1. | B95: Structural steel work with solid/hollow sections: Providing and fixing M.S. work in built-up section such as staircase railing, balcony railing, grating, MS drain cover, MS mumty door including hold fast/fastener etc. with square/round MS Pipes, MS flats, MS Hollow section etc., as per design electrically welded and fixing in RCC/brick masonry or/and treads of steps with cement concrete 1:2:4 (1 cement : 2 corse sand : 4 grades stone aggregate 20 mm nominal sie), complete in all respect as per drawing & direction of EIC, including a coat of red oxide steel primer. (Basic Rate of Str. Steel - Rs. 60/- Per Kg. F.O.R excluding GST) | C95: KG | D95: 39665 | E95: 110 | F95: =$D95*E95 -> 4363150 | I95: =J95-H95 -> 0 | L95: =M95-K95 -> 0 | M95: =E95*J95 -> 0 | N95: =J95/D95 -> 0
B96: Total of Strutural Steel Work | F96: =SUBTOTAL(9,F95) -> 4363150
A98: 8 | B98: WOOD WORK
A99: 1 | B99: Providing and Fixing seasoned Red Meranti door frame including painting the portion in contact with masonary / R.C.C. with 2 or more coats of Antitermite treatment paint and fixng the frames with suitable 3 Nos. M.S. holdfasts each side made out of 40 x 5 mm flat iron 230 mm long with bolts and nuts/ dash fasteners for RCC surfaces, duly embedded in C.C. Blocks of required size in (1:2:4 ) 1 cement : 2 coarse sand : 4 stone aggregate 20 mm nominal size) including tarring the hold fast etc.all complete as per direction of EIC. (Finished size to be confirmed by client before procurement) (Sample of wood shall be get approved by client before procurement) | C99: CUM | D99: 50 | E99: 79000 | F99: =$D99*E99 -> 3950000 | I99: =J99-H99 -> 0 | L99: =M99-K99 -> 0 | M99: =E99*J99 -> 0 | N99: =J99/D99 -> 0
B100: Total of Wood Work | F100: =SUBTOTAL(9,F99) -> 3950000
A102: 9 | B102: WATERPROOFING
B103: TERRACE WATERPROOFING:
A104: 1 | B104: Providing and laying 120 mm average thickness of brick bat Coba and 65 mm at Khurra on Terrace through an approved agency, approved by the Architect as per steps given. (a) Surface Preparation, Cleaning the mother slab, reapir of joints, Providing and applying URP with cement slurry as primer to fill all the pores etc on mother slab over primer Providing and applying two coats of Fast Flex @ 2kg/Sqm including sandwiching the layer with fiber mesh of 45 GSM between two layers. (It shall also be execute up to 300 mm height of wall) (b) laying cement concrete using broken bricks/ brick bats of size 25 mm to 100 mm size with 50 % of cement mortar 1:5 ( 1 cement : 5 coarse sand) admixed with proprietary water proofing compound conforming to IS:2645 over 20 mm thick layer of cement mortar of mix 1:5 ( 1 cement : 5 coarse sand) admixed with admixed with proprietary water proofing compound conforming to IS:2645 to required slope and treating similarly the adjoining wall upto 300 mm height including rounding of junctions of wall and slabs. (c) After two days of proper curing applying a second coat of cement slurry admixed with proprietary water proofing compound conforming to IS:2645 (d) Finishing the surface with 20 mm thick jointless cement mortar of mix 1:4 (1 cement : 4 coarse sand) admixed with proprietary water proofing compound conforming to IS:2645 and finally finishing the surface with trowel with neat cement slurry and making 300X300 mm square. (e) The whole terrace so finished sshall be looded with water for a minimum period of two weeks for curing and for final test. All above operations to be done in order and as directed and specified by the engineer in charge. With average thickness of 100 mm thickness and minimum thickness at khurra as 65 mm. | C104: SQM | D104: 1000 | E104: 1150 | F104: =$D104*E104 -> 1150000 | I104: =J104-H104 -> 0 | L104: =M104-K104 -> 0 | M104: =E104*J104 -> 0 | N104: =J104/D104 -> 0
B105: Providing gola in 1: 2: 4 cement concrete with 12 mm nominal size stone ballast, finished with cement plaster 1:2 (1 cement: 2 medium sand) laid, cured complete as per design. (Approx. Size 100mm x 100mm) Making khurras 450 x 450 mm with average min. thk. Of 50 mm over PVCsheet of 1m x 1m x 400 micron with cement concrete 1:2:4 (1 cement: 2 coarse sand: 4 graded stone aggregate of 12 mm nominal size) finished with 12 mm cement plaster 1:3 (1 cement: 3 coarse sand) and a coat of neat cement, rounding the edges, making and finishing complete. (Only plan area shall be paid).
B106: Total of Waterproofing Work | F106: =SUBTOTAL(9,F104:F105) -> 1150000
B109: Grand Total (Excluding GST) | F109: =SUBTOTAL(9,F8:F106) -> 162074375 | H109: =SUM(H9:H108) -> 12528.794 | I109: =SUM(I9:I108) -> 1572.8793 | J109: =SUM(J9:J108) -> 14101.673 | K109: =SUM(K9:K108) -> 16826127 | L109: =SUM(L9:L108) -> 2015626 | M109: =SUM(M9:M108) -> 18841753
M112: =158*80000 -> 12640000
M113: =+M112+M109 -> 31481753
M114: =+M113/10000000 -> 3.1481753

Sheet APP. BASIC RATE
A2: TOWER-E RMC APPROVED RATE LIST
A3: S.NO. | B3: DATE | C3: RMC PLANT NAME | D3: UNIT | E3: GRADE OF CONCRTE WITH CEMENT | J3: GRADE OF CONCRTE WITHOUT CEMENT | O3: REMARKS
E4: M10 | F4: M25 | G4: M30 | H4: M35 | I4: M40 | J4: M10 | K4: M25 | L4: M30 | M4: M35 | N4: M40
A5: 1 | B5: 45796 | C5: SHUBHAM RMC | D5: CUM | E5: 4400 | F5: 5100 | G5: 5300 | H5: 5500 | J5: 3300 | K5: 3300 | L5: 3300 | M5: 3300
A6: 2 | C6: SRIJAN INFRA | D6: CUM | E6: 4600 | F6: 5300 | G6: 5550 | H6: 5700 | J6: 3450 | K6: 3450 | L6: 3400 | M6: 3400
A9: 1 | B9: 45964 | C9: SHUBHAM RMC | D9: CUM | H9: 5200 | I9: 5300
A10: 2 | C10: ULTRATECH | D10: CUM | H10: 5300 | I10: 5500
A12: 1 | B12: 45978 | C12: SHUBHAM RMC | D12: CUM | E12: 4400 | F12: 4950
A13: 2 | C13: ULTRATECH | D13: CUM | E13: 4500 | F13: 5100

Sheet RMC BASIC RATE DIFF
A1: M/s. MARCO ENTERPRISES : RMC BASIC RATE DIFF. AT OMAXE ANANDA TOWER-E -PRAYAGRAJ
A2: SN | B2: DATE | C2: RMC SUPPLIER | D2: MATERIAL GRADE | E2: UNIT | F2: QTY | G2: BASIC RATE | H2: APPROVED RATE | I2: DIFF. IN RATE | J2: DIFF. AMOUNT | K2: REMARKS
A3: 1 | B3: 45791 | C3: ELSA | D3: M10 | E3: CUM | F3: 3.3 | G3: 4200 | H3: 4400 | I3: =H3-G3 -> 200 | J3: =F3*I3 -> 660
A4: 2 | B4: 45797 | C4: ELSA | D4: M10 | E4: CUM | F4: 5.4 | G4: 4200 | H4: 4400 | I4: =H4-G4 -> 200 | J4: =F4*I4 -> 1080
A5: 3 | B5: 45786 | C5: SHUBHAM | D5: M10 | E5: CUM | F5: 40 | G5: 4200 | H5: 4400 | I5: =H5-G5 -> 200 | J5: =F5*I5 -> 8000
A6: 4 | B6: 45789 | C6: SHUBHAM | D6: M10 | E6: CUM | F6: 17.5 | G6: 4200 | H6: 4400 | I6: =H6-G6 -> 200 | J6: =F6*I6 -> 3500
A7: 5 | B7: 45802 | C7: SHUBHAM | D7: M10 | E7: CUM | F7: 7.2 | G7: 4200 | H7: 4400 | I7: =H7-G7 -> 200 | J7: =F7*I7 -> 1440
A8: 6 | B8: 45803 | C8: SHUBHAM | D8: M10 | E8: CUM | F8: 10 | G8: 4200 | H8: 4400 | I8: =H8-G8 -> 200 | J8: =F8*I8 -> 2000
A9: 7 | B9: 45806 | C9: SHUBHAM | D9: M25 | E9: CUM | F9: 35 | G9: 5200 | H9: 5100 | I9: =H9-G9 -> -100 | J9: =F9*I9 -> -3500
A10: 8 | B10: 45806 | C10: ULTRATECH | D10: M25 | E10: CUM | F10: 35 | G10: 5200 | H10: 5300 | I10: =H10-G10 -> 100 | J10: =F10*I10 -> 3500
A11: 9 | B11: 45806 | C11: SHUBHAM | D11: M25 | E11: CUM | F11: 273 | G11: 5200 | H11: 5100 | I11: =H11-G11 -> -100 | J11: =F11*I11 -> -27300
A12: 10 | B12: 45807 | C12: ULTRATECH | D12: M25 | E12: CUM | F12: 56 | G12: 5200 | H12: 5300 | I12: =H12-G12 -> 100 | J12: =F12*I12 -> 5600
A13: 11 | B13: 45808 | C13: SHUBHAM | D13: M25 | E13: CUM | F13: 182 | G13: 5200 | H13: 5100 | I13: =H13-G13 -> -100 | J13: =F13*I13 -> -18200
A14: 12 | B14: 45808 | C14: ULTRATECH | D14: M25 | E14: CUM | F14: 182 | G14: 5200 | H14: 5300 | I14: =H14-G14 -> 100 | J14: =F14*I14 -> 18200
... A74: 72 | B74: 46009 | C74: ELSA | D74: M25 | E74: CUM | F74: 1 | G74: 5200 | H74: 4950 | I74: =H74-G74 -> -250 | J74: =F74*I74 -> -250
A75: 73 | B75: 18.12.2025 | C75: SHUBHAM | D75: M40 | E75: CUM | F75: 2 | G75: 5200 | H75: 5300 | I75: =H75-G75 -> 100 | J75: =F75*I75 -> 200
A76: 74 | B76: 19.12.2025 | C76: SHUBHAM | D76: M40 | E76: CUM | F76: 3 | G76: 5200 | H76: 5300 | I76: =H76-G76 -> 100 | J76: =F76*I76 -> 300
A77: 75 | B77: 20.12.2025 | C77: SHUBHAM | D77: M40 | E77: CUM | F77: 3 | G77: 5200 | H77: 5300 | I77: =H77-G77 -> 100 | J77: =F77*I77 -> 300
A78: 76 | B78: 20.12.2025 | C78: SHUBHAM | D78: M40 | E78: CUM | F78: 3.5 | G78: 5200 | H78: 5300 | I78: =H78-G78 -> 100 | J78: =F78*I78 -> 350
A79: 77 | B79: 21.12.2025 | C79: SHUBHAM | D79: M40 | E79: CUM | F79: 3 | G79: 5200 | H79: 5300 | I79: =H79-G79 -> 100 | J79: =F79*I79 -> 300
A80: 78 | B80: 21.12.2025 | C80: SHUBHAM | D80: M40 | E80: CUM | F80: 3 | G80: 5200 | H80: 5300 | I80: =H80-G80 -> 100 | J80: =F80*I80 -> 300
A81: 79 | B81: 23.12.2025 | C81: SHUBHAM | D81: M40 | E81: CUM | F81: 3 | G81: 5200 | H81: 5300 | I81: =H81-G81 -> 100 | J81: =F81*I81 -> 300
A82: 80 | B82: 25.12.2025 | C82: SHUBHAM | D82: M40 | E82: CUM | F82: 3 | G82: 5200 | H82: 5300 | I82: =H82-G82 -> 100 | J82: =F82*I82 -> 300
A83: 81 | B83: 25.12.2025 | C83: SHUBHAM | D83: M40 | E83: CUM | F83: 2.5 | G83: 5200 | H83: 5300 | I83: =H83-G83 -> 100 | J83: =F83*I83 -> 250
A84: 82 | B84: 26.12.2025 | C84: SHUBHAM | D84: M40 | E84: CUM | F84: 3 | G84: 5200 | H84: 5300 | I84: =H84-G84 -> 100 | J84: =F84*I84 -> 300
A85: 83 | B85: 29.12.2025 | C85: SHUBHAM | D85: M40 | E85: CUM | F85: 3 | G85: 5200 | H85: 5300 | I85: =H85-G85 -> 100 | J85: =F85*I85 -> 300
A86: 84 | B86: 31.12.2025 | C86: SHUBHAM | D86: M40 | E86: CUM | F86: 3.5 | G86: 5200 | H86: 5300 | I86: =H86-G86 -> 100 | J86: =F86*I86 -> 350
... A99: 97 | B99: 31.01.2026 | C99: SHUBHAM | D99: M25 | E99: CUM | F99: 28 | G99: 5200 | H99: 4950 | I99: =H99-G99 -> -250 | J99: =F99*I99 -> -7000
B102: Total Qty upto date | F102: =SUM(F3:F101) -> 2113.46 | J102: =SUM(J3:J101) -> 340

Sheet EARTH WORK MB
A1: COMPANY- OMAXE PANCHAM REALCON PVT LTD
A2: PROJECT- TOWER-E
A3: LOCATION- NAINI, PRAYAGRAJ
A4: MB SHEET- SOIL SURFACE DRESSING BELOW PLINTH BEAM
B5: & SOIL BACK FILLING WORK
A6: S.NO. | B6: DESCRIPTION | C6: UNIT | D6: NOS | E6: NOS | F6: MEASUREMENT | I6: QTY. | J6: REMARKS
F7: L | G7: B | H7: H/T
B8: SOIL DRESSING FOR RAFT PCC
A9: 1 | B9: GRID (22'-43'/A-Q') | C9: SQM | D9: 1 | E9: 1 | F9: =31.935+0.115+0.115+0.1+0.1 -> 32.365 | G9: =36.895+0.115+0.1+0.115+0.1 -> 37.325 | I9: =PRODUCT(D9:H9) -> 1208.0236 | J9: 3RD RA
A10: 2 | C10: SQM | D10: 1 | E10: 1 | F10: =8.78+0.115+0.115+0.1+0.1 -> 9.21 | G10: 0.515 | I10: =PRODUCT(D10:H10) -> 4.74315
A11: 3 | B11: GRID (22'-26'/M'-Q') | C11: SQM | D11: -1 | E11: 1 | F11: 11.005 | G11: 12.415 | I11: =PRODUCT(D11:H11) -> -136.62707
A12: 4 | B12: GRID (38'-43'/A-E') | C12: SQM | D12: -1 | E12: 1 | F12: 11.09 | G12: 10.285 | I12: =PRODUCT(D12:H12) -> -114.06065
A13: 5 | B13: GRID (22'-30'/A-B') | C13: SQM | D13: -1 | E13: 1 | F13: 11.285 | G13: =1.405+0.815+1.5 -> 3.72 | I13: =PRODUCT(D13:H13) -> -41.9802
A14: 6 | C14: SQM | D14: -1 | E14: 1 | F14: 1.695 | G14: =0.815+1.5 -> 2.315 | I14: =PRODUCT(D14:H14) -> -3.923925
A15: 7 | C15: SQM | D15: -1 | E15: 1 | F15: 3.95 | G15: 1.5 | I15: =PRODUCT(D15:H15) -> -5.925
A16: 8 | C16: SQM | D16: -1 | E16: 1 | F16: 15.8 | G16: =0.115+0.1 -> 0.215 | I16: =PRODUCT(D16:H16) -> -3.397
A17: 1 | B17: GRID (1-22'/A-Q') | C17: SQM | D17: 1 | E17: 1 | F17: =31.935+0.115+0.115+0.1+0.1 -> 32.365 | G17: =40.165+0.9+0.115+0.1+0.115+0.1 -> 41.495 | I17: =PRODUCT(D17:H17) -> 1342.9857 | J17: 4TH RA
A18: 2 | C18: SQM | D18: 1 | E18: 1 | F18: =8.78+0.115+0.115+0.1+0.1 -> 9.21 | G18: 0.515 | I18: =PRODUCT(D18:H18) -> 4.74315
A19: 3 | B19: GRID (17'-22'/M'-Q') | C19: SQM | D19: -1 | E19: 1 | F19: =14.275+0.9 -> 15.175 | G19: 12.415 | I19: =PRODUCT(D19:H19) -> -188.39763
A20: 4 | B20: GRID (1-5'/A-E') | C20: SQM | D20: -1 | E20: 1 | F20: 11.09 | G20: 10.285 | I20: =PRODUCT(D20:H20) -> -114.06065
A21: 5 | B21: GRID (14'-22'/A-B') | C21: SQM | D21: -1 | E21: 1 | F21: =14.555+0.9 -> 15.455 | G21: =1.405+0.815+1.5 -> 3.72 | I21: =PRODUCT(D21:H21) -> -57.4926
A22: 6 | C22: SQM | D22: -1 | E22: 1 | F22: 1.695 | G22: =0.815+1.5 -> 2.315 | I22: =PRODUCT(D22:H22) -> -3.923925
A23: 7 | C23: SQM | D23: -1 | E23: 1 | F23: 3.95 | G23: 1.5 | I23: =PRODUCT(D23:H23) -> -5.925
A24: 8 | C24: SQM | D24: -1 | E24: 1 | F24: 15.8 | G24: =0.115+0.1 -> 0.215 | I24: =PRODUCT(D24:H24) -> -3.397
B25: FLAT AREA SOIL DRESSING WORK GRID (22-43/A-Q)
J26: 7TH RA
B27: 1 | C27: SQM | D27: 1 | E27: 1 | F27: 5.15 | G27: =3.035+0.115 -> 3.15
B28: 2,3 | C28: SQM | D28: 1 | E28: 2 | F28: 3.17 | G28: 2.41
B29: 2' | C29: SQM | D29: 1 | E29: 1 | F29: 3.55 | G29: 3.17
B30: 4,10 | C30: SQM | D30: 1 | E30: 1 | F30: 5.49 | G30: 3.25
B31: 5,9 | C31: SQM | D31: 1 | E31: 1 | F31: 2.925 | G31: 1.7
B32: 6 | C32: SQM | D32: 1 | E32: 1 | F32: 3.385 | G32: 1.425
B33: 7 | C33: SQM | D33: 1 | E33: 1 | F33: 1.455 | G33: 1.425
B34: 8 | C34: SQM | D34: 1 | E34: 1 | F34: 1.7 | G34: 1.425
B35: 11 | C35: SQM | D35: 1 | E35: 1 | F35: 3.33 | G35: 1.83
C36: SQM | D36: 1 | E36: 1 | F36: 4.27 | G36: 1.93
C37: SQM | D37: 1 | E37: 1 | F37: 7.665 | G37: 3.14
B38: 12 | C38: SQM | D38: 1 | E38: 1 | F38: 4.27 | G38: 1.7
B39: 13 | C39: SQM | D39: 1 | E39: 1 | F39: 1.6 | G39: 1.44
B40: 14 | C40: SQM | D40: 1 | E40: 1 | F40: 1.69 | G40: 1.6
B41: 15,16 | C41: SQM | D41: 1 | E41: 2 | F41: 3.56 | G41: 3.275
B42: 17 | C42: SQM | D42: 1 | E42: 1 | F42: 2.25 | G42: 1.525
B43: 18 | C43: SQM | D43: 1 | E43: 1 | F43: 6.165 | G43: 3.72
C44: SQM | D44: 1 | E44: 1 | F44: 3.915 | G44: 0.385
B45: 19 | C45: SQM | D45: 1 | E45: 1 | F45: 3.55 | G45: 3.2
B46: 20 | C46: SQM | D46: 1 | E46: 1 | F46: 5.35 | G46: 3.575
B47: 21 | C47: SQM | D47: 1 | E47: 1 | F47: 2.815 | G47: 1.8
C48: SQM | D48: 1 | E48: 1 | F48: 4.945 | G48: 2.1
C49: SQM | D49: 1 | E49: 1 | F49: 3.115 | G49: 0.95
B50: 22 | C50: SQM | D50: 1 | E50: 1 | F50: 5.935 | G50: 2.345
C51: SQM | D51: -1 | E51: 1 | F51: 1.3 | G51: 0.5
C52: SQM | D52: 1 | E52: 1 | F52: 2.03 | G52: 1.5
B53: 23 | C53: SQM | D53: 1 | E53: 1 | F53: 5.7 | G53: 3.2
B54: 24 | C54: SQM | D54: 1 | E54: 1 | F54: 3.95 | G54: 1.61
C55: SQM | D55: 1 | E55: 1 | F55: 1.92 | G55: 1.5
B56: 25 | C56: SQM | D56: 1 | E56: 1 | F56: 2.225 | G56: 1.495
B57: 26 | C57: SQM | D57: 1 | E57: 1 | F57: 3.95 | G57: 3.845
B58: 27 | C58: SQM | D58: 1 | E58: 1 | F58: 5.72 | G58: 2.44
C59: SQM | D59: 1 | E59: 1 | F59: 1.2 | G59: 0.35
B60: 28 | C60: SQM | D60: 1 | E60: 1 | F60: 3.23 | G60: 3.075
C61: SQM | D61: 1 | E61: 1 | F61: 5.14 | G61: 3.17
B62: 29 | C62: SQM | D62: 1 | E62: 1 | F62: 3.86 | G62: 3.335
B63: 30 | C63: SQM | D63: 1 | E63: 1 | F63: 4.92 | G63: 3.86
B64: 31 | C64: SQM | D64: 1 | E64: 1 | F64: 3.55 | G64: 3.265
B65: 32 | C65: SQM | D65: 1 | E65: 1 | F65: 3.52 | G65: 3.08
B66: 33 | C66: SQM | D66: 1 | E66: 1 | F66: 3.435 | G66: 2.345
B67: 34 | C67: SQM | D67: 1 | E67: 1 | F67: 3.435 | G67: 2.245
B68: 35 | C68: SQM | D68: 1 | E68: 1 | F68: 4.79 | G68: 3.19
C69: SQM | D69: 1 | E69: 1 | F69: 1.4 | G69: 0.655
B70: 36 | C70: SQM | D70: 1 | E70: 1 | F70: 3.475 | G70: 2.23
B71: 37,42 | C71: SQM | D71: 1 | E71: 2 | F71: 3.55 | G71: 3.265
B72: 38,41 | C72: SQM | D72: 1 | E72: 2 | F72: 3.55 | G72: 3.08
B73: 39,40 | C73: SQM | D73: 1 | E73: 2 | F73: 5.15 | G73: 3.27
C74: SQM | D74: 1 | E74: 2 | F74: 3.24 | G74: 3.075
B75: 43.46 | C75: SQM | D75: 1 | E75: 2 | F75: 4.92 | G75: 3.86
B76: 44,45 | C76: SQM | D76: 1 | E76: 2 | F76: 3.86 | G76: 3.335
H78: TOTAL | I78: =SUM(I8:I77) -> 1881.385
B80: SOIL BACK FILLING GRID (1-43/A-Q)
B81: BACK FILLING | C81: SQM | D81: 1 | E81: 1 | F81: 2463.03 | H81: 2.65 | I81: =+PRODUCT(D81:H81) -> 6527.0295 | K81: Upto Road LVL. (HT From JK Bill)
B82: DED. PCC | C82: SQM | D82: -1 | E82: 1 | F82: 1851.82 | H82: 0.1 | I82: =+PRODUCT(D82:H82) -> -185.182
B83: DED. RAFT RCC | C83: SQM | D83: -1 | E83: 1 | H83: ='CONCRETE RECO.'!F7+'CONCRETE RECO.'!F9+'CONCRETE RECO.'!F10 -> 1552.4224 | I83: =+PRODUCT(D83:H83) -> -1552.4224
B84: DED. PADESTIAL RCC | C84: SQM | D84: -1 | E84: 1 | H84: ='CONCRETE RECO.'!F11 -> 64.025912 | I84: =+PRODUCT(D84:H84) -> -64.025912
H86: TOTAL | I86: =SUM(I81:I85) -> 4725.3991

Sheet CONCRETE SUMMARY
A2: TOWER-E CONCRETE WORK SUMMARY
D3: QTY | M3: TOTAL
A4: 2 | B4: CONCRETE WORK | D4: 3rd RA | E4: 4th RA | F4: 5th RA | G4: 6th RA | H4: 7th RA | I4: 8th RA | J4: 9th RA
B5: Rates for all cement concrete items plain and reinforced described below shall include work from Basement Level to top of last roof including roof of machine room, mumty, over head water tanks and parapets above at all floors and for all heights. The contractor should provide full time sufficient pipes with accessories and pumps based on the site requirement for pumping and laying of concrete as directed by the EIC. The rate inclusive of standard rigid pipe line and its supports, lifting, laying charges, etc., at all heights and levels. No additional payment shall be payable to the contractor on account of using or change in any size of coarse aggregate in PCC/ RCC work at any stage during currency of works. (This section covers cast in situ structural and architectural as well.)
A6: 2.1 | B6: Plain Cement Concrete: Providing and laying plain cement concrete of specified grade as bed concrete under foundation, bases for rafts, underground water tank, building machine equipments, column footing, under floor landings, below road and pathways, cill, coping, screeding at roof to required slope and other locations as called for laid, consolidated and cured etc. complete including finishing the top surface to receive the next course / layer as per specification and drawing. (Shuttering shall be paid in Item No.3.1.1) M10 Grade (Basic Rate of PCC - Rs. 4200/cum) without pump | C6: CUM | D6: 56.798193 | E6: 22.668463 | M6: =SUM(D6:L6) -> 79.466655
A7: 2.2. | B7: Providing and laying cement concrete 1:2:4 (1 cement : 2 coarse sand : 4 graded stone aggregate 20mm nominal size) for ledge wall below balcony railings, band, mullion, lintel etc. (Shuttering shall be paid separately in respective item) as per drawing and as directed by the Project Manager. | C7: CUM | M7: =SUM(D7:L7) -> 0
A8: 2.3. | B8: Providing and laying damp proof course 40mm thick including shttering with cement concrete 1:2:4 (1 cement : 2 coarse sand : 4 graded stone aggregate 20mm nominal size) including mixing of water proofing compound @ 2% of cement content and applying two layers of bitumen @ 1.70 Kg/Sqm of grade 85/25 and as directed by the Project Manager. | C8: SQM | M8: =SUM(D8:L8) -> 0
A10: 2.4. | B10: RCC WORK
B11: Providing & Laying RMC M-25 Grade as per approved design mix concrete (strictly controlled conditions) with flyash (as per approved design mix) with automatic batching plant machine mixed and machine vibrated RCC with melamine based plasticisers etc., upto any level, including finishing the exposed surface, fixing/ removal of pockets, fixing of sleeves and inserts (sleeves provided by client), curing etc complete, as per drawing (including all size and shape like circular, semi-circular, oval etc.) and as directed for all lead and lift, excluding cost of centering, shuttering and steel reinforcement but including cost of making shear keys and provision of construction / contraction / control joints in various locations. Checking from Client should not be considered as final and any defects arising during or after casting should be borne & bear by contractor at his own cost. This is inclusive of leaving shuttering & centring for pour strip, slab in slope, RCC members in curved, etc., nothing is payable extra on this account. RMC (M-25) Basic Rate - Rs. 5200/cum without pump excluding GST
A12: 2.4.1. | B12: Foundation, column footings, raft slab, raft beams, plinth beam, lift pits, sump pits, pedestals / bases of column, column upto plinth, swimming pool, Retaining wall foundations, grade slab etc. | C12: CUM | D12: 748.20967 | E12: 792.12577 | F12: 76.112912 | H12: 70.098772 | M12: =SUM(D12:L12) -> 1686.5471
A13: 2.4.2. | B13: Suspended floors, roofs, balconies, shelves/ counters, stair waist slabs, folded plate stairs and landings, swimming pool slab, lintel and floor beams, landing beams, girders (deep beams), RCC bands, swimming pool beam, cantilever projections, coping, cills, slab of tank etc at all levels.
A14: 2.4.2.1. | B14: Stilt Floor level to 7th Floor level | C14: CUM | I14: =+'CONCRETE WORK MB'!I478 -> 153.7933 | J14: ='CONCRETE WORK MB'!I698 -> 153.7933 | M14: =SUM(D14:L14) -> 307.58661
A15: 2.4.2.2. | B15: 7th Floor level to to Terrace Including OHT, Mumty, Machine Room, Parapet | C15: CUM | M15: =SUM(D15:L15) -> 0
A16: 2.4.2.3. | B16: All type of Moulding, Bands, Elevation/Architectural Features as per drawing and as directed by EIC. at all level | C16: CUM | M16: =SUM(D16:L16) -> 0
A18: 2.5. | B18: Columns, Wall, pillars, piers, abutments, posts and struts, offset and projection of columns, water tank walls, lift walls, Retaining Wall, swimming pool, Parapets, planters, vertical projection of pergolas, wall and ramp walls etc. at all levels.
A19: 2.5.1. | B19: Stilt Floor level to 7th Floor level | C19: CUM | H19: 48.0455 | I19: =+'CONCRETE WORK MB'!I260*0.9+'CONCRETE WORK MB'!I243*0.9 -> 45.828882 | M19: =SUM(D19:L19) -> 93.874382
A20: 2.5.2. | B20: 7th Floor level to to Terrace Including OHT, Mumty, Machine Room, Parapet | C20: CUM | M20: =SUM(D20:L20) -> 0
A21: 2.5.3. | B21: All type of Moulding, Bands, Elevation/Architectural Features as per drawing and as directed by EIC. at all level | C21: CUM | M21: =SUM(D21:L21) -> 0
A22: 2.5.4. | B22: Finishing vaccum dewatering continuous concrete flooring 100-150 mm thick with specified grade concrete including necessary formwork in required level, vibrating concrete both by poker vibrators / leveling vaccum processing of the concrete and planning the surface by skin powered floater trowels with broom/plain finish including groove cutting & filling etc. complete. (Concrete shall be paid in the respective items above). | C22: SQM | M22: =SUM(D22:L22) -> 0
D24: =SUM(D5:D23) -> 805.00787 | E24: =SUM(E5:E23) -> 814.79424 | F24: =SUM(F5:F23) -> 76.112912 | G24: =SUM(G5:G23) -> 0 | H24: =SUM(H5:H23) -> 118.14427 | I24: =SUM(I5:I23) -> 199.62219 | J24: =SUM(J5:J23) -> 153.7933 | K24: =SUM(K5:K23) -> 0 | L24: TOTAL | M24: =SUM(M5:M23) -> 2167.4748

Sheet CONCRETE RECO.
B1: RCC SUMMARY : OMAXE TOWER-E
B2: M/s. MARCO ENTERPRISES
A3: S.No. | B3: Item Discription | C3: Grade | D3: Floor Name | E3: NO | F3: Unit Qty. | G3: Quantity | H3: Unit | I3: M10 | J3: M25 | K3: M30 | L3: M35 | M3: M40
B4: TOWER-E
A6: 1 | B6: RAFT PCC GRID (A-Q/23-43) | C6: M10 | D6: AS SUB-STRUCTURE | E6: 1 | F6: ='CONCRETE WORK MB'!I22 -> 56.798193 | G6: =E6*F6 -> 56.798193 | H6: Cum | I6: =IF(I$3=$C6,$G6,"-") -> 56.798193 | J6: =IF(J$3=$C6,$G6,"-") -> - | K6: =IF(K$3=$C6,$G6,"-") -> - | L6: =IF(L$3=$C6,$G6,"-") -> - | M6: =IF(M$3=$C6,$G6,"-") -> -
A7: 2 | B7: RAFT RCC GRID (A-Q/23-43) | C7: M25 | D7: AS SUB-STRUCTURE | E7: =E6 -> 1 | F7: ='CONCRETE WORK MB'!I47 -> 748.20967 | G7: =E7*F7 -> 748.20967 | H7: Cum | I7: =IF(I$3=$C7,$G7,"-") -> - | J7: =IF(J$3=$C7,$G7,"-") -> 748.20967 | K7: =IF(K$3=$C7,$G7,"-") -> - | L7: =IF(L$3=$C7,$G7,"-") -> - | M7: =IF(M$3=$C7,$G7,"-") -> -
A8: 3 | B8: RAFT PCC GRID (A-Q/1-23) | C8: M10 | D8: AS SUB-STRUCTURE | E8: 1 | F8: ='CONCRETE WORK MB'!I34 -> 22.668463 | G8: =E8*F8 -> 22.668463 | H8: Cum | I8: =IF(I$3=$C8,$G8,"-") -> 22.668463 | J8: =IF(J$3=$C8,$G8,"-") -> - | K8: =IF(K$3=$C8,$G8,"-") -> - | L8: =IF(L$3=$C8,$G8,"-") -> - | M8: =IF(M$3=$C8,$G8,"-") -> -
A9: 4 | B9: RAFT RCC GRID (A-Q/1-43) | C9: M25 | D9: AS SUB-STRUCTURE | E9: =E8 -> 1 | F9: ='CONCRETE WORK MB'!I56 -> 792.12577 | G9: =E9*F9 -> 792.12577 | H9: Cum | I9: =IF(I$3=$C9,$G9,"-") -> - | J9: =IF(J$3=$C9,$G9,"-") -> 792.12577 | K9: =IF(K$3=$C9,$G9,"-") -> - | L9: =IF(L$3=$C9,$G9,"-") -> - | M9: =IF(M$3=$C9,$G9,"-") -> -
A10: 5 | B10: COMPENSATORY STRIP (22-23/B'-L') | C10: M25 | D10: AS SUB-STRUCTURE | E10: =E9 -> 1 | F10: ='CONCRETE WORK MB'!I60 -> 12.087 | G10: =E10*F10 -> 12.087 | H10: Cum | I10: =IF(I$3=$C10,$G10,"-") -> - | J10: =IF(J$3=$C10,$G10,"-") -> 12.087 | K10: =IF(K$3=$C10,$G10,"-") -> - | L10: =IF(L$3=$C10,$G10,"-") -> - | M10: =IF(M$3=$C10,$G10,"-") -> -
A11: 6 | B11: PADESTIAL & LIFT (1-43/A-Q) | C11: M35 | D11: AS SUB-STRUCTURE | E11: =E10 -> 1 | F11: ='CONCRETE WORK MB'!I93 -> 64.025912 | G11: =E11*F11 -> 64.025912 | H11: Cum | I11: =IF(I$3=$C11,$G11,"-") -> - | J11: =IF(J$3=$C11,$G11,"-") -> - | K11: =IF(K$3=$C11,$G11,"-") -> - | L11: =IF(L$3=$C11,$G11,"-") -> 64.025912 | M11: =IF(M$3=$C11,$G11,"-") -> -
A12: 7 | B12: PLINTH BEAM (1-43/A-Q) | C12: M25 | D12: AS SUB-STRUCTURE | E12: =E11 -> 1 | F12: ='CONCRETE WORK MB'!I168 -> 51.601792 | G12: =E12*F12 -> 51.601792 | H12: Cum | I12: =IF(I$3=$C12,$G12,"-") -> - | J12: =IF(J$3=$C12,$G12,"-") -> 51.601792 | K12: =IF(K$3=$C12,$G12,"-") -> - | L12: =IF(L$3=$C12,$G12,"-") -> - | M12: =IF(M$3=$C12,$G12,"-") -> -
A13: 8 | B13: COLUMN JUNCTION AT PLINTH BEAM LVL (1-43/A-Q) | C13: M35 | D13: AS SUB-STRUCTURE | E13: =E12 -> 1 | F13: 14 | G13: =E13*F13 -> 14 | H13: Cum | I13: =IF(I$3=$C13,$G13,"-") -> - | J13: =IF(J$3=$C13,$G13,"-") -> - | K13: =IF(K$3=$C13,$G13,"-") -> - | L13: =IF(L$3=$C13,$G13,"-") -> 14 | M13: =IF(M$3=$C13,$G13,"-") -> -
A14: 9 | B14: COLUMN JUNCTION AT PLINTH BEAM LVL (1-43/A-Q) | C14: M40 | D14: AS SUB-STRUCTURE | E14: =E13 -> 1 | F14: ='CONCRETE WORK MB'!I193-F13 -> 4.49698 | G14: =E14*F14 -> 4.49698 | H14: Cum | I14: =IF(I$3=$C14,$G14,"-") -> - | J14: =IF(J$3=$C14,$G14,"-") -> - | K14: =IF(K$3=$C14,$G14,"-") -> - | L14: =IF(L$3=$C14,$G14,"-") -> - | M14: =IF(M$3=$C14,$G14,"-") -> 4.49698
A15: 10 | B15: COLUMN FROM PLINTH BEAM LVL TO 1ST FLOOR LVL (22-43/A-Q) | C15: M40 | D15: AS SUPER-STRUCTURE | E15: =E13 -> 1 | F15: ='CONCRETE WORK MB'!I217 -> 48.0455 | G15: =E15*F15 -> 48.0455 | H15: Cum | I15: =IF(I$3=$C15,$G15,"-") -> - | J15: =IF(J$3=$C15,$G15,"-") -> - | K15: =IF(K$3=$C15,$G15,"-") -> - | L15: =IF(L$3=$C15,$G15,"-") -> - | M15: =IF(M$3=$C15,$G15,"-") -> 48.0455
A16: 11 | B16: COLUMN FROM PLINTH BEAM LVL TO 1ST FLOOR LVL (1-22/A-Q) | C16: M40 | D16: AS SUPER-STRUCTURE | E16: =E14 -> 1 | F16: ='CONCRETE WORK MB'!I243 -> 45.9755 | G16: =E16*F16 -> 45.9755 | H16: Cum | I16: =IF(I$3=$C16,$G16,"-") -> - | J16: =IF(J$3=$C16,$G16,"-") -> - | K16: =IF(K$3=$C16,$G16,"-") -> - | L16: =IF(L$3=$C16,$G16,"-") -> - | M16: =IF(M$3=$C16,$G16,"-") -> 45.9755
A17: 12 | B17: EXTRA HEIGHT COLUMN FROM PLINTH BEAM LVL TO 1ST FLOOR LVL (1-43/A-Q) | C17: M40 | D17: AS SUPER-STRUCTURE | E17: =E15 -> 1 | F17: ='CONCRETE WORK MB'!I260 -> 4.94548 | G17: =E17*F17 -> 4.94548 | H17: Cum | I17: =IF(I$3=$C17,$G17,"-") -> - | J17: =IF(J$3=$C17,$G17,"-") -> - | K17: =IF(K$3=$C17,$G17,"-") -> - | L17: =IF(L$3=$C17,$G17,"-") -> - | M17: =IF(M$3=$C17,$G17,"-") -> 4.94548
A18: 13 | B18: SLAB AT GROUND FLOOR LVL (22-43/A-Q) | C18: M40 | D18: AS SUPER-STRUCTURE | E18: =E15 -> 1 | F18: 24 | G18: =E18*F18 -> 24 | H18: Cum | I18: =IF(I$3=$C18,$G18,"-") -> - | J18: =IF(J$3=$C18,$G18,"-") -> - | K18: =IF(K$3=$C18,$G18,"-") -> - | L18: =IF(L$3=$C18,$G18,"-") -> - | M18: =IF(M$3=$C18,$G18,"-") -> 24
A19: 14 | B19: SLAB AT GROUND FLOOR LVL (22-43/A-Q) | C19: M25 | D19: AS SUPER-STRUCTURE | E19: =E16 -> 1 | F19: ='CONCRETE WORK MB'!I478-F18 -> 129.7933 | G19: =E19*F19 -> 129.7933 | H19: Cum | I19: =IF(I$3=$C19,$G19,"-") -> - | J19: =IF(J$3=$C19,$G19,"-") -> 129.7933 | K19: =IF(K$3=$C19,$G19,"-") -> - | L19: =IF(L$3=$C19,$G19,"-") -> - | M19: =IF(M$3=$C19,$G19,"-") -> -
A20: 14 | B20: SLAB AT GROUND FLOOR LVL (1-22/A-Q) | C20: M40 | D20: AS SUPER-STRUCTURE | E20: =E17 -> 1 | F20: 15 | G20: =E20*F20 -> 15 | H20: Cum | I20: =IF(I$3=$C20,$G20,"-") -> - | J20: =IF(J$3=$C20,$G20,"-") -> - | K20: =IF(K$3=$C20,$G20,"-") -> - | L20: =IF(L$3=$C20,$G20,"-") -> - | M20: =IF(M$3=$C20,$G20,"-") -> 15
A21: 15 | B21: SLAB AT GROUND FLOOR LVL (1-22/A-Q) | C21: M25 | D21: AS SUPER-STRUCTURE | E21: =E17 -> 1 | F21: ='CONCRETE WORK MB'!I698-F20 -> 138.7933 | G21: =E21*F21 -> 138.7933 | H21: Cum | I21: =IF(I$3=$C21,$G21,"-") -> - | J21: =IF(J$3=$C21,$G21,"-") -> 138.7933 | K21: =IF(K$3=$C21,$G21,"-") -> - | L21: =IF(L$3=$C21,$G21,"-") -> - | M21: =IF(M$3=$C21,$G21,"-") -> -
B23: TOTAL RCC QTY (THEORITICAL) | G23: =SUM(G4:G22) -> 2172.5669 | H23: Cum | I23: =SUM(I4:I22) -> 79.466655 | J23: =SUM(J4:J22) -> 1872.6108 | K23: =SUM(K4:K22) -> 0 | L23: =SUM(L4:L22) -> 78.025912 | M23: =SUM(M4:M22) -> 142.46346
B24: TOTAL RCC QTY (CASTING) | G24: ='PCC & RCC REC.'!T96 -> 2232.46 | H24: Cum | I24: ='PCC & RCC REC.'!D98+'PCC & RCC REC.'!I98+'PCC & RCC REC.'!N98 -> 83.4 | J24: ='PCC & RCC REC.'!E98+'PCC & RCC REC.'!J98+'PCC & RCC REC.'!O98 -> 1910.06 | K24: ='PCC & RCC REC.'!F98+'PCC & RCC REC.'!K98+'PCC & RCC REC.'!P98 -> 0 | L24: ='PCC & RCC REC.'!G98+'PCC & RCC REC.'!L98+'PCC & RCC REC.'!Q98 -> 82 | M24: ='PCC & RCC REC.'!H98+'PCC & RCC REC.'!M98+'PCC & RCC REC.'!R98 -> 157
B25: DIFFERENCE (WASTAGE) | G25: =G23-G24 -> -59.893124 | H25: Cum | I25: =I23-I24 -> -3.933345 | J25: =J23-J24 -> -37.449151 | K25: =K23-K24 -> 0 | L25: =L23-L24 -> -3.974088 | M25: =M23-M24 -> -14.53654
B26: WASTAGE % | G26: =G25/G23 -> -0.027567908 | I26: =I25/I23 -> -0.049496798 | J26: =J25/J23 -> -0.019998363 | K26: =K25/K23 -> #DIV/0! | L26: =L25/L23 -> -0.050932926 | M26: =M25/M23 -> -0.10203697
B28: PREV. BILL RCC QTY (THEORITICAL) | G28: =+I28+J28+K28+L28+M28 -> 1814.0567 | H28: Cum | I28: 79.466655 | J28: 1604.02 | K28: 0 | L28: 78.03 | M28: 52.54
B29: PREV. BILL RCC QTY (CASTING-ACTUAL) | G29: =+I29+J29+K29+L29+M29 -> 1857.98 | H29: Cum | I29: 83.4 | J29: 1636.58 | K29: 0 | L29: 82 | M29: 56
B30: DIFFERENCE (WASTAGE) | G30: =G28-G29 -> -43.923345 | H30: Cum | I30: =I28-I29 -> -3.933345 | J30: =J28-J29 -> -32.56 | K30: =K28-K29 -> 0 | L30: =L28-L29 -> -3.97 | M30: =M28-M29 -> -3.46
B31: WASTAGE % | G31: =G30/G28 -> -0.024212775 | I31: =I30/I28 -> -0.049496798 | J31: =J30/J28 -> -0.020298999 | K31: =K30/K28 -> #DIV/0! | L31: =L30/L28 -> -0.050877867 | M31: =M30/M28 -> -0.065854587
B33: THIS BILL RCC QTY (THEORITICAL) | G33: =G23-G28 -> 358.51022 | H33: Cum | I33: =I23-I28 -> 0 | J33: =J23-J28 -> 268.59085 | K33: =K23-K28 -> 0 | L33: =L23-L28 -> -0.004088 | M33: =M23-M28 -> 89.92346
B34: THIS BILL RCC QTY (CASTING-ACTUAL) | G34: =G24-G29 -> 374.48 | H34: Cum | I34: =I24-I29 -> 0 | J34: =J24-J29 -> 273.48 | K34: =K24-K29 -> 0 | L34: =L24-L29 -> 0 | M34: =M24-M29 -> 101
B35: DIFFERENCE (WASTAGE) | G35: =G33-G34 -> -15.969779 | H35: Cum | I35: =I33-I34 -> 0 | J35: =J33-J34 -> -4.8891512 | K35: =K33-K34 -> 0 | L35: =L33-L34 -> -0.004088 | M35: =M33-M34 -> -11.07654
B36: WASTAGE % | G36: =G35/G33 -> -0.044544837 | I36: =I35/I33 -> #DIV/0! | J36: =J35/J33 -> -0.01820297 | K36: =K35/K33 -> #DIV/0! | L36: =L35/L33 -> 1 | M36: =M35/M33 -> -0.12317742

Sheet PCC & RCC REC.
A1: S.NO. | B1: MONTH | C1: DATE | D1: RMC | I1: ELSA | N1: MANUAL | S1: WORK IN PROGRSS | T1: TOTAL | U1: REMARK
D2: GRADE | I2: GRADE | N2: GRADE
D3: M10 | E3: M25 | F3: M30 | G3: M35 | H3: M40 | I3: M10 | J3: M25 | K3: M30 | L3: M35 | M3: M40 | N3: M10 | O3: M25 | P3: M30 | Q3: M35 | R3: M40
A4: 1 | B4: 45778 | C4: 45791 | I4: 3.3 | U4: TOWER-E RAFT PCC
A5: 2 | C5: 45797 | I5: 5.4 | U5: TOWER-E RAFT PCC
A6: 3 | C6: 45786 | D6: 40 | U6: TOWER-E RAFT PCC
A7: 4 | C7: 45789 | D7: 17.5 | U7: TOWER-E RAFT PCC
A8: 5 | C8: 45802 | I8: 7.2 | U8: TOWER-E RAFT PCC
A9: 6 | C9: 45803 | I9: 10 | U9: TOWER-E RAFT PCC
A10: 7 | C10: 45806 | E10: 70 | U10: TOWER-E RAFT RCC (23-43)
A11: 8 | C11: 45807 | E11: 329 | U11: TOWER-E RAFT RCC (23-43)
A12: 9 | C12: 45808 | E12: =357+7 -> 364 | U12: TOWER-E RAFT RCC (23-43)
A13: 10 | B13: 45809 | C13: 45818 | E13: 147 | U13: TOWER-E RAFT RCC (1-23)
A14: 11 | C14: 45819 | E14: 2 | U14: TOWER-E RAFT RCC (1-23)
A15: 12 | C15: 45820 | E15: 154 | U15: TOWER-E RAFT RCC (1-23)
A16: 13 | C16: 45821 | E16: 431 | U16: TOWER-E RAFT RCC (1-23)
A17: 14 | C17: 45822 | E17: 73 | U17: TOWER-E RAFT RCC (1-23)
A18: 15 | C18: 45830 | G18: 3 | U18: TOWER-E PADESTIAL (1-42/A-Q)
A19: 16 | C19: 45831 | G19: 4 | U19: TOWER-E PADESTIAL (1-42/A-Q)
A20: 17 | C20: 45832 | G20: 5 | U20: TOWER-E PADESTIAL (1-42/A-Q)
A21: 18 | C21: 45833 | G21: 5 | U21: TOWER-E PADESTIAL (1-42/A-Q)
A22: 19 | C22: 45834 | G22: 6 | U22: TOWER-E PADESTIAL (1-42/A-Q)
A23: 20 | C23: 45835 | G23: 4 | U23: TOWER-E PADESTIAL (1-42/A-Q)
A24: 21 | C24: 45837 | G24: 3 | U24: TOWER-E PADESTIAL (1-42/A-Q)
A25: 22 | B25: 45839 | C25: 45839 | G25: 8 | U25: TOWER-E PADESTIAL (1-42/A-Q)
A26: 23 | C26: 45840 | G26: 4.5 | U26: TOWER-E PADESTIAL (1-42/A-Q)
A27: 24 | C27: 45842 | G27: 3.5 | U27: TOWER-E PADESTIAL (1-42/A-Q)
A28: 25 | C28: 45843 | G28: 8 | U28: TOWER-E PADESTIAL (1-42/A-Q)
A29: 26 | C29: 45845 | G29: 3 | U29: TOWER-E PADESTIAL (1-42/A-Q)
A30: 27 | C30: 45846 | G30: 4 | U30: TOWER-E PADESTIAL (1-42/A-Q)
A31: 28 | C31: 45846 | E31: 14 | U31: TOWER-E RAFT COMPENSATORY STRIP (22-23/B'-L')
A32: 29 | C32: 45847 | G32: 3.5 | U32: TOWER-E PADESTIAL (1-42/A-Q)
A33: 30 | C33: 45848 | G33: 3.5 | U33: TOWER-E PADESTIAL (1-42/A-Q)
A34: 31 | B34: 45901 | C34: 45925 | G34: 3 | U34: COLUMN JUNCTION AT PLINTH BEAM
A35: 32 | C35: 45925 | E35: 4 | U35: PLINTH BEAM
A36: 33 | C36: 45925 | E36: 4.5 | U36: PLINTH BEAM
A37: 34 | B37: 45931 | C37: 45931 | G37: 3 | U37: COLUMN JUNCTION AT PLINTH BEAM
A38: 35 | C38: 45931 | E38: 4 | U38: PLINTH BEAM
A39: 36 | C39: 45931 | E39: 3.5 | U39: PLINTH BEAM
A40: 37 | C40: 45937 | G40: 3 | U40: COLUMN JUNCTION AT PLINTH BEAM
A41: 38 | C41: 45939 | E41: 4 | U41: PLINTH BEAM
A42: 39 | C42: 45939 | G42: 2 | U42: COLUMN JUNCTION AT PLINTH BEAM
A43: 40 | C43: 45939 | E43: 3 | U43: PLINTH BEAM
A44: 41 | C44: 45940 | E44: 2 | U44: PLINTH BEAM
A45: 42 | C45: 45959 | G45: 3 | U45: COLUMN JUNCTION AT PLINTH BEAM
A46: 43 | C46: 45960 | E46: 4 | U46: PLINTH BEAM
A47: 44 | C47: 45960 | E47: 3.5
A48: 45 | B48: 45962 | C48: 45972 | H48: 2.5 | U48: COLUMN PLINTH BEAM TO 1ST FLOOR LVL
A49: 46 | C49: 45978 | E49: 4 | U49: PLINTH BEAM
A50: 47 | C50: 45978 | H50: 3.5 | U50: COLUMN PLINTH BEAM TO 1ST FLOOR LVL
A51: 48 | C51: 45979 | H51: 4.5 | U51: COLUMN PLINTH BEAM TO 1ST FLOOR LVL
A52: 49 | C52: 45980 | E52: 3 | U52: PLINTH BEAM
A53: 50 | C53: 45980 | H53: 3.5 | U53: COLUMN PLINTH BEAM TO 1ST FLOOR LVL
A54: 51 | C54: 45981 | H54: 3.5 | U54: COLUMN PLINTH BEAM TO 1ST FLOOR LVL
A55: 52 | C55: 45985 | J55: 0.58 | U55: PLINTH BEAM
A56: 53 | C56: 45989 | H56: 3 | U56: COLUMN PLINTH BEAM TO 1ST FLOOR LVL
A57: 54 | C57: 45990 | H57: 7 | U57: COLUMN PLINTH BEAM TO 1ST FLOOR LVL
A58: 55 | C58: 45991 | H58: 3 | U58: COLUMN PLINTH BEAM TO 1ST FLOOR LVL
A59: 56 | B59: 45992 | C59: 45992 | J59: 6.82 | U59: PLINTH BEAM
A60: 57 | C60: 45993 | J60: 0.66 | U60: PLINTH BEAM
A61: 58 | C61: 45993 | H61: 3 | U61: COLUMN PLINTH BEAM TO 1ST FLOOR LVL
A62: 59 | C62: 45993 | H62: 4.5 | U62: COLUMN PLINTH BEAM TO 1ST FLOOR LVL
A63: 60 | C63: 45994 | H63: 6.5 | U63: COLUMN PLINTH BEAM TO 1ST FLOOR LVL
A64: 61 | C64: 45996 | H64: 3 | U64: COLUMN PLINTH BEAM TO 1ST FLOOR LVL
A65: 62 | C65: 45997 | H65: 6 | U65: COLUMN PLINTH BEAM TO 1ST FLOOR LVL
A66: 63 | C66: 45999 | H66: 2.5 | U66: COLUMN PLINTH BEAM TO 1ST FLOOR LVL
A67: 64 | C67: 46000 | E67: 6.5 | U67: PLINTH BEAM
A68: 65 | C68: 46009 | J68: 1 | U68: PLINTH BEAM
A69: 66 | C69: 18.12.2025 | H69: 2 | U69: COLUMN PLINTH BEAM TO 1ST FLOOR LVL
A70: 67 | C70: 19.12.2025 | H70: 3 | U70: COLUMN PLINTH BEAM TO 1ST FLOOR LVL
A71: 68 | C71: 20.12.2025 | H71: 3 | U71: COLUMN PLINTH BEAM TO 1ST FLOOR LVL
A72: 69 | C72: 20.12.2025 | H72: 3.5 | U72: COLUMN PLINTH BEAM TO 1ST FLOOR LVL
A73: 70 | C73: 21.12.2025 | H73: 3 | U73: COLUMN PLINTH BEAM TO 1ST FLOOR LVL
A74: 71 | C74: 21.12.2025 | H74: 3 | U74: COLUMN PLINTH BEAM TO 1ST FLOOR LVL
A75: 72 | C75: 23.12.2025 | H75: 3 | U75: COLUMN PLINTH BEAM TO 1ST FLOOR LVL
A76: 73 | C76: 25.12.2025 | H76: 3 | U76: COLUMN PLINTH BEAM TO 1ST FLOOR LVL
A77: 74 | C77: 25.12.2025 | H77: 2.5 | U77: COLUMN PLINTH BEAM TO 1ST FLOOR LVL
A78: 75 | C78: 26.12.2025 | H78: 3 | U78: COLUMN PLINTH BEAM TO 1ST FLOOR LVL
A79: 76 | C79: 29.12.2025 | H79: 3 | U79: COLUMN PLINTH BEAM TO 1ST FLOOR LVL
A80: 77 | C80: 31.12.2025 | H80: 3.5 | U80: COLUMN PLINTH BEAM TO 1ST FLOOR LVL
A81: 78 | C81: 31.12.2025 | H81: 4 | U81: COLUMN PLINTH BEAM TO 1ST FLOOR LVL
A82: 79 | B82: 46023 | C82: 01.01.2026 | H82: 3.5 | U82: COLUMN PLINTH BEAM TO 1ST FLOOR LVL
A83: 80 | C83: 03.01.2026 | H83: 3.5 | U83: COLUMN PLINTH BEAM TO 1ST FLOOR LVL
A84: 81 | C84: 04.01.2026 | H84: 6 | U84: COLUMN PLINTH BEAM TO 1ST FLOOR LVL
A85: 82 | C85: 05.01.2026 | H85: 4 | U85: COLUMN PLINTH BEAM TO 1ST FLOOR LVL
A86: 83 | C86: 06.01.2026 | H86: 5.5 | U86: COLUMN PLINTH BEAM TO 1ST FLOOR LVL
A87: 84 | C87: 21.01.2026 | H87: 12 | U87: 1ST FLOOR LVL SLAB
A88: 85 | C88: 21.01.2026 | E88: 35 | U88: 1ST FLOOR LVL SLAB
A89: 86 | C89: 22.01.2026 | E89: 69 | U89: 1ST FLOOR LVL SLAB
A90: 87 | C90: 30.01.2026 | E90: 35 | H90: 12 | U90: 1ST FLOOR LVL SLAB
A91: 88 | C91: 31.01.2026 | E91: 28 | U91: 1ST FLOOR LVL SLAB
A92: 89 | C92: 12.02.2026 | H92: 15 | U92: 1ST FLOOR LVL SLAB
A93: 90 | C93: 12.02.2026 | E93: 104 | U93: 1ST FLOOR LVL SLAB
B96: TOTAL | D96: =SUM(D4:D95) -> 57.5 | E96: =SUM(E4:E95) -> 1901 | F96: =SUM(F4:F95) -> 0 | G96: =SUM(G4:G95) -> 82 | H96: =SUM(H4:H95) -> 157 | I96: =SUM(I4:I95) -> 25.9 | J96: =SUM(J4:J95) -> 9.06 | K96: =SUM(K4:K95) -> 0 | ... S96: =SUM(S4:S95) -> 0 | T96: =SUM(D96:S96) -> 2232.46
B98: GRAND TOTAL | D98: =D96 -> 57.5 | E98: =E96 -> 1901 | F98: =F96 -> 0 | G98: =G96 -> 82 | H98: =H96 -> 157 | I98: =I96 -> 25.9 | J98: =J96 -> 9.06 | K98: =K96 -> 0 | ... T98: =T96 -> 2232.46
B99: TOTAL RCC BY RMC/ELSA /MANUAL | D99: =SUM(D98:H98) -> 2197.5 | I99: =SUM(I98:M98) -> 34.96 | N99: =SUM(N98:R98) -> 0 | S99: =S98 -> 0 | T99: =D99+I99+S99+N99 -> 2232.46
B100: RCC BY RMC + ELSA | D100: =SUM(D99:R99) -> 2232.46

Sheet RMC RECEIVING
A1: M/s. MARCO ENTERPRISES : RMC RECEIVING AT OMAXE ANANDA TOWER-E -PRAYAGRAJ
A2: SN | B2: DATE | C2: VEHICLE NO | D2: CHALLAN NO/INVOICE NO. | E2: MATERIAL GRADE | F2: UNIT | G2: RMC PLANT QTY (M 10) | H2: RMC PLANT QTY (M 25) | I2: RMC PLANT QTY (M 30) | J2: RMC PLANT QTY (M 35) | K2: RMC PLANT QTY (M 40) | L2: ACTUAL CEMENT WEIGHT BY DESIGN MIX | M2: CEMENT WEIGHT BY RMC PLANT | N2: CEMENT DIFF (IN KG) | O2: IN TIME | P2: OUT TIME | Q2: TOWER NO | R2: TYPE OF WORK | S2: RMC SUPPLIER | T2: REMARKS
A3: 1 | B3: 45786 | C3: UP32VN6145 | D3: 449 | E3: RMC10 | F3: CUM | G3: 7 | L3: =G3*220 -> 1540 | M3: 1540 | N3: =M3-L3 -> 0 | O3: 0.45138889 | P3: 0.51041667 | Q3: TOWER-E RAFT PCC | R3: RAFT PCC | S3: SHUBHAM
A4: 2 | B4: 45786 | C4: UP32WN8332 | D4: 450 | E4: RMC10 | F4: CUM | G4: 7 | L4: =G4*220 -> 1540 | M4: 1540 | N4: =M4-L4 -> 0 | O4: 0.52083333 | P4: 0.56944444 | Q4: TOWER-E RAFT PCC | R4: RAFT PCC | S4: SHUBHAM
A5: 3 | B5: 45786 | C5: UP53HT5034 | D5: 451 | E5: RMC10 | F5: CUM | G5: 7 | L5: =G5*220 -> 1540 | M5: 1540 | N5: =M5-L5 -> 0 | O5: 0.57777778 | P5: 0.61111111 | Q5: TOWER-E RAFT PCC | R5: RAFT PCC | S5: SHUBHAM
A6: 4 | B6: 45786 | C6: UP32VN6145 | D6: 453 | E6: RMC10 | F6: CUM | G6: 7 | L6: =G6*220 -> 1540 | M6: 1540 | N6: =M6-L6 -> 0 | O6: 0.61805556 | P6: 0.66666667 | Q6: TOWER-E RAFT PCC | R6: RAFT PCC | S6: SHUBHAM
A7: 5 | B7: 45786 | C7: UP32WN8334 | D7: 454 | E7: RMC10 | F7: CUM | G7: 6 | L7: =G7*220 -> 1320 | M7: 1320 | N7: =M7-L7 -> 0 | O7: 0.6875 | P7: 0.73958333 | Q7: TOWER-E RAFT PCC | R7: RAFT PCC | S7: SHUBHAM
A8: 6 | B8: 45786 | C8: UP53HT5034 | D8: 457 | E8: RMC10 | F8: CUM | G8: 6 | L8: =G8*220 -> 1320 | M8: 1320 | N8: =M8-L8 -> 0 | O8: 0.77430556 | P8: 0.8125 | Q8: TOWER-E RAFT PCC | R8: RAFT PCC | S8: SHUBHAM
A9: 7 | B9: 45789 | C9: UP32WN8334 | D9: 487 | E9: RMC10 | F9: CUM | G9: 5 | L9: =G9*220 -> 1100 | M9: 1096 | N9: =M9-L9 -> -4 | O9: 0.77430556 | P9: 0.8125 | Q9: TOWER-E RAFT PCC | R9: RAFT PCC | S9: SHUBHAM
A10: 8 | B10: 45789 | C10: UP32WN8334 | D10: 488 | E10: RMC10 | F10: CUM | G10: 5 | L10: =G10*220 -> 1100 | M10: 1096 | N10: =M10-L10 -> -4 | O10: 0.77430556 | P10: 0.8125 | Q10: TOWER-E RAFT PCC | R10: RAFT PCC | S10: SHUBHAM
A11: 9 | B11: 45789 | C11: UP32VN6144 | D11: 490 | E11: RMC10 | F11: CUM | G11: 5.5 | L11: =G11*220 -> 1210 | M11: 1210 | N11: =M11-L11 -> 0 | O11: 0.77430556 | P11: 0.8125 | Q11: TOWER-E RAFT PCC | R11: RAFT PCC | S11: SHUBHAM
A12: 10 | B12: 45789 | C12: UP32VN6144 | D12: 494 | E12: RMC10 | F12: CUM | G12: 2 | L12: =G12*220 -> 440 | M12: 440 | N12: =M12-L12 -> 0 | O12: 0.77430556 | P12: 0.8125 | Q12: TOWER-E RAFT PCC | R12: RAFT PCC | S12: SHUBHAM
A13: 11 | B13: 29.05.2025 | C13: UP32VN6145 | D13: 721 | E13: RMC 25 | F13: CUM | H13: 7 | L13: =H13*365 -> 2555 | M13: 2563 | N13: =M13-L13 -> 8 | O13: 0.9375 | P13: 0.96388889 | Q13: TOWER-E (23-43) | R13: RAFT | S13: SHUBHAM
A14: 12 | B14: 29.05.2025 | C14: UP32WN8334 | D14: 722 | E14: RMC 25 | F14: CUM | H14: 7 | L14: =H14*365 -> 2555 | M14: 2558 | N14: =M14-L14 -> 3 | O14: 0.96666667 | P14: 0.98125 | Q14: TOWER-E (23-43) | R14: RAFT | S14: SHUBHAM
A15: 13 | B15: 29.05.2025 | C15: UP32WN8333 | D15: 723 | E15: RMC 25 | F15: CUM | H15: 7 | L15: =H15*365 -> 2555 | M15: 2564 | N15: =M15-L15 -> 9 | O15: 0.98541667 | P15: 12:02PM | Q15: TOWER-E (23-43) | R15: RAFT | S15: SHUBHAM
A16: 14 | B16: 29.05.2025 | C16: UP32HT5032 | D16: 724 | E16: RMC 25 | F16: CUM | H16: 7 | L16: =H16*365 -> 2555 | M16: 2574 | N16: =M16-L16 -> 19 | O16: 0.50347222 | P16: 0.013194444 | Q16: TOWER-E (23-43) | R16: RAFT | S16: SHUBHAM
A17: 15 | B17: 29.05.2025 | C17: UP32HT5034 | D17: 725 | E17: RMC 25 | F17: CUM | H17: 5.5 | L17: =H17*365 -> 2007.5 | M17: 2018 | N17: =M17-L17 -> 10.5 | O17: 0.015972222 | P17: 0.029166667 | Q17: TOWER-E (23-43) | R17: RAFT | S17: SHUBHAM
B18: 29.05.2025 | C18: UP32HT5034 | D18: 726 | E18: RMC 25 | F18: CUM | H18: 1.5 | L18: =H18*365 -> 547.5 | M18: 548 | N18: =M18-L18 -> 0.5 | O18: 0.015972222 | P18: 0.029166667 | Q18: TOWER-E (23-43) | R18: RAFT | S18: SHUBHAM
A19: 16 | B19: 29.05.2025 | C19: UP70QT2013 | D19: 905350012 | E19: RMC 25 | F19: CUM | H19: 7 | L19: =H19*365 -> 2555 | M19: 2555 | N19: =M19-L19 -> 0 | O19: 0.9375 | P19: 0.96319444 | Q19: TOWER-E (23-43) | R19: RAFT | S19: ULTRATECH
A20: 17 | B20: 29.05.2025 | C20: UP70QT2341 | D20: 905350013 | E20: RMC 25 | F20: CUM | H20: 7 | L20: =H20*365 -> 2555 | M20: 2555 | N20: =M20-L20 -> 0 | O20: 0.96736111 | P20: 0.98680556 | Q20: TOWER-E (23-43) | R20: RAFT | S20: ULTRATECH
A21: 18 | B21: 29.05.2025 | C21: UP70QT2015 | D21: 905350014 | E21: RMC 25 | F21: CUM | H21: 7 | L21: =H21*365 -> 2555 | M21: 2555 | N21: =M21-L21 -> 0 | O21: 0.98680556 | P21: 1.0083333 | Q21: TOWER-E (23-43) | R21: RAFT | S21: ULTRATECH
A22: 19 | B22: 29.05.2025 | C22: UP70QT2342 | D22: 905350015 | E22: RMC 25 | F22: CUM | H22: 7 | L22: =H22*365 -> 2555 | M22: 2556 | N22: =M22-L22 -> 1 | O22: 0.052777778 | P22: 0.071527778 | Q22: TOWER-E (23-43) | R22: RAFT | S22: ULTRATECH
A23: 20 | B23: 29.05.2025 | C23: UP70QT2014 | D23: 905350016 | E23: RMC 25 | F23: CUM | H23: 7 | L23: =H23*365 -> 2555 | M23: 2555 | N23: =M23-L23 -> 0 | O23: 0.075694444 | P23: 0.086805556 | Q23: TOWER-E (23-43) | R23: RAFT | S23: ULTRATECH
A24: 21 | B24: 30.05.2025 | C24: UP32VN6145 | D24: 727 | E24: RMC 25 | F24: CUM | H24: 7 | L24: =H24*365 -> 2555 | M24: 2561 | N24: =M24-L24 -> 6 | O24: 0.043055556 | P24: 0.076388889 | Q24: TOWER-E (23-43) | R24: RAFT | S24: SHUBHAM
A25: 22 | B25: 30.05.2025 | C25: UP32WN8334 | D25: 728 | E25: RMC 25 | F25: CUM | H25: 7 | L25: =H25*365 -> 2555 | M25: 2551 | N25: =M25-L25 -> -4 | O25: 0.077777778 | P25: 0.09375 | Q25: TOWER-E (23-43) | R25: RAFT | S25: SHUBHAM
A26: 23 | B26: 30.05.2025 | C26: UP32WN8332 | D26: 729 | E26: RMC 25 | F26: CUM | H26: 7 | L26: =H26*365 -> 2555 | M26: 2557 | N26: =M26-L26 -> 2 | O26: 0.096527778 | P26: 0.10625 | Q26: TOWER-E (23-43) | R26: RAFT | S26: SHUBHAM
A27: 24 | B27: 30.05.2025 | C27: UP32WN8333 | D27: 730 | E27: RMC 25 | F27: CUM | H27: 7 | L27: =H27*365 -> 2555 | M27: 2557 | N27: =M27-L27 -> 2 | O27: 0.10763889 | P27: 0.12708333 | Q27: TOWER-E (23-43) | R27: RAFT | S27: SHUBHAM
A28: 25 | B28: 30.05.2025 | C28: UP32VN6144 | D28: 731 | E28: RMC 25 | F28: CUM | H28: 7 | L28: =H28*365 -> 2555 | M28: 2561 | N28: =M28-L28 -> 6 | O28: 0.12708333 | P28: 0.14097222 | Q28: TOWER-E (23-43) | R28: RAFT | S28: SHUBHAM
A29: 26 | B29: 30.05.2025 | C29: UP53HT5032 | D29: 732 | E29: RMC 25 | F29: CUM | H29: 7 | L29: =H29*365 -> 2555 | M29: 2560 | N29: =M29-L29 -> 5 | O29: 0.14305556 | P29: 0.15833333 | Q29: TOWER-E (23-43) | R29: RAFT | S29: SHUBHAM
A30: 27 | B30: 30.05.2025 | C30: UP32VN6145 | D30: 733 | E30: RMC 25 | F30: CUM | H30: 7 | L30: =H30*365 -> 2555 | M30: 2570 | N30: =M30-L30 -> 15 | O30: 0.16180556 | P30: 0.17083333 | Q30: TOWER-E (23-43) | R30: RAFT | S30: SHUBHAM
... A238: 235 | B238: 14.06.2025 | C238: UP70QT2013 | D238: 905350139 | E238: RMC 25 | F238: CUM | H238: 7 | L238: =H238*365 -> 2555 | M238: 2555 | N238: =M238-L238 -> 0 | O238: 0.72222222 | P238: 0.75694444 | Q238: TOWER-E (1-23) | R238: RAFT | S238: ULTRATECH
A239: 236 | B239: 45830 | C239: UP70QT2341 | D239: 905350161 | E239: RMC 35 | F239: CUM | J239: 3 | L239: =J239*415 -> 1245 | M239: =L239 -> 1245 | N239: =M239-L239 -> 0 | Q239: TOWER-E (1-43) | R239: PADESTIAL | S239: ULTRATECH
A240: 237 | B240: 45831 | C240: UP70QT2013 | D240: 905350165 | E240: RMC 35 | F240: CUM | J240: 4 | L240: =J240*415 -> 1660 | M240: =L240 -> 1660 | N240: =M240-L240 -> 0 | Q240: TOWER-E (1-43) | R240: PADESTIAL | S240: ULTRATECH
A241: 238 | B241: 45832 | C241: UP70QT2342 | D241: 905350166 | E241: RMC 35 | F241: CUM | J241: 5 | L241: =J241*415 -> 2075 | M241: =L241 -> 2075 | N241: =M241-L241 -> 0 | Q241: TOWER-E (1-43) | R241: PADESTIAL | S241: ULTRATECH
A242: 239 | B242: 45833 | C242: UP70QT2342 | D242: 905350167 | E242: RMC 35 | F242: CUM | J242: 5 | L242: =J242*415 -> 2075 | M242: =L242 -> 2075 | N242: =M242-L242 -> 0 | Q242: TOWER-E (1-43) | R242: PADESTIAL | S242: ULTRATECH
A243: 240 | B243: 45834 | C243: UP70QT2014 | D243: 905350168 | E243: RMC 35 | F243: CUM | J243: 6 | L243: =J243*415 -> 2490 | M243: =L243 -> 2490 | N243: =M243-L243 -> 0 | Q243: TOWER-E (1-43) | R243: PADESTIAL | S243: ULTRATECH
A244: 241 | B244: 45835 | C244: UP70QT2342 | D244: 905350171 | E244: RMC 35 | F244: CUM | J244: 4 | L244: =J244*415 -> 1660 | M244: =L244 -> 1660 | N244: =M244-L244 -> 0 | Q244: TOWER-E (1-43) | R244: PADESTIAL | S244: ULTRATECH
A245: 242 | B245: 45837 | C245: UP70QT2014 | D245: 905350190 | E245: RMC 35 | F245: CUM | J245: 3 | L245: =J245*415 -> 1245 | M245: =L245 -> 1245 | N245: =M245-L245 -> 0 | Q245: TOWER-E (1-43) | R245: PADESTIAL | S245: ULTRATECH
A246: 243 | B246: 45839 | C246: 9655 | D246: 563 | E246: RMC 35 | F246: CUM | J246: 4 | L246: =J246*415 -> 1660 | M246: =L246 -> 1660 | N246: =M246-L246 -> 0 | Q246: TOWER-E (1-43) | R246: PADESTIAL | S246: SRIJAN
A247: 244 | B247: 45839 | C247: UP70NT8336 | D247: 564 | E247: RMC 35 | F247: CUM | J247: 4 | L247: =J247*415 -> 1660 | M247: =L247 -> 1660 | N247: =M247-L247 -> 0 | Q247: TOWER-E (1-43) | R247: PADESTIAL | S247: SRIJAN
A248: 245 | B248: 45840 | C248: 9048 | D248: 565 | E248: RMC 35 | F248: CUM | J248: 4.5 | L248: =J248*415 -> 1867.5 | M248: =L248 -> 1867.5 | N248: =M248-L248 -> 0 | Q248: TOWER-E (1-43) | R248: PADESTIAL | S248: SRIJAN
A249: 246 | B249: 45842 | C249: 9048 | D249: 571 | E249: RMC 35 | F249: CUM | J249: 3.5 | L249: =J249*415 -> 1452.5 | M249: =L249 -> 1452.5 | N249: =M249-L249 -> 0 | Q249: TOWER-E (1-43) | R249: PADESTIAL | S249: SRIJAN
A250: 247 | B250: 45843 | C250: 9048 | D250: 582 | E250: RMC 35 | F250: CUM | J250: 4 | L250: =J250*415 -> 1660 | M250: =L250 -> 1660 | N250: =M250-L250 -> 0 | Q250: TOWER-E (1-43) | R250: PADESTIAL | S250: SRIJAN
A251: 248 | B251: 45843 | C251: 8917 | D251: 583 | E251: RMC 35 | F251: CUM | J251: 4 | L251: =J251*415 -> 1660 | M251: =L251 -> 1660 | N251: =M251-L251 -> 0 | Q251: TOWER-E (1-43) | R251: PADESTIAL | S251: SRIJAN
A252: 249 | B252: 45845 | C252: UP70NT8335 | D252: 591 | E252: RMC 35 | F252: CUM | J252: 3 | L252: =J252*415 -> 1245 | M252: =L252 -> 1245 | N252: =M252-L252 -> 0 | Q252: TOWER-E (1-43) | R252: PADESTIAL | S252: SRIJAN
A253: 250 | B253: 45846 | C253: UP70NT8335 | D253: 600 | E253: RMC 35 | F253: CUM | J253: 4 | L253: =J253*415 -> 1660 | M253: =L253 -> 1660 | N253: =M253-L253 -> 0 | Q253: TOWER-E (1-43) | R253: PADESTIAL | S253: SRIJAN
A254: 251 | B254: 45846 | C254: UP70NT8335 | D254: 604 | E254: RMC 25 | F254: CUM | H254: 7 | L254: =H254*365 -> 2555 | M254: =L254 -> 2555 | N254: =M254-L254 -> 0 | Q254: TOWER-E (1-43) | R254: COMP. STRIP | S254: SRIJAN
A255: 252 | B255: 45846 | C255: UP70NT8336 | D255: 603 | E255: RMC 25 | F255: CUM | H255: 7 | L255: =H255*365 -> 2555 | M255: =L255 -> 2555 | N255: =M255-L255 -> 0 | Q255: TOWER-E (1-43) | R255: COMP. STRIP | S255: SRIJAN
A256: 253 | B256: 45847 | C256: 9048 | D256: 605 | E256: RMC 35 | F256: CUM | J256: 3.5 | L256: =J256*415 -> 1452.5 | M256: =L256 -> 1452.5 | N256: =M256-L256 -> 0 | Q256: TOWER-E (1-43) | R256: PADESTIAL | S256: SRIJAN
A257: 254 | B257: 45848 | C257: 8917 | D257: 6009 | E257: RMC 35 | F257: CUM | J257: 3.5 | L257: =J257*415 -> 1452.5 | M257: =L257 -> 1452.5 | N257: =M257-L257 -> 0 | Q257: TOWER-E (1-43) | R257: PADESTIAL | S257: SRIJAN
A258: 255 | B258: 25.09.2025 | C258: UP32WN8333 | D258: 1950 | E258: M35 | F258: CUM | J258: 3 | L258: =J258*415 -> 1245 | M258: =L258 -> 1245 | N258: =M258-L258 -> 0 | Q258: TOWER-E PLINTH BEAM | R258: COL. JUN. | S258: SHUBHAM
A259: 256 | B259: 25.09.2025 | C259: UP32WN8333 | D259: 1957 | E259: M25 | F259: CUM | H259: 4 | L259: =H259*415 -> 1660 | M259: =L259 -> 1660 | N259: =M259-L259 -> 0 | Q259: TOWER-E | R259: PLINTH BEAM | S259: SHUBHAM
A260: 257 | B260: 25.09.2025 | C260: UP32WN8333 | D260: 1959 | E260: M25 | F260: CUM | H260: 4.5 | L260: =H260*415 -> 1867.5 | M260: =L260 -> 1867.5 | N260: =M260-L260 -> 0 | Q260: TOWER-E | R260: PLINTH BEAM | S260: SHUBHAM
A261: 258 | B261: 01.10.2025 | C261: UP32VN6140 | D261: 1990 | E261: M35 | F261: CUM | J261: 3 | L261: =J261*415 -> 1245 | M261: =L261 -> 1245 | N261: =M261-L261 -> 0 | Q261: TOWER-E PLINTH BEAM | R261: COL. JUN. | S261: SHUBHAM
A262: 259 | B262: 01.10.2025 | C262: UP32WN8334 | D262: 1993 | E262: M25 | F262: CUM | H262: 4 | L262: =H262*415 -> 1660 | M262: =L262 -> 1660 | N262: =M262-L262 -> 0 | Q262: TOWER-E | R262: PLINTH BEAM | S262: SHUBHAM
A263: 260 | B263: 01.10.2025 | C263: UP32VN6140 | D263: 1994 | E263: M25 | F263: CUM | H263: 3.5 | L263: =H263*415 -> 1452.5 | M263: =L263 -> 1452.5 | N263: =M263-L263 -> 0 | Q263: TOWER-E | R263: PLINTH BEAM | S263: SHUBHAM
A264: 261 | B264: 07.10.2025 | C264: UP32VN6140 | D264: 2037 | E264: M35 | F264: CUM | J264: 3 | L264: =J264*415 -> 1245 | M264: =L264 -> 1245 | N264: =M264-L264 -> 0 | Q264: TOWER-E PLINTH BEAM | R264: COL. JUN. | S264: SHUBHAM
A265: 262 | B265: 09.10.2025 | C265: UP32WN8332 | D265: 2071 | E265: M25 | F265: CUM | H265: 4 | L265: =H265*415 -> 1660 | M265: =L265 -> 1660 | N265: =M265-L265 -> 0 | Q265: TOWER-E | R265: PLINTH BEAM | S265: SHUBHAM
A266: 263 | B266: 09.10.2025 | C266: UP32VN6140 | D266: 2072 | E266: M35 | F266: CUM | J266: 2 | L266: =J266*415 -> 830 | M266: =L266 -> 830 | N266: =M266-L266 -> 0 | Q266: TOWER-E PLINTH BEAM | R266: COL. JUN. | S266: SHUBHAM
A267: 264 | B267: 09.10.2025 | C267: UP53HT5032 | D267: 2073 | E267: M25 | F267: CUM | H267: 3 | L267: =H267*415 -> 1245 | M267: =L267 -> 1245 | N267: =M267-L267 -> 0 | Q267: TOWER-E | R267: PLINTH BEAM | S267: SHUBHAM
A268: 265 | B268: 10.10.2025 | C268: UP32WN8334 | D268: 2087 | E268: M25 | F268: CUM | H268: 2 | L268: =H268*415 -> 830 | M268: =L268 -> 830 | N268: =M268-L268 -> 0 | Q268: TOWER-E | R268: PLINTH BEAM | S268: SHUBHAM
A269: 266 | B269: 29.10.2025 | C269: UP53HT5034 | D269: 2316 | E269: M35 | F269: CUM | J269: 3 | L269: =J269*415 -> 1245 | M269: =L269 -> 1245 | N269: =M269-L269 -> 0 | Q269: TOWER-E PLINTH BEAM | R269: COL. JUN. | S269: SHUBHAM
A270: 267 | B270: 30.10.2025 | C270: UP32VN6144 | D270: 2332 | E270: M25 | F270: CUM | H270: 4 | L270: =H270*415 -> 1660 | M270: =L270 -> 1660 | N270: =M270-L270 -> 0 | Q270: TOWER-E | R270: PLINTH BEAM | S270: SHUBHAM
A271: 268 | B271: 30.10.2025 | C271: UP53HT5032 | D271: 2338 | E271: M25 | F271: CUM | H271: 3.5 | L271: =H271*415 -> 1452.5 | M271: =L271 -> 1452.5 | N271: =M271-L271 -> 0 | Q271: TOWER-E | R271: PLINTH BEAM | S271: SHUBHAM
A272: 269 | B272: 11.11.2025 | C272: UP53HT5034 | D272: 2535 | E272: M40 | F272: CUM | K272: 2.5 | L272: =K272*415 -> 1037.5 | M272: =L272 -> 1037.5 | N272: =M272-L272 -> 0 | Q272: TOWER-E | R272: G.F. COLUMN | S272: SHUBHAM
A273: 270 | B273: 17.11.2025 | C273: UP32WN8334 | D273: 2615 | E273: M25 | F273: CUM | H273: 4 | L273: =H273*415 -> 1660 | M273: =L273 -> 1660 | N273: =M273-L273 -> 0 | Q273: TOWER-E | R273: PLINTH BEAM | S273: SHUBHAM
A274: 271 | B274: 17.11.2025 | C274: UP32VN6144 | D274: 2604 | E274: M40 | F274: CUM | K274: 3.5 | L274: =K274*415 -> 1452.5 | M274: =L274 -> 1452.5 | N274: =M274-L274 -> 0 | Q274: TOWER-E | R274: G.F. COLUMN | S274: SHUBHAM
A275: 272 | B275: 18.11.2025 | C275: UP53HT5032 | D275: 2633 | E275: M40 | F275: CUM | K275: 4.5 | L275: =K275*415 -> 1867.5 | M275: =L275 -> 1867.5 | N275: =M275-L275 -> 0 | Q275: TOWER-E | R275: G.F. COLUMN | S275: SHUBHAM
A276: 273 | B276: 19.11.2025 | C276: UP32WN8333 | D276: 2643 | E276: M25 | F276: CUM | H276: 3 | L276: =H276*415 -> 1245 | M276: =L276 -> 1245 | N276: =M276-L276 -> 0 | Q276: TOWER-E | R276: PLINTH BEAM | S276: SHUBHAM
A277: 274 | B277: 19.11.2025 | C277: UP32WN8334 | D277: 2661 | E277: M40 | F277: CUM | K277: 3.5 | L277: =K277*415 -> 1452.5 | M277: =L277 -> 1452.5 | N277: =M277-L277 -> 0 | Q277: TOWER-E | R277: G.F. COLUMN | S277: SHUBHAM
A278: 275 | B278: 20.11.2025 | C278: UP32WN8334 | D278: 2694 | E278: M40 | F278: CUM | K278: 3.5 | L278: =K278*415 -> 1452.5 | M278: =L278 -> 1452.5 | N278: =M278-L278 -> 0 | Q278: TOWER-E | R278: G.F. COLUMN | S278: SHUBHAM
A279: 276 | B279: 28.11.2025 | C279: UP32WN8333 | D279: 2831 | E279: M40 | F279: CUM | K279: 3 | L279: =K279*415 -> 1245 | M279: =L279 -> 1245 | N279: =M279-L279 -> 0 | Q279: TOWER-E | R279: G.F. COLUMN | S279: SHUBHAM
A280: 277 | B280: 29.11.2025 | C280: UP32VN6144 | D280: 2844 | E280: M40 | F280: CUM | K280: 3 | L280: =K280*415 -> 1245 | M280: =L280 -> 1245 | N280: =M280-L280 -> 0 | Q280: TOWER-E | R280: G.F. COLUMN | S280: SHUBHAM
A281: 278 | B281: 29.11.2025 | C281: UP53HT5032 | D281: 2855 | E281: M40 | F281: CUM | K281: 4 | L281: =K281*415 -> 1660 | M281: =L281 -> 1660 | N281: =M281-L281 -> 0 | Q281: TOWER-E | R281: G.F. COLUMN | S281: SHUBHAM
A282: 279 | B282: 30.11.2025 | C282: UP32WN8334 | D282: 2874 | E282: M40 | F282: CUM | K282: 3 | L282: =K282*415 -> 1245 | M282: =L282 -> 1245 | N282: =M282-L282 -> 0 | Q282: TOWER-E | R282: G.F. COLUMN | S282: SHUBHAM
A283: 280 | B283: 02.12.2025 | C283: UP53HT5034 | D283: 2912 | E283: M40 | F283: CUM | K283: 3 | L283: =K283*415 -> 1245 | M283: =L283 -> 1245 | N283: =M283-L283 -> 0 | Q283: TOWER-E | R283: G.F. COLUMN | S283: SHUBHAM
A284: 281 | B284: 02.12.2025 | C284: UP32WN8332 | D284: 2920 | E284: M40 | F284: CUM | K284: 4.5 | L284: =K284*415 -> 1867.5 | M284: =L284 -> 1867.5 | N284: =M284-L284 -> 0 | Q284: TOWER-E | R284: G.F. COLUMN | S284: SHUBHAM
A285: 282 | B285: 03.12.2025 | C285: UP32WN8333 | D285: 2931 | E285: M40 | F285: CUM | K285: 3.5 | L285: =K285*415 -> 1452.5 | M285: =L285 -> 1452.5 | N285: =M285-L285 -> 0 | Q285: TOWER-E | R285: G.F. COLUMN | S285: SHUBHAM
A286: 283 | B286: 03.12.2025 | C286: UP32WN8333 | D286: 2935 | E286: M40 | F286: CUM | K286: 3 | L286: =K286*415 -> 1245 | M286: =L286 -> 1245 | N286: =M286-L286 -> 0 | Q286: TOWER-E | R286: G.F. COLUMN | S286: SHUBHAM
A287: 284 | B287: 05.12.2025 | C287: UP32VN6140 | D287: 2954 | E287: M40 | F287: CUM | K287: 3 | L287: =K287*415 -> 1245 | M287: =L287 -> 1245 | N287: =M287-L287 -> 0 | Q287: TOWER-E | R287: G.F. COLUMN | S287: SHUBHAM
A288: 285 | B288: 06.12.2025 | C288: UP32WN8332 | D288: 2957 | E288: M40 | F288: CUM | K288: 3.5 | L288: =K288*415 -> 1452.5 | M288: =L288 -> 1452.5 | N288: =M288-L288 -> 0 | Q288: TOWER-E | R288: G.F. COLUMN | S288: SHUBHAM
... A290: 287 | B290: 08.12.2025 | C290: UP53HT5032 | D290: 2995 | E290: M40 | F290: CUM | K290: 2.5 | L290: =K290*415 -> 1037.5 | M290: =L290 -> 1037.5 | N290: =M290-L290 -> 0 | Q290: TOWER-E | R290: G.F. COLUMN | S290: SHUBHAM
A291: 288 | B291: 09.12.2025 | C291: UP32VN6140 | D291: 3009 | E291: M25 | F291: CUM | H291: 3.5 | L291: =H291*415 -> 1452.5 | M291: =L291 -> 1452.5 | N291: =M291-L291 -> 0 | Q291: TOWER-E | R291: PLINTH BEAM | S291: SHUBHAM
A292: 289 | B292: 09.12.2025 | C292: UP32WN8333 | D292: 3012 | E292: M25 | F292: CUM | H292: 3 | L292: =H292*415 -> 1245 | M292: =L292 -> 1245 | N292: =M292-L292 -> 0 | Q292: TOWER-E | R292: PLINTH BEAM | S292: SHUBHAM
A293: 290 | B293: 18.12.2025 | C293: UP32VN6144 | D293: 3183 | E293: M40 | F293: CUM | K293: 2 | L293: =K293*415 -> 830 | N293: =M293-L293 -> -830 | Q293: TOWER-E | R293: G.F. COLUMN | S293: SHUBHAM
A294: 291 | B294: 19.12.2025 | C294: UP32WN8334 | D294: 3197 | E294: M40 | F294: CUM | K294: 3 | L294: =K294*415 -> 1245 | N294: =M294-L294 -> -1245 | Q294: TOWER-E | R294: G.F. COLUMN | S294: SHUBHAM
A295: 292 | B295: 20.12.2025 | C295: UP32WN8332 | D295: 3217 | E295: M40 | F295: CUM | K295: 3 | L295: =K295*415 -> 1245 | N295: =M295-L295 -> -1245 | Q295: TOWER-E | R295: G.F. COLUMN | S295: SHUBHAM
A296: 293 | B296: 20.12.2025 | C296: UP32WN8332 | D296: 3220 | E296: M40 | F296: CUM | K296: 3.5 | L296: =K296*415 -> 1452.5 | N296: =M296-L296 -> -1452.5 | Q296: TOWER-E | R296: G.F. COLUMN | S296: SHUBHAM
A297: 294 | B297: 21.12.2025 | C297: UP53HT5034 | D297: 3227 | E297: M40 | F297: CUM | K297: 3 | L297: =K297*415 -> 1245 | N297: =M297-L297 -> -1245 | Q297: TOWER-E | R297: G.F. COLUMN | S297: SHUBHAM
A298: 295 | B298: 21.12.2025 | C298: UP53HT5032 | D298: 3231 | E298: M40 | F298: CUM | K298: 3 | L298: =K298*415 -> 1245 | N298: =M298-L298 -> -1245 | Q298: TOWER-E | R298: G.F. COLUMN | S298: SHUBHAM
A299: 296 | B299: 23.12.2025 | C299: UP32WN8332 | D299: 3262 | E299: M40 | F299: CUM | K299: 3 | L299: =K299*415 -> 1245 | N299: =M299-L299 -> -1245 | Q299: TOWER-E | R299: G.F. COLUMN | S299: SHUBHAM
A300: 300 | B300: 25.12.2025 | C300: UP53HT5032 | D300: 3292 | E300: M40 | F300: CUM | K300: 3 | L300: =K300*415 -> 1245 | N300: =M300-L300 -> -1245 | Q300: TOWER-E | R300: G.F. COLUMN | S300: SHUBHAM
A301: 301 | B301: 25.12.2025 | C301: UP32WN8334 | D301: 3295 | E301: M40 | F301: CUM | K301: 2.5 | L301: =K301*415 -> 1037.5 | N301: =M301-L301 -> -1037.5 | Q301: TOWER-E | R301: G.F. COLUMN | S301: SHUBHAM
A302: 302 | B302: 26.12.2025 | C302: UP53HT5034 | D302: 3312 | E302: M40 | F302: CUM | K302: 3 | L302: =K302*415 -> 1245 | N302: =M302-L302 -> -1245 | Q302: TOWER-E | R302: G.F. COLUMN | S302: SHUBHAM
A303: 303 | B303: 29.12.2025 | C303: UP32VN6144 | D303: 3375 | E303: M40 | F303: CUM | K303: 3 | L303: =K303*415 -> 1245 | N303: =M303-L303 -> -1245 | Q303: TOWER-E | R303: G.F. COLUMN | S303: SHUBHAM
A304: 304 | B304: 31.12.2025 | C304: UP32WN8333 | D304: 3405 | E304: M40 | F304: CUM | K304: 3.5 | L304: =K304*415 -> 1452.5 | N304: =M304-L304 -> -1452.5 | Q304: TOWER-E | R304: G.F. COLUMN | S304: SHUBHAM
... A315: 330 | B315: 21.01.2026 | C315: UP70QT2015 | D315: 905351167 | E315: M40 | F315: CUM | K315: 4 | L315: =K315*415 -> 1660 | N315: =M315-L315 -> -1660 | Q315: TOWER-E 1ST FLOOR LVL | R315: SLAB | S315: ULTRATECH
A316: 331 | B316: 21.01.2026 | C316: UP70QT2014 | D316: 905351170 | E316: M25 | F316: CUM | H316: 7 | L316: =H316*365 -> 2555 | N316: =M316-L316 -> -2555 | Q316: TOWER-E 1ST FLOOR LVL | R316: SLAB | S316: ULTRATECH
A317: 332 | B317: 21.01.2026 | C317: UP70QT2013 | D317: 905351171 | E317: M25 | F317: CUM | H317: 7 | L317: =H317*365 -> 2555 | N317: =M317-L317 -> -2555 | Q317: TOWER-E 1ST FLOOR LVL | R317: SLAB | S317: ULTRATECH
A318: 333 | B318: 21.01.2026 | C318: UP70QT2341 | D318: 905351172 | E318: M25 | F318: CUM | H318: 7 | L318: =H318*365 -> 2555 | N318: =M318-L318 -> -2555 | Q318: TOWER-E 1ST FLOOR LVL | R318: SLAB | S318: ULTRATECH
...

Sheet CONCRETE WORK MB
A1: COMPANY- OMAXE PANCHAM REALCON PVT LTD
A2: PROJECT- TOWER-E
A3: LOCATION- NAINI, PRAYAGRAJ
A4: MB SHEET- CONCRETE WORK
A6: S.NO. | B6: DESCRIPTION | C6: UNIT | D6: NOS | E6: NOS | F6: MEASUREMENT | I6: QTY. | J6: REMARKS
F7: L | G7: B | H7: H/T
B8: RAFT PCC- M10 BELOW PLINTH BEAM
A9: 1 | B9: GRID (22'-43'/A-Q') | C9: CUM | D9: 1 | E9: 1 | F9: =31.935+0.115+0.115 -> 32.165 | G9: =36.895+0.115+0.115 -> 37.125 | H9: 0.1 | I9: =PRODUCT(D9:H9) -> 119.41256 | J9: 3rd RA
A10: 2 | C10: CUM | D10: 1 | E10: 1 | F10: =8.78+0.115+0.115 -> 9.01 | G10: 0.515 | H10: 0.1 | I10: =PRODUCT(D10:H10) -> 0.464015
A11: 3 | B11: GRID (22'-26'/M'-Q') | C11: CUM | D11: -1 | E11: 1 | F11: 11.005 | G11: 12.415 | H11: 0.1 | I11: =PRODUCT(D11:H11) -> -13.662707
A12: 4 | B12: GRID (38'-43'/A-E') | C12: CUM | D12: -1 | E12: 1 | F12: 11.09 | G12: 10.285 | H12: 0.1 | I12: =PRODUCT(D12:H12) -> -11.406065
A13: 5 | B13: GRID (22'-30'/A-B') | C13: CUM | D13: -1 | E13: 1 | F13: 11.285 | G13: 3.72 | H13: 0.1 | I13: =PRODUCT(D13:H13) -> -4.19802
A14: 6 | C14: CUM | D14: -1 | E14: 1 | F14: 1.695 | G14: 2.315 | H14: 0.1 | I14: =PRODUCT(D14:H14) -> -0.3923925
A15: 7 | C15: CUM | D15: -1 | E15: 1 | F15: 3.95 | G15: 1.5 | H15: 0.1 | I15: =PRODUCT(D15:H15) -> -0.5925
D16: -1 | E16: 1 | F16: 15.8 | G16: =0.115 -> 0.115 | H16: 0.1 | I16: =PRODUCT(D16:H16) -> -0.1817
A17: 8 | B17: EXISTING RAFT (DETAILS IN JMR) | C17: CUM | D17: -1 | E17: 1 | F17: 9 | G17: =5.8+0.115 -> 5.915 | H17: 0.1 | I17: =PRODUCT(D17:H17) -> -5.3235
A18: 9 | C18: CUM | D18: -1 | E18: 1 | F18: 19.05 | G18: 10 | H18: 0.1 | I18: =PRODUCT(D18:H18) -> -19.05
A19: 10 | C19: CUM | D19: -1 | E19: 1 | F19: 6.2 | G19: 6.2 | H19: 0.1 | I19: =PRODUCT(D19:H19) -> -3.844
A20: 11 | C20: CUM | D20: -1 | E20: 1 | F20: =11.7-6.2 -> 5.5 | G20: 8.05 | H20: 0.1 | I20: =PRODUCT(D20:H20) -> -4.4275
H22: TOTAL | I22: =SUM(I8:I21) -> 56.798193
A23: 1 | B23: GRID (5'-20/A-C') (DETAILS IN JMR) | C23: CUM | D23: 1 | E23: 1 | F23: 3 | G23: 1.5 | H23: 0.1 | I23: =PRODUCT(D23:H23) -> 0.45 | J23: 4th RA
A24: 2 | C24: CUM | D24: 1 | E24: 1 | F24: 5.875 | G24: 1.5 | H24: 0.1 | I24: =PRODUCT(D24:H24) -> 0.88125
A25: 3 | C25: CUM | D25: 1 | E25: 1 | F25: 9.825 | G25: 0.815 | H25: 0.1 | I25: =PRODUCT(D25:H25) -> 0.8007375
A26: 4 | C26: CUM | D26: 1 | E26: 1 | F26: 11.52 | G26: 1.405 | H26: 0.1 | I26: =PRODUCT(D26:H26) -> 1.61856
A27: 5 | C27: CUM | D27: 1 | E27: 1 | F27: 16.5 | G27: 1 | H27: 0.1 | I27: =PRODUCT(D27:H27) -> 1.65
A28: 6 | B28: GRID (1-18/M'-Q') (DETAILS IN JMR) | C28: CUM | D28: 1 | E28: 1 | F28: 11.03 | G28: 8.67 | H28: 0.1 | I28: =PRODUCT(D28:H28) -> 9.56301
A29: 7 | C29: CUM | D29: 1 | E29: 1 | F29: 11.545 | G29: 2.715 | H29: 0.1 | I29: =PRODUCT(D29:H29) -> 3.1344675
A30: 8 | C30: CUM | D30: 1 | E30: 1 | F30: 6.065 | G30: 2.515 | H30: 0.1 | I30: =PRODUCT(D30:H30) -> 1.5253475
A31: 9 | C31: CUM | D31: 1 | E31: 1 | F31: 1.05 | G31: 2 | H31: 0.1 | I31: =PRODUCT(D31:H31) -> 0.21
A32: 10 | C32: CUM | D32: 1 | E32: 1 | F32: 8.67 | G32: 3.27 | H32: 0.1 | I32: =PRODUCT(D32:H32) -> 2.83509
H34: TOTAL | I34: =SUM(I23:I33) -> 22.668463
A36: S.NO. | B36: DESCRIPTION | C36: UNIT | D36: NOS | E36: NOS | F36: MEASUREMENT | I36: QTY. | J36: REMARKS
F37: L | G37: B | H37: H/T
B38: RAFT RCC- M25 BELOW PLINTH BEAM
A39: 1 | B39: GRID (22'-43'/A-Q') | C39: CUM | D39: 1 | E39: 1 | F39: =31.935 -> 31.935 | G39: =36.895 -> 36.895 | H39: 0.85 | I39: =PRODUCT(D39:H39) -> 1001.5056 | J39: 3rd RA
A40: 2 | C40: CUM | D40: 1 | E40: 1 | F40: =8.78 -> 8.78 | G40: 0.515 | H40: 0.85 | I40: =PRODUCT(D40:H40) -> 3.843445
A41: 3 | B41: GRID (22'-26'/M'-Q') | C41: CUM | D41: -1 | E41: 1 | F41: 11.005 | G41: 12.415 | H41: 0.85 | I41: =PRODUCT(D41:H41) -> -116.13301
A42: 4 | B42: GRID (38'-43'/A-E') | C42: CUM | D42: -1 | E42: 1 | F42: 11.09 | G42: 10.285 | H42: 0.85 | I42: =PRODUCT(D42:H42) -> -96.951552
A43: 5 | B43: GRID (22'-30'/A-B') | C43: CUM | D43: -1 | E43: 1 | F43: 11.285 | G43: 3.72 | H43: 0.85 | I43: =PRODUCT(D43:H43) -> -35.68317
A44: 6 | C44: CUM | D44: -1 | E44: 1 | F44: 1.695 | G44: 2.315 | H44: 0.85 | I44: =PRODUCT(D44:H44) -> -3.3353363
A45: 7 | C45: CUM | D45: -1 | E45: 1 | F45: 3.95 | G45: 1.5 | H45: 0.85 | I45: =PRODUCT(D45:H45) -> -5.03625
H47: TOTAL | I47: =SUM(I38:I46) -> 748.20967
A48: 1 | B48: GRID (22'-43'/A-Q') | C48: CUM | D48: 1 | E48: 1 | F48: =31.935 -> 31.935 | G48: 40.165 | H48: 0.85 | I48: =PRODUCT(D48:H48) -> 1090.2689 | J48: 4th RA
A49: 2 | C49: CUM | D49: 1 | E49: 1 | F49: =8.78 -> 8.78 | G49: 0.515 | H49: 0.85 | I49: =PRODUCT(D49:H49) -> 3.843445
A50: 3 | B50: GRID (22'-26'/M'-Q') | C50: CUM | D50: -1 | E50: 1 | F50: 14.275 | G50: 12.415 | H50: 0.85 | I50: =PRODUCT(D50:H50) -> -150.64051
A51: 4 | B51: GRID (38'-43'/A-E') | C51: CUM | D51: -1 | E51: 1 | F51: 11.09 | G51: 10.285 | H51: 0.85 | I51: =PRODUCT(D51:H51) -> -96.951552
A52: 5 | B52: GRID (22'-30'/A-B') | C52: CUM | D52: -1 | E52: 1 | F52: 14.555 | G52: 3.72 | H52: 0.85 | I52: =PRODUCT(D52:H52) -> -46.02291
A53: 6 | C53: CUM | D53: -1 | E53: 1 | F53: 1.695 | G53: 2.315 | H53: 0.85 | I53: =PRODUCT(D53:H53) -> -3.3353363
A54: 7 | C54: CUM | D54: -1 | E54: 1 | F54: 3.95 | G54: 1.5 | H54: 0.85 | I54: =PRODUCT(D54:H54) -> -5.03625
H56: TOTAL | I56: =SUM(I48:I55) -> 792.12577
B57: COMPENSATORY STRIP
A58: 1 | B58: GRID (22-23/B'-L') | C58: CUM | D58: 1 | E58: 1 | F58: 15.8 | G58: 0.9 | H58: 0.85 | I58: =PRODUCT(D58:H58) -> 12.087 | J58: 5th RA
H60: TOTAL | I60: =SUBTOTAL(9,I58:I59) -> 12.087
B61: PADESTIAL GRID (1-43/A-Q)
A62: 1 | B62: C1, C2, C3, C8 (300X600) | C62: CUM | D62: =31*2-16 -> 46 | E62: 1 | F62: 0.3 | G62: 0.6 | H62: 1.48 | I62: =PRODUCT(D62:H62) -> 12.2544
A63: 2 | B63: C1 (300X600) | C63: CUM | D63: 6 | E63: 1 | F63: 0.3 | G63: 0.6 | H63: 1.68 | I63: =PRODUCT(D63:H63) -> 1.8144
A64: 3 | B64: C2 (300X600) | C64: CUM | D64: 6 | E64: 1 | F64: 0.3 | G64: 0.6 | H64: 1.68 | I64: =PRODUCT(D64:H64) -> 1.8144
A65: 4 | B65: C3 (300X600) | C65: CUM | D65: 2 | E65: 1 | F65: 0.3 | G65: 0.6 | H65: 1.68 | I65: =PRODUCT(D65:H65) -> 0.6048
A66: 5 | B66: C8 (300X600) | C66: CUM | D66: 2 | E66: 1 | F66: 0.3 | G66: 0.6 | H66: 1.68 | I66: =PRODUCT(D66:H66) -> 0.6048
A67: 6 | B67: C4, C5 (300X750) | C67: CUM | D67: =15*2-6 -> 24 | E67: 1 | F67: 0.3 | G67: 0.7 | H67: 1.48 | I67: =PRODUCT(D67:H67) -> 7.4592
A68: 7 | B68: C4 (300X750) | C68: CUM | D68: 4 | E68: 1 | F68: 0.3 | G68: 0.7 | H68: 1.68 | I68: =PRODUCT(D68:H68) -> 1.4112
A69: 8 | B69: C5 (300X750) | C69: CUM | D69: 2 | E69: 1 | F69: 0.3 | G69: 0.7 | H69: 1.68 | I69: =PRODUCT(D69:H69) -> 0.7056
A70: 9 | B70: C6 (300X715) | C70: CUM | D70: =7*2 -> 14 | E70: 1 | F70: 0.3 | G70: 0.715 | H70: 1.48 | I70: =PRODUCT(D70:H70) -> 4.44444
A71: 10 | B71: C7 (300X800) | C71: CUM | D71: =2*2-2 -> 2 | E71: 1 | F71: 0.3 | G71: 0.8 | H71: 1.48 | I71: =PRODUCT(D71:H71) -> 0.7104
A72: 11 | B72: C7 (300X800) | C72: CUM | D72: 2 | E72: 1 | F72: 0.3 | G72: 0.8 | H72: 1.68 | I72: =PRODUCT(D72:H72) -> 0.8064
A73: 12 | B73: SW 1 (L-SHAPE) | C73: CUM | D73: =1*2 -> 2 | E73: 1 | F73: 0.23 | G73: 0.65 | H73: 1.48 | I73: =PRODUCT(D73:H73) -> 0.44252
A74: 13 | C74: CUM | D74: 2 | E74: 1 | F74: 0.23 | G74: =1.65-0.23 -> 1.42 | H74: 1.48 | I74: =PRODUCT(D74:H74) -> 0.966736
A75: 14 | B75: SW 2 (L-SHAPE) | C75: CUM | D75: =1*2 -> 2 | E75: 1 | F75: 0.23 | G75: 0.65 | H75: 1.48 | I75: =PRODUCT(D75:H75) -> 0.44252
A76: 15 | C76: CUM | D76: 2 | E76: 1 | F76: 0.23 | G76: =1.85-0.23 -> 1.62 | H76: 1.48 | I76: =PRODUCT(D76:H76) -> 1.102896
A77: 16 | B77: SW 3 (230x1000) | C77: CUM | D77: =1*2 -> 2 | E77: 1 | F77: 0.23 | G77: 1 | H77: 1.48 | I77: =PRODUCT(D77:H77) -> 0.6808
A78: 17 | B78: SW 4 (230x1150) | C78: CUM | D78: =1*2 -> 2 | E78: 1 | F78: 0.23 | G78: 1.15 | H78: 1.48 | I78: =PRODUCT(D78:H78) -> 0.78292
A79: 18 | B79: SW 5 (230x1700) | C79: CUM | D79: 4 | E79: 1 | F79: 0.23 | G79: 1.7 | H79: 1.68 | I79: =PRODUCT(D79:H79) -> 2.62752
A80: 19 | B80: SW 6 (230x1185) | C80: CUM | D80: 2 | E80: 1 | F80: 0.23 | G80: 1.185 | H80: 1.48 | I80: =PRODUCT(D80:H80) -> 0.806748
A81: 20 | B81: SW 6 (230x1185) | C81: CUM | D81: 2 | E81: 1 | F81: 0.23 | G81: 1.185 | H81: 1.68 | I81: =PRODUCT(D81:H81) -> 0.915768
A82: 21 | B82: SW 7 (230x1855) | C82: CUM | D82: =1*2 -> 2 | E82: 1 | F82: 0.23 | G82: 1.855 | H82: 1.48 | I82: =PRODUCT(D82:H82) -> 1.262884
A83: 22 | B83: SW 8 (230x3600) | C83: CUM | D83: 1 | E83: 1 | F83: 0.23 | G83: 3.6 | H83: 1.48 | I83: =PRODUCT(D83:H83) -> 1.22544
A84: 23 | B84: SW 9 (L-SHAPE) | C84: CUM | D84: =3*2 -> 6 | E84: 1 | F84: 0.23 | G84: 0.65 | H84: 1.48 | I84: =PRODUCT(D84:H84) -> 1.32756
A85: 24 | C85: CUM | D85: 6 | E85: 1 | F85: 0.23 | G85: =1.85-0.23 -> 1.62 | H85: 1.48 | I85: =PRODUCT(D85:H85) -> 3.308688
A86: 25 | B86: SW 10 (230x3445) | C86: CUM | D86: =1*2 -> 2 | E86: 1 | F86: 0.23 | G86: 3.445 | H86: 1.68 | I86: =PRODUCT(D86:H86) -> 2.662296
A87: 26 | B87: SW 11 (230x4065) | C87: CUM | D87: =1*2 -> 2 | E87: 1 | F87: 0.23 | G87: 4.065 | H87: 1.68 | I87: =PRODUCT(D87:H87) -> 3.141432
A88: 27 | B88: SW 12 (L-SHAPE) | C88: CUM | D88: =1*2 -> 2 | E88: 1 | F88: 0.23 | G88: 0.65 | H88: 1.68 | I88: =PRODUCT(D88:H88) -> 0.50232
A89: 28 | C89: CUM | D89: 2 | E89: 1 | F89: 0.23 | G89: =1.535-0.23 -> 1.305 | H89: 1.68 | I89: =PRODUCT(D89:H89) -> 1.008504
A90: 29 | B90: SW 13 (200x3445) | C90: CUM | D90: =1*2 -> 2 | E90: 1 | F90: 0.2 | G90: 3.445 | H90: 1.68 | I90: =PRODUCT(D90:H90) -> 2.31504
A91: 30 | B91: LIFT WALL | C91: CUM | D91: =4*2 -> 8 | E91: 1 | F91: 0.23 | G91: 1.9 | H91: 1.68 | I91: =PRODUCT(D91:H91) -> 5.87328
H93: TOTAL | I93: =SUBTOTAL(9,I62:I92) -> 64.025912
H95: TOTAL | I95: =SUBTOTAL(9,I58:I94) -> 76.112912
B97: PLINTH BEAM (1-43/A-Q) | J97: 7TH RA
A98: 1 | B98: PB1 | C98: CUM | D98: 1 | E98: 2 | F98: 3.025 | G98: 0.2 | H98: =0.45-0.115 -> 0.335 | I98: =PRODUCT(D98:H98) -> 0.40535
A99: 2 | B99: PB1 | C99: CUM | D99: 1 | E99: 2 | F99: 2.8 | G99: 0.2 | H99: =0.45-0.115 -> 0.335 | I99: =PRODUCT(D99:H99) -> 0.3752
A100: 3 | B100: PB2 | C100: CUM | D100: 1 | E100: 2 | F100: 3.3 | G100: 0.2 | H100: =0.45-0.115 -> 0.335 | I100: =PRODUCT(D100:H100) -> 0.4422
A101: 4 | B101: PB3 | C101: CUM | D101: 1 | E101: 4 | F101: 1.395 | G101: 0.1 | H101: =0.45-0.115 -> 0.335 | I101: =PRODUCT(D101:H101) -> 0.18693
A102: 5 | B102: PB3 | C102: CUM | D102: 1 | E102: 6 | F102: 1.4 | G102: 0.1 | H102: =0.45-0.115 -> 0.335 | I102: =PRODUCT(D102:H102) -> 0.2814
A103: 6 | B103: PB3 | C103: CUM | D103: 1 | E103: 2 | F103: 1.2 | G103: 0.1 | H103: =0.45-0.115 -> 0.335 | I103: =PRODUCT(D103:H103) -> 0.0804
A104: 7 | B104: PB3 | C104: CUM | D104: 1 | E104: 6 | F104: 1.55 | G104: 0.1 | H104: =0.45-0.115 -> 0.335 | I104: =PRODUCT(D104:H104) -> 0.31155
A105: 8 | B105: PB3 | C105: CUM | D105: 1 | E105: 6 | F105: 0.97 | G105: 0.1 | H105: =0.45-0.115 -> 0.335 | I105: =PRODUCT(D105:H105) -> 0.19497
A106: 9 | B106: PB4 | C106: CUM | D106: 1 | E106: 6 | F106: 1.395 | G106: 0.2 | H106: =0.45-0.115 -> 0.335 | I106: =PRODUCT(D106:H106) -> 0.56079
A107: 10 | B107: PB5 | C107: CUM | D107: 1 | E107: 2 | F107: 3.1 | G107: 0.2 | H107: =0.45-0.115 -> 0.335 | I107: =PRODUCT(D107:H107) -> 0.4154
A108: 11 | B108: PB6 | C108: CUM | D108: 1 | E108: 1 | F108: =18.91-2.4 -> 16.51 | G108: 0.2 | H108: =0.45-0.115 -> 0.335 | I108: =PRODUCT(D108:H108) -> 1.10617
A109: 12 | B109: PB7 | C109: CUM | D109: 1 | E109: 2 | F109: 2.875 | G109: 0.2 | H109: =0.45-0.115 -> 0.335 | I109: =PRODUCT(D109:H109) -> 0.38525
A110: 13 | B110: PB7 | C110: CUM | D110: 1 | E110: 2 | F110: 2.93 | G110: 0.2 | H110: =0.45-0.115 -> 0.335 | I110: =PRODUCT(D110:H110) -> 0.39262
...

Sheet SHUTT. WORK SUMMARY
A1: TOWER-E CENTERING & SHUTTERING WORK SUMMARY
D2: QTY | M2: TOTAL
A3: 3 | B3: CENTRING AND SHUTTERING | D3: 3rd RA | E3: 4th RA | F3: 5th RA | G3: 6th RA | H3: 7th RA | I3: 8th RA | J3: 9th RA
B4: Providing and fixing plywood or steel plate shuttering and centring for structural concrete work in locations called for including strutting, propping, bracing, bolting, wedging, casing, striking, removal etc. complete for any size, section, thickness. Props shall consist of well designed steel pipes adequately braced (wooden ballies as props shall not be permitted). The item to include centering and shuttering at all heights and levels. Allow for forming grooves, drip course, chamfers, cut-outs, openings etc. where called for and for dressing with approved shuttering oil to prevent adhesion. Unexposed concrete surfaces subsequently left untreated (in the condition obtained on removal of form work) shall not constitute exposed concrete work and shall be measured under this item only Irregular shapes with sides (like circular, semi-circular, oval etc.) which may not be perpendicular to each other for shapes not conforming to rectangle or square, and circular shuttering shall not be paid separately. Joints of soffits of the slab shall be made clean after concreting and de-shuttering. (quoted rate to include all staging upto 3.50 mtr height). Note:- Contractor shall take necessary precautions such as watertight shuttering. This is inclusive of RCC members, leaving shuttering & centring for pour strip, slab in slope, RCC members in curved (in plan), etc., nothing is payable extra on this account.
A5: 3.1.1. | B5: Foundation, column footings, raft slab, raft beams, plinth beam, lift pits, sump pits, pedestals / bases of column, column up to plinth, swimming pool, Retaining wall foundations, grade slab etc. | C5: SQM | D5: 93.6125 | E5: 82.707 | F5: 619.2036 | H5: 849.97425 | M5: =SUM(D5:L5) -> 1645.4974
A6: 3.1.2. | B6: Suspended floors, roofs, balconies, shelves/ counters, stair waist slabs, folded plate stairs and landings, swimming pool slab, lintel and floor beams, landing beams, girders (deep beams), RCC bands, swimming pool beam, cantilever projections, coping, cills, slab of tank etc at all levels.
A7: 3.1.2.1. | B7: Stilt Floor level to 7th Floor level | C7: SQM | I7: =+'SHUTTERING WORK MB'!I802 -> 1195.8149 | J7: ='SHUTTERING WORK MB'!I1243 -> 1195.8149 | M7: =SUM(D7:L7) -> 2391.6299
A8: 3.1.2.2. | B8: 7th Floor level to to Terrace Including OHT, Mumty, Machine Room, Parapet | C8: SQM | M8: =SUM(D8:L8) -> 0
A9: 3.1.2..3 | B9: All type of Moulding, Bands, Elevation/Architectural Features as per drawing and as directed by EIC. at all level | C9: SQM | M9: =SUM(D9:L9) -> 0
A11: 3.2. | B11: Columns, Wall, pillars, piers, abutments, posts and struts, offset and projection of columns, water tank walls, lift walls, Retaining Wall, swimming pool, Parapets, planters, vertical projection of pergolas, wall and ramp walls etc. at all levels.
A12: 3.2.1. | B12: Stilt Floor level to 7th Floor level | C12: SQM | H12: 246.83 | I12: =+'SHUTTERING WORK MB'!I361 -> 751.279 | M12: =SUM(D12:L12) -> 998.109
A13: 3.2.2. | B13: 7th Floor level to to Terrace Including OHT, Mumty, Machine Room, Parapet | C13: SQM | M13: =SUM(D13:L13) -> 0
A14: 3.2.3. | B14: All type of Moulding, Bands, Elevation/Architectural Features as per drawing and as directed by EIC. at all level | C14: SQM | M14: =SUM(D14:L14) -> 0
A16: 3.3. | B16: Extra for additional height in centring, shuttering where ever required with adequate bracing, propping etc. including cost of de-shuttering and decentring at all levels, over and above height of 3.50 mtr (Plan area to be measured and shall be paid proportionately on actual height) – for every 1.0 mtr. height | C16: SQM | M16: =SUM(D16:L16) -> 0
D18: =SUM(D4:D17) -> 93.6125 | E18: =SUM(E4:E17) -> 82.707 | F18: =SUM(F4:F17) -> 619.2036 | G18: =SUM(G4:G17) -> 0 | H18: =SUM(H4:H17) -> 1096.8043 | I18: =SUM(I4:I17) -> 1947.0939 | J18: =SUM(J4:J17) -> 1195.8149 | L18: TOTAL | M18: =SUM(M4:M17) -> 5035.2362

Sheet SHUTTERING WORK MB
A1: COMPANY- OMAXE PANCHAM REALCON PVT LTD
A2: PROJECT- TOWER-E
A3: LOCATION- NAINI, PRAYAGRAJ
A4: MB SHEET- SHUTTERING WORK
A6: S.NO. | B6: DESCRIPTION | C6: UNIT | D6: NOS | E6: NOS | F6: MEASUREMENT | I6: QTY. | J6: REMARKS
F7: L | G7: B | H7: H/T
B8: PCC SHUTTERING
A9: 1 | B9: GRID (26'/Q') | C9: SQM | D9: 1 | E9: 1 | F9: 0.7 | H9: 0.1 | I9: =PRODUCT(D9:H9) -> 0.07 | K9: 3rd RA
A10: 2 | B10: GRID (26'-43'/Q') | C10: SQM | D10: 1 | E10: 1 | F10: =25.89+0.515+0.515 -> 26.92 | H10: 0.1 | I10: =PRODUCT(D10:H10) -> 2.692
A11: 3 | B11: GRID (43'/E'-Q') | C11: SQM | D11: 1 | E11: 1 | F11: 21.65 | H11: 0.1 | I11: =PRODUCT(D11:H11) -> 2.165
A12: 4 | B12: GRID (38'-43'/E') | C12: SQM | D12: 1 | E12: 1 | F12: 11.09 | H12: 0.1 | I12: =PRODUCT(D12:H12) -> 1.109
A13: 5 | B13: GRID (38'/A-E') | C13: SQM | D13: 1 | E13: 1 | F13: 10.285 | H13: 0.1 | I13: =PRODUCT(D13:H13) -> 1.0285
A14: 6 | B14: GRID (30-38'/A) | C14: SQM | D14: 1 | E14: 1 | F14: 8.875 | H14: 0.1 | I14: =PRODUCT(D14:H14) -> 0.8875
A15: 7 | B15: GRID (30/A-A') | C15: SQM | D15: 1 | E15: 1 | F15: 1.5 | H15: 0.1 | I15: =PRODUCT(D15:H15) -> 0.15
A16: 8 | B16: GRID (27'-30/A') | C16: SQM | D16: 1 | E16: 1 | F16: 3.95 | H16: 0.1 | I16: =PRODUCT(D16:H16) -> 0.395
A17: 9 | B17: GRID (27'/A'-B) | C17: SQM | D17: 1 | E17: 1 | F17: 0.815 | H17: 0.1 | I17: =PRODUCT(D17:H17) -> 0.0815
A18: 10 | B18: GRID (26'-27'/B) | C18: SQM | D18: 1 | E18: 1 | F18: 1.695 | H18: 0.1 | I18: =PRODUCT(D18:H18) -> 0.1695
A19: 11 | B19: GRID (26'/B-B') | C19: SQM | D19: 1 | E19: 1 | F19: 1.405 | H19: 0.1 | I19: =PRODUCT(D19:H19) -> 0.1405
A20: 12 | B20: GRID (22'-26'/B') | C20: SQM | D20: 1 | E20: 1 | F20: =11.285-9 -> 2.285 | H20: 0.1 | I20: =PRODUCT(D20:H20) -> 0.2285 | J20: -9mtr as per JMR
B21: RAFT SHUTTERING
A22: 1 | B22: GRID (22'-26'/M') | C22: SQM | D22: 1 | E22: 1 | F22: 11.005 | H22: =0.85-0.3 -> 0.55 | I22: =PRODUCT(D22:H22) -> 6.05275
A23: =+A22+1 -> 2 | B23: GRID (26/M'-Q) | C23: SQM | D23: 1 | E23: 1 | F23: 12.415 | H23: =0.85-0.3 -> 0.55 | I23: =PRODUCT(D23:H23) -> 6.82825
A24: =+A23+1 -> 3 | B24: GRID (26'-43'/Q') | C24: SQM | D24: 1 | E24: 1 | F24: =25.89+0.515+0.515 -> 26.92 | H24: =0.85-0.3 -> 0.55 | I24: =PRODUCT(D24:H24) -> 14.806
A25: =+A24+1 -> 4 | B25: GRID (43'/E'-Q') | C25: SQM | D25: 1 | E25: 1 | F25: 21.65 | H25: =0.85-0.3 -> 0.55 | I25: =PRODUCT(D25:H25) -> 11.9075
A26: =+A25+1 -> 5 | B26: GRID (38'-43'/E') | C26: SQM | D26: 1 | E26: 1 | F26: 11.09 | H26: =0.85-0.3 -> 0.55 | I26: =PRODUCT(D26:H26) -> 6.0995
A27: =+A26+1 -> 6 | B27: GRID (38'/A-E') | C27: SQM | D27: 1 | E27: 1 | F27: 10.285 | H27: =0.85-0.3 -> 0.55 | I27: =PRODUCT(D27:H27) -> 5.65675
A28: =+A27+1 -> 7 | B28: GRID (30-38'/A) | C28: SQM | D28: 1 | E28: 1 | F28: 8.875 | H28: =0.85-0.3 -> 0.55 | I28: =PRODUCT(D28:H28) -> 4.88125
A29: =+A28+1 -> 8 | B29: GRID (30/A-A') | C29: SQM | D29: 1 | E29: 1 | F29: 1.5 | H29: =0.85-0.3 -> 0.55 | I29: =PRODUCT(D29:H29) -> 0.825
A30: =+A29+1 -> 9 | B30: GRID (27'-30/A') | C30: SQM | D30: 1 | E30: 1 | F30: 3.95 | H30: =0.85-0.3 -> 0.55 | I30: =PRODUCT(D30:H30) -> 2.1725
A31: =+A30+1 -> 10 | B31: GRID (27'/A'-B) | C31: SQM | D31: 1 | E31: 1 | F31: 0.815 | H31: =0.85-0.3 -> 0.55 | I31: =PRODUCT(D31:H31) -> 0.44825
A32: =+A31+1 -> 11 | B32: GRID (26'-27'/B) | C32: SQM | D32: 1 | E32: 1 | F32: 1.695 | H32: =0.85-0.3 -> 0.55 | I32: =PRODUCT(D32:H32) -> 0.93225
A33: =+A32+1 -> 12 | B33: GRID (26'/B-B') | C33: SQM | D33: 1 | E33: 1 | F33: 1.405 | H33: =0.85-0.3 -> 0.55 | I33: =PRODUCT(D33:H33) -> 0.77275
A34: =+A33+1 -> 13 | B34: GRID (22'-26'/B') | C34: SQM | D34: 1 | E34: 1 | F34: 11.285 | H34: =0.85-0.3 -> 0.55 | I34: =PRODUCT(D34:H34) -> 6.20675
A35: =+A34+1 -> 14 | B35: GRID (22'-26'/B') | C35: SQM | D35: 1 | E35: 1 | F35: =15.8 -> 15.8 | H35: =0.85-0.4+0.3+0.16+0.16 -> 1.07 | I35: =PRODUCT(D35:H35) -> 16.906
H37: TOTAL | I37: =SUM(I8:I36) -> 93.6125
B38: PCC SHUTTERING
A39: 1 | B39: GRID (5'-20/A-C') (DETAILS IN JMR) | C39: SQM | D39: 1 | E39: 1 | F39: 1.5 | H39: 0.1 | I39: =PRODUCT(D39:H39) -> 0.15 | K39: 4th RA
A40: 2 | C40: SQM | D40: 1 | E40: 1 | F40: 8.875 | H40: 0.1 | I40: =PRODUCT(D40:H40) -> 0.8875
A41: 3 | C41: SQM | D41: 1 | E41: 1 | F41: 1.5 | H41: 0.1 | I41: =PRODUCT(D41:H41) -> 0.15
A42: 4 | C42: SQM | D42: 1 | E42: 1 | F42: 3.95 | H42: 0.1 | I42: =PRODUCT(D42:H42) -> 0.395
A43: 5 | C43: SQM | D43: 1 | E43: 1 | F43: 0.815 | H43: 0.1 | I43: =PRODUCT(D43:H43) -> 0.0815
A44: 6 | C44: SQM | D44: 1 | E44: 1 | F44: 1.695 | H44: 0.1 | I44: =PRODUCT(D44:H44) -> 0.1695
A45: 7 | C45: SQM | D45: 1 | E45: 1 | F45: 1.405 | H45: 0.1 | I45: =PRODUCT(D45:H45) -> 0.1405
A46: 8 | C46: SQM | D46: 1 | E46: 1 | F46: 1.98 | H46: 0.1 | I46: =PRODUCT(D46:H46) -> 0.198
A47: 9 | C47: SQM | D47: 1 | E47: 1 | F47: 1 | H47: 0.1 | I47: =PRODUCT(D47:H47) -> 0.1
A48: 10 | B48: GRID (1-18/M'-Q') (DETAILS IN JMR) | C48: SQM | D48: 1 | E48: 1 | F48: 11.03 | H48: 0.1 | I48: =PRODUCT(D48:H48) -> 1.103
A49: 11 | C49: SQM | D49: 1 | E49: 1 | F49: 8.67 | H49: 0.1 | I49: =PRODUCT(D49:H49) -> 0.867
A50: 12 | C50: SQM | D50: 1 | E50: 1 | F50: 0.515 | H50: 0.1 | I50: =PRODUCT(D50:H50) -> 0.0515
A51: 13 | C51: SQM | D51: 1 | E51: 1 | F51: =6.065+2.715 -> 8.78 | H51: 0.1 | I51: =PRODUCT(D51:H51) -> 0.878
A52: 14 | C52: SQM | D52: 1 | E52: 1 | F52: 0.515 | H52: 0.1 | I52: =PRODUCT(D52:H52) -> 0.0515
A53: 15 | C53: SQM | D53: 1 | E53: 1 | F53: =1.05+8.67 -> 9.72 | H53: 0.1 | I53: =PRODUCT(D53:H53) -> 0.972
A54: 16 | C54: SQM | D54: 1 | E54: 1 | F54: 3.27 | H54: 0.1 | I54: =PRODUCT(D54:H54) -> 0.327
B55: RAFT SHUTTERING
A56: 1 | B56: GRID (17'-22'/M') | C56: SQM | D56: 1 | E56: 1 | F56: =14.275 -> 14.275 | H56: =0.85-0.3 -> 0.55 | I56: =PRODUCT(D56:H56) -> 7.85125
A57: =+A56+1 -> 2 | B57: GRID (17'/M'-Q) | C57: SQM | D57: 1 | E57: 1 | F57: 12.415 | H57: =0.85-0.3 -> 0.55 | I57: =PRODUCT(D57:H57) -> 6.82825
A58: =+A57+1 -> 3 | B58: GRID (1-17'/Q') | C58: SQM | D58: 1 | E58: 1 | F58: =25.89+0.515+0.515 -> 26.92 | H58: =0.85-0.3 -> 0.55 | I58: =PRODUCT(D58:H58) -> 14.806
A59: =+A58+1 -> 4 | B59: GRID (1-5'/E') | C59: SQM | D59: 1 | E59: 1 | F59: 11.09 | H59: =0.85-0.3 -> 0.55 | I59: =PRODUCT(D59:H59) -> 6.0995
A60: =+A59+1 -> 5 | B60: GRID (5'/A-E') | C60: SQM | D60: 1 | E60: 1 | F60: 10.285 | H60: =0.85-0.3 -> 0.55 | I60: =PRODUCT(D60:H60) -> 5.65675
A61: =+A60+1 -> 6 | B61: GRID (5'-14'/A) | C61: SQM | D61: 1 | E61: 1 | F61: 8.875 | H61: =0.85-0.3 -> 0.55 | I61: =PRODUCT(D61:H61) -> 4.88125
A62: =+A61+1 -> 7 | B62: GRID (14'/A-A') | C62: SQM | D62: 1 | E62: 1 | F62: 1.5 | H62: =0.85-0.3 -> 0.55 | I62: =PRODUCT(D62:H62) -> 0.825
A63: =+A62+1 -> 8 | B63: GRID (14'-16'/A') | C63: SQM | D63: 1 | E63: 1 | F63: 3.95 | H63: =0.85-0.3 -> 0.55 | I63: =PRODUCT(D63:H63) -> 2.1725
A64: =+A63+1 -> 9 | B64: GRID (16'/A'-B) | C64: SQM | D64: 1 | E64: 1 | F64: 0.815 | H64: =0.85-0.3 -> 0.55 | I64: =PRODUCT(D64:H64) -> 0.44825
A65: =+A64+1 -> 10 | B65: GRID (16'-17'/B) | C65: SQM | D65: 1 | E65: 1 | F65: 1.695 | H65: =0.85-0.3 -> 0.55 | I65: =PRODUCT(D65:H65) -> 0.93225
A66: =+A65+1 -> 11 | B66: GRID (17'/B-B') | C66: SQM | D66: 1 | E66: 1 | F66: 1.405 | H66: =0.85-0.3 -> 0.55 | I66: =PRODUCT(D66:H66) -> 0.77275
A67: =+A66+1 -> 12 | B67: GRID (17'-22'/B') | C67: SQM | D67: 1 | E67: 1 | F67: =14.555 -> 14.555 | H67: =0.85-0.3 -> 0.55 | I67: =PRODUCT(D67:H67) -> 8.00525
A68: =+A67+1 -> 13 | B68: GRID (22'-26'/B') | C68: SQM | D68: 1 | E68: 1 | F68: =15.8 -> 15.8 | H68: =0.85-0.4+0.3+0.16+0.16 -> 1.07 | I68: =PRODUCT(D68:H68) -> 16.906
H70: TOTAL | I70: =SUM(I38:I69) -> 82.707
B71: COMPENSATORY STRIP
A72: 1 | B72: GRID (22-23/B'-L') | C72: SQM | D72: 1 | E72: 2 | G72: 0.9 | H72: 0.85 | I72: =PRODUCT(D72:H72) -> 1.53 | K72: 5th RA
B73: PADESTIAL GRID (1-43/A-Q)
A74: 1 | B74: C1, C2, C3, C8 (300X600) | C74: SQM | D74: 46 | E74: 1 | F74: 0.3 | G74: 0.6 | H74: 1.48 | I74: =D74*E74*2*(F74+G74)*H74 -> 122.544
A75: 2 | B75: C1 (300X600) | C75: SQM | D75: 6 | E75: 1 | F75: 0.3 | G75: 0.6 | H75: 1.68 | I75: =D75*E75*2*(F75+G75)*H75 -> 18.144
A76: 3 | B76: C2 (300X600) | C76: SQM | D76: 6 | E76: 1 | F76: 0.3 | G76: 0.6 | H76: 1.68 | I76: =D76*E76*2*(F76+G76)*H76 -> 18.144
A77: 4 | B77: C3 (300X600) | C77: SQM | D77: 2 | E77: 1 | F77: 0.3 | G77: 0.6 | H77: 1.68 | I77: =D77*E77*2*(F77+G77)*H77 -> 6.048
A78: 5 | B78: C3 (300X600) | C78: SQM | D78: 2 | E78: 1 | F78: 0.3 | G78: 0.6 | H78: 1.68 | I78: =D78*E78*2*(F78+G78)*H78 -> 6.048
A79: 6 | B79: C4, C5 (300X750) | C79: SQM | D79: 24 | E79: 1 | F79: 0.3 | G79: 0.7 | H79: 1.48 | I79: =D79*E79*2*(F79+G79)*H79 -> 71.04
A80: 7 | B80: C4 (300X750) | C80: SQM | D80: 4 | E80: 1 | F80: 0.3 | G80: 0.7 | H80: 1.68 | I80: =D80*E80*2*(F80+G80)*H80 -> 13.44
A81: 8 | B81: C5 (300X750) | C81: SQM | D81: 2 | E81: 1 | F81: 0.3 | G81: 0.7 | H81: 1.68 | I81: =D81*E81*2*(F81+G81)*H81 -> 6.72
A82: 9 | B82: C6 (300X715) | C82: SQM | D82: 14 | E82: 1 | F82: 0.3 | G82: 0.715 | H82: 1.48 | I82: =D82*E82*2*(F82+G82)*H82 -> 42.0616
A83: 10 | B83: C7 (300X800) | C83: SQM | D83: 2 | E83: 1 | F83: 0.3 | G83: 0.8 | H83: 1.48 | I83: =D83*E83*2*(F83+G83)*H83 -> 6.512
A84: 11 | B84: C7 (300X800) | C84: SQM | D84: 2 | E84: 1 | F84: 0.3 | G84: 0.8 | H84: 1.68 | I84: =D84*E84*2*(F84+G84)*H84 -> 7.392
A85: 12 | B85: SW 1 (L-SHAPE) | C85: SQM | D85: 2 | E85: 1 | F85: 0.23 | G85: 0.65 | H85: 1.48 | I85: =D85*E85*2*(F85+G85)*H85 -> 5.2096
A86: 13 | C86: SQM | D86: 2 | E86: 1 | F86: 0 | G86: 1.42 | H86: 1.48 | I86: =D86*E86*2*(F86+G86)*H86 -> 8.4064
A87: 14 | B87: SW 2 (L-SHAPE) | C87: SQM | D87: 2 | E87: 1 | F87: 0.23 | G87: 0.65 | H87: 1.48 | I87: =D87*E87*2*(F87+G87)*H87 -> 5.2096
A88: 15 | C88: SQM | D88: 2 | E88: 1 | F88: 0 | G88: 1.62 | H88: 1.48 | I88: =D88*E88*2*(F88+G88)*H88 -> 9.5904
A89: 16 | B89: SW 3 (230x1000) | C89: SQM | D89: 2 | E89: 1 | F89: 0.23 | G89: 1 | H89: 1.48 | I89: =D89*E89*2*(F89+G89)*H89 -> 7.2816
A90: 17 | B90: SW 4 (230x1150) | C90: SQM | D90: 2 | E90: 1 | F90: 0.23 | G90: 1.15 | H90: 1.48 | I90: =D90*E90*2*(F90+G90)*H90 -> 8.1696
A91: 18 | B91: SW 5 (230x1700) | C91: SQM | D91: 4 | E91: 1 | F91: 0.23 | G91: 1.7 | H91: 1.68 | I91: =D91*E91*2*(F91+G91)*H91 -> 25.9392
A92: 19 | B92: SW 6 (230x1185) | C92: SQM | D92: 2 | E92: 1 | F92: 0.23 | G92: 1.185 | H92: 1.48 | I92: =D92*E92*2*(F92+G92)*H92 -> 8.3768
A93: 20 | B93: SW 6 (230x1185) | C93: SQM | D93: 2 | E93: 1 | F93: 0.23 | G93: 1.185 | H93: 1.68 | I93: =D93*E93*2*(F93+G93)*H93 -> 9.5088
A94: 21 | B94: SW 7 (230x1855) | C94: SQM | D94: 2 | E94: 1 | F94: 0.23 | G94: 1.855 | H94: 1.48 | I94: =D94*E94*2*(F94+G94)*H94 -> 12.3432
A95: 22 | B95: SW 8 (230x3600) | C95: SQM | D95: 1 | E95: 1 | F95: 0.23 | G95: 3.6 | H95: 1.48 | I95: =D95*E95*2*(F95+G95)*H95 -> 11.3368
A96: 23 | B96: SW 9 (L-SHAPE) | C96: SQM | D96: 6 | E96: 1 | F96: 0.23 | G96: 0.65 | H96: 1.48 | I96: =D96*E96*2*(F96+G96)*H96 -> 15.6288
A97: 24 | C97: SQM | D97: 6 | E97: 1 | F97: 0 | G97: 1.62 | H97: 1.48 | I97: =D97*E97*2*(F97+G97)*H97 -> 28.7712
A98: 25 | B98: SW 10 (230x3445) | C98: SQM | D98: 2 | E98: 1 | F98: 0.23 | G98: 3.445 | H98: 1.68 | I98: =D98*E98*2*(F98+G98)*H98 -> 24.696
A99: 26 | B99: SW 11 (230x4065) | C99: SQM | D99: 2 | E99: 1 | F99: 0.23 | G99: 4.065 | H99: 1.68 | I99: =D99*E99*2*(F99+G99)*H99 -> 28.8624
A100: 27 | B100: SW 12 (L-SHAPE) | C100: SQM | D100: 2 | E100: 1 | F100: 0.23 | G100: 0.65 | H100: 1.68 | I100: =D100*E100*2*(F100+G100)*H100 -> 5.9136
A101: 28 | C101: SQM | D101: 2 | E101: 1 | F101: 0 | G101: 1.305 | H101: 1.68 | I101: =D101*E101*2*(F101+G101)*H101 -> 8.7696
A102: 29 | B102: SW 13 (200x3445) | C102: SQM | D102: 2 | E102: 1 | F102: 0.2 | G102: 3.445 | H102: 1.68 | I102: =D102*E102*2*(F102+G102)*H102 -> 24.4944
A103: 30 | B103: LIFT WALL | C103: SQM | D103: 8 | E103: 1 | F103: 0 | G103: 1.9 | H103: 1.68 | I103: =D103*E103*2*(F103+G103)*H103 -> 51.072
...

Sheet BRICK WORK SUMMARY
A2: TOWER-E BRICK WORK SUMMARY
D3: QTY | J3: TOTAL
A4: 5 | B4: MASONARY WORK | D4: 3rd RA | E4: 4th RA | F4: 5th RA | G4: 6th RA | H4: 7th RA | I4: 8th RA
B5: (Quoted Rates are for all heights, all depths, all levels, including basement to roof (mumty) & all leads and lifts, including curved or circular including elevation masonary work) (Basic Rate of Brick @ Rs. 7/No. FOR at site without GST)
A6: 5.1. | B6: Brick work in Sub Structure (Up to Stilt Floor level):
B7: Providing and laying 230mm thick brick masonry using 1st quality burnt clay FPS bricks in Sub-Structure laid in cement mortar 1:6 (1 cement : 6 coarse sand) mix, joints finished, flush/ raked to 6mm depth including scaffolding, curing complete as per specification and drawing or as directed by Project Manager. | C7: CUM | J7: =SUM(D7:I7) -> 0
A8: 5.2. | B8: Brick work in Sub Structure (Up to Stilt Floor level):
B9: Providing and laying of 115 mm thick brick work with 1st quality burnt clay FPS bricks in sub-superstructure laid in cement mortar 1:4 (1 cement : 4 coarse sand) mix, joints finished, including placing hoop iron as per specification at every third course, scaffolding, curing complete in all respect as per direction of EIC. (Hoop iron shall be provided by client free of cost) (Items of RCC bands like shuttering, concrete and reinforcement to be paid in respective items). | C9: SQM | D9: ='BRICK WORK MB'!I23 -> 36.867 | E9: ='BRICK WORK MB'!I39 -> 51.2765 | J9: =SUM(D9:I9) -> 88.1435
A10: 5.3. | B10: Brick work in Super Structure (Above Stilt FLoor level)
A11: 5.3.1 | B11: Providing and laying 230mm thick brick masonry using 1st quality burnt clay FPS bricks in Super-Structure laid in cement mortar 1:6 (1 cement : 6 coarse sand) mix, joints finished, flush/ raked to 6mm depth including scaffolding, curing complete as per specification and drawing or as directed by Project Manager.
A12: (a) | B12: Stilt Floor level to 7th Floor level | C12: CUM | J12: =SUM(D12:I12) -> 0
A13: (b) | B13: 7th Floor level to to Terrace Including OHT, Mumty, Machine Room, Parapet | C13: CUM | J13: =SUM(D13:I13) -> 0
A14: 5.4. | B14: Brick work in Super Structure (Above Stilt FLoor level)
A15: 5.4.1 | B15: Providing and laying of 115 mm thick brick work with 1st quality burnt clay FPS bricks in Super-Superstructure laid in cement mortar 1:4 (1 cement : 4 coarse sand) mix, joints finished, including placing hoop iron as per specification at every third course, scaffolding, curing complete in all respect as per direction of EIC. (Hoop iron shall be provided by client free of cost) (Items of RCC bands like shuttering, concrete and reinforcement to be paid in respective items).
A16: (a) | B16: Stilt Floor level to 7th Floor level | C16: SQM | J16: =SUM(D16:I16) -> 0
A17: (b) | B17: 7th Floor level to to Terrace Including OHT, Mumty, Machine Room, Parapet | C17: SQM | J17: =SUM(D17:I17) -> 0
A18: 5.8. | B18: Brick work in staircase steps:
B19: Providing and laying and constructing brickwork in staircase steps using 1st quality burnt clay FPS bricks in cement mortar 1:3 (1 cement : 3 coarse sand) at all heights and levels including cutting, chamfering scaffolding, curing, complete as per specification. | C19: CUM | J19: =SUM(D19:I19) -> 0
I21: TOTAL | J21: =SUM(J7:J20) -> 88.1435

Sheet BRICK WORK MB
A1: COMPANY- OMAXE PANCHAM REALCON PVT LTD
A2: PROJECT- TOWER-E
A3: LOCATION- NAINI, PRAYAGRAJ
A4: MB SHEET- BRICK WORK BELOW PLINTH BEAM
A6: S.NO. | B6: DESCRIPTION | C6: UNIT | D6: NOS | E6: NOS | F6: MEASUREMENT | I6: QTY. | J6: REMARKS
F7: L | G7: B | H7: H/T
B8: RAFT OUTTER 115MM BRICK WORK
A9: 1 | B9: GRID (22'-26'/M') | C9: SQM | D9: 1 | E9: 1 | F9: 11.005 | H9: 0.3 | I9: =PRODUCT(D9:H9) -> 3.3015 | K9: 3rd RA
A10: =+A9+1 -> 2 | B10: GRID (26/M'-Q) | C10: SQM | D10: 1 | E10: 1 | F10: 12.415 | H10: 0.3 | I10: =PRODUCT(D10:H10) -> 3.7245
A11: =+A10+1 -> 3 | B11: GRID (26'-43'/Q') | C11: SQM | D11: 1 | E11: 1 | F11: =25.89+0.515+0.515 -> 26.92 | H11: 0.3 | I11: =PRODUCT(D11:H11) -> 8.076
A12: =+A11+1 -> 4 | B12: GRID (43'/E'-Q') | C12: SQM | D12: 1 | E12: 1 | F12: 21.65 | H12: 0.3 | I12: =PRODUCT(D12:H12) -> 6.495
A13: =+A12+1 -> 5 | B13: GRID (38'-43'/E') | C13: SQM | D13: 1 | E13: 1 | F13: 11.09 | H13: 0.3 | I13: =PRODUCT(D13:H13) -> 3.327
A14: =+A13+1 -> 6 | B14: GRID (38'/A-E') | C14: SQM | D14: 1 | E14: 1 | F14: 10.285 | H14: 0.3 | I14: =PRODUCT(D14:H14) -> 3.0855
A15: =+A14+1 -> 7 | B15: GRID (30-38'/A) | C15: SQM | D15: 1 | E15: 1 | F15: 8.875 | H15: 0.3 | I15: =PRODUCT(D15:H15) -> 2.6625
A16: =+A15+1 -> 8 | B16: GRID (30/A-A') | C16: SQM | D16: 1 | E16: 1 | F16: 1.5 | H16: 0.3 | I16: =PRODUCT(D16:H16) -> 0.45
A17: =+A16+1 -> 9 | B17: GRID (27'-30/A') | C17: SQM | D17: 1 | E17: 1 | F17: 3.95 | H17: 0.3 | I17: =PRODUCT(D17:H17) -> 1.185
A18: =+A17+1 -> 10 | B18: GRID (27'/A'-B) | C18: SQM | D18: 1 | E18: 1 | F18: 0.815 | H18: 0.3 | I18: =PRODUCT(D18:H18) -> 0.2445
A19: =+A18+1 -> 11 | B19: GRID (26'-27'/B) | C19: SQM | D19: 1 | E19: 1 | F19: 1.695 | H19: 0.3 | I19: =PRODUCT(D19:H19) -> 0.5085
A20: =+A19+1 -> 12 | B20: GRID (26'/B-B') | C20: SQM | D20: 1 | E20: 1 | F20: 1.405 | H20: 0.3 | I20: =PRODUCT(D20:H20) -> 0.4215
A21: =+A20+1 -> 13 | B21: GRID (22'-26'/B') | C21: SQM | D21: 1 | E21: 1 | F21: 11.285 | H21: 0.3 | I21: =PRODUCT(D21:H21) -> 3.3855
H23: TOTAL | I23: =SUM(I8:I22) -> 36.867
B24: RAFT OUTTER 115MM BRICK WORK
A25: 1 | B25: GRID (17'-22'/M') | C25: SQM | D25: 1 | E25: 1 | F25: =14.275+0.9 -> 15.175 | H25: 0.3 | I25: =PRODUCT(D25:H25) -> 4.5525 | K25: 4th RA
A26: =+A25+1 -> 2 | B26: GRID (17'/M'-Q) | C26: SQM | D26: 1 | E26: 1 | F26: 12.415 | H26: 0.3 | I26: =PRODUCT(D26:H26) -> 3.7245
A27: =+A26+1 -> 3 | B27: GRID (1-17'/Q') | C27: SQM | D27: 1 | E27: 1 | F27: =25.89+0.515+0.515 -> 26.92 | H27: 0.3 | I27: =PRODUCT(D27:H27) -> 8.076
A28: =+A27+1 -> 4 | B28: GRID (1/E'-Q') | C28: SQM | D28: 1 | E28: 1 | F28: 21.65 | H28: 0.85 | I28: =PRODUCT(D28:H28) -> 18.4025
A29: =+A28+1 -> 5 | B29: GRID (1-5'/E') | C29: SQM | D29: 1 | E29: 1 | F29: 11.09 | H29: 0.3 | I29: =PRODUCT(D29:H29) -> 3.327
A30: =+A29+1 -> 6 | B30: GRID (5'/A-E') | C30: SQM | D30: 1 | E30: 1 | F30: 10.285 | H30: 0.3 | I30: =PRODUCT(D30:H30) -> 3.0855
A31: =+A30+1 -> 7 | B31: GRID (5'-14'/A) | C31: SQM | D31: 1 | E31: 1 | F31: 8.875 | H31: 0.3 | I31: =PRODUCT(D31:H31) -> 2.6625
A32: =+A31+1 -> 8 | B32: GRID (14'/A-A') | C32: SQM | D32: 1 | E32: 1 | F32: 1.5 | H32: 0.3 | I32: =PRODUCT(D32:H32) -> 0.45
A33: =+A32+1 -> 9 | B33: GRID (14'-16'/A') | C33: SQM | D33: 1 | E33: 1 | F33: 3.95 | H33: 0.3 | I33: =PRODUCT(D33:H33) -> 1.185
A34: =+A33+1 -> 10 | B34: GRID (16'/A'-B) | C34: SQM | D34: 1 | E34: 1 | F34: 0.815 | H34: 0.3 | I34: =PRODUCT(D34:H34) -> 0.2445
A35: =+A34+1 -> 11 | B35: GRID (16'-17'/B) | C35: SQM | D35: 1 | E35: 1 | F35: 1.695 | H35: 0.3 | I35: =PRODUCT(D35:H35) -> 0.5085
A36: =+A35+1 -> 12 | B36: GRID (17'/B-B') | C36: SQM | D36: 1 | E36: 1 | F36: 1.405 | H36: 0.3 | I36: =PRODUCT(D36:H36) -> 0.4215
A37: =+A36+1 -> 13 | B37: GRID (17'-22'/B') | C37: SQM | D37: 1 | E37: 1 | F37: =14.555+0.9 -> 15.455 | H37: 0.3 | I37: =PRODUCT(D37:H37) -> 4.6365
H39: TOTAL | I39: =SUM(I24:I38) -> 51.2765

Sheet TMT STEEL RECO.
A1: MARCO ENTERPRISES
A2: TOWER-E
A3: Reconcialation of TMT Steel
A4: S.NO. | B4: Description | C4: Unit | D4: Dia wise | K4: Total
D5: 6mm | E5: 8mm | F5: 10mm | G5: 12mm | H5: 16mm | I5: 20mm | J5: 25mm
A6: A | B6: Total Steel Received upto date | C6: Kg | D6: =+'TMT STEEL REC.'!D31 -> 0 | E6: =+'TMT STEEL REC.'!E31 -> 46096.74 | F6: =+'TMT STEEL REC.'!F31 -> 43427.81 | G6: =+'TMT STEEL REC.'!G31 -> 29397.88 | H6: =+'TMT STEEL REC.'!H31 -> 112548.11 | I6: =+'TMT STEEL REC.'!I31 -> 68874.19 | J6: =+'TMT STEEL REC.'!J31 -> 24640 | K6: =SUM(D6:J6) -> 324984.73
A8: B | B8: Consumption Detail
A9: 4.1.1 | B9: Up To Stilt Floor Lvl. | C9: Kg | D9: ='TMT SUMMARY'!F15 -> 0 | E9: ='TMT SUMMARY'!G15 -> 5122.9778 | F9: ='TMT SUMMARY'!H15 -> 9115.7643 | G9: ='TMT SUMMARY'!I15 -> 5609.2314 | H9: ='TMT SUMMARY'!J15 -> 60025.549 | I9: ='TMT SUMMARY'!K15 -> 34914.631 | J9: ='TMT SUMMARY'!L15 -> 17380.444 | K9: =SUM(D9:J9) -> 132168.6
A10: 4.1.2 | B10: Stilt Floor level to to Terrace Including OHT, Mumty, Machine Room, Parapet) | C10: Kg | D10: ='TMT SUMMARY'!F22 -> 0 | E10: 22528.288 | F10: 11816.469 | G10: 7479.2281 | H10: 12590.973 | I10: 4836.4253 | J10: 1635.4834 | K10: =SUM(D10:J10) -> 60886.867
A11: 4.1.3 | B11: All type of Moulding, Bands, Elevation/Architectural Features as per drawing and as directed by EIC. at all level | C11: Kg | D11: ='TMT SUMMARY'!F27 -> 0 | E11: ='TMT SUMMARY'!G27 -> 36.1504 | F11: ='TMT SUMMARY'!H27 -> 0 | G11: ='TMT SUMMARY'!I27 -> 0 | H11: ='TMT SUMMARY'!J27 -> 0 | I11: ='TMT SUMMARY'!K27 -> 0 | J11: ='TMT SUMMARY'!L27 -> 0 | K11: =SUM(D11:J11) -> 36.1504
A13: C | B13: Total consumption | D13: =SUM(D9:D12) -> 0 | E13: =SUM(E9:E12) -> 27687.416 | F13: =SUM(F9:F12) -> 20932.234 | G13: =SUM(G9:G12) -> 13088.459 | H13: =SUM(H9:H12) -> 72616.522 | I13: =SUM(I9:I12) -> 39751.057 | J13: =SUM(J9:J12) -> 19015.928 | K13: =SUM(K9:K12) -> 193091.62
A14: D | B14: Theoretical Balance | C14: Kg | D14: =D6-D13 -> 0 | E14: =E6-E13 -> 18409.324 | F14: =F6-F13 -> 22495.576 | G14: =G6-G13 -> 16309.421 | H14: =H6-H13 -> 39931.588 | I14: =I6-I13 -> 29123.133 | J14: =J6-J13 -> 5624.0723 | K14: =SUM(D14:J14) -> 131893.11
A15: E | B15: Steel available at yard | C15: Kg | D15: 0 | E15: 6000 | F15: 17000 | G15: 10000 | H15: 24500 | I15: 23500 | J15: 4800 | K15: =SUM(D15:J15) -> 85800
A16: F | B16: Dowel Steel in column | C16: Kg | G16: 1936.242 | H16: 2406.7429 | I16: 1462.5684 | J16: 272.58 | K16: =SUM(E16:J16) -> 6078.1333
B17: W.I.P. Steel in column | C17: Kg | E17: 4818.3996 | F17: 5267.1141 | G17: 2814.1651 | H17: 5637.993 | I17: 3369.6488 | J17: 422.96 | K17: =SUM(E17:J17) -> 22330.281
B18: W.I.P. Steel in slab (1-22) | C18: Kg | E18: 6500 | F18: 0 | G18: 1000 | H18: 5500 | I18: 0 | K18: =SUM(E18:J18) -> 13000
K19: =SUM(D19:J19) -> 0
A20: G | B20: Total In Progress | C20: Kg | D20: =SUM(D16:D19) -> 0 | E20: =SUM(E16:E19) -> 11318.4 | F20: =SUM(F16:F19) -> 5267.1141 | G20: =SUM(G16:G19) -> 5750.4071 | H20: =SUM(H16:H19) -> 13544.736 | I20: =SUM(I16:I19) -> 4832.2172 | J20: =SUM(J16:J19) -> 695.54 | K20: =SUM(D20:J20) -> 41408.414
A23: H | B23: Wastage (D-E-G) | C23: Kg | D23: =D14-D15-D20 -> 0 | E23: =E14-E15-E20 -> 1090.9244 | F23: =F14-F15-F20 -> 228.4623 | G23: =G14-G15-G20 -> 559.01344 | H23: =H14-H15-H20 -> 1886.8522 | I23: =I14-I15-I20 -> 790.91618 | J23: =J14-J15-J20 -> 128.53232 | K23: =SUM(D23:J23) -> 4684.7009 | L23: =+K23/K13 -> 0.024261545
B24: SCRAP SALE | K24: 0
B25: Allowed Wastage 2.5% | C25: Kg | K25: =K13*2.5% -> 4827.2904

Sheet TMT STEEL REC.
A1: (OMAXE TOWER-E, PRAYAGRAJ )
A2: TMT STEEL BAR ISSUE BY OMAXE
A3: S.NO. | B3: DATE | C3: Unit | D3: 6mm Dia. | E3: 8mm Dia. | F3: 10mm Dia. | G3: 12mm Dia. | H3: 16mm Dia. | I3: 20mm Dia. | J3: 25mm Dia. | K3: TOTAL | L3: COMULAT.
A5: 1 | B5: RECEIVED FROM OMAXE AT 19/4/25 | C5: KG | G5: 7700 | H5: 37621 | I5: 9370 | J5: 5474 | K5: =SUM(D5:J5) -> 60165 | L5: =K5 -> 60165
A6: 2 | B6: RECEIVED FROM OMAXE AT 13/5/25 | C6: KG | E6: 9070 | F6: 6840 | I6: 20010 | K6: =SUM(D6:J6) -> 35920 | L6: =L5+K6 -> 96085
A7: 3 | B7: RECEIVED FROM OMAXE AT 17/5/25 | C7: KG | H7: 29850 | J7: 9850 | K7: =SUM(D7:J7) -> 39700 | L7: =L6+K7 -> 135785
A8: 4 | B8: RECEIVED FROM OMAXE AT 03/6/25 | C8: KG | G8: 3766 | I8: 6282 | J8: 3148 | K8: =SUM(D8:J8) -> 13196 | L8: =L7+K8 -> 148981
A9: 5 | B9: RECEIVED FROM OMAXE AT 03/6/25 | C9: KG | I9: 4800 | K9: =SUM(D9:J9) -> 4800 | L9: =L8+K9 -> 153781
A10: 6 | B10: RECEIVED FROM OMAXE AT 29/6/25 | C10: KG | F10: 6101 | H10: 10573 | I10: 2344 | K10: =SUM(D10:J10) -> 19018 | L10: =L9+K10 -> 172799
A11: 7 | B11: TRANSFER FROM LIG AT 5/8/25 | C11: KG | G11: 1505 | H11: 1758 | I11: 892 | K11: =SUM(D11:J11) -> 4155 | L11: =L10+K11 -> 176954
A12: 8 | B12: TRANSFER TO LIG AT 7/8/25 | C12: KG | F12: -1419 | K12: =SUM(D12:J12) -> -1419 | L12: =L11+K12 -> 175535
A13: 9 | B13: RECEIVED FROM OMAXE AT 7/8/25 | C13: KG | E13: 2874 | F13: 2860 | K13: =SUM(D13:J13) -> 5734 | L13: =L12+K13 -> 181269
A14: 10 | B14: RECEIVED FROM OMAXE AT 22/8/25 | C14: KG | E14: 26488 | F14: 12498 | G14: 3334 | K14: =SUM(D14:J14) -> 42320 | L14: =L13+K14 -> 223589
A15: 11 | B15: GIVE TO OMAXE AT 21/9/25 | C15: KG | E15: -2730 | F15: -3520 | K15: =SUM(D15:J15) -> -6250 | L15: =L14+K15 -> 217339
A16: 12 | B16: GIVE TO OMAXE AT 08/10/25 | C16: KG | E16: -5620 | K16: =SUM(D16:J16) -> -5620 | L16: =L15+K16 -> 211719
A17: 13 | B17: RECEIVED FROM OMAXE AT 17/10/25 | C17: KG | H17: 14269 | I17: 11506 | J17: 3502 | K17: =SUM(D17:J17) -> 29277 | L17: =L16+K17 -> 240996
A18: 14 | B18: RECEIVED FROM OMAXE AT 10/12/25 | C18: KG | E18: 5472 | H18: 12742 | K18: =SUM(D18:J18) -> 18214 | L18: =L17+K18 -> 259210
A19: 15 | B19: RECEIVED FROM OMAXE AT 13/12/25 | C19: KG | G19: 8880 | I19: 11167 | K19: =SUM(D19:J19) -> 20047 | L19: =L18+K19 -> 279257
A20: 16 | B20: RECEIVED FROM OMAXE AT 22/12/25 | C20: KG | F20: 13058 | K20: =SUM(D20:J20) -> 13058 | L20: =L19+K20 -> 292315
A21: 17 | B21: RECEIVED FROM OMAXE AT 30/12/25 | C21: KG | H21: 3237 | J21: 3078 | K21: =SUM(D21:J21) -> 6315 | L21: =L20+K21 -> 298630
A22: 18 | B22: TRANSFER FROM SHIVA-3 AT 03/01/26 | C22: KG | E22: 3011 | K22: =SUM(D22:J22) -> 3011 | L22: =L21+K22 -> 301641
A23: 19 | B23: TRANSFER FROM MLP AT 03/01/26 | C23: KG | E23: 3175 | K23: =SUM(D23:J23) -> 3175 | L23: =L22+K23 -> 304816
A24: 20 | B24: RECEIVED FROM OMAXE AT 11/01/26 | C24: KG | E24: 1422 | K24: =SUM(D24:J24) -> 1422 | L24: =L23+K24 -> 306238
A25: 21 | B25: RECEIVED FROM OMAXE AT 21/01/26 | C25: KG | E25: 12124 | F25: 8657 | G25: 8936 | H25: 6810 | I25: 5492 | K25: =SUM(D25:J25) -> 42019 | L25: =L24+K25 -> 348257
A26: 22 | B26: TRANSFER TO EWS T-3 | E26: -8188 | F26: -793 | G26: -2794 | H26: -3696.59 | I26: -740.55 | K26: =SUM(D26:J26) -> -16212.14 | L26: =L25+K26 -> 332044.86
A27: 23 | B27: TRANSFER TO LIG T-1 | E27: -1001.26 | F27: -854.19 | G27: -1929.12 | H27: -615.3 | I27: -2248.26 | J27: -412 | K27: =SUM(D27:J27) -> -7060.13 | L27: =L26+K27 -> 324984.73
K28: =SUM(D28:J28) -> 0 | L28: =L27+K28 -> 324984.73
B31: TOTAL QTY. | D31: =SUM(D4:D30) -> 0 | E31: =SUM(E4:E30) -> 46096.74 | F31: =SUM(F4:F30) -> 43427.81 | G31: =SUM(G4:G30) -> 29397.88 | H31: =SUM(H4:H30) -> 112548.11 | I31: =SUM(I4:I30) -> 68874.19 | J31: =SUM(J4:J30) -> 24640 | K31: =SUM(K4:K30) -> 324984.73 | L31: KG

Sheet TMT SUMMARY
A1: (OMAXE TOWER-E, PRAYAGRAJ )
A2: STEEL CONSUMPTION SUMMARY
A3: S.NO. | B3: DESCRIPTION | C3: LOCATION | D3: Unit | E3: NOS | F3: 6mm Dia. | G3: 8mm Dia. | H3: 10mm Dia. | I3: 12mm Dia. | J3: 16mm Dia. | K3: 20mm Dia. | L3: 25mm Dia. | M3: TOTAL
B4: 4.1 TMT REINFORCEMENT
A5: 4.1.1. | B5: UPTO STILT FLOOR LVL
A6: 1 | B6: TOWER-E COLUMN GRID (22-23/A-Q) | C6: UPTO RAFT | D6: KG | E6: 1 | G6: ='COL BBS'!P615*$E$6 -> 0 | H6: ='COL BBS'!Q615*$E$6 -> 752.92149 | I6: ='COL BBS'!R615*$E$6 -> 352.90008 | J6: ='COL BBS'!S615*$E$6 -> 875.36424 | K6: ='COL BBS'!T615*$E$6 -> 698.34677 | L6: ='COL BBS'!U615*$E$6 -> 76.61988 | M6: =SUM(F6:L6) -> 2756.1525
A7: 2 | B7: TOWER-E RAFT GRID (22-23/A-Q) | C7: AS SUB-STRUCTURE | D7: KG | E7: 1 | G7: ='RAFT BBS'!Q786*$E$7 -> 0 | H7: ='RAFT BBS'!R786*$E$7 -> 574.24807 | I7: ='RAFT BBS'!S786*$E$7 -> 1139.0793 | J7: ='RAFT BBS'!T786*$E$7 -> 24893.957 | K7: ='RAFT BBS'!U786*$E$7 -> 15376.006 | L7: ='RAFT BBS'!V786*$E$7 -> 8483.9735 | M7: =SUM(F7:L7) -> 50467.264
A8: 3 | B8: TOWER-E COLUMN GRID (1-22/A-Q) | C8: UPTO RAFT | D8: KG | E8: 1 | G8: ='COL BBS'!P615*$E$8 -> 0 | H8: ='COL BBS'!Q615*$E$8 -> 752.92149 | I8: ='COL BBS'!R615*$E$8 -> 352.90008 | J8: ='COL BBS'!S615*$E$8 -> 875.36424 | K8: ='COL BBS'!T615*$E$8 -> 698.34677 | L8: ='COL BBS'!U615*$E$8 -> 76.61988 | M8: =SUM(F8:L8) -> 2756.1525
A9: 4 | B9: TOWER-E RAFT GRID (1-22/A-Q) | C9: AS SUB-STRUCTURE | D9: KG | E9: 1 | G9: ='RAFT BBS'!Q1572 -> 0 | H9: ='RAFT BBS'!R1572 -> 574.24807 | I9: ='RAFT BBS'!S1572 -> 1152.783 | J9: ='RAFT BBS'!T1572 -> 25482.949 | K9: ='RAFT BBS'!U1572 -> 15753.763 | L9: ='RAFT BBS'!V1572 -> 8483.9735 | M9: =SUM(F9:L9) -> 51447.717
A10: 5 | B10: TOWER-E PADESTIAL GRID (1-43/A-Q) | C10: AS SUB-STRUCTURE | D10: KG | E10: 1 | G10: ='COL BBS'!P1687 -> 1630.8341 | H10: ='COL BBS'!Q1687 -> 6329.7327 | I10: ='COL BBS'!R1687 -> 1135.8728 | J10: ='COL BBS'!S1687 -> 2996.767 | K10: ='COL BBS'!T1687 -> 2240.6669 | L10: ='COL BBS'!U1687 -> 259.2576 | M10: =SUM(F10:L10) -> 14593.131
A11: 6 | B11: COMPENSATORY STRIP GRID (22-23/B'-L') | C11: AS SUB-STRUCTURE | D11: KG | E11: 1 | G11: ='RAFT BBS'!Q1593 -> 0 | H11: ='RAFT BBS'!R1593 -> 0 | I11: ='RAFT BBS'!S1593 -> 0 | J11: ='RAFT BBS'!T1593 -> 139.84896 | K11: ='RAFT BBS'!U1593 -> 0 | L11: ='RAFT BBS'!V1593 -> 0 | M11: =SUM(F11:L11) -> 139.84896
A12: 7 | B12: PLINTH BEAM GRID (1-43/A-Q) | C12: AS SUB-STRUCTURE | D12: KG | E12: 1 | G12: ='PLINTH BEAM BBS'!M384 -> 3492.1437 | H12: ='PLINTH BEAM BBS'!N384 -> 131.69248 | I12: ='PLINTH BEAM BBS'!O384 -> 1475.6962 | J12: ='PLINTH BEAM BBS'!P384 -> 4761.2984 | K12: ='PLINTH BEAM BBS'!Q384 -> 147.5016 | L12: ='PLINTH BEAM BBS'!R384 -> 0 | M12: =SUM(F12:L12) -> 10008.332
F15: =SUM(F6:F14) -> 0 | G15: =SUM(G6:G14) -> 5122.9778 | H15: =SUM(H6:H14) -> 9115.7643 | I15: =SUM(I6:I14) -> 5609.2314 | J15: =SUM(J6:J14) -> 60025.549 | K15: =SUM(K6:K14) -> 34914.631 | L15: =SUM(L6:L14) -> 17380.444 | M15: =SUM(M6:M14) -> 132168.6
A16: 4.1.2. | B16: Stilt Floor level to to Terrace Including OHT, Mumty, Machine Room, Parapet)
A17: 1 | B17: COLUMN PLINTH TO 1ST FLOOR LVL (1-43/A-Q) | C17: AS SUPER-STRUCTURE | D17: KG | E17: 1 | G17: ='TYP COL BBS'!M215*$E17 -> 4818.3996 | H17: ='TYP COL BBS'!N215*$E17 -> 6767.1141 | I17: ='TYP COL BBS'!O215*$E17 -> 2814.1651 | J17: ='TYP COL BBS'!P215*$E17 -> 5637.993 | K17: ='TYP COL BBS'!Q215*$E17 -> 4369.6488 | L17: ='TYP COL BBS'!R215*$E17 -> 1422.96 | M17: =SUM(F17:L17) -> 25830.281
A18: 2 | B18: 1ST FLOOR LVL SLAB (22-43/A-Q) | C18: AS SUPER-STRUCTURE | D18: KG | E18: 1 | G18: =('1ST FLOOR LVL SLAB BBS'!M490+'1ST FLOOR LVL SLAB BBS'!M1208)*$E18 -> 8854.9441 | H18: =('1ST FLOOR LVL SLAB BBS'!N490+'1ST FLOOR LVL SLAB BBS'!N1208)*$E18 -> 2524.6776 | I18: =('1ST FLOOR LVL SLAB BBS'!O490+'1ST FLOOR LVL SLAB BBS'!O1208)*$E18 -> 2329.9078 | J18: =('1ST FLOOR LVL SLAB BBS'!P490+'1ST FLOOR LVL SLAB BBS'!P1208)*$E18 -> 3476.4898 | K18: =('1ST FLOOR LVL SLAB BBS'!Q490+'1ST FLOOR LVL SLAB BBS'!Q1208)*$E18 -> 225.4863 | L18: =('1ST FLOOR LVL SLAB BBS'!R490+'1ST FLOOR LVL SLAB BBS'!R1208)*$E18 -> 104.566 | M18: =SUM(F18:L18) -> 17516.072 | O18: 17516
A19: 3 | B19: 1ST FLOOR LVL SLAB (1-22/A-Q) | C19: AS SUPER-STRUCTURE | D19: KG | E19: 1 | G19: =('1ST FLOOR LVL SLAB BBS'!M490+'1ST FLOOR LVL SLAB BBS'!M1208)*$E19 -> 8854.9441 | H19: =('1ST FLOOR LVL SLAB BBS'!N490+'1ST FLOOR LVL SLAB BBS'!N1208)*$E19 -> 2524.6776 | I19: =('1ST FLOOR LVL SLAB BBS'!O490+'1ST FLOOR LVL SLAB BBS'!O1208)*$E19 -> 2329.9078 | J19: =('1ST FLOOR LVL SLAB BBS'!P490+'1ST FLOOR LVL SLAB BBS'!P1208)*$E19 -> 3476.4898 | K19: =('1ST FLOOR LVL SLAB BBS'!Q490+'1ST FLOOR LVL SLAB BBS'!Q1208)*$E19 -> 225.4863 | L19: =('1ST FLOOR LVL SLAB BBS'!R490+'1ST FLOOR LVL SLAB BBS'!R1208)*$E19 -> 104.566 | M19: =SUM(F19:L19) -> 17516.072 | O19: 17516
A20: 3 | B20: COLUMN 1ST TO 2ND FLOOR LVL (1-43/A-Q) | C20: AS SUPER-STRUCTURE | D20: KG | E20: 0.5 | G20: ='TYP COL BBS'!M424*$E20 -> 2166.891 | H20: ='TYP COL BBS'!N424*$E20 -> 2758.388 | I20: ='TYP COL BBS'!O424*$E20 -> 1936.242 | J20: ='TYP COL BBS'!P424*$E20 -> 2406.7429 | K20: ='TYP COL BBS'!Q424*$E20 -> 1462.5684 | L20: ='TYP COL BBS'!R424*$E20 -> 272.58 | M20: =SUM(F20:L20) -> 11003.412 | O20: 17516
F22: =SUM(F17:F21) -> 0 | G22: =SUM(G17:G21) -> 24695.179 | H22: =SUM(H17:H21) -> 14574.857 | I22: =SUM(I17:I21) -> 9410.2226 | J22: =SUM(J17:J21) -> 14997.715 | K22: =SUM(K17:K21) -> 6283.1898 | L22: =SUM(L17:L21) -> 1904.672 | M22: =SUM(M17:M21) -> 71865.836
A23: 4.1.3. | B23: All type of Moulding, Bands, Elevation/Architectural Features as per drawing and as directed by EIC. at all level
A24: 1 | B24: COLUMN CLIT FIXING WORK (RAFT COL., G.F.) | D24: KG | E24: 2 | G24: ='RAFT BBS'!Q1607*$E24 -> 36.1504 | H24: ='RAFT BBS'!R1607*$E24 -> 0 | I24: ='RAFT BBS'!S1607*$E24 -> 0 | J24: ='RAFT BBS'!T1607*$E24 -> 0 | K24: ='RAFT BBS'!U1607*$E24 -> 0 | L24: ='RAFT BBS'!V1607*$E24 -> 0 | M24: =SUM(F24:L24) -> 36.1504
A25: 2 | M25: =SUM(F25:L25) -> 0
F27: =SUM(F24:F26) -> 0 | G27: =SUM(G24:G26) -> 36.1504 | H27: =SUM(H24:H26) -> 0 | I27: =SUM(I24:I26) -> 0 | J27: =SUM(J24:J26) -> 0 | K27: =SUM(K24:K26) -> 0 | L27: =SUM(L24:L26) -> 0 | M27: =SUM(M24:M26) -> 36.1504
M29: =M15+M22+M27 -> 204070.58

Sheet RAFT BBS
A1: TOWER-E RAFT BBS
A2: TOWER-E RAFT BBS GRID (22'-43/A-Q)
A3: S.No. | B3: Description | C3: Shape of Bar in mm | G3: Spacing c/c | H3: Dia of Bar | I3: No's of Set | J3: No's of Bar | K3: Actual Length | L3: Lap | M3: No. Of Bend | N3: Deduction In mm | O3: Cut Length | P3: Total Length | Q3: TMT BAR Fe-500D or EQR | W3: Remarks
A4: A | B4: RAFT | Q4: 8mm | R4: 10mm | S4: 12mm | T4: 16mm | U4: 20mm | V4: 25mm
B5: BOTTOM MAIN BAR | Q5: =IF($H5=8,$P5,"") | R5: =IF($H5=10,$P5,"") | S5: =IF($H5=12,$P5,"") | T5: =IF($H5=16,$P5,"") | U5: =IF($H5=20,$P5,"") | V5: =IF($H5=25,$P5,"")
A6: 1 | B6: GRID (39'-43/E'-Q') | Q6: =IF($H6=8,$P6,"") | R6: =IF($H6=10,$P6,"") | S6: =IF($H6=12,$P6,"") | T6: =IF($H6=16,$P6,"") | U6: =IF($H6=20,$P6,"") | V6: =IF($H6=25,$P6,"")
B7: MAIN BAR BOTTOM (ALTH.) | C7: 0.5 | D7: =21.65-2*0.05 -> 21.55 | F7: 0.5 | G7: 0.25 | H7: 16 | I7: 1 | J7: =ROUNDDOWN(8.855/G7/2+1,0) -> 18 | K7: =D7 -> 21.55 | L7: =IF(O7<12,"0",0.049*H7)*2 -> 1.568 | M7: 2 | N7: =M7*2*H7/1000 -> 0.064 | O7: =(D7+C7+F7)-N7 -> 22.486 | P7: =(I7*J7*O7)+L7 -> 406.316 | Q7: =IF($H7=8,$P7,"") | R7: =IF($H7=10,$P7,"") | S7: =IF($H7=12,$P7,"") | T7: =IF($H7=16,$P7,"") -> 406.316 | U7: =IF($H7=20,$P7,"") | V7: =IF($H7=25,$P7,"")
Q8: =IF($H8=8,$P8,"") | R8: =IF($H8=10,$P8,"") | S8: =IF($H8=12,$P8,"") | T8: =IF($H8=16,$P8,"") | U8: =IF($H8=20,$P8,"") | V8: =IF($H8=25,$P8,"")
A9: 1 | B9: GRID (39'-43/E'-Q') | Q9: =IF($H9=8,$P9,"") | R9: =IF($H9=10,$P9,"") | S9: =IF($H9=12,$P9,"") | T9: =IF($H9=16,$P9,"") | U9: =IF($H9=20,$P9,"") | V9: =IF($H9=25,$P9,"")
B10: MAIN BAR BOTTOM (ALTH.) | C10: 0.5 | D10: =21.65-2*0.05 -> 21.55 | F10: 0.5 | G10: 0.25 | H10: 16 | I10: 1 | J10: =ROUNDDOWN(8.855/G10/2,0) -> 17 | K10: =D10 -> 21.55 | L10: =IF(O10<12,"0",0.049*H10) -> 0.784 | M10: 2 | N10: =M10*2*H10/1000 -> 0.064 | O10: =(D10+C10+F10)-N10 -> 22.486 | P10: =(I10*J10*O10)+L10 -> 383.046 | Q10: =IF($H10=8,$P10,"") | R10: =IF($H10=10,$P10,"") | S10: =IF($H10=12,$P10,"") | T10: =IF($H10=16,$P10,"") -> 383.046 | U10: =IF($H10=20,$P10,"") | V10: =IF($H10=25,$P10,"")
Q11: =IF($H11=8,$P11,"") | R11: =IF($H11=10,$P11,"") | S11: =IF($H11=12,$P11,"") | T11: =IF($H11=16,$P11,"") | U11: =IF($H11=20,$P11,"") | V11: =IF($H11=25,$P11,"")
A12: 2 | B12: GRID (38'-39'/E'-Q') | Q12: =IF($H12=8,$P12,"") | R12: =IF($H12=10,$P12,"") | S12: =IF($H12=12,$P12,"") | T12: =IF($H12=16,$P12,"") | U12: =IF($H12=20,$P12,"") | V12: =IF($H12=25,$P12,"")
B13: MAIN BAR BOTTOM (ALTH.) | C13: 0.5 | D13: =21.65+0.515-2*0.05 -> 22.065 | F13: 0.5 | G13: 0.25 | H13: 16 | I13: 1 | J13: =ROUNDDOWN(2.535/G13/2+1,0) -> 6 | K13: =D13 -> 22.065 | L13: =IF(O13<12,"0",0.049*H13)*2 -> 1.568 | M13: 2 | N13: =M13*2*H13/1000 -> 0.064 | O13: =(D13+C13+F13)-N13 -> 23.001 | P13: =(I13*J13*O13)+L13 -> 139.574 | Q13: =IF($H13=8,$P13,"") | R13: =IF($H13=10,$P13,"") | S13: =IF($H13=12,$P13,"") | T13: =IF($H13=16,$P13,"") -> 139.574 | U13: =IF($H13=20,$P13,"") | V13: =IF($H13=25,$P13,"")
Q14: =IF($H14=8,$P14,"") | R14: =IF($H14=10,$P14,"") | S14: =IF($H14=12,$P14,"") | T14: =IF($H14=16,$P14,"") | U14: =IF($H14=20,$P14,"") | V14: =IF($H14=25,$P14,"")
A15: 2 | B15: GRID (38'-39'/E'-Q') | Q15: =IF($H15=8,$P15,"") | R15: =IF($H15=10,$P15,"") | S15: =IF($H15=12,$P15,"") | T15: =IF($H15=16,$P15,"") | U15: =IF($H15=20,$P15,"") | V15: =IF($H15=25,$P15,"")
B16: MAIN BAR BOTTOM (ALTH.) | C16: 0.5 | D16: =21.65+0.515-2*0.05 -> 22.065 | F16: 0.5 | G16: 0.25 | H16: 16 | I16: 1 | J16: =ROUNDDOWN(2.535/G16/2,0) -> 5 | K16: =D16 -> 22.065 | L16: =IF(O16<12,"0",0.049*H16) -> 0.784 | M16: 2 | N16: =M16*2*H16/1000 -> 0.064 | O16: =(D16+C16+F16)-N16 -> 23.001 | P16: =(I16*J16*O16)+L16 -> 115.789 | Q16: =IF($H16=8,$P16,"") | R16: =IF($H16=10,$P16,"") | S16: =IF($H16=12,$P16,"") | T16: =IF($H16=16,$P16,"") -> 115.789 | U16: =IF($H16=20,$P16,"") | V16: =IF($H16=25,$P16,"")
Q17: =IF($H17=8,$P17,"") | R17: =IF($H17=10,$P17,"") | S17: =IF($H17=12,$P17,"") | T17: =IF($H17=16,$P17,"") | U17: =IF($H17=20,$P17,"") | V17: =IF($H17=25,$P17,"")
A18: 3 | B18: GRID (32'-38'/A-Q') | Q18: =IF($H18=8,$P18,"") | R18: =IF($H18=10,$P18,"") | S18: =IF($H18=12,$P18,"") | T18: =IF($H18=16,$P18,"") | U18: =IF($H18=20,$P18,"") | V18: =IF($H18=25,$P18,"")
B19: MAIN BAR BOTTOM (ALTH.) | C19: 0.5 | D19: =32.45-2*0.05 -> 32.35 | F19: 0.5 | G19: 0.25 | H19: 16 | I19: 1 | J19: =ROUND(6.245/G19/2+1,0) -> 13 | K19: =D19 -> 32.35 | L19: =IF(O19<12,"0",0.049*H19)*3 -> 2.352 | M19: 2 | N19: =M19*2*H19/1000 -> 0.064 | O19: =(D19+C19+F19)-N19 -> 33.286 | P19: =(I19*J19*O19)+L19 -> 435.07 | Q19: =IF($H19=8,$P19,"") | R19: =IF($H19=10,$P19,"") | S19: =IF($H19=12,$P19,"") | T19: =IF($H19=16,$P19,"") -> 435.07 | U19: =IF($H19=20,$P19,"") | V19: =IF($H19=25,$P19,"")
Q20: =IF($H20=8,$P20,"") | R20: =IF($H20=10,$P20,"") | S20: =IF($H20=12,$P20,"") | T20: =IF($H20=16,$P20,"") | U20: =IF($H20=20,$P20,"") | V20: =IF($H20=25,$P20,"")
A21: 3 | B21: GRID (32'-38'/A-Q') | Q21: =IF($H21=8,$P21,"") | R21: =IF($H21=10,$P21,"") | S21: =IF($H21=12,$P21,"") | T21: =IF($H21=16,$P21,"") | U21: =IF($H21=20,$P21,"") | V21: =IF($H21=25,$P21,"")
B22: MAIN BAR BOTTOM (ALTH.) | C22: 0.5 | D22: =32.45-2*0.05 -> 32.35 | F22: 0.5 | G22: 0.25 | H22: 16 | I22: 1 | J22: =ROUND(6.245/G22/2+0,0) -> 12 | K22: =D22 -> 32.35 | L22: =IF(O22<12,"0",0.049*H22)*2 -> 1.568 | M22: 2 | N22: =M22*2*H22/1000 -> 0.064 | O22: =(D22+C22+F22)-N22 -> 33.286 | P22: =(I22*J22*O22)+L22 -> 401 | Q22: =IF($H22=8,$P22,"") | R22: =IF($H22=10,$P22,"") | S22: =IF($H22=12,$P22,"") | T22: =IF($H22=16,$P22,"") -> 401 | U22: =IF($H22=20,$P22,"") | V22: =IF($H22=25,$P22,"")
Q23: =IF($H23=8,$P23,"") | R23: =IF($H23=10,$P23,"") | S23: =IF($H23=12,$P23,"") | T23: =IF($H23=16,$P23,"") | U23: =IF($H23=20,$P23,"") | V23: =IF($H23=25,$P23,"")
A24: 4 | B24: GRID (30'-32'/A-Q') | Q24: =IF($H24=8,$P24,"") | R24: =IF($H24=10,$P24,"") | S24: =IF($H24=12,$P24,"") | T24: =IF($H24=16,$P24,"") | U24: =IF($H24=20,$P24,"") | V24: =IF($H24=25,$P24,"")
B25: MAIN BAR BOTTOM (ALTH.) | C25: 0.5 | D25: =31.935-2*0.05 -> 31.835 | F25: 0.5 | G25: 0.25 | H25: 16 | I25: 1 | J25: =ROUND(2.63/G25/2+1,0) -> 6 | K25: =D25 -> 31.835 | L25: =IF(O25<12,"0",0.049*H25)*3 -> 2.352 | M25: 2 | N25: =M25*2*H25/1000 -> 0.064 | O25: =(D25+C25+F25)-N25 -> 32.771 | P25: =(I25*J25*O25)+L25 -> 198.978 | Q25: =IF($H25=8,$P25,"") | R25: =IF($H25=10,$P25,"") | S25: =IF($H25=12,$P25,"") | T25: =IF($H25=16,$P25,"") -> 198.978 | U25: =IF($H25=20,$P25,"") | V25: =IF($H25=25,$P25,"")
Q26: =IF($H26=8,$P26,"") | R26: =IF($H26=10,$P26,"") | S26: =IF($H26=12,$P26,"") | T26: =IF($H26=16,$P26,"") | U26: =IF($H26=20,$P26,"") | V26: =IF($H26=25,$P26,"")
A27: 4 | B27: GRID (30'-32'/A-Q') | Q27: =IF($H27=8,$P27,"") | R27: =IF($H27=10,$P27,"") | S27: =IF($H27=12,$P27,"") | T27: =IF($H27=16,$P27,"") | U27: =IF($H27=20,$P27,"") | V27: =IF($H27=25,$P27,"")
B28: MAIN BAR BOTTOM (ALTH.) | C28: 0.5 | D28: =31.935-2*0.05 -> 31.835 | F28: 0.5 | G28: 0.25 | H28: 16 | I28: 1 | J28: =ROUND(2.63/G28/2,0) -> 5 | K28: =D28 -> 31.835 | L28: =IF(O28<12,"0",0.049*H28)*2 -> 1.568 | M28: 2 | N28: =M28*2*H28/1000 -> 0.064 | O28: =(D28+C28+F28)-N28 -> 32.771 | P28: =(I28*J28*O28)+L28 -> 165.423 | Q28: =IF($H28=8,$P28,"") | R28: =IF($H28=10,$P28,"") | S28: =IF($H28=12,$P28,"") | T28: =IF($H28=16,$P28,"") -> 165.423 | U28: =IF($H28=20,$P28,"") | V28: =IF($H28=25,$P28,"")
Q29: =IF($H29=8,$P29,"") | R29: =IF($H29=10,$P29,"") | S29: =IF($H29=12,$P29,"") | T29: =IF($H29=16,$P29,"") | U29: =IF($H29=20,$P29,"") | V29: =IF($H29=25,$P29,"")
A30: 5 | B30: GRID (27'-30/A-Q') | Q30: =IF($H30=8,$P30,"") | R30: =IF($H30=10,$P30,"") | S30: =IF($H30=12,$P30,"") | T30: =IF($H30=16,$P30,"") | U30: =IF($H30=20,$P30,"") | V30: =IF($H30=25,$P30,"")
B31: MAIN BAR BOTTOM (ALTH.) | C31: 0.5 | D31: =31.95-2*0.05-1.5 -> 30.35 | F31: 0.5 | G31: 0.25 | H31: 16 | I31: 1 | J31: =ROUND(3.95/G31/2+1,0) -> 9 | K31: =D31 -> 30.35 | L31: =IF(O31<12,"0",0.049*H31)*3 -> 2.352 | M31: 2 | N31: =M31*2*H31/1000 -> 0.064 | O31: =(D31+C31+F31)-N31 -> 31.286 | P31: =(I31*J31*O31)+L31 -> 283.926 | Q31: =IF($H31=8,$P31,"") | R31: =IF($H31=10,$P31,"") | S31: =IF($H31=12,$P31,"") | T31: =IF($H31=16,$P31,"") -> 283.926 | U31: =IF($H31=20,$P31,"") | V31: =IF($H31=25,$P31,"")
Q32: =IF($H32=8,$P32,"") | R32: =IF($H32=10,$P32,"") | S32: =IF($H32=12,$P32,"") | T32: =IF($H32=16,$P32,"") | U32: =IF($H32=20,$P32,"") | V32: =IF($H32=25,$P32,"")
A33: 5 | B33: GRID (27'-30/A-Q') | Q33: =IF($H33=8,$P33,"") | R33: =IF($H33=10,$P33,"") | S33: =IF($H33=12,$P33,"") | T33: =IF($H33=16,$P33,"") | U33: =IF($H33=20,$P33,"") | V33: =IF($H33=25,$P33,"")
B34: MAIN BAR BOTTOM (ALTH.) | C34: 0.5 | D34: =31.95-2*0.05-1.5 -> 30.35 | F34: 0.5 | G34: 0.25 | H34: 16 | I34: 1 | J34: =ROUND(3.95/G34/2,0) -> 8 | K34: =D34 -> 30.35 | L34: =IF(O34<12,"0",0.049*H34)*2 -> 1.568 | M34: 2 | N34: =M34*2*H34/1000 -> 0.064 | O34: =(D34+C34+F34)-N34 -> 31.286 | P34: =(I34*J34*O34)+L34 -> 251.856 | Q34: =IF($H34=8,$P34,"") | R34: =IF($H34=10,$P34,"") | S34: =IF($H34=12,$P34,"") | T34: =IF($H34=16,$P34,"") -> 251.856 | U34: =IF($H34=20,$P34,"") | V34: =IF($H34=25,$P34,"")
Q35: =IF($H35=8,$P35,"") | R35: =IF($H35=10,$P35,"") | S35: =IF($H35=12,$P35,"") | T35: =IF($H35=16,$P35,"") | U35: =IF($H35=20,$P35,"") | V35: =IF($H35=25,$P35,"")
A36: 6 | B36: GRID (26'-27'/A'-Q') | Q36: =IF($H36=8,$P36,"") | R36: =IF($H36=10,$P36,"") | S36: =IF($H36=12,$P36,"") | T36: =IF($H36=16,$P36,"") | U36: =IF($H36=20,$P36,"") | V36: =IF($H36=25,$P36,"")
B37: MAIN BAR BOTTOM (ALTH.) | C37: 0.5 | D37: =31.95-2*0.05-1.5-0.815 -> 29.535 | F37: 0.5 | G37: 0.25 | H37: 16 | I37: 1 | J37: =ROUND(1.695/G37/2+1,0) -> 4 | K37: =D37 -> 29.535 | L37: =IF(O37<12,"0",0.049*H37)*3 -> 2.352 | M37: 2 | N37: =M37*2*H37/1000 -> 0.064 | O37: =(D37+C37+F37)-N37 -> 30.471 | P37: =(I37*J37*O37)+L37 -> 124.236 | Q37: =IF($H37=8,$P37,"") | R37: =IF($H37=10,$P37,"") | S37: =IF($H37=12,$P37,"") | T37: =IF($H37=16,$P37,"") -> 124.236 | U37: =IF($H37=20,$P37,"") | V37: =IF($H37=25,$P37,"")
Q38: =IF($H38=8,$P38,"") | R38: =IF($H38=10,$P38,"") | S38: =IF($H38=12,$P38,"") | T38: =IF($H38=16,$P38,"") | U38: =IF($H38=20,$P38,"") | V38: =IF($H38=25,$P38,"")
A39: 6 | B39: GRID (26'-27'/A'-Q') | Q39: =IF($H39=8,$P39,"") | R39: =IF($H39=10,$P39,"") | S39: =IF($H39=12,$P39,"") | T39: =IF($H39=16,$P39,"") | U39: =IF($H39=20,$P39,"") | V39: =IF($H39=25,$P39,"")
B40: MAIN BAR BOTTOM (ALTH.) | C40: 0.5 | D40: =31.95-2*0.05-1.5-0.815 -> 29.535 | F40: 0.5 | G40: 0.25 | H40: 16 | I40: 1 | J40: =ROUND(1.695/G40/2,0) -> 3 | K40: =D40 -> 29.535 | L40: =IF(O40<12,"0",0.049*H40)*2 -> 1.568 | M40: 2 | N40: =M40*2*H40/1000 -> 0.064 | O40: =(D40+C40+F40)-N40 -> 30.471 | P40: =(I40*J40*O40)+L40 -> 92.981 | Q40: =IF($H40=8,$P40,"") | R40: =IF($H40=10,$P40,"") | S40: =IF($H40=12,$P40,"") | T40: =IF($H40=16,$P40,"") -> 92.981 | U40: =IF($H40=20,$P40,"") | V40: =IF($H40=25,$P40,"")
Q41: =IF($H41=8,$P41,"") | R41: =IF($H41=10,$P41,"") | S41: =IF($H41=12,$P41,"") | T41: =IF($H41=16,$P41,"") | U41: =IF($H41=20,$P41,"") | V41: =IF($H41=25,$P41,"")
A42: 7 | B42: GRID (22'-26'/B-Q') | Q42: =IF($H42=8,$P42,"") | R42: =IF($H42=10,$P42,"") | S42: =IF($H42=12,$P42,"") | T42: =IF($H42=16,$P42,"") | U42: =IF($H42=20,$P42,"") | V42: =IF($H42=25,$P42,"")
B43: MAIN BAR BOTTOM (ALTH.) | C43: 0.5 | D43: =15.8-2*0.05 -> 15.7 | F43: 0.5 | G43: 0.25 | H43: 16 | I43: 1 | J43: =ROUND(11.285/G43+1,0) -> 46 | K43: =D43 -> 15.7 | L43: =IF(O43<12,"0",0.049*H43) -> 0.784 | M43: 2 | N43: =M43*2*H43/1000 -> 0.064 | O43: =(D43+C43+F43)-N43 -> 16.636 | P43: =(I43*J43*O43)+L43 -> 766.04 | Q43: =IF($H43=8,$P43,"") | R43: =IF($H43=10,$P43,"") | S43: =IF($H43=12,$P43,"") | T43: =IF($H43=16,$P43,"") -> 766.04 | U43: =IF($H43=20,$P43,"") | V43: =IF($H43=25,$P43,"")
Q44: =IF($H44=8,$P44,"") | R44: =IF($H44=10,$P44,"") | S44: =IF($H44=12,$P44,"") | T44: =IF($H44=16,$P44,"") | U44: =IF($H44=20,$P44,"") | V44: =IF($H44=25,$P44,"")
Q45: =IF($H45=8,$P45,"") | R45: =IF($H45=10,$P45,"") | S45: =IF($H45=12,$P45,"") | T45: =IF($H45=16,$P45,"") | U45: =IF($H45=20,$P45,"") | V45: =IF($H45=25,$P45,"")
B46: BOTTOM DISTRIBUTION BAR | Q46: =IF($H46=8,$P46,"") | R46: =IF($H46=10,$P46,"") | S46: =IF($H46=12,$P46,"") | T46: =IF($H46=16,$P46,"") | U46: =IF($H46=20,$P46,"") | V46: =IF($H46=25,$P46,"")
A47: 1 | B47: GRID (30-38'/A) | Q47: =IF($H47=8,$P47,"") | R47: =IF($H47=10,$P47,"") | S47: =IF($H47=12,$P47,"") | T47: =IF($H47=16,$P47,"") | U47: =IF($H47=20,$P47,"") | V47: =IF($H47=25,$P47,"")
B48: DIST. BAR BOTTOM (ALTH.) | C48: 0.5 | D48: =8.875-2*0.05 -> 8.775 | F48: 0.5 | G48: 0.25 | H48: 16 | I48: 1 | J48: =ROUND(1.5/G48+1,0) -> 7 | K48: =D48 -> 8.775 | L48: =IF(O48<12,"0",0.049*H48) -> 0 | M48: 2 | N48: =M48*2*H48/1000 -> 0.064 | O48: =(D48+C48+F48)-N48 -> 9.711 | P48: =(I48*J48*O48)+L48 -> 67.977 | Q48: =IF($H48=8,$P48,"") | R48: =IF($H48=10,$P48,"") | S48: =IF($H48=12,$P48,"") | T48: =IF($H48=16,$P48,"") -> 67.977 | U48: =IF($H48=20,$P48,"") | V48: =IF($H48=25,$P48,"")
Q49: =IF($H49=8,$P49,"") | R49: =IF($H49=10,$P49,"") | S49: =IF($H49=12,$P49,"") | T49: =IF($H49=16,$P49,"") | U49: =IF($H49=20,$P49,"") | V49: =IF($H49=25,$P49,"")
A50: 2 | B50: GRID (27'-38'/A-B) | Q50: =IF($H50=8,$P50,"") | R50: =IF($H50=10,$P50,"") | S50: =IF($H50=12,$P50,"") | T50: =IF($H50=16,$P50,"") | U50: =IF($H50=20,$P50,"") | V50: =IF($H50=25,$P50,"")
B51: DIST. BAR BOTTOM (ALTH.) | C51: 0.5 | D51: =12.825-2*0.05 -> 12.725 | F51: 0.5 | G51: 0.25 | H51: 16 | I51: 1 | J51: =ROUND(0.815/G51+1,0) -> 4 | K51: =D51 -> 12.725 | L51: =IF(O51<12,"0",0.049*H51) -> 0.784 | M51: 2 | N51: =M51*2*H51/1000 -> 0.064 | O51: =(D51+C51+F51)-N51 -> 13.661 | P51: =(I51*J51*O51)+L51 -> 55.428 | Q51: =IF($H51=8,$P51,"") | R51: =IF($H51=10,$P51,"") | S51: =IF($H51=12,$P51,"") | T51: =IF($H51=16,$P51,"") -> 55.428 | U51: =IF($H51=20,$P51,"") | V51: =IF($H51=25,$P51,"")
Q52: =IF($H52=8,$P52,"") | R52: =IF($H52=10,$P52,"") | S52: =IF($H52=12,$P52,"") | T52: =IF($H52=16,$P52,"") | U52: =IF($H52=20,$P52,"") | V52: =IF($H52=25,$P52,"")
A53: 3 | B53: GRID (26'-38'/B-B') | Q53: =IF($H53=8,$P53,"") | R53: =IF($H53=10,$P53,"") | S53: =IF($H53=12,$P53,"") | T53: =IF($H53=16,$P53,"") | U53: =IF($H53=20,$P53,"") | V53: =IF($H53=25,$P53,"")
B54: DIST. BAR BOTTOM (ALTH.) | C54: 0.5 | D54: =14.52-2*0.05 -> 14.42 | F54: 0.5 | G54: 0.25 | H54: 16 | I54: 1 | J54: =ROUND(1.405/G54+1,0) -> 7 | K54: =D54 -> 14.42 | L54: =IF(O54<12,"0",0.049*H54) -> 0.784 | M54: 2 | N54: =M54*2*H54/1000 -> 0.064 | O54: =(D54+C54+F54)-N54 -> 15.356 | P54: =(I54*J54*O54)+L54 -> 108.276 | Q54: =IF($H54=8,$P54,"") | R54: =IF($H54=10,$P54,"") | S54: =IF($H54=12,$P54,"") | T54: =IF($H54=16,$P54,"") -> 108.276 | U54: =IF($H54=20,$P54,"") | V54: =IF($H54=25,$P54,"")
Q55: =IF($H55=8,$P55,"") | R55: =IF($H55=10,$P55,"") | S55: =IF($H55=12,$P55,"") | T55: =IF($H55=16,$P55,"") | U55: =IF($H55=20,$P55,"") | V55: =IF($H55=25,$P55,"")
A56: 4 | B56: GRID (22'-38'/B'-E') | Q56: =IF($H56=8,$P56,"") | R56: =IF($H56=10,$P56,"") | S56: =IF($H56=12,$P56,"") | T56: =IF($H56=16,$P56,"") | U56: =IF($H56=20,$P56,"") | V56: =IF($H56=25,$P56,"")
B57: DIST. BAR BOTTOM (ALTH.) | D57: =25.805-1*0.05 -> 25.755 | F57: 0.5 | G57: 0.25 | H57: 16 | I57: 1 | J57: =ROUND(6.565/G57+1,0) -> 27 | K57: =D57 -> 25.755 | L57: =IF(O57<12,"0",0.049*H57)*2 -> 1.568 | M57: 1 | N57: =M57*1*H57/1000 -> 0.016 | O57: =(D57+C57+F57)-N57 -> 26.239 | P57: =(I57*J57*O57)+L57 -> 710.021 | Q57: =IF($H57=8,$P57,"") | R57: =IF($H57=10,$P57,"") | S57: =IF($H57=12,$P57,"") | T57: =IF($H57=16,$P57,"") -> 710.021 | U57: =IF($H57=20,$P57,"") | V57: =IF($H57=25,$P57,"")
Q58: =IF($H58=8,$P58,"") | R58: =IF($H58=10,$P58,"") | S58: =IF($H58=12,$P58,"") | T58: =IF($H58=16,$P58,"") | U58: =IF($H58=20,$P58,"") | V58: =IF($H58=25,$P58,"")
A59: 5 | B59: GRID (22'-43'/E'-K) | Q59: =IF($H59=8,$P59,"") | R59: =IF($H59=10,$P59,"") | S59: =IF($H59=12,$P59,"") | T59: =IF($H59=16,$P59,"") | U59: =IF($H59=20,$P59,"") | V59: =IF($H59=25,$P59,"")
B60: DIST. BAR BOTTOM (ALTH.) | D60: =36.89-1*0.05 -> 36.84 | F60: 0.5 | G60: 0.25 | H60: 16 | I60: 1 | J60: =ROUND(9.235/G60+1,0)-8 -> 30 | K60: =D60 -> 36.84 | L60: =IF(O60<12,"0",0.049*H60)*3 -> 2.352 | M60: 1 | N60: =M60*1*H60/1000 -> 0.016 | O60: =(D60+C60+F60)-N60 -> 37.324 | P60: =(I60*J60*O60)+L60 -> 1122.072 | Q60: =IF($H60=8,$P60,"") | R60: =IF($H60=10,$P60,"") | S60: =IF($H60=12,$P60,"") | T60: =IF($H60=16,$P60,"") -> 1122.072 | U60: =IF($H60=20,$P60,"") | V60: =IF($H60=25,$P60,"")
Q61: =IF($H61=8,$P61,"") | R61: =IF($H61=10,$P61,"") | S61: =IF($H61=12,$P61,"") | T61: =IF($H61=16,$P61,"") | U61: =IF($H61=20,$P61,"") | V61: =IF($H61=25,$P61,"")
A62: 6 | B62: GRID (26'-43'/M-Q) | Q62: =IF($H62=8,$P62,"") | R62: =IF($H62=10,$P62,"") | S62: =IF($H62=12,$P62,"") | T62: =IF($H62=16,$P62,"") | U62: =IF($H62=20,$P62,"") | V62: =IF($H62=25,$P62,"")
B63: DIST. BAR BOTTOM (ALTH.) | C63: 0.5 | D63: =25.89-2*0.05 -> 25.79 | F63: 0.5 | G63: 0.25 | H63: 16 | I63: 1 | J63: =ROUND(12.415/G63+1,0) -> 51 | K63: =D63 -> 25.79 | L63: =IF(O63<12,"0",0.049*H63)*2 -> 1.568 | M63: 2 | N63: =M63*2*H63/1000 -> 0.064 | O63: =(D63+C63+F63)-N63 -> 26.726 | P63: =(I63*J63*O63)+L63 -> 1364.594 | Q63: =IF($H63=8,$P63,"") | R63: =IF($H63=10,$P63,"") | S63: =IF($H63=12,$P63,"") | T63: =IF($H63=16,$P63,"") -> 1364.594 | U63: =IF($H63=20,$P63,"") | V63: =IF($H63=25,$P63,"")
Q64: =IF($H64=8,$P64,"") | R64: =IF($H64=10,$P64,"") | S64: =IF($H64=12,$P64,"") | T64: =IF($H64=16,$P64,"") | U64: =IF($H64=20,$P64,"") | V64: =IF($H64=25,$P64,"")
A65: 7 | B65: GRID (33-39/Q') | Q65: =IF($H65=8,$P65,"") | R65: =IF($H65=10,$P65,"") | S65: =IF($H65=12,$P65,"") | T65: =IF($H65=16,$P65,"") | U65: =IF($H65=20,$P65,"") | V65: =IF($H65=25,$P65,"")
B66: DIST. BAR BOTTOM (ALTH.) | C66: 0.5 | D66: =8.78-2*0.05 -> 8.68 | F66: 0.5 | G66: 0.25 | H66: 16 | I66: 1 | J66: =ROUND(0.515/G66+1,0) -> 3 | K66: =D66 -> 8.68 | L66: =IF(O66<12,"0",0.049*H66) -> 0 | M66: 2 | N66: =M66*2*H66/1000 -> 0.064 | O66: =(D66+C66+F66)-N66 -> 9.616 | P66: =(I66*J66*O66)+L66 -> 28.848 | Q66: =IF($H66=8,$P66,"") | R66: =IF($H66=10,$P66,"") | S66: =IF($H66=12,$P66,"") | T66: =IF($H66=16,$P66,"") -> 28.848 | U66: =IF($H66=20,$P66,"") | V66: =IF($H66=25,$P66,"")
Q67: =IF($H67=8,$P67,"") | R67: =IF($H67=10,$P67,"") | S67: =IF($H67=12,$P67,"") | T67: =IF($H67=16,$P67,"") | U67: =IF($H67=20,$P67,"") | V67: =IF($H67=25,$P67,"")
Q68: =IF($H68=8,$P68,"") | R68: =IF($H68=10,$P68,"") | S68: =IF($H68=12,$P68,"") | T68: =IF($H68=16,$P68,"") | U68: =IF($H68=20,$P68,"") | V68: =IF($H68=25,$P68,"")
B69: TOP MAIN BAR | Q69: =IF($H69=8,$P69,"") | R69: =IF($H69=10,$P69,"") | S69: =IF($H69=12,$P69,"") | T69: =IF($H69=16,$P69,"") | U69: =IF($H69=20,$P69,"") | V69: =IF($H69=25,$P69,"")
A70: 1 | B70: GRID (39'-43/E'-Q') | Q70: =IF($H70=8,$P70,"") | R70: =IF($H70=10,$P70,"") | S70: =IF($H70=12,$P70,"") | T70: =IF($H70=16,$P70,"") | U70: =IF($H70=20,$P70,"") | V70: =IF($H70=25,$P70,"")
B71: MAIN BAR BOTTOM (ALTH.) | C71: 0.5 | D71: =21.65-2*0.05 -> 21.55 | F71: 0.5 | G71: 0.25 | H71: 16 | I71: 1 | J71: =ROUND(8.855/G71/2+1,0) -> 19 | K71: =D71 -> 21.55 | L71: =IF(O71<12,"0",0.049*H71)*2 -> 1.568 | M71: 2 | N71: =M71*2*H71/1000 -> 0.064 | O71: =(D71+C71+F71)-N71 -> 22.486 | P71: =(I71*J71*O71)+L71 -> 428.802 | Q71: =IF($H71=8,$P71,"") | R71: =IF($H71=10,$P71,"") | S71: =IF($H71=12,$P71,"") | T71: =IF($H71=16,$P71,"") -> 428.802 | U71: =IF($H71=20,$P71,"") | V71: =IF($H71=25,$P71,"")
Q72: =IF($H72=8,$P72,"") | R72: =IF($H72=10,$P72,"") | S72: =IF($H72=12,$P72,"") | T72: =IF($H72=16,$P72,"") | U72: =IF($H72=20,$P72,"") | V72: =IF($H72=25,$P72,"")
A73: 1 | B73: GRID (39'-43/E'-Q') | Q73: =IF($H73=8,$P73,"") | R73: =IF($H73=10,$P73,"") | S73: =IF($H73=12,$P73,"") | T73: =IF($H73=16,$P73,"") | U73: =IF($H73=20,$P73,"") | V73: =IF($H73=25,$P73,"")
B74: MAIN BAR BOTTOM (ALTH.) | C74: 0.5 | D74: =21.65-2*0.05 -> 21.55 | F74: 0.5 | G74: 0.25 | H74: 16 | I74: 1 | J74: =ROUND(8.855/G74/2,0) -> 18 | K74: =D74 -> 21.55 | L74: =IF(O74<12,"0",0.049*H74) -> 0.784 | M74: 2 | N74: =M74*2*H74/1000 -> 0.064 | O74: =(D74+C74+F74)-N74 -> 22.486 | P74: =(I74*J74*O74)+L74 -> 405.532 | Q74: =IF($H74=8,$P74,"") | R74: =IF($H74=10,$P74,"") | S74: =IF($H74=12,$P74,"") | T74: =IF($H74=16,$P74,"") -> 405.532 | U74: =IF($H74=20,$P74,"") | V74: =IF($H74=25,$P74,"")
Q75: =IF($H75=8,$P75,"") | R75: =IF($H75=10,$P75,"") | S75: =IF($H75=12,$P75,"") | T75: =IF($H75=16,$P75,"") | U75: =IF($H75=20,$P75,"") | V75: =IF($H75=25,$P75,"")
A76: 2 | B76: GRID (38'-39'/E'-Q') | Q76: =IF($H76=8,$P76,"") | R76: =IF($H76=10,$P76,"") | S76: =IF($H76=12,$P76,"") | T76: =IF($H76=16,$P76,"") | U76: =IF($H76=20,$P76,"") | V76: =IF($H76=25,$P76,"")
B77: MAIN BAR BOTTOM (ALTH.) | C77: 0.5 | D77: =21.65+0.515-2*0.05 -> 22.065 | F77: 0.5 | G77: 0.25 | H77: 16 | I77: 1 | J77: =ROUND(2.535/G77/2+1,0) -> 6 | K77: =D77 -> 22.065 | L77: =IF(O77<12,"0",0.049*H77)*2 -> 1.568 | M77: 2 | N77: =M77*2*H77/1000 -> 0.064 | O77: =(D77+C77+F77)-N77 -> 23.001 | P77: =(I77*J77*O77)+L77 -> 139.574 | Q77: =IF($H77=8,$P77,"") | R77: =IF($H77=10,$P77,"") | S77: =IF($H77=12,$P77,"") | T77: =IF($H77=16,$P77,"") -> 139.574 | U77: =IF($H77=20,$P77,"") | V77: =IF($H77=25,$P77,"")
Q78: =IF($H78=8,$P78,"") | R78: =IF($H78=10,$P78,"") | S78: =IF($H78=12,$P78,"") | T78: =IF($H78=16,$P78,"") | U78: =IF($H78=20,$P78,"") | V78: =IF($H78=25,$P78,"")
A79: 2 | B79: GRID (38'-39'/E'-Q') | Q79: =IF($H79=8,$P79,"") | R79: =IF($H79=10,$P79,"") | S79: =IF($H79=12,$P79,"") | T79: =IF($H79=16,$P79,"") | U79: =IF($H79=20,$P79,"") | V79: =IF($H79=25,$P79,"")
B80: MAIN BAR BOTTOM (ALTH.) | C80: 0.5 | D80: =21.65+0.515-2*0.05 -> 22.065 | F80: 0.5 | G80: 0.25 | H80: 16 | I80: 1 | J80: =ROUND(2.535/G80/2,0) -> 5 | K80: =D80 -> 22.065 | L80: =IF(O80<12,"0",0.049*H80) -> 0.784 | M80: 2 | N80: =M80*2*H80/1000 -> 0.064 | O80: =(D80+C80+F80)-N80 -> 23.001 | P80: =(I80*J80*O80)+L80 -> 115.789 | Q80: =IF($H80=8,$P80,"") | R80: =IF($H80=10,$P80,"") | S80: =IF($H80=12,$P80,"") | T80: =IF($H80=16,$P80,"") -> 115.789 | U80: =IF($H80=20,$P80,"") | V80: =IF($H80=25,$P80,"")
Q81: =IF($H81=8,$P81,"") | R81: =IF($H81=10,$P81,"") | S81: =IF($H81=12,$P81,"") | T81: =IF($H81=16,$P81,"") | U81: =IF($H81=20,$P81,"") | V81: =IF($H81=25,$P81,"")
A82: 3 | B82: GRID (32'-38'/A-Q') | Q82: =IF($H82=8,$P82,"") | R82: =IF($H82=10,$P82,"") | S82: =IF($H82=12,$P82,"") | T82: =IF($H82=16,$P82,"") | U82: =IF($H82=20,$P82,"") | V82: =IF($H82=25,$P82,"")
B83: MAIN BAR BOTTOM (ALTH.) | C83: 0.5 | D83: =32.45-2*0.05 -> 32.35 | F83: 0.5 | G83: 0.25 | H83: 16 | I83: 1 | J83: =ROUND(6.245/G83/2+1,0) -> 13 | K83: =D83 -> 32.35 | L83: =IF(O83<12,"0",0.049*H83)*3 -> 2.352 | M83: 2 | N83: =M83*2*H83/1000 -> 0.064 | O83: =(D83+C83+F83)-N83 -> 33.286 | P83: =(I83*J83*O83)+L83 -> 435.07 | Q83: =IF($H83=8,$P83,"") | R83: =IF($H83=10,$P83,"") | S83: =IF($H83=12,$P83,"") | T83: =IF($H83=16,$P83,"") -> 435.07 | U83: =IF($H83=20,$P83,"") | V83: =IF($H83=25,$P83,"")
Q84: =IF($H84=8,$P84,"") | R84: =IF($H84=10,$P84,"") | S84: =IF($H84=12,$P84,"") | T84: =IF($H84=16,$P84,"") | U84: =IF($H84=20,$P84,"") | V84: =IF($H84=25,$P84,"")
A85: 3 | B85: GRID (32'-38'/A-Q') | Q85: =IF($H85=8,$P85,"") | R85: =IF($H85=10,$P85,"") | S85: =IF($H85=12,$P85,"") | T85: =IF($H85=16,$P85,"") | U85: =IF($H85=20,$P85,"") | V85: =IF($H85=25,$P85,"")
B86: MAIN BAR BOTTOM (ALTH.) | C86: 0.5 | D86: =32.45-2*0.05 -> 32.35 | F86: 0.5 | G86: 0.25 | H86: 16 | I86: 1 | J86: =ROUND(6.245/G86/2,0) -> 12 | K86: =D86 -> 32.35 | L86: =IF(O86<12,"0",0.049*H86)*2 -> 1.568 | M86: 2 | N86: =M86*2*H86/1000 -> 0.064 | O86: =(D86+C86+F86)-N86 -> 33.286 | P86: =(I86*J86*O86)+L86 -> 401 | Q86: =IF($H86=8,$P86,"") | R86: =IF($H86=10,$P86,"") | S86: =IF($H86=12,$P86,"") | T86: =IF($H86=16,$P86,"") -> 401 | U86: =IF($H86=20,$P86,"") | V86: =IF($H86=25,$P86,"")
Q87: =IF($H87=8,$P87,"") | R87: =IF($H87=10,$P87,"") | S87: =IF($H87=12,$P87,"") | T87: =IF($H87=16,$P87,"") | U87: =IF($H87=20,$P87,"") | V87: =IF($H87=25,$P87,"")
A88: 4 | B88: GRID (30'-32'/A-Q') | Q88: =IF($H88=8,$P88,"") | R88: =IF($H88=10,$P88,"") | S88: =IF($H88=12,$P88,"") | T88: =IF($H88=16,$P88,"") | U88: =IF($H88=20,$P88,"") | V88: =IF($H88=25,$P88,"")
B89: MAIN BAR BOTTOM (ALTH.) | C89: 0.5 | D89: =31.935-2*0.05 -> 31.835 | F89: 0.5 | G89: 0.25 | H89: 16 | I89: 1 | J89: =ROUND(2.63/G89/2+1,0) -> 6 | K89: =D89 -> 31.835 | L89: =IF(O89<12,"0",0.049*H89)*3 -> 2.352 | M89: 2 | N89: =M89*2*H89/1000 -> 0.064 | O89: =(D89+C89+F89)-N89 -> 32.771 | P89: =(I89*J89*O89)+L89 -> 198.978 | Q89: =IF($H89=8,$P89,"") | R89: =IF($H89=10,$P89,"") | S89: =IF($H89=12,$P89,"") | T89: =IF($H89=16,$P89,"") -> 198.978 | U89: =IF($H89=20,$P89,"") | V89: =IF($H89=25,$P89,"")
Q90: =IF($H90=8,$P90,"") | R90: =IF($H90=10,$P90,"") | S90: =IF($H90=12,$P90,"") | T90: =IF($H90=16,$P90,"") | U90: =IF($H90=20,$P90,"") | V90: =IF($H90=25,$P90,"")
A91: 4 | B91: GRID (30'-32'/A-Q') | Q91: =IF($H91=8,$P91,"") | R91: =IF($H91=10,$P91,"") | S91: =IF($H91=12,$P91,"") | T91: =IF($H91=16,$P91,"") | U91: =IF($H91=20,$P91,"") | V91: =IF($H91=25,$P91,"")
B92: MAIN BAR BOTTOM (ALTH.) | C92: 0.5 | D92: =31.935-2*0.05 -> 31.835 | F92: 0.5 | G92: 0.25 | H92: 16 | I92: 1 | J92: =ROUND(2.63/G92/2,0) -> 5 | K92: =D92 -> 31.835 | L92: =IF(O92<12,"0",0.049*H92)*2 -> 1.568 | M92: 2 | N92: =M92*2*H92/1000 -> 0.064 | O92: =(D92+C92+F92)-N92 -> 32.771 | P92: =(I92*J92*O92)+L92 -> 165.423 | Q92: =IF($H92=8,$P92,"") | R92: =IF($H92=10,$P92,"") | S92: =IF($H92=12,$P92,"") | T92: =IF($H92=16,$P92,"") -> 165.423 | U92: =IF($H92=20,$P92,"") | V92: =IF($H92=25,$P92,"")
Q93: =IF($H93=8,$P93,"") | R93: =IF($H93=10,$P93,"") | S93: =IF($H93=12,$P93,"") | T93: =IF($H93=16,$P93,"") | U93: =IF($H93=20,$P93,"") | V93: =IF($H93=25,$P93,"")
A94: 5 | B94: GRID (27'-30/A-Q') | Q94: =IF($H94=8,$P94,"") | R94: =IF($H94=10,$P94,"") | S94: =IF($H94=12,$P94,"") | T94: =IF($H94=16,$P94,"") | U94: =IF($H94=20,$P94,"") | V94: =IF($H94=25,$P94,"")
B95: MAIN BAR BOTTOM (ALTH.) | C95: 0.5 | D95: =31.95-2*0.05-1.5 -> 30.35 | F95: 0.5 | G95: 0.25 | H95: 16 | I95: 1 | J95: =ROUND(3.95/G95/2+1,0) -> 9 | K95: =D95 -> 30.35 | L95: =IF(O95<12,"0",0.049*H95)*3 -> 2.352 | M95: 2 | N95: =M95*2*H95/1000 -> 0.064 | O95: =(D95+C95+F95)-N95 -> 31.286 | P95: =(I95*J95*O95)+L95 -> 283.926 | Q95: =IF($H95=8,$P95,"") | R95: =IF($H95=10,$P95,"") | S95: =IF($H95=12,$P95,"") | T95: =IF($H95=16,$P95,"") -> 283.926 | U95: =IF($H95=20,$P95,"") | V95: =IF($H95=25,$P95,"")
Q96: =IF($H96=8,$P96,"") | R96: =IF($H96=10,$P96,"") | S96: =IF($H96=12,$P96,"") | T96: =IF($H96=16,$P96,"") | U96: =IF($H96=20,$P96,"") | V96: =IF($H96=25,$P96,"")
A97: 5 | B97: GRID (27'-30/A-Q') | Q97: =IF($H97=8,$P97,"") | R97: =IF($H97=10,$P97,"") | S97: =IF($H97=12,$P97,"") | T97: =IF($H97=16,$P97,"") | U97: =IF($H97=20,$P97,"") | V97: =IF($H97=25,$P97,"")
B98: MAIN BAR BOTTOM (ALTH.) | C98: 0.5 | D98: =31.95-2*0.05-1.5 -> 30.35 | F98: 0.5 | G98: 0.25 | H98: 16 | I98: 1 | J98: =ROUND(3.95/G98/2,0) -> 8 | K98: =D98 -> 30.35 | L98: =IF(O98<12,"0",0.049*H98)*2 -> 1.568 | M98: 2 | N98: =M98*2*H98/1000 -> 0.064 | O98: =(D98+C98+F98)-N98 -> 31.286 | P98: =(I98*J98*O98)+L98 -> 251.856 | Q98: =IF($H98=8,$P98,"") | R98: =IF($H98=10,$P98,"") | S98: =IF($H98=12,$P98,"") | T98: =IF($H98=16,$P98,"") -> 251.856 | U98: =IF($H98=20,$P98,"") | V98: =IF($H98=25,$P98,"")
Q99: =IF($H99=8,$P99,"") | R99: =IF($H99=10,$P99,"") | S99: =IF($H99=12,$P99,"") | T99: =IF($H99=16,$P99,"") | U99: =IF($H99=20,$P99,"") | V99: =IF($H99=25,$P99,"")
A100: 6 | B100: GRID (26'-27'/A'-Q') | Q100: =IF($H100=8,$P100,"") | R100: =IF($H100=10,$P100,"") | S100: =IF($H100=12,$P100,"") | T100: =IF($H100=16,$P100,"") | U100: =IF($H100=20,$P100,"") | V100: =IF($H100=25,$P100,"")
...

Sheet COL BBS
A1: TOWER-E COLUMN FOUNDATION BBS (BELOW PLINTH BEAM)
A3: S.No. | B3: Description | C3: Shape of Bar in mm | F3: Spacing c/c | G3: Dia of Bar | H3: Nos of Columns | I3: Nos of Bar | J3: Actual Length | K3: Lap | L3: No. Of Bend | M3: Deduction | N3: Cut Length | O3: Total Length | P3: TMT BAR Fe-500D or EQR | V3: Remarks
P4: 8mm | Q4: 10mm | R4: 12mm | S4: 16mm | T4: 20mm | U4: 25mm
P5: =IF($G5=8,$O5,"") | Q5: =IF($G5=10,$O5,"") | R5: =IF($G5=12,$O5,"") | S5: =IF($G5=16,$O5,"") | T5: =IF($G5=20,$O5,"") | U5: =IF($G5=25,$O5,"")
A6: 1 | B6: Column C1 (300x600) | P6: =IF($G6=8,$O6,"") | Q6: =IF($G6=10,$O6,"") | R6: =IF($G6=12,$O6,"") | S6: =IF($G6=16,$O6,"") | T6: =IF($G6=20,$O6,"") | U6: =IF($G6=25,$O6,"")
B7: VERTICAL BARS A | D7: =0.85-0.075-2*0.016 -> 0.743 | G7: 16 | H7: 16 | I7: 4 | J7: =D7 -> 0.743 | K7: =IF(N7<12,"0",0.049*G7) -> 0 | L7: 1 | M7: =2*G7*L7/1000 -> 0.032 | N7: =J7+E9-M7 -> 1.011 | O7: =H7*I7*N7 -> 64.704 | P7: =IF($G7=8,$O7,"") | Q7: =IF($G7=10,$O7,"") | R7: =IF($G7=12,$O7,"") | S7: =IF($G7=16,$O7,"") -> 64.704 | T7: =IF($G7=20,$O7,"") | U7: =IF($G7=25,$O7,"")
B8: VERTICAL BARS B | G8: 12 | H8: 16 | I8: 2 | J8: =D7 -> 0.743 | K8: =IF(N8<12,"0",0.049*G8) -> 0 | L8: 1 | M8: =2*G8*L8/1000 -> 0.024 | N8: =J8+E9-M8 -> 1.019 | O8: =H8*I8*N8 -> 32.608 | P8: =IF($G8=8,$O8,"") | Q8: =IF($G8=10,$O8,"") | R8: =IF($G8=12,$O8,"") -> 32.608 | S8: =IF($G8=16,$O8,"") | T8: =IF($G8=20,$O8,"") | U8: =IF($G8=25,$O8,"")
B9: VERTICAL BARS C | E9: 0.3 | G9: 16 | H9: 16 | I9: 4 | J9: =D7 -> 0.743 | K9: =IF(N9<12,"0",0.049*G9) -> 0 | L9: 1 | M9: =2*G9*L9/1000 -> 0.032 | N9: =J9+E9-M9 -> 1.011 | O9: =H9*I9*N9 -> 64.704 | P9: =IF($G9=8,$O9,"") | Q9: =IF($G9=10,$O9,"") | R9: =IF($G9=12,$O9,"") | S9: =IF($G9=16,$O9,"") -> 64.704 | T9: =IF($G9=20,$O9,"") | U9: =IF($G9=25,$O9,"")
B10: VERTICAL BARS D | G10: 12 | H10: 16 | I10: 4 | J10: =D7 -> 0.743 | K10: =IF(N10<12,"0",0.049*G10) -> 0 | L10: 1 | M10: =2*G10*L10/1000 -> 0.024 | N10: =J10+E9-M10 -> 1.019 | O10: =H10*I10*N10 -> 65.216 | P10: =IF($G10=8,$O10,"") | Q10: =IF($G10=10,$O10,"") | R10: =IF($G10=12,$O10,"") -> 65.216 | S10: =IF($G10=16,$O10,"") | T10: =IF($G10=20,$O10,"") | U10: =IF($G10=25,$O10,"")
P11: =IF($G11=8,$O11,"") | Q11: =IF($G11=10,$O11,"") | R11: =IF($G11=12,$O11,"") | S11: =IF($G11=16,$O11,"") | T11: =IF($G11=20,$O11,"") | U11: =IF($G11=25,$O11,"")
C12: 0.08 | P12: =IF($G12=8,$O12,"") | Q12: =IF($G12=10,$O12,"") | R12: =IF($G12=12,$O12,"") | S12: =IF($G12=16,$O12,"") | T12: =IF($G12=20,$O12,"") | U12: =IF($G12=25,$O12,"")
B13: Stirupps a | E13: =0.6-0.08 -> 0.52 | G13: 10 | H13: 16 | I13: 4 | J13: =2*(D15+E13)+2*8*G13/1000 -> 1.64 | L13: 5 | M13: =2*G13*L13/1000 -> 0.1 | N13: =(J13+K13-M13)+0.02 -> 1.56 | O13: =(H13*I13*N13) -> 99.84 | P13: =IF($G13=8,$O13,"") | Q13: =IF($G13=10,$O13,"") -> 99.84 | R13: =IF($G13=12,$O13,"") | S13: =IF($G13=16,$O13,"") | T13: =IF($G13=20,$O13,"") | U13: =IF($G13=25,$O13,"")
P14: =IF($G14=8,$O14,"") | Q14: =IF($G14=10,$O14,"") | R14: =IF($G14=12,$O14,"") | S14: =IF($G14=16,$O14,"") | T14: =IF($G14=20,$O14,"") | U14: =IF($G14=25,$O14,"")
D15: =0.3-0.08 -> 0.22 | P15: =IF($G15=8,$O15,"") | Q15: =IF($G15=10,$O15,"") | R15: =IF($G15=12,$O15,"") | S15: =IF($G15=16,$O15,"") | T15: =IF($G15=20,$O15,"") | U15: =IF($G15=25,$O15,"")
P16: =IF($G16=8,$O16,"") | Q16: =IF($G16=10,$O16,"") | R16: =IF($G16=12,$O16,"") | S16: =IF($G16=16,$O16,"") | T16: =IF($G16=20,$O16,"") | U16: =IF($G16=25,$O16,"")
C17: 0.08 | P17: =IF($G17=8,$O17,"") | Q17: =IF($G17=10,$O17,"") | R17: =IF($G17=12,$O17,"") | S17: =IF($G17=16,$O17,"") | T17: =IF($G17=20,$O17,"") | U17: =IF($G17=25,$O17,"")
B18: Stirupps b | E18: =((0.6-0.08-0.016)/5)+0.012+0.02 -> 0.1328 | G18: 10 | H18: 16 | I18: 1 | J18: =2*(D20+E18)+2*8*G18/1000 -> 0.8656 | L18: 5 | M18: =2*G18*L18/1000 -> 0.1 | N18: =(J18+K18-M18)+0.02 -> 0.7856 | O18: =(H18*I18*N18) -> 12.5696 | P18: =IF($G18=8,$O18,"") | Q18: =IF($G18=10,$O18,"") -> 12.5696 | R18: =IF($G18=12,$O18,"") | S18: =IF($G18=16,$O18,"") | T18: =IF($G18=20,$O18,"") | U18: =IF($G18=25,$O18,"")
P19: =IF($G19=8,$O19,"") | Q19: =IF($G19=10,$O19,"") | R19: =IF($G19=12,$O19,"") | S19: =IF($G19=16,$O19,"") | T19: =IF($G19=20,$O19,"") | U19: =IF($G19=25,$O19,"")
D20: =0.3-0.08 -> 0.22 | P20: =IF($G20=8,$O20,"") | Q20: =IF($G20=10,$O20,"") | R20: =IF($G20=12,$O20,"") | S20: =IF($G20=16,$O20,"") | T20: =IF($G20=20,$O20,"") | U20: =IF($G20=25,$O20,"")
P21: =IF($G21=8,$O21,"") | Q21: =IF($G21=10,$O21,"") | R21: =IF($G21=12,$O21,"") | S21: =IF($G21=16,$O21,"") | T21: =IF($G21=20,$O21,"") | U21: =IF($G21=25,$O21,"")
B22: Stirupps c | G22: 10 | H22: 16 | I22: 1 | J22: =C23+D25+E23+2*8*G22/1000 -> 0.73 | L22: 4 | M22: =2*G22*L22/1000 -> 0.08 | N22: =(J22+K22-M22) -> 0.65 | O22: =(H22*I22*N22) -> 10.4 | P22: =IF($G22=8,$O22,"") | Q22: =IF($G22=10,$O22,"") -> 10.4 | R22: =IF($G22=12,$O22,"") | S22: =IF($G22=16,$O22,"") | T22: =IF($G22=20,$O22,"") | U22: =IF($G22=25,$O22,"")
C23: 0.175 | E23: 0.175 | P23: =IF($G23=8,$O23,"") | Q23: =IF($G23=10,$O23,"") | R23: =IF($G23=12,$O23,"") | S23: =IF($G23=16,$O23,"") | T23: =IF($G23=20,$O23,"") | U23: =IF($G23=25,$O23,"")
P24: =IF($G24=8,$O24,"") | Q24: =IF($G24=10,$O24,"") | R24: =IF($G24=12,$O24,"") | S24: =IF($G24=16,$O24,"") | T24: =IF($G24=20,$O24,"") | U24: =IF($G24=25,$O24,"")
D25: =0.3-0.08 -> 0.22 | P25: =IF($G25=8,$O25,"") | Q25: =IF($G25=10,$O25,"") | R25: =IF($G25=12,$O25,"") | S25: =IF($G25=16,$O25,"") | T25: =IF($G25=20,$O25,"") | U25: =IF($G25=25,$O25,"")
P26: =IF($G26=8,$O26,"") | Q26: =IF($G26=10,$O26,"") | R26: =IF($G26=12,$O26,"") | S26: =IF($G26=16,$O26,"") | T26: =IF($G26=20,$O26,"") | U26: =IF($G26=25,$O26,"")
B27: Stirupps d | G27: 10 | H27: 16 | I27: 1 | J27: =C28+D30+E28+2*8*G27/1000 -> 0.73 | L27: 4 | M27: =2*G27*L27/1000 -> 0.08 | N27: =(J27+K27-M27) -> 0.65 | O27: =(H27*I27*N27) -> 10.4 | P27: =IF($G27=8,$O27,"") | Q27: =IF($G27=10,$O27,"") -> 10.4 | R27: =IF($G27=12,$O27,"") | S27: =IF($G27=16,$O27,"") | T27: =IF($G27=20,$O27,"") | U27: =IF($G27=25,$O27,"")
C28: 0.175 | E28: 0.175 | P28: =IF($G28=8,$O28,"") | Q28: =IF($G28=10,$O28,"") | R28: =IF($G28=12,$O28,"") | S28: =IF($G28=16,$O28,"") | T28: =IF($G28=20,$O28,"") | U28: =IF($G28=25,$O28,"")
P29: =IF($G29=8,$O29,"") | Q29: =IF($G29=10,$O29,"") | R29: =IF($G29=12,$O29,"") | S29: =IF($G29=16,$O29,"") | T29: =IF($G29=20,$O29,"") | U29: =IF($G29=25,$O29,"")
D30: =0.3-0.08 -> 0.22 | P30: =IF($G30=8,$O30,"") | Q30: =IF($G30=10,$O30,"") | R30: =IF($G30=12,$O30,"") | S30: =IF($G30=16,$O30,"") | T30: =IF($G30=20,$O30,"") | U30: =IF($G30=25,$O30,"")
P31: =IF($G31=8,$O31,"") | Q31: =IF($G31=10,$O31,"") | R31: =IF($G31=12,$O31,"") | S31: =IF($G31=16,$O31,"") | T31: =IF($G31=20,$O31,"") | U31: =IF($G31=25,$O31,"")
A32: 2 | B32: Column C2 (300x600) | P32: =IF($G32=8,$O32,"") | Q32: =IF($G32=10,$O32,"") | R32: =IF($G32=12,$O32,"") | S32: =IF($G32=16,$O32,"") | T32: =IF($G32=20,$O32,"") | U32: =IF($G32=25,$O32,"")
B33: VERTICAL BARS A | D33: =0.85-0.075-2*0.016 -> 0.743 | G33: 20 | H33: 11 | I33: 4 | J33: =D33 -> 0.743 | K33: =IF(N33<12,"0",0.049*G33) -> 0 | L33: 1 | M33: =2*G33*L33/1000 -> 0.04 | N33: =J33+E35-M33 -> 1.003 | O33: =H33*I33*N33 -> 44.132 | P33: =IF($G33=8,$O33,"") | Q33: =IF($G33=10,$O33,"") | R33: =IF($G33=12,$O33,"") | S33: =IF($G33=16,$O33,"") | T33: =IF($G33=20,$O33,"") -> 44.132 | U33: =IF($G33=25,$O33,"")
B34: VERTICAL BARS B | G34: 20 | H34: 11 | I34: 2 | J34: =D33 -> 0.743 | K34: =IF(N34<12,"0",0.049*G34) -> 0 | L34: 1 | M34: =2*G34*L34/1000 -> 0.04 | N34: =J34+E35-M34 -> 1.003 | O34: =H34*I34*N34 -> 22.066 | P34: =IF($G34=8,$O34,"") | Q34: =IF($G34=10,$O34,"") | R34: =IF($G34=12,$O34,"") | S34: =IF($G34=16,$O34,"") | T34: =IF($G34=20,$O34,"") -> 22.066 | U34: =IF($G34=25,$O34,"")
B35: VERTICAL BARS C | E35: 0.3 | G35: 16 | H35: 11 | I35: 4 | J35: =D33 -> 0.743 | K35: =IF(N35<12,"0",0.049*G35) -> 0 | L35: 1 | M35: =2*G35*L35/1000 -> 0.032 | N35: =J35+E35-M35 -> 1.011 | O35: =H35*I35*N35 -> 44.484 | P35: =IF($G35=8,$O35,"") | Q35: =IF($G35=10,$O35,"") | R35: =IF($G35=12,$O35,"") | S35: =IF($G35=16,$O35,"") -> 44.484 | T35: =IF($G35=20,$O35,"") | U35: =IF($G35=25,$O35,"")
B36: VERTICAL BARS D | G36: 16 | H36: 11 | I36: 4 | J36: =D33 -> 0.743 | K36: =IF(N36<12,"0",0.049*G36) -> 0 | L36: 1 | M36: =2*G36*L36/1000 -> 0.032 | N36: =J36+E35-M36 -> 1.011 | O36: =H36*I36*N36 -> 44.484 | P36: =IF($G36=8,$O36,"") | Q36: =IF($G36=10,$O36,"") | R36: =IF($G36=12,$O36,"") | S36: =IF($G36=16,$O36,"") -> 44.484 | T36: =IF($G36=20,$O36,"") | U36: =IF($G36=25,$O36,"")
P37: =IF($G37=8,$O37,"") | Q37: =IF($G37=10,$O37,"") | R37: =IF($G37=12,$O37,"") | S37: =IF($G37=16,$O37,"") | T37: =IF($G37=20,$O37,"") | U37: =IF($G37=25,$O37,"")
C38: 0.08 | P38: =IF($G38=8,$O38,"") | Q38: =IF($G38=10,$O38,"") | R38: =IF($G38=12,$O38,"") | S38: =IF($G38=16,$O38,"") | T38: =IF($G38=20,$O38,"") | U38: =IF($G38=25,$O38,"")
B39: Stirupps a | E39: =0.6-0.08 -> 0.52 | G39: 10 | H39: 11 | I39: 4 | J39: =2*(D41+E39)+2*8*G39/1000 -> 1.64 | L39: 5 | M39: =2*G39*L39/1000 -> 0.1 | N39: =(J39+K39-M39) -> 1.54 | O39: =(H39*I39*N39) -> 67.76 | P39: =IF($G39=8,$O39,"") | Q39: =IF($G39=10,$O39,"") -> 67.76 | R39: =IF($G39=12,$O39,"") | S39: =IF($G39=16,$O39,"") | T39: =IF($G39=20,$O39,"") | U39: =IF($G39=25,$O39,"")
P40: =IF($G40=8,$O40,"") | Q40: =IF($G40=10,$O40,"") | R40: =IF($G40=12,$O40,"") | S40: =IF($G40=16,$O40,"") | T40: =IF($G40=20,$O40,"") | U40: =IF($G40=25,$O40,"")
D41: =0.3-0.08 -> 0.22 | P41: =IF($G41=8,$O41,"") | Q41: =IF($G41=10,$O41,"") | R41: =IF($G41=12,$O41,"") | S41: =IF($G41=16,$O41,"") | T41: =IF($G41=20,$O41,"") | U41: =IF($G41=25,$O41,"")
P42: =IF($G42=8,$O42,"") | Q42: =IF($G42=10,$O42,"") | R42: =IF($G42=12,$O42,"") | S42: =IF($G42=16,$O42,"") | T42: =IF($G42=20,$O42,"") | U42: =IF($G42=25,$O42,"")
C43: 0.08 | P43: =IF($G43=8,$O43,"") | Q43: =IF($G43=10,$O43,"") | R43: =IF($G43=12,$O43,"") | S43: =IF($G43=16,$O43,"") | T43: =IF($G43=20,$O43,"") | U43: =IF($G43=25,$O43,"")
B44: Stirupps b | E44: =((0.6-0.08-0.016)/5)+0.012+0.02 -> 0.1328 | G44: 10 | H44: 11 | I44: 1 | J44: =2*(D46+E44)+2*8*G44/1000 -> 0.8656 | L44: 5 | M44: =2*G44*L44/1000 -> 0.1 | N44: =(J44+K44-M44) -> 0.7656 | O44: =(H44*I44*N44) -> 8.4216 | P44: =IF($G44=8,$O44,"") | Q44: =IF($G44=10,$O44,"") -> 8.4216 | R44: =IF($G44=12,$O44,"") | S44: =IF($G44=16,$O44,"") | T44: =IF($G44=20,$O44,"") | U44: =IF($G44=25,$O44,"")
P45: =IF($G45=8,$O45,"") | Q45: =IF($G45=10,$O45,"") | R45: =IF($G45=12,$O45,"") | S45: =IF($G45=16,$O45,"") | T45: =IF($G45=20,$O45,"") | U45: =IF($G45=25,$O45,"")
D46: =0.3-0.08 -> 0.22 | P46: =IF($G46=8,$O46,"") | Q46: =IF($G46=10,$O46,"") | R46: =IF($G46=12,$O46,"") | S46: =IF($G46=16,$O46,"") | T46: =IF($G46=20,$O46,"") | U46: =IF($G46=25,$O46,"")
P47: =IF($G47=8,$O47,"") | Q47: =IF($G47=10,$O47,"") | R47: =IF($G47=12,$O47,"") | S47: =IF($G47=16,$O47,"") | T47: =IF($G47=20,$O47,"") | U47: =IF($G47=25,$O47,"")
B48: Stirupps c | G48: 10 | H48: 11 | I48: 1 | J48: =C49+D51+E49+2*8*G48/1000 -> 0.73 | L48: 4 | M48: =2*G48*L48/1000 -> 0.08 | N48: =(J48+K48-M48) -> 0.65 | O48: =(H48*I48*N48) -> 7.15 | P48: =IF($G48=8,$O48,"") | Q48: =IF($G48=10,$O48,"") -> 7.15 | R48: =IF($G48=12,$O48,"") | S48: =IF($G48=16,$O48,"") | T48: =IF($G48=20,$O48,"") | U48: =IF($G48=25,$O48,"")
C49: 0.175 | E49: 0.175 | P49: =IF($G49=8,$O49,"") | Q49: =IF($G49=10,$O49,"") | R49: =IF($G49=12,$O49,"") | S49: =IF($G49=16,$O49,"") | T49: =IF($G49=20,$O49,"") | U49: =IF($G49=25,$O49,"")
P50: =IF($G50=8,$O50,"") | Q50: =IF($G50=10,$O50,"") | R50: =IF($G50=12,$O50,"") | S50: =IF($G50=16,$O50,"") | T50: =IF($G50=20,$O50,"") | U50: =IF($G50=25,$O50,"")
D51: =0.3-0.08 -> 0.22 | P51: =IF($G51=8,$O51,"") | Q51: =IF($G51=10,$O51,"") | R51: =IF($G51=12,$O51,"") | S51: =IF($G51=16,$O51,"") | T51: =IF($G51=20,$O51,"") | U51: =IF($G51=25,$O51,"")
P52: =IF($G52=8,$O52,"") | Q52: =IF($G52=10,$O52,"") | R52: =IF($G52=12,$O52,"") | S52: =IF($G52=16,$O52,"") | T52: =IF($G52=20,$O52,"") | U52: =IF($G52=25,$O52,"")
B53: Stirupps d | G53: 10 | H53: 11 | I53: 1 | J53: =C54+D56+E54+2*8*G53/1000 -> 0.73 | L53: 4 | M53: =2*G53*L53/1000 -> 0.08 | N53: =(J53+K53-M53) -> 0.65 | O53: =(H53*I53*N53) -> 7.15 | P53: =IF($G53=8,$O53,"") | Q53: =IF($G53=10,$O53,"") -> 7.15 | R53: =IF($G53=12,$O53,"") | S53: =IF($G53=16,$O53,"") | T53: =IF($G53=20,$O53,"") | U53: =IF($G53=25,$O53,"")
C54: 0.175 | E54: 0.175 | P54: =IF($G54=8,$O54,"") | Q54: =IF($G54=10,$O54,"") | R54: =IF($G54=12,$O54,"") | S54: =IF($G54=16,$O54,"") | T54: =IF($G54=20,$O54,"") | U54: =IF($G54=25,$O54,"")
P55: =IF($G55=8,$O55,"") | Q55: =IF($G55=10,$O55,"") | R55: =IF($G55=12,$O55,"") | S55: =IF($G55=16,$O55,"") | T55: =IF($G55=20,$O55,"") | U55: =IF($G55=25,$O55,"")
D56: =0.3-0.08 -> 0.22 | P56: =IF($G56=8,$O56,"") | Q56: =IF($G56=10,$O56,"") | R56: =IF($G56=12,$O56,"") | S56: =IF($G56=16,$O56,"") | T56: =IF($G56=20,$O56,"") | U56: =IF($G56=25,$O56,"")
P57: =IF($G57=8,$O57,"") | Q57: =IF($G57=10,$O57,"") | R57: =IF($G57=12,$O57,"") | S57: =IF($G57=16,$O57,"") | T57: =IF($G57=20,$O57,"") | U57: =IF($G57=25,$O57,"")
A58: 3 | B58: Column C3 (300x600) | P58: =IF($G58=8,$O58,"") | Q58: =IF($G58=10,$O58,"") | R58: =IF($G58=12,$O58,"") | S58: =IF($G58=16,$O58,"") | T58: =IF($G58=20,$O58,"") | U58: =IF($G58=25,$O58,"")
B59: VERTICAL BARS A | D59: =0.85-0.075-2*0.016 -> 0.743 | G59: 25 | H59: 2 | I59: 4 | J59: =D59 -> 0.743 | K59: =IF(N59<12,"0",0.049*G59) -> 0 | L59: 1 | M59: =2*G59*L59/1000 -> 0.05 | N59: =J59+E$61-M59 -> 0.993 | O59: =H59*I59*N59 -> 7.944 | P59: =IF($G59=8,$O59,"") | Q59: =IF($G59=10,$O59,"") | R59: =IF($G59=12,$O59,"") | S59: =IF($G59=16,$O59,"") | T59: =IF($G59=20,$O59,"") | U59: =IF($G59=25,$O59,"") -> 7.944
B60: VERTICAL BARS B | G60: 25 | H60: 2 | I60: 2 | J60: =D59 -> 0.743 | K60: =IF(N60<12,"0",0.049*G60) -> 0 | L60: 1 | M60: =2*G60*L60/1000 -> 0.05 | N60: =J60+E$61-M60 -> 0.993 | O60: =H60*I60*N60 -> 3.972 | P60: =IF($G60=8,$O60,"") | Q60: =IF($G60=10,$O60,"") | R60: =IF($G60=12,$O60,"") | S60: =IF($G60=16,$O60,"") | T60: =IF($G60=20,$O60,"") | U60: =IF($G60=25,$O60,"") -> 3.972
B61: VERTICAL BARS C | E61: 0.3 | G61: 25 | H61: 2 | I61: 4 | J61: =D59 -> 0.743 | K61: =IF(N61<12,"0",0.049*G61) -> 0 | L61: 1 | M61: =2*G61*L61/1000 -> 0.05 | N61: =J61+E$61-M61 -> 0.993 | O61: =H61*I61*N61 -> 7.944 | P61: =IF($G61=8,$O61,"") | Q61: =IF($G61=10,$O61,"") | R61: =IF($G61=12,$O61,"") | S61: =IF($G61=16,$O61,"") | T61: =IF($G61=20,$O61,"") | U61: =IF($G61=25,$O61,"") -> 7.944
B62: VERTICAL BARS D | G62: 20 | H62: 2 | I62: 4 | J62: =D59 -> 0.743 | K62: =IF(N62<12,"0",0.049*G62) -> 0 | L62: 1 | M62: =2*G62*L62/1000 -> 0.04 | N62: =J62+E$61-M62 -> 1.003 | O62: =H62*I62*N62 -> 8.024 | P62: =IF($G62=8,$O62,"") | Q62: =IF($G62=10,$O62,"") | R62: =IF($G62=12,$O62,"") | S62: =IF($G62=16,$O62,"") | T62: =IF($G62=20,$O62,"") -> 8.024 | U62: =IF($G62=25,$O62,"")
P63: =IF($G63=8,$O63,"") | Q63: =IF($G63=10,$O63,"") | R63: =IF($G63=12,$O63,"") | S63: =IF($G63=16,$O63,"") | T63: =IF($G63=20,$O63,"") | U63: =IF($G63=25,$O63,"")
C64: 0.08 | P64: =IF($G64=8,$O64,"") | Q64: =IF($G64=10,$O64,"") | R64: =IF($G64=12,$O64,"") | S64: =IF($G64=16,$O64,"") | T64: =IF($G64=20,$O64,"") | U64: =IF($G64=25,$O64,"")
B65: Stirupps a | E65: =0.6-0.08 -> 0.52 | G65: 10 | H65: 2 | I65: 4 | J65: =2*(D67+E65)+2*8*G65/1000 -> 1.64 | L65: 5 | M65: =2*G65*L65/1000 -> 0.1 | N65: =(J65+K65-M65) -> 1.54 | O65: =(H65*I65*N65) -> 12.32 | P65: =IF($G65=8,$O65,"") | Q65: =IF($G65=10,$O65,"") -> 12.32 | R65: =IF($G65=12,$O65,"") | S65: =IF($G65=16,$O65,"") | T65: =IF($G65=20,$O65,"") | U65: =IF($G65=25,$O65,"")
P66: =IF($G66=8,$O66,"") | Q66: =IF($G66=10,$O66,"") | R66: =IF($G66=12,$O66,"") | S66: =IF($G66=16,$O66,"") | T66: =IF($G66=20,$O66,"") | U66: =IF($G66=25,$O66,"")
D67: =0.3-0.08 -> 0.22 | P67: =IF($G67=8,$O67,"") | Q67: =IF($G67=10,$O67,"") | R67: =IF($G67=12,$O67,"") | S67: =IF($G67=16,$O67,"") | T67: =IF($G67=20,$O67,"") | U67: =IF($G67=25,$O67,"")
P68: =IF($G68=8,$O68,"") | Q68: =IF($G68=10,$O68,"") | R68: =IF($G68=12,$O68,"") | S68: =IF($G68=16,$O68,"") | T68: =IF($G68=20,$O68,"") | U68: =IF($G68=25,$O68,"")
C69: 0.08 | P69: =IF($G69=8,$O69,"") | Q69: =IF($G69=10,$O69,"") | R69: =IF($G69=12,$O69,"") | S69: =IF($G69=16,$O69,"") | T69: =IF($G69=20,$O69,"") | U69: =IF($G69=25,$O69,"")
B70: Stirupps b | E70: =((0.6-0.08-0.016)/5)+0.012+0.02 -> 0.1328 | G70: 10 | H70: 2 | I70: 1 | J70: =2*(D72+E70)+2*8*G70/1000 -> 0.8656 | L70: 5 | M70: =2*G70*L70/1000 -> 0.1 | N70: =(J70+K70-M70) -> 0.7656 | O70: =(H70*I70*N70) -> 1.5312 | P70: =IF($G70=8,$O70,"") | Q70: =IF($G70=10,$O70,"") -> 1.5312 | R70: =IF($G70=12,$O70,"") | S70: =IF($G70=16,$O70,"") | T70: =IF($G70=20,$O70,"") | U70: =IF($G70=25,$O70,"")
P71: =IF($G71=8,$O71,"") | Q71: =IF($G71=10,$O71,"") | R71: =IF($G71=12,$O71,"") | S71: =IF($G71=16,$O71,"") | T71: =IF($G71=20,$O71,"") | U71: =IF($G71=25,$O71,"")
D72: =0.3-0.08 -> 0.22 | P72: =IF($G72=8,$O72,"") | Q72: =IF($G72=10,$O72,"") | R72: =IF($G72=12,$O72,"") | S72: =IF($G72=16,$O72,"") | T72: =IF($G72=20,$O72,"") | U72: =IF($G72=25,$O72,"")
P73: =IF($G73=8,$O73,"") | Q73: =IF($G73=10,$O73,"") | R73: =IF($G73=12,$O73,"") | S73: =IF($G73=16,$O73,"") | T73: =IF($G73=20,$O73,"") | U73: =IF($G73=25,$O73,"")
B74: Stirupps c | G74: 10 | H74: 2 | I74: 1 | J74: =C75+D77+E75+2*8*G74/1000 -> 0.73 | L74: 4 | M74: =2*G74*L74/1000 -> 0.08 | N74: =(J74+K74-M74) -> 0.65 | O74: =(H74*I74*N74) -> 1.3 | P74: =IF($G74=8,$O74,"") | Q74: =IF($G74=10,$O74,"") -> 1.3 | R74: =IF($G74=12,$O74,"") | S74: =IF($G74=16,$O74,"") | T74: =IF($G74=20,$O74,"") | U74: =IF($G74=25,$O74,"")
C75: 0.175 | E75: 0.175 | P75: =IF($G75=8,$O75,"") | Q75: =IF($G75=10,$O75,"") | R75: =IF($G75=12,$O75,"") | S75: =IF($G75=16,$O75,"") | T75: =IF($G75=20,$O75,"") | U75: =IF($G75=25,$O75,"")
P76: =IF($G76=8,$O76,"") | Q76: =IF($G76=10,$O76,"") | R76: =IF($G76=12,$O76,"") | S76: =IF($G76=16,$O76,"") | T76: =IF($G76=20,$O76,"") | U76: =IF($G76=25,$O76,"")
D77: =0.3-0.08 -> 0.22 | P77: =IF($G77=8,$O77,"") | Q77: =IF($G77=10,$O77,"") | R77: =IF($G77=12,$O77,"") | S77: =IF($G77=16,$O77,"") | T77: =IF($G77=20,$O77,"") | U77: =IF($G77=25,$O77,"")
P78: =IF($G78=8,$O78,"") | Q78: =IF($G78=10,$O78,"") | R78: =IF($G78=12,$O78,"") | S78: =IF($G78=16,$O78,"") | T78: =IF($G78=20,$O78,"") | U78: =IF($G78=25,$O78,"")
B79: Stirupps d | G79: 10 | H79: 2 | I79: 1 | J79: =C80+D82+E80+2*8*G79/1000 -> 0.73 | L79: 4 | M79: =2*G79*L79/1000 -> 0.08 | N79: =(J79+K79-M79) -> 0.65 | O79: =(H79*I79*N79) -> 1.3 | P79: =IF($G79=8,$O79,"") | Q79: =IF($G79=10,$O79,"") -> 1.3 | R79: =IF($G79=12,$O79,"") | S79: =IF($G79=16,$O79,"") | T79: =IF($G79=20,$O79,"") | U79: =IF($G79=25,$O79,"")
C80: 0.175 | E80: 0.175 | P80: =IF($G80=8,$O80,"") | Q80: =IF($G80=10,$O80,"") | R80: =IF($G80=12,$O80,"") | S80: =IF($G80=16,$O80,"") | T80: =IF($G80=20,$O80,"") | U80: =IF($G80=25,$O80,"")
P81: =IF($G81=8,$O81,"") | Q81: =IF($G81=10,$O81,"") | R81: =IF($G81=12,$O81,"") | S81: =IF($G81=16,$O81,"") | T81: =IF($G81=20,$O81,"") | U81: =IF($G81=25,$O81,"")
D82: =0.3-0.08 -> 0.22 | P82: =IF($G82=8,$O82,"") | Q82: =IF($G82=10,$O82,"") | R82: =IF($G82=12,$O82,"") | S82: =IF($G82=16,$O82,"") | T82: =IF($G82=20,$O82,"") | U82: =IF($G82=25,$O82,"")
P83: =IF($G83=8,$O83,"") | Q83: =IF($G83=10,$O83,"") | R83: =IF($G83=12,$O83,"") | S83: =IF($G83=16,$O83,"") | T83: =IF($G83=20,$O83,"") | U83: =IF($G83=25,$O83,"")
A84: 4 | B84: Column C4 (300x750) | P84: =IF($G84=8,$O84,"") | Q84: =IF($G84=10,$O84,"") | R84: =IF($G84=12,$O84,"") | S84: =IF($G84=16,$O84,"") | T84: =IF($G84=20,$O84,"") | U84: =IF($G84=25,$O84,"")
B85: VERTICAL BARS A | D85: =0.85-0.075-2*0.016 -> 0.743 | G85: 20 | H85: 8 | I85: 4 | J85: =D85 -> 0.743 | K85: =IF(N85<12,"0",0.049*G85) -> 0 | L85: 1 | M85: =2*G85*L85/1000 -> 0.04 | N85: =J85+E$87-M85 -> 1.003 | O85: =H85*I85*N85 -> 32.096 | P85: =IF($G85=8,$O85,"") | Q85: =IF($G85=10,$O85,"") | R85: =IF($G85=12,$O85,"") | S85: =IF($G85=16,$O85,"") | T85: =IF($G85=20,$O85,"") -> 32.096 | U85: =IF($G85=25,$O85,"")
B86: VERTICAL BARS B | G86: 20 | H86: 8 | I86: 2 | J86: =D85 -> 0.743 | K86: =IF(N86<12,"0",0.049*G86) -> 0 | L86: 1 | M86: =2*G86*L86/1000 -> 0.04 | N86: =J86+E$87-M86 -> 1.003 | O86: =H86*I86*N86 -> 16.048 | P86: =IF($G86=8,$O86,"") | Q86: =IF($G86=10,$O86,"") | R86: =IF($G86=12,$O86,"") | S86: =IF($G86=16,$O86,"") | T86: =IF($G86=20,$O86,"") -> 16.048 | U86: =IF($G86=25,$O86,"")
B87: VERTICAL BARS C | E87: 0.3 | G87: 20 | H87: 8 | I87: 4 | J87: =D85 -> 0.743 | K87: =IF(N87<12,"0",0.049*G87) -> 0 | L87: 1 | M87: =2*G87*L87/1000 -> 0.04 | N87: =J87+E$87-M87 -> 1.003 | O87: =H87*I87*N87 -> 32.096 | P87: =IF($G87=8,$O87,"") | Q87: =IF($G87=10,$O87,"") | R87: =IF($G87=12,$O87,"") | S87: =IF($G87=16,$O87,"") | T87: =IF($G87=20,$O87,"") -> 32.096 | U87: =IF($G87=25,$O87,"")
B88: VERTICAL BARS D | G88: 20 | H88: 8 | I88: 4 | J88: =D85 -> 0.743 | K88: =IF(N88<12,"0",0.049*G88) -> 0 | L88: 1 | M88: =2*G88*L88/1000 -> 0.04 | N88: =J88+E$87-M88 -> 1.003 | O88: =H88*I88*N88 -> 32.096 | P88: =IF($G88=8,$O88,"") | Q88: =IF($G88=10,$O88,"") | R88: =IF($G88=12,$O88,"") | S88: =IF($G88=16,$O88,"") | T88: =IF($G88=20,$O88,"") -> 32.096 | U88: =IF($G88=25,$O88,"")
B89: VERTICAL BARS E | G89: 20 | H89: 8 | I89: 2 | J89: =D85 -> 0.743 | K89: =IF(N89<12,"0",0.049*G89) -> 0 | L89: 1 | M89: =2*G89*L89/1000 -> 0.04 | N89: =J89+E$87-M89 -> 1.003 | O89: =H89*I89*N89 -> 16.048 | P89: =IF($G89=8,$O89,"") | Q89: =IF($G89=10,$O89,"") | R89: =IF($G89=12,$O89,"") | S89: =IF($G89=16,$O89,"") | T89: =IF($G89=20,$O89,"") -> 16.048 | U89: =IF($G89=25,$O89,"")
P90: =IF($G90=8,$O90,"") | Q90: =IF($G90=10,$O90,"") | R90: =IF($G90=12,$O90,"") | S90: =IF($G90=16,$O90,"") | T90: =IF($G90=20,$O90,"") | U90: =IF($G90=25,$O90,"")
C91: 0.08 | P91: =IF($G91=8,$O91,"") | Q91: =IF($G91=10,$O91,"") | R91: =IF($G91=12,$O91,"") | S91: =IF($G91=16,$O91,"") | T91: =IF($G91=20,$O91,"") | U91: =IF($G91=25,$O91,"")
B92: Stirupps a | E92: =0.75-0.08 -> 0.67 | G92: 10 | H92: 8 | I92: 4 | J92: =2*(D94+E92)+2*8*G92/1000 -> 1.94 | L92: 5 | M92: =2*G92*L92/1000 -> 0.1 | N92: =(J92+K92-M92) -> 1.84 | O92: =(H92*I92*N92) -> 58.88 | P92: =IF($G92=8,$O92,"") | Q92: =IF($G92=10,$O92,"") -> 58.88 | R92: =IF($G92=12,$O92,"") | S92: =IF($G92=16,$O92,"") | T92: =IF($G92=20,$O92,"") | U92: =IF($G92=25,$O92,"")
P93: =IF($G93=8,$O93,"") | Q93: =IF($G93=10,$O93,"") | R93: =IF($G93=12,$O93,"") | S93: =IF($G93=16,$O93,"") | T93: =IF($G93=20,$O93,"") | U93: =IF($G93=25,$O93,"")
D94: =0.3-0.08 -> 0.22 | P94: =IF($G94=8,$O94,"") | Q94: =IF($G94=10,$O94,"") | R94: =IF($G94=12,$O94,"") | S94: =IF($G94=16,$O94,"") | T94: =IF($G94=20,$O94,"") | U94: =IF($G94=25,$O94,"")
P95: =IF($G95=8,$O95,"") | Q95: =IF($G95=10,$O95,"") | R95: =IF($G95=12,$O95,"") | S95: =IF($G95=16,$O95,"") | T95: =IF($G95=20,$O95,"") | U95: =IF($G95=25,$O95,"")
C96: 0.08 | P96: =IF($G96=8,$O96,"") | Q96: =IF($G96=10,$O96,"") | R96: =IF($G96=12,$O96,"") | S96: =IF($G96=16,$O96,"") | T96: =IF($G96=20,$O96,"") | U96: =IF($G96=25,$O96,"")
B97: Stirupps b | E97: =(2*((0.75-0.08-0.016)/6))+0.012+0.02 -> 0.25 | G97: 10 | H97: 8 | I97: 1 | J97: =2*(D99+E97)+2*8*G97/1000 -> 1.1 | L97: 5 | M97: =2*G97*L97/1000 -> 0.1 | N97: =(J97+K97-M97) -> 1 | O97: =(H97*I97*N97) -> 8 | P97: =IF($G97=8,$O97,"") | Q97: =IF($G97=10,$O97,"") -> 8 | R97: =IF($G97=12,$O97,"") | S97: =IF($G97=16,$O97,"") | T97: =IF($G97=20,$O97,"") | U97: =IF($G97=25,$O97,"")
P98: =IF($G98=8,$O98,"") | Q98: =IF($G98=10,$O98,"") | R98: =IF($G98=12,$O98,"") | S98: =IF($G98=16,$O98,"") | T98: =IF($G98=20,$O98,"") | U98: =IF($G98=25,$O98,"")
D99: =0.3-0.08 -> 0.22 | P99: =IF($G99=8,$O99,"") | Q99: =IF($G99=10,$O99,"") | R99: =IF($G99=12,$O99,"") | S99: =IF($G99=16,$O99,"") | T99: =IF($G99=20,$O99,"") | U99: =IF($G99=25,$O99,"")
P100: =IF($G100=8,$O100,"") | Q100: =IF($G100=10,$O100,"") | R100: =IF($G100=12,$O100,"") | S100: =IF($G100=16,$O100,"") | T100: =IF($G100=20,$O100,"") | U100: =IF($G100=25,$O100,"")
B101: Stirupps c | G101: 10 | H101: 8 | I101: 1 | J101: =C102+D104+E102+2*8*G101/1000 -> 0.73 | L101: 4 | M101: =2*G101*L101/1000 -> 0.08 | N101: =(J101+K101-M101) -> 0.65 | O101: =(H101*I101*N101) -> 5.2 | P101: =IF($G101=8,$O101,"") | Q101: =IF($G101=10,$O101,"") -> 5.2 | R101: =IF($G101=12,$O101,"") | S101: =IF($G101=16,$O101,"") | T101: =IF($G101=20,$O101,"") | U101: =IF($G101=25,$O101,"")
...

Sheet PLINTH BEAM BBS
A1: Reinforcement
A2: Sr. No. | B2: Designation | C2: Dia | D2: C/C (mm) | E2: No | F2: No | G2: No of Bars | H2: Bar Length (mtr) | K2: Lap Length | L2: One Bar Length (MTR) | M2: Dia Wise Weight (Kg)
H3: a | I3: b | J3: c | M3: 8mm | N3: 10mm | O3: 12mm | P3: 16mm | Q3: 20MM | R3: 25mm
B4: Typical Beam
A5: 200X450 | B5: PB1 | L5: =SUM(H5:J5)+K5 -> 0 | M5: =+ROUND(IF(C5=8,PRODUCT(E5,F5,G5,L5),0),2) -> 0 | N5: =+ROUND(IF(C5=10,PRODUCT(E5,F5,G5,L5),0),2) -> 0 | O5: =+ROUND(IF(C5=12,PRODUCT(E5,F5,G5,L5),0),2) -> 0 | P5: =+ROUND(IF(C5=16,PRODUCT(E5,F5,G5,L5),0),2) -> 0 | Q5: =+ROUND(IF(C5=20,PRODUCT(E5,F5,G5,L5),0),2) -> 0 | R5: =+ROUND(IF(C5=25,PRODUCT(E5,F5,G5,L5),0),2) -> 0
B6: BOTTOM | C6: 16 | E6: 2 | F6: 1 | G6: 2 | H6: 0.3 | I6: =7.375-0.06 -> 7.315 | J6: 0.3 | L6: =SUM(H6:J6)+K6 -> 7.915 | M6: =+ROUND(IF(C6=8,PRODUCT(E6,F6,G6,L6),0),2) -> 0 | N6: =+ROUND(IF(C6=10,PRODUCT(E6,F6,G6,L6),0),2) -> 0 | O6: =+ROUND(IF(C6=12,PRODUCT(E6,F6,G6,L6),0),2) -> 0 | P6: =+ROUND(IF(C6=16,PRODUCT(E6,F6,G6,L6),0),2) -> 31.66 | Q6: =+ROUND(IF(C6=20,PRODUCT(E6,F6,G6,L6),0),2) -> 0 | R6: =+ROUND(IF(C6=25,PRODUCT(E6,F6,G6,L6),0),2) -> 0
B7: TOP | C7: 16 | E7: 2 | F7: 1 | G7: 2 | H7: 0.3 | I7: =7.375-0.06 -> 7.315 | J7: 0.3 | L7: =SUM(H7:J7)+K7 -> 7.915 | M7: =+ROUND(IF(C7=8,PRODUCT(E7,F7,G7,L7),0),2) -> 0 | N7: =+ROUND(IF(C7=10,PRODUCT(E7,F7,G7,L7),0),2) -> 0 | O7: =+ROUND(IF(C7=12,PRODUCT(E7,F7,G7,L7),0),2) -> 0 | P7: =+ROUND(IF(C7=16,PRODUCT(E7,F7,G7,L7),0),2) -> 31.66 | Q7: =+ROUND(IF(C7=20,PRODUCT(E7,F7,G7,L7),0),2) -> 0 | R7: =+ROUND(IF(C7=25,PRODUCT(E7,F7,G7,L7),0),2) -> 0
B8: TOP EXTRA | C8: 0 | E8: 2 | F8: 1 | G8: 2 | H8: 0.3 | I8: =0.65-0.03+0.9 -> 1.52 | L8: =SUM(H8:J8)+K8 -> 1.82 | M8: =+ROUND(IF(C8=8,PRODUCT(E8,F8,G8,L8),0),2) -> 0 | N8: =+ROUND(IF(C8=10,PRODUCT(E8,F8,G8,L8),0),2) -> 0 | O8: =+ROUND(IF(C8=12,PRODUCT(E8,F8,G8,L8),0),2) -> 0 | P8: =+ROUND(IF(C8=16,PRODUCT(E8,F8,G8,L8),0),2) -> 0 | Q8: =+ROUND(IF(C8=20,PRODUCT(E8,F8,G8,L8),0),2) -> 0 | R8: =+ROUND(IF(C8=25,PRODUCT(E8,F8,G8,L8),0),2) -> 0
B9: STIRRUPS | C9: 8 | D9: 100 | E9: 2 | F9: 1 | G9: =+ROUND(1.8/0.1,0) -> 18 | I9: =2*(0.14+0.39)+16*C9/1000 -> 1.188 | L9: =SUM(H9:J9)+K9 -> 1.188 | M9: =+ROUND(IF(C9=8,PRODUCT(E9,F9,G9,L9),0),2) -> 42.77 | N9: =+ROUND(IF(C9=10,PRODUCT(E9,F9,G9,L9),0),2) -> 0 | O9: =+ROUND(IF(C9=12,PRODUCT(E9,F9,G9,L9),0),2) -> 0 | P9: =+ROUND(IF(C9=16,PRODUCT(E9,F9,G9,L9),0),2) -> 0 | Q9: =+ROUND(IF(C9=20,PRODUCT(E9,F9,G9,L9),0),2) -> 0 | R9: =+ROUND(IF(C9=25,PRODUCT(E9,F9,G9,L9),0),2) -> 0
C10: 8 | D10: 150 | E10: 2 | F10: 1 | G10: =+ROUND(1.225/0.15+1,0) -> 9 | I10: =2*(0.14+0.39)+16*C10/1000 -> 1.188 | L10: =SUM(H10:J10)+K10 -> 1.188 | M10: =+ROUND(IF(C10=8,PRODUCT(E10,F10,G10,L10),0),2) -> 21.38 | N10: =+ROUND(IF(C10=10,PRODUCT(E10,F10,G10,L10),0),2) -> 0 | O10: =+ROUND(IF(C10=12,PRODUCT(E10,F10,G10,L10),0),2) -> 0 | P10: =+ROUND(IF(C10=16,PRODUCT(E10,F10,G10,L10),0),2) -> 0 | Q10: =+ROUND(IF(C10=20,PRODUCT(E10,F10,G10,L10),0),2) -> 0 | R10: =+ROUND(IF(C10=25,PRODUCT(E10,F10,G10,L10),0),2) -> 0
B11: STIRRUPS | C11: 8 | D11: 100 | E11: 2 | F11: 1 | G11: =+ROUND(1.8/0.1,0) -> 18 | I11: =2*(0.14+0.39)+16*C11/1000 -> 1.188 | L11: =SUM(H11:J11)+K11 -> 1.188 | M11: =+ROUND(IF(C11=8,PRODUCT(E11,F11,G11,L11),0),2) -> 42.77 | N11: =+ROUND(IF(C11=10,PRODUCT(E11,F11,G11,L11),0),2) -> 0 | O11: =+ROUND(IF(C11=12,PRODUCT(E11,F11,G11,L11),0),2) -> 0 | P11: =+ROUND(IF(C11=16,PRODUCT(E11,F11,G11,L11),0),2) -> 0 | Q11: =+ROUND(IF(C11=20,PRODUCT(E11,F11,G11,L11),0),2) -> 0 | R11: =+ROUND(IF(C11=25,PRODUCT(E11,F11,G11,L11),0),2) -> 0
C12: 8 | D12: 150 | E12: 2 | F12: 1 | G12: =+ROUND(1/0.15+1,0) -> 8 | I12: =2*(0.14+0.39)+16*C12/1000 -> 1.188 | L12: =SUM(H12:J12)+K12 -> 1.188 | M12: =+ROUND(IF(C12=8,PRODUCT(E12,F12,G12,L12),0),2) -> 19.01 | N12: =+ROUND(IF(C12=10,PRODUCT(E12,F12,G12,L12),0),2) -> 0 | O12: =+ROUND(IF(C12=12,PRODUCT(E12,F12,G12,L12),0),2) -> 0 | P12: =+ROUND(IF(C12=16,PRODUCT(E12,F12,G12,L12),0),2) -> 0 | Q12: =+ROUND(IF(C12=20,PRODUCT(E12,F12,G12,L12),0),2) -> 0 | R12: =+ROUND(IF(C12=25,PRODUCT(E12,F12,G12,L12),0),2) -> 0
A13: 200X450 | B13: PB2 | L13: =SUM(H13:J13)+K13 -> 0 | M13: =+ROUND(IF(C13=8,PRODUCT(E13,F13,G13,L13),0),2) -> 0 | N13: =+ROUND(IF(C13=10,PRODUCT(E13,F13,G13,L13),0),2) -> 0 | O13: =+ROUND(IF(C13=12,PRODUCT(E13,F13,G13,L13),0),2) -> 0 | P13: =+ROUND(IF(C13=16,PRODUCT(E13,F13,G13,L13),0),2) -> 0 | Q13: =+ROUND(IF(C13=20,PRODUCT(E13,F13,G13,L13),0),2) -> 0 | R13: =+ROUND(IF(C13=25,PRODUCT(E13,F13,G13,L13),0),2) -> 0
B14: BOTTOM | C14: 16 | E14: 2 | F14: 1 | G14: 2 | H14: 0.3 | I14: =4.15-0.06 -> 4.09 | J14: 0.3 | L14: =SUM(H14:J14)+K14 -> 4.69 | M14: =+ROUND(IF(C14=8,PRODUCT(E14,F14,G14,L14),0),2) -> 0 | N14: =+ROUND(IF(C14=10,PRODUCT(E14,F14,G14,L14),0),2) -> 0 | O14: =+ROUND(IF(C14=12,PRODUCT(E14,F14,G14,L14),0),2) -> 0 | P14: =+ROUND(IF(C14=16,PRODUCT(E14,F14,G14,L14),0),2) -> 18.76 | Q14: =+ROUND(IF(C14=20,PRODUCT(E14,F14,G14,L14),0),2) -> 0 | R14: =+ROUND(IF(C14=25,PRODUCT(E14,F14,G14,L14),0),2) -> 0
B15: TOP | C15: 16 | E15: 2 | F15: 1 | G15: 2 | H15: 0.3 | I15: =4.15-0.06 -> 4.09 | J15: 0.3 | L15: =SUM(H15:J15)+K15 -> 4.69 | M15: =+ROUND(IF(C15=8,PRODUCT(E15,F15,G15,L15),0),2) -> 0 | N15: =+ROUND(IF(C15=10,PRODUCT(E15,F15,G15,L15),0),2) -> 0 | O15: =+ROUND(IF(C15=12,PRODUCT(E15,F15,G15,L15),0),2) -> 0 | P15: =+ROUND(IF(C15=16,PRODUCT(E15,F15,G15,L15),0),2) -> 18.76 | Q15: =+ROUND(IF(C15=20,PRODUCT(E15,F15,G15,L15),0),2) -> 0 | R15: =+ROUND(IF(C15=25,PRODUCT(E15,F15,G15,L15),0),2) -> 0
B16: TOP EXTRA | C16: 0 | E16: 2 | F16: 1 | G16: 2 | H16: 0.3 | I16: =0.65-0.03+0.9 -> 1.52 | L16: =SUM(H16:J16)+K16 -> 1.82 | M16: =+ROUND(IF(C16=8,PRODUCT(E16,F16,G16,L16),0),2) -> 0 | N16: =+ROUND(IF(C16=10,PRODUCT(E16,F16,G16,L16),0),2) -> 0 | O16: =+ROUND(IF(C16=12,PRODUCT(E16,F16,G16,L16),0),2) -> 0 | P16: =+ROUND(IF(C16=16,PRODUCT(E16,F16,G16,L16),0),2) -> 0 | Q16: =+ROUND(IF(C16=20,PRODUCT(E16,F16,G16,L16),0),2) -> 0 | R16: =+ROUND(IF(C16=25,PRODUCT(E16,F16,G16,L16),0),2) -> 0
A17: 3.3 | B17: STIRRUPS | C17: 8 | D17: 100 | E17: 2 | F17: 1 | G17: =+ROUND(1.8/0.1,0) -> 18 | I17: =2*(0.14+0.39)+16*C17/1000 -> 1.188 | L17: =SUM(H17:J17)+K17 -> 1.188 | M17: =+ROUND(IF(C17=8,PRODUCT(E17,F17,G17,L17),0),2) -> 42.77 | N17: =+ROUND(IF(C17=10,PRODUCT(E17,F17,G17,L17),0),2) -> 0 | O17: =+ROUND(IF(C17=12,PRODUCT(E17,F17,G17,L17),0),2) -> 0 | P17: =+ROUND(IF(C17=16,PRODUCT(E17,F17,G17,L17),0),2) -> 0 | Q17: =+ROUND(IF(C17=20,PRODUCT(E17,F17,G17,L17),0),2) -> 0 | R17: =+ROUND(IF(C17=25,PRODUCT(E17,F17,G17,L17),0),2) -> 0
C18: 8 | D18: 150 | E18: 2 | F18: 1 | G18: =+ROUND((+A17-1.8)/0.15+1,0) -> 11 | I18: =2*(0.14+0.39)+16*C18/1000 -> 1.188 | L18: =SUM(H18:J18)+K18 -> 1.188 | M18: =+ROUND(IF(C18=8,PRODUCT(E18,F18,G18,L18),0),2) -> 26.14 | N18: =+ROUND(IF(C18=10,PRODUCT(E18,F18,G18,L18),0),2) -> 0 | O18: =+ROUND(IF(C18=12,PRODUCT(E18,F18,G18,L18),0),2) -> 0 | P18: =+ROUND(IF(C18=16,PRODUCT(E18,F18,G18,L18),0),2) -> 0 | Q18: =+ROUND(IF(C18=20,PRODUCT(E18,F18,G18,L18),0),2) -> 0 | R18: =+ROUND(IF(C18=25,PRODUCT(E18,F18,G18,L18),0),2) -> 0
A19: 100X450 | B19: PB3 | L19: =SUM(H19:J19)+K19 -> 0 | M19: =+ROUND(IF(C19=8,PRODUCT(E19,F19,G19,L19),0),2) -> 0 | N19: =+ROUND(IF(C19=10,PRODUCT(E19,F19,G19,L19),0),2) -> 0 | O19: =+ROUND(IF(C19=12,PRODUCT(E19,F19,G19,L19),0),2) -> 0 | P19: =+ROUND(IF(C19=16,PRODUCT(E19,F19,G19,L19),0),2) -> 0 | Q19: =+ROUND(IF(C19=20,PRODUCT(E19,F19,G19,L19),0),2) -> 0 | R19: =+ROUND(IF(C19=25,PRODUCT(E19,F19,G19,L19),0),2) -> 0
B20: BOTTOM | C20: 10 | E20: 4 | F20: 1 | G20: 2 | H20: 0.3 | I20: =1.925-0.06 -> 1.865 | J20: 0.3 | L20: =SUM(H20:J20)+K20 -> 2.465 | M20: =+ROUND(IF(C20=8,PRODUCT(E20,F20,G20,L20),0),2) -> 0 | N20: =+ROUND(IF(C20=10,PRODUCT(E20,F20,G20,L20),0),2) -> 19.72 | O20: =+ROUND(IF(C20=12,PRODUCT(E20,F20,G20,L20),0),2) -> 0 | P20: =+ROUND(IF(C20=16,PRODUCT(E20,F20,G20,L20),0),2) -> 0 | Q20: =+ROUND(IF(C20=20,PRODUCT(E20,F20,G20,L20),0),2) -> 0 | R20: =+ROUND(IF(C20=25,PRODUCT(E20,F20,G20,L20),0),2) -> 0
B21: TOP | C21: 10 | E21: 4 | F21: 1 | G21: 2 | H21: 0.3 | I21: =1.925-0.06 -> 1.865 | J21: 0.3 | L21: =SUM(H21:J21)+K21 -> 2.465 | M21: =+ROUND(IF(C21=8,PRODUCT(E21,F21,G21,L21),0),2) -> 0 | N21: =+ROUND(IF(C21=10,PRODUCT(E21,F21,G21,L21),0),2) -> 19.72 | O21: =+ROUND(IF(C21=12,PRODUCT(E21,F21,G21,L21),0),2) -> 0 | P21: =+ROUND(IF(C21=16,PRODUCT(E21,F21,G21,L21),0),2) -> 0 | Q21: =+ROUND(IF(C21=20,PRODUCT(E21,F21,G21,L21),0),2) -> 0 | R21: =+ROUND(IF(C21=25,PRODUCT(E21,F21,G21,L21),0),2) -> 0
B22: STIRRUPS | C22: 8 | D22: 150 | E22: 4 | F22: 1 | G22: =+ROUND(1.395/0.15+1,0) -> 10 | I22: =2*(0.05+0.39)+16*C22/1000 -> 1.008 | L22: =SUM(H22:J22)+K22 -> 1.008 | M22: =+ROUND(IF(C22=8,PRODUCT(E22,F22,G22,L22),0),2) -> 40.32 | N22: =+ROUND(IF(C22=10,PRODUCT(E22,F22,G22,L22),0),2) -> 0 | O22: =+ROUND(IF(C22=12,PRODUCT(E22,F22,G22,L22),0),2) -> 0 | P22: =+ROUND(IF(C22=16,PRODUCT(E22,F22,G22,L22),0),2) -> 0 | Q22: =+ROUND(IF(C22=20,PRODUCT(E22,F22,G22,L22),0),2) -> 0 | R22: =+ROUND(IF(C22=25,PRODUCT(E22,F22,G22,L22),0),2) -> 0
A23: 100X450 | B23: PB3 | L23: =SUM(H23:J23)+K23 -> 0 | M23: =+ROUND(IF(C23=8,PRODUCT(E23,F23,G23,L23),0),2) -> 0 | N23: =+ROUND(IF(C23=10,PRODUCT(E23,F23,G23,L23),0),2) -> 0 | O23: =+ROUND(IF(C23=12,PRODUCT(E23,F23,G23,L23),0),2) -> 0 | P23: =+ROUND(IF(C23=16,PRODUCT(E23,F23,G23,L23),0),2) -> 0 | Q23: =+ROUND(IF(C23=20,PRODUCT(E23,F23,G23,L23),0),2) -> 0 | R23: =+ROUND(IF(C23=25,PRODUCT(E23,F23,G23,L23),0),2) -> 0
B24: BOTTOM | C24: 10 | E24: 2 | F24: 1 | G24: 2 | H24: 0.3 | I24: =1.53-0.06 -> 1.47 | J24: 0.3 | L24: =SUM(H24:J24)+K24 -> 2.07 | M24: =+ROUND(IF(C24=8,PRODUCT(E24,F24,G24,L24),0),2) -> 0 | N24: =+ROUND(IF(C24=10,PRODUCT(E24,F24,G24,L24),0),2) -> 8.28 | O24: =+ROUND(IF(C24=12,PRODUCT(E24,F24,G24,L24),0),2) -> 0 | P24: =+ROUND(IF(C24=16,PRODUCT(E24,F24,G24,L24),0),2) -> 0 | Q24: =+ROUND(IF(C24=20,PRODUCT(E24,F24,G24,L24),0),2) -> 0 | R24: =+ROUND(IF(C24=25,PRODUCT(E24,F24,G24,L24),0),2) -> 0
B25: TOP | C25: 10 | E25: 2 | F25: 1 | G25: 2 | H25: 0.3 | I25: =1.53-0.06 -> 1.47 | J25: 0.3 | L25: =SUM(H25:J25)+K25 -> 2.07 | M25: =+ROUND(IF(C25=8,PRODUCT(E25,F25,G25,L25),0),2) -> 0 | N25: =+ROUND(IF(C25=10,PRODUCT(E25,F25,G25,L25),0),2) -> 8.28 | O25: =+ROUND(IF(C25=12,PRODUCT(E25,F25,G25,L25),0),2) -> 0 | P25: =+ROUND(IF(C25=16,PRODUCT(E25,F25,G25,L25),0),2) -> 0 | Q25: =+ROUND(IF(C25=20,PRODUCT(E25,F25,G25,L25),0),2) -> 0 | R25: =+ROUND(IF(C25=25,PRODUCT(E25,F25,G25,L25),0),2) -> 0
