Workbook
Name \0: #REF!
Name \0: #REF!
Name \B: #REF!
Name \B: #REF!
Name \C: #REF!
Name \C: #REF!
Name \G: #REF!
Name \I: #REF!
Name \M: #REF!
Name \O: #REF!
Name \P: #REF!
Name \Q: #REF!
Name \R: #REF!
Name \S: #REF!
Name __aoc10: #N/A
Name __aoc11: #REF!
Name __aoc11: #REF!
Name __aoc11: #REF!
Name __aoc7: #REF!
Name __aoc7: #REF!
Name __aoc7: #REF!
Name __aoc8: #REF!
Name __aoc8: #REF!
Name __aoc9: #REF!
Name __aoc9: #REF!
Name __ERA1: #REF!
Name __ERA1: #REF!
Name __ERA10: #REF!
Name __ERA10: #REF!
Name __ERA11: #REF!
Name __ERA11: #REF!
Name __ERA2: #REF!
Name __ERA3: #REF!
Name __ERA5: #REF!
Name __ERA5: #REF!
Name __ERA9: #REF!
Name __ERA9: #REF!
Name __HED1: #REF!
Name __HED1: #REF!
Name __HED2: #REF!
Name __HED2: #REF!
Name __vut02533: #REF!
Name __vut02533: #REF!
Name __vut02533: #REF!
Name __xlnm.Print_Area: "$#REF!.$A$2:$I$161"
Name __xlnm.Print_Area_1: #REF!
Name __xlnm.Print_Area_1: #REF!
Name __xlnm.Print_Area_1: #REF!
Name __xlnm.Print_Area_10: #REF!
Name __xlnm.Print_Area_10: #REF!
Name __xlnm.Print_Area_11: #REF!
Name __xlnm.Print_Area_11: #REF!
Name __xlnm.Print_Area_12: #REF!
Name __xlnm.Print_Area_12: #REF!
Name __xlnm.Print_Area_13: #REF!
Name __xlnm.Print_Area_13: #REF!
Name __xlnm.Print_Area_14: #REF!
Name __xlnm.Print_Area_14: #REF!
Name __xlnm.Print_Area_15: #REF!
Name __xlnm.Print_Area_15: #REF!

Sheet TOP SHEET
A1: OMAXE LTD. | F1: Tracker NO | G1: Office NO
A2: NAME OF PROJECT : OMAXE ANANDA TOWER-E (Location: Tower-E STILT + 14 FLOORS) | E2: CONTRACT VALUE ; | G2: =+ABSTRACT!F108 -> 162074375
A3: NATURE OF WORK : CIVIL STRUCTURE WORK | E3: PROGRESS OF WORK: | G3: =D11/G2 -> 0.035935252
A4: NAME OF THE CONTRACTOR :- M/s MARCO-ENTERPRISES | E4: VENDOR CODE:
A5: WORK ORDER NO. & DATE : OPRL/ATE/11094106758 (14 FEB, 2025) | E5: DATE OF START: 01.MAY.2025
A6: THIS R/A BILL NO. & DATE : 3RD RA BILL, DATE 07-06-2025 | E6: COMPLETION PERIOD : Upto 31-Aug-2026 (18 Months)
A7: PERIOD OF BILL :- FROM 01-05-2025 TO 31-05-2025 | E7: GST No. : 09BLDPK5228HIZ2
A8: ERP PROJECT CODE : 127018 | E8: PAN NO. : BLDPK5228H
A9: DATE OF BILL REC. AT SITE :- | C9: DATE OF BILL RECEIVED AT H.O. :- | E9: DATE OF BILL CHECKING AT H.O. :-
A10: S.NO. | B10: PARTICULARS | C10: CLAIMED BY CONTRACTOR | D10: GROSS AMT | E10: PREVIOUS AMT. | F10: THIS BILL AMT | G10: REMARKS
A11: 1 | B11: WORK DONE(CIVIL) | D11: =ABSTRACT!M108 -> 5824183.5 | E11: =ABSTRACT!K108 -> 0 | F11: =+D11-E11 -> 5824183.5 | I11: 5824183.5
A12: 2 | B12: WORK DONE(ELECT/ PLUMBING)
A13: 3 | B13: DIFF. OF CEMENT
A14: 4 | B14: RATE DIFF OF TILES
B15: TOTAL (A) | D15: =SUM(D11:D14) -> 5824183.5 | E15: =SUM(E11:E14) -> 0 | F15: =SUM(F11:F14) -> 5824183.5
A16: 5 | B16: Add GST 18% On (A) | D16: =D15*18% -> 1048353 | E16: =E15*18% -> 0 | F16: =F15*18% -> 1048353
B17: TOTAL (B) | D17: =D16+D15 -> 6872536.5 | E17: =E16+E15 -> 0 | F17: =F16+F15 -> 6872536.5
B18: ADVANCES
A21: 7.1 | B21: Add Mobilization Advance | D21: =+F21+E21 -> 400000 | E21: 400000 | F21: 0
A22: 7.2 | B22: Recover Mobilization Advance | F22: =+D22-E22 -> 0
B23: TOTAL (C) | D23: =SUM(D17:D22) -> 7272536.5 | E23: =SUM(E17:E22) -> 400000 | F23: =SUM(F17:F22) -> 6872536.5
B24: DEDUCTIONS
A25: 8 | B25: SECURITY @ 5 % (ON TOTAL A) | D25: =ROUND(D15*5%,0) -> 291209 | E25: =ROUND(E15*5%,0) -> 0 | F25: =ROUND(F15*5%,0) -> 291209
A26: 9 | B26: TDS @ 1% (ON TOTAL A) | D26: =ROUND((D15+D19+D20+D21)*1%,0) -> 62242 | E26: =ROUND((E15+E19+E20+E21)*1%,0) -> 4000 | F26: =ROUND((F15+F19+F20+F21)*1%,0) -> 58242
B28: TOTAL DEDUCTION (C) | D28: =SUM(D25:D27) -> 353451 | E28: =SUM(E25:E27) -> 4000 | F28: =SUM(F25:F27) -> 349451
A29: 11 | B29: NET PAYABLE AMOUNT (D) | D29: =D23-D28 -> 6919085.5 | E29: =E23-E28 -> 396000 | F29: =F23-F28 -> 6523085.5 | G29: =+G30*0.7 -> 3832312.8
B30: NOW PAYABLE | F30: =F29 -> 6523085.5 | G30: =+F30-F16 -> 5474732.5
B31: PREPARED BY
C32: PRIYANK BARANWAL
C33: MANAGER (BILLING)
C34: 9988294677
B35: ACCOUNT (SITE) | E35: PREVIOUS RA BILL NO:-
C36: ANUP SINGH | E36: PREVIOUS RA GROSS AMOUNT:-
C37: DY. MANAGER
C38: 9315403180
B39: PROJECT INCHARGE {CPC/PC/ASST V.P./SR GM /GM}
E40: S K PANDEY
E41: G.M. - PROJECT
E42: 9711800470
B43: HO BILL MONITORING
C44: UPENDER SINGH | E44: NARENDER KR. SHARMA
C45: CHIEF MANAGER | E45: G.M.-HO BILLING
E46: 8700437240

Sheet ABSTRACT
A1: OMAXE PANCHAM REALCON PVT. LTD.
B2: =+'TOP SHEET'!A5 -> WORK ORDER NO. & DATE : OPRL/ATE/11094106758 (14 FEB, 2025) | J2: =+'TOP SHEET'!A8 -> ERP PROJECT CODE : 127018
B3: =+'TOP SHEET'!A6 -> THIS R/A BILL NO. & DATE : 3RD RA BILL, DATE 07-06-2025 | J3: =+'TOP SHEET'!A9 -> DATE OF BILL REC. AT SITE :-
B4: =+'TOP SHEET'!A3 -> NATURE OF WORK : CIVIL STRUCTURE WORK | J4: =+'TOP SHEET'!A7 -> PERIOD OF BILL :- FROM 01-05-2025 TO 31-05-2025
A5: ABSTRACT OF COST
A6: S.No. | B6: DESCRIPTION OF ITEM | C6: Unit | D6: AS PER W.O. (R0) | H6: Qty | K6: Amount | N6: Executed %
D7: Qty | E7: Rate | F7: Amount | G7: Part Rate | H7: Prev. Bill | I7: This Bill | J7: UpTo Date | K7: Prev. Bill | L7: This Bill | M7: UpTo Date
A8: 1 | B8: EARTH WORK
A9: 1.1. | B9: Earth work in excavation in foundation trenches, column pits, plinth beam, under grade/ raft slab etc. by mechanical and/or manual means up to a depth of 1.5 mtr in soil from existing excavated soil level, stacking/spreading the excavated material within site premises (within a stretch of 1500 M) as per direction of Project Manager including dressing of bottom, sides strutting, timbering, shoring, trimming of sides, all leads and lifts, bailing or pumping out the water from the excavated areas collected from any source including subsoil water and keeping the excavated surface dry for subsequent works incidentals, etc. complete with ramming of bottom, surface preparation as per specifications to receive the PCC. | C9: CUM | D9: 1000 | E9: 120 | F9: =$D9*E9 -> 120000 | I9: =J9-H9 -> 0 | L9: =M9-K9 -> 0 | M9: =E9*J9 -> 0 | N9: =J9/D9 -> 0
B10: Excavation shall be payable only for vertical cut up to the outer edge of foundation lean concrete as indicated in drawings for all depths. Cost of extra excavation required for working space, supporting side shuttering of foundations and retaining walls, planking, dewatering, strutting etc. and that required for making slopes for stability of excavation shall be deemed to be included in the rate quoted. This item is not for Mass Excavation. | L10: =M10-K10 -> 0 | M10: =E10*J10 -> 0
A11: 1.2. | B11: Prepare the surface for PCC by manual excavation upto 30 cm depth including dressing the surface, ramming the bottom, disposal and spreading of the surplus earth at the specified location within premises including proper levelling, watering and consolidation complete as directed by E I C. (The item shall be measured as per plan area of PCC, Working space shall not be taken into measurement, deemed to be included into rates) (This item is only applicable if excavation item is not being executed by contractor and excavation already done by client for the location) | C11: SQM | D11: 1500 | E11: 65 | F11: =$D11*E11 -> 97500 | G11: =+E11 -> 65 | I11: =J11-H11 -> 906.85293 | J11: ='EARTH WORK MB'!I18 -> 906.85293 | L11: =M11-K11 -> 58945.44 | M11: =G11*J11 -> 58945.44 | N11: =J11/D11 -> 0.60456862
A12: 1.3. | B12: Filling available excavated earth in trenches, plinth, sides of foundations etc. in layers not exceeding 20cm in depth: consolidating each deposited layer by ramming and watering, lead within the premises and upto any depth. (Compacted Volume shall be payable as per drawing) - Actual volume shall be paid incase excavation is done by Client. | C12: CUM | D12: 2400 | E12: 100 | F12: =$D12*E12 -> 240000 | I12: =J12-H12 -> 0 | L12: =M12-K12 -> 0 | M12: =E12*J12 -> 0 | N12: =J12/D12 -> 0
B13: Total of Earthwork | F13: =SUBTOTAL(9,F9:F12) -> 457500
A15: 2 | B15: CONCRETE WORK
B16: Rates for all cement concrete items plain and reinforced described below shall include work from Basement Level to top of last roof including roof of machine room, mumty, over head water tanks and parapets above at all floors and for all heights. The contractor should provide full time sufficient pipes with accessories and pumps based on the site requirement for pumping and laying of concrete as directed by the EIC. The rate inclusive of standard rigid pipe line and its supports, lifting, laying charges, etc., at all heights and levels. No additional payment shall be payable to the contractor on account of using or change in any size of coarse aggregate in PCC/ RCC work at any stage during currency of works. (This section covers cast in situ structural and architectural as well.)
A17: 2.1 | B17: Plain Cement Concrete: Providing and laying plain cement concrete of specified grade as bed concrete under foundation, bases for rafts, underground water tank, building machine equipments, column footing, under floor landings, below road and pathways, cill, coping, screeding at roof to required slope and other locations as called for laid, consolidated and cured etc. complete including finishing the top surface to receive the next course / layer as per specification and drawing. (Shuttering shall be paid in Item No.3.1.1) M10 Grade (Basic Rate of PCC - Rs. 4200/cum) without pump | C17: CUM | D17: 100 | E17: 5550 | F17: =$D17*E17 -> 555000 | G17: 5550 | I17: =J17-H17 -> 56.798193 | J17: ='CONCRETE SUMMARY'!J6 -> 56.798193 | L17: =M17-K17 -> 315229.97 | M17: =G17*J17 -> 315229.97 | N17: =J17/D17 -> 0.56798193
A18: 2.2. | B18: Providing and laying cement concrete 1:2:4 (1 cement : 2 coarse sand : 4 graded stone aggregate 20mm nominal size) for ledge wall below balcony railings, band, mullion, lintel etc. (Shuttering shall be paid separately in respective item) as per drawing and as directed by the Project Manager. | C18: CUM | D18: 50 | E18: 5750 | F18: =$D18*E18 -> 287500 | I18: =J18-H18 -> 0 | J18: ='CONCRETE SUMMARY'!J7 -> 0 | L18: =M18-K18 -> 0 | M18: =E18*J18 -> 0 | N18: =J18/D18 -> 0
A19: 2.3. | B19: Providing and laying damp proof course 40mm thick including shttering with cement concrete 1:2:4 (1 cement : 2 coarse sand : 4 graded stone aggregate 20mm nominal size) including mixing of water proofing compound @ 2% of cement content and applying two layers of bitumen @ 1.70 Kg/Sqm of grade 85/25 and as directed by the Project Manager. | C19: SQM | D19: 200 | E19: 480 | F19: =$D19*E19 -> 96000 | I19: =J19-H19 -> 0 | J19: ='CONCRETE SUMMARY'!J8 -> 0 | L19: =M19-K19 -> 0 | M19: =E19*J19 -> 0 | N19: =J19/D19 -> 0
A21: 2.4. | B21: RCC WORK
B22: Providing & Laying RMC M-25 Grade as per approved design mix concrete (strictly controlled conditions) with flyash (as per approved design mix) with automatic batching plant machine mixed and machine vibrated RCC with melamine based plasticisers etc., upto any level, including finishing the exposed surface, fixing/ removal of pockets, fixing of sleeves and inserts (sleeves provided by client), curing etc complete, as per drawing (including all size and shape like circular, semi-circular, oval etc.) and as directed for all lead and lift, excluding cost of centering, shuttering and steel reinforcement but including cost of making shear keys and provision of construction / contraction / control joints in various locations. Checking from Client should not be considered as final and any defects arising during or after casting should be borne & bear by contractor at his own cost. This is inclusive of leaving shuttering & centring for pour strip, slab in slope, RCC members in curved, etc., nothing is payable extra on this account. RMC (M-25) Basic Rate - Rs. 5200/cum without pump excluding GST
A23: 2.4.1. | B23: Foundation, column footings, raft slab, raft beams, plinth beam, lift pits, sump pits, pedestals / bases of column, column upto plinth, swimming pool, Retaining wall foundations, grade slab etc. | C23: CUM | D23: 2080 | E23: 6600 | F23: =$D23*E23 -> 13728000 | G23: 6600 | I23: =J23-H23 -> 748.20967 | J23: ='CONCRETE SUMMARY'!J12 -> 748.20967 | L23: =M23-K23 -> 4938183.8 | M23: =G23*J23 -> 4938183.8 | N23: =J23/D23 -> 0.35971619
A24: 2.4.2. | B24: Suspended floors, roofs, balconies, shelves/ counters, stair waist slabs, folded plate stairs and landings, swimming pool slab, lintel and floor beams, landing beams, girders (deep beams), RCC bands, swimming pool beam, cantilever projections, coping, cills, slab of tank etc at all levels.
A25: 2.4.2.1. | B25: Stilt Floor level to 7th Floor level | C25: CUM | D25: 2200 | E25: 6550 | F25: =$D25*E25 -> 14410000 | I25: =J25-H25 -> 0 | J25: ='CONCRETE SUMMARY'!J14 -> 0 | L25: =M25-K25 -> 0 | M25: =E25*J25 -> 0 | N25: =J25/D25 -> 0
A26: 2.4.2.2. | B26: 7th Floor level to to Terrace Including OHT, Mumty, Machine Room, Parapet | C26: CUM | D26: 2440 | E26: 6750 | F26: =$D26*E26 -> 16470000 | I26: =J26-H26 -> 0 | J26: ='CONCRETE SUMMARY'!J15 -> 0 | L26: =M26-K26 -> 0 | M26: =E26*J26 -> 0 | N26: =J26/D26 -> 0
A27: 2.4.2.3. | B27: All type of Moulding, Bands, Elevation/Architectural Features as per drawing and as directed by EIC. at all level | C27: CUM | D27: 70 | E27: 7300 | F27: =$D27*E27 -> 511000 | I27: =J27-H27 -> 0 | J27: ='CONCRETE SUMMARY'!J16 -> 0 | L27: =M27-K27 -> 0 | M27: =E27*J27 -> 0 | N27: =J27/D27 -> 0
A29: 2.5. | B29: Columns, Wall, pillars, piers, abutments, posts and struts, offset and projection of columns, water tank walls, lift walls, Retaining Wall, swimming pool, Parapets, planters, vertical projection of pergolas, wall and ramp walls etc. at all levels.
A30: 2.5.1. | B30: Stilt Floor level to 7th Floor level | C30: CUM | D30: 860 | E30: 6850 | F30: =$D30*E30 -> 5891000 | I30: =J30-H30 -> 0 | J30: ='CONCRETE SUMMARY'!J19 -> 0 | L30: =M30-K30 -> 0 | M30: =E30*J30 -> 0 | N30: =J30/D30 -> 0
A31: 2.5.2. | B31: 7th Floor level to to Terrace Including OHT, Mumty, Machine Room, Parapet | C31: CUM | D31: 950 | E31: 7050 | F31: =$D31*E31 -> 6697500 | I31: =J31-H31 -> 0 | J31: ='CONCRETE SUMMARY'!J20 -> 0 | L31: =M31-K31 -> 0 | M31: =E31*J31 -> 0 | N31: =J31/D31 -> 0
A32: 2.5.3. | B32: All type of Moulding, Bands, Elevation/Architectural Features as per drawing and as directed by EIC. at all level | C32: CUM | D32: 30 | E32: 7650 | F32: =$D32*E32 -> 229500 | I32: =J32-H32 -> 0 | J32: ='CONCRETE SUMMARY'!J21 -> 0 | L32: =M32-K32 -> 0 | M32: =E32*J32 -> 0 | N32: =J32/D32 -> 0
A33: 2.5.4. | B33: Finishing vaccum dewatering continuous concrete flooring 100-150 mm thick with specified grade concrete including necessary formwork in required level, vibrating concrete both by poker vibrators / leveling vaccum processing of the concrete and planning the surface by skin powered floater trowels with broom/plain finish including groove cutting & filling etc. complete. (Concrete shall be paid in the respective items above). | C33: SQM | D33: 1625 | E33: 100 | F33: =$D33*E33 -> 162500 | J33: ='CONCRETE SUMMARY'!J22 -> 0
B35: Total of RCC Work | F35: =SUBTOTAL(9,F17:F34) -> 59038000
A37: 3 | B37: CENTRING AND SHUTTERING
B38: Providing and fixing plywood or steel plate shuttering and centring for structural concrete work in locations called for including strutting, propping, bracing, bolting, wedging, casing, striking, removal etc. complete for any size, section, thickness. Props shall consist of well designed steel pipes adequately braced (wooden ballies as props shall not be permitted). The item to include centering and shuttering at all heights and levels. Allow for forming grooves, drip course, chamfers, cut-outs, openings etc. where called for and for dressing with approved shuttering oil to prevent adhesion. Unexposed concrete surfaces subsequently left untreated (in the condition obtained on removal of form work) shall not constitute exposed concrete work and shall be measured under this item only Irregular shapes with sides (like circular, semi-circular, oval etc.) which may not be perpendicular to each other for shapes not conforming to rectangle or square, and circular shuttering shall not be paid separately. Joints of soffits of the slab shall be made clean after concreting and de-shuttering. (quoted rate to include all staging upto 3.50 mtr height). Note:- Contractor shall take necessary precautions such as watertight shuttering. This is inclusive of RCC members, leaving shuttering & centring for pour strip, slab in slope, RCC members in curved (in plan), etc., nothing is payable extra on this account.
A39: 3.1.1. | B39: Foundation, column footings, raft slab, raft beams, plinth beam, lift pits, sump pits, pedestals / bases of column, column up to plinth, swimming pool, Retaining wall foundations, grade slab etc. | C39: SQM | D39: 2150 | E39: 360 | F39: =$D39*E39 -> 774000 | G39: =+E39 -> 360 | I39: =J39-H39 -> 90.1365 | J39: ='SHUTT. WORK SUMMARY'!J5 -> 90.1365 | L39: =M39-K39 -> 32449.14 | M39: =G39*J39 -> 32449.14 | N39: =J39/D39 -> 0.041923953
A40: 3.1.2. | B40: Suspended floors, roofs, balconies, shelves/ counters, stair waist slabs, folded plate stairs and landings, swimming pool slab, lintel and floor beams, landing beams, girders (deep beams), RCC bands, swimming pool beam, cantilever projections, coping, cills, slab of tank etc at all levels.
A41: 3.1.2.1. | B41: Stilt Floor level to 7th Floor level | C41: SQM | D41: 17600 | E41: 465 | F41: =$D41*E41 -> 8184000 | I41: =J41-H41 -> 0 | J41: ='SHUTT. WORK SUMMARY'!J7 -> 0 | L41: =M41-K41 -> 0 | M41: =E41*J41 -> 0 | N41: =J41/D41 -> 0
A42: 3.1.2.2. | B42: 7th Floor level to to Terrace Including OHT, Mumty, Machine Room, Parapet | C42: SQM | D42: 18800 | E42: 485 | F42: =$D42*E42 -> 9118000 | I42: =J42-H42 -> 0 | J42: ='SHUTT. WORK SUMMARY'!J8 -> 0 | L42: =M42-K42 -> 0 | M42: =E42*J42 -> 0 | N42: =J42/D42 -> 0
A43: 3.1.2..3 | B43: All type of Moulding, Bands, Elevation/Architectural Features as per drawing and as directed by EIC. at all level | C43: SQM | D43: 400 | E43: 550 | F43: =$D43*E43 -> 220000 | I43: =J43-H43 -> 0 | J43: ='SHUTT. WORK SUMMARY'!J9 -> 0 | L43: =M43-K43 -> 0 | M43: =E43*J43 -> 0 | N43: =J43/D43 -> 0
L44: =M44-K44 -> 0 | M44: =E44*J44 -> 0
A45: 3.2. | B45: Columns, Wall, pillars, piers, abutments, posts and struts, offset and projection of columns, water tank walls, lift walls, Retaining Wall, swimming pool, Parapets, planters, vertical projection of pergolas, wall and ramp walls etc. at all levels.
A46: 3.2.1. | B46: Stilt Floor level to 7th Floor level | C46: SQM | D46: 7825 | E46: 465 | F46: =$D46*E46 -> 3638625 | I46: =J46-H46 -> 0 | J46: ='SHUTT. WORK SUMMARY'!J12 -> 0 | L46: =M46-K46 -> 0 | M46: =E46*J46 -> 0 | N46: =J46/D46 -> 0
A47: 3.2.2. | B47: 7th Floor level to to Terrace Including OHT, Mumty, Machine Room, Parapet | C47: SQM | D47: 8200 | E47: 485 | F47: =$D47*E47 -> 3977000 | I47: =J47-H47 -> 0 | J47: ='SHUTT. WORK SUMMARY'!J13 -> 0 | L47: =M47-K47 -> 0 | M47: =E47*J47 -> 0 | N47: =J47/D47 -> 0
A48: 3.2.3. | B48: All type of Moulding, Bands, Elevation/Architectural Features as per drawing and as directed by EIC. at all level | C48: SQM | D48: 150 | E48: 550 | F48: =$D48*E48 -> 82500 | I48: =J48-H48 -> 0 | J48: ='SHUTT. WORK SUMMARY'!J14 -> 0 | L48: =M48-K48 -> 0 | M48: =E48*J48 -> 0 | N48: =J48/D48 -> 0
A50: 3.3. | B50: Extra for additional height in centring, shuttering where ever required with adequate bracing, propping etc. including cost of de-shuttering and decentring at all levels, over and above height of 3.50 mtr (Plan area to be measured and shall be paid proportionately on actual height) – for every 1.0 mtr. height | C50: SQM | D50: 1000 | E50: 115 | F50: =$D50*E50 -> 115000 | I50: =J50-H50 -> 0 | J50: ='SHUTT. WORK SUMMARY'!J16 -> 0 | L50: =M50-K50 -> 0 | M50: =E50*J50 -> 0 | N50: =J50/D50 -> 0
B51: Total of Shuttering | F51: =SUBTOTAL(9,F39:F50) -> 26109125
A53: 4 | B53: REINFORCEMENT
B54: Receiving, laying and fixing in position steel reinforcement in all reinforced concrete work, including straightening, cutting, removal of loose rust by wire brush and coating with cement slurry, bending, hoisting, laying in position to the shape and profile required at all levels and heights as per drawing and design and/ or as directed, binding with double folded steel wire as approved by EIC etc. complete. (Contractor shall prepare BBS and submit to EIC for approval prior to cutting, bending & laying of steel bars and payments shall be released as per approved BBS complete in all respect as per direction and approval of EIC Rate shall include cost of 18 gauge GI binding wire, cover blocks as per Indian Standards, unloading the steel & moving to the steel yard, moving site to site within project etc) (Only Steel reinforcement shall be provided by the owner free of cost at one point)
A55: 4.1. | B55: Thermomechanically Treated Reinforcement (TMT) or High yield strength Deformed (Tor steel) bars of all size & grades.
A56: 4.1.1. | B56: Up to Stilt Floor Level | C56: MT | D56: 150 | E56: 8500 | F56: =$D56*E56 -> 1275000 | G56: =+E56 -> 8500 | I56: =J56-H56 -> 52.927237 | J56: ='TMT SUMMARY'!M9/1000 -> 52.927237 | L56: =M56-K56 -> 449881.52 | M56: =G56*J56 -> 449881.52 | N56: =J56/D56 -> 0.35284825
A57: 4.1.2. | B57: Stilt Floor level to to Terrace Including OHT, Mumty, Machine Room, Parapet) | C57: MT | D57: 805 | E57: 9400 | F57: =$D57*E57 -> 7567000 | I57: =J57-H57 -> 0 | J57: ='TMT SUMMARY'!M14 -> 0 | L57: =M57-K57 -> 0 | M57: =E57*J57 -> 0 | N57: =J57/D57 -> 0
A58: 4.1.3. | B58: All type of Moulding, Bands, Elevation/Architectural Features as per drawing and as directed by EIC. at all level | C58: MT | D58: 10 | E58: 11000 | F58: =$D58*E58 -> 110000 | I58: =J58-H58 -> 0 | J58: ='TMT SUMMARY'!M19 -> 0 | L58: =M58-K58 -> 0 | M58: =E58*J58 -> 0 | N58: =J58/D58 -> 0
B59: Total of Reinforcement | F59: =SUBTOTAL(9,F55:F58) -> 8952000
A61: 5 | B61: MASONARY WORK
B62: (Quoted Rates are for all heights, all depths, all levels, including basement to roof (mumty) & all leads and lifts, including curved or circular including elevation masonary work) (Basic Rate of Brick @ Rs. 7/No. FOR at site without GST)
A63: 5.1. | B63: Brick work in Sub Structure (Up to Stilt Floor level):
B64: Providing and laying 230mm thick brick masonry using 1st quality burnt clay FPS bricks in Sub-Structure laid in cement mortar 1:6 (1 cement : 6 coarse sand) mix, joints finished, flush/ raked to 6mm depth including scaffolding, curing complete as per specification and drawing or as directed by Project Manager. | C64: CUM | D64: 100 | E64: 6000 | F64: =$D64*E64 -> 600000 | I64: =J64-H64 -> 0 | J64: ='BRICK WORK SUMMARY'!J7 -> 0 | L64: =M64-K64 -> 0 | M64: =E64*J64 -> 0 | N64: =J64/D64 -> 0
A65: 5.2. | B65: Brick work in Sub Structure (Up to Stilt Floor level):
B66: Providing and laying of 115 mm thick brick work with 1st quality burnt clay FPS bricks in sub-superstructure laid in cement mortar 1:4 (1 cement : 4 coarse sand) mix, joints finished, including placing hoop iron as per specification at every third course, scaffolding, curing complete in all respect as per direction of EIC. (Hoop iron shall be provided by client free of cost) (Items of RCC bands like shuttering, concrete and reinforcement to be paid in respective items). | C66: SQM | D66: 1000 | E66: 800 | F66: =$D66*E66 -> 800000 | G66: =+E66 -> 800 | I66: =J66-H66 -> 36.867 | J66: ='BRICK WORK SUMMARY'!J9 -> 36.867 | L66: =M66-K66 -> 29493.6 | M66: =G66*J66 -> 29493.6 | N66: =J66/D66 -> 0.036867
A67: 5.3. | B67: Brick work in Super Structure (Above Stilt FLoor level)
A68: 5.3.1 | B68: Providing and laying 230mm thick brick masonry using 1st quality burnt clay FPS bricks in Super-Structure laid in cement mortar 1:6 (1 cement : 6 coarse sand) mix, joints finished, flush/ raked to 6mm depth including scaffolding, curing complete as per specification and drawing or as directed by Project Manager. | L68: =M68-K68 -> 0 | M68: =E68*J68 -> 0
A69: (a) | B69: Stilt Floor level to 7th Floor level | C69: CUM | D69: 1185 | E69: 6300 | F69: =$D69*E69 -> 7465500 | I69: =J69-H69 -> 0 | J69: ='BRICK WORK SUMMARY'!J12 -> 0 | L69: =M69-K69 -> 0 | M69: =E69*J69 -> 0 | N69: =J69/D69 -> 0
A70: (b) | B70: 7th Floor level to to Terrace Including OHT, Mumty, Machine Room, Parapet | C70: CUM | D70: 1355 | E70: 6500 | F70: =$D70*E70 -> 8807500 | I70: =J70-H70 -> 0 | J70: ='BRICK WORK SUMMARY'!J13 -> 0 | L70: =M70-K70 -> 0 | M70: =E70*J70 -> 0 | N70: =J70/D70 -> 0
A71: 5.4. | B71: Brick work in Super Structure (Above Stilt FLoor level)
A72: 5.4.1 | B72: Providing and laying of 115 mm thick brick work with 1st quality burnt clay FPS bricks in Super-Superstructure laid in cement mortar 1:4 (1 cement : 4 coarse sand) mix, joints finished, including placing hoop iron as per specification at every third course, scaffolding, curing complete in all respect as per direction of EIC. (Hoop iron shall be provided by client free of cost) (Items of RCC bands like shuttering, concrete and reinforcement to be paid in respective items).
A73: (a) | B73: Stilt Floor level to 7th Floor level | C73: SQM | D73: 7100 | E73: 875 | F73: =$D73*E73 -> 6212500 | I73: =J73-H73 -> 0 | J73: ='BRICK WORK SUMMARY'!J16 -> 0 | L73: =M73-K73 -> 0 | M73: =E73*J73 -> 0 | N73: =J73/D73 -> 0
A74: (b) | B74: 7th Floor level to to Terrace Including OHT, Mumty, Machine Room, Parapet | C74: SQM | D74: 8155 | E74: 915 | F74: =$D74*E74 -> 7461825 | I74: =J74-H74 -> 0 | J74: ='BRICK WORK SUMMARY'!J17 -> 0 | L74: =M74-K74 -> 0 | M74: =E74*J74 -> 0 | N74: =J74/D74 -> 0
A75: 5.8. | B75: Brick work in staircase steps:
B76: Providing and laying and constructing brickwork in staircase steps using 1st quality burnt clay FPS bricks in cement mortar 1:3 (1 cement : 3 coarse sand) at all heights and levels including cutting, chamfering scaffolding, curing, complete as per specification. | C76: CUM | D76: 40 | E76: 7000 | F76: =$D76*E76 -> 280000 | I76: =J76-H76 -> 0 | J76: ='BRICK WORK SUMMARY'!J19 -> 0 | L76: =M76-K76 -> 0 | M76: =E76*J76 -> 0 | N76: =J76/D76 -> 0
B77: Total of Masonary Work | F77: =SUBTOTAL(9,F63:F76) -> 31627325
A79: 6 | B79: FINISHING WORKS (PLASTER)
B80: (Quoted Rate shall be for all heights, depths, levels, leads and lifts and to include providing and fixing chicken wire mesh in junction RCC and brick / AAC Block walls and at all chased for electrical conduits & plumbing pipes etc. for internal and external plaster works including minor chipping of RCC, brickwork surface).
A82: 6.1. | B82: Internal Plaster Super-Structure:
B83: Wall Plaster: Providing and applying 12 to 15mm thick plaster to masonry and RCC walls, columns etc. in cement mortar 1:5 (1 cement : 5 screened coarse sand) finished smooth including hacking the surfaces, steel scaffolding, curing, making grooves at desired location etc. complete for all levels as per approved drawing.
A84: (a) | B84: Stilt Floor level to 7th Floor level | C84: SQM | D84: 19970 | E84: 265 | F84: =$D84*E84 -> 5292050 | I84: =J84-H84 -> 0 | L84: =M84-K84 -> 0 | M84: =E84*J84 -> 0 | N84: =J84/D84 -> 0
A85: (b) | B85: 7th Floor level to to Terrace Including OHT, Mumty, Machine Room, Parapet | C85: SQM | D85: 22825 | E85: 280 | F85: =$D85*E85 -> 6391000 | I85: =J85-H85 -> 0 | L85: =M85-K85 -> 0 | M85: =E85*J85 -> 0 | N85: =J85/D85 -> 0
A86: 6.2. | B86: Internal Plaster Super-Structure:
B87: Ceiling Plaster: Providing and applying 6-10mm thick plaster to RCC slab, beam in cement mortar 1:4 (1 cement : 4 screened coarse sand) finished smooth including hacking the surfaces, steel scaffolding, curing, making grooves at desired location etc. complete for all levels as per approved drawing.
A88: (a) | B88: Stilt Floor level to 7th Floor level | C88: SQM | D88: 9135 | E88: 255 | F88: =$D88*E88 -> 2329425 | I88: =J88-H88 -> 0 | L88: =M88-K88 -> 0 | M88: =E88*J88 -> 0 | N88: =J88/D88 -> 0
A89: (b) | B89: 7th Floor level to to Terrace Including OHT, Mumty, Machine Room, Parapet | C89: SQM | D89: 10440 | E89: 270 | F89: =$D89*E89 -> 2818800 | I89: =J89-H89 -> 0 | L89: =M89-K89 -> 0 | M89: =E89*J89 -> 0 | N89: =J89/D89 -> 0
A90: 6.3 | B90: Double Layer External Plaster: Providing and applying 20 mm thick external cement plaster in two coats under layer 12 mm thick cement plaster 1:5 (1 cement : 5 screened coarse sand) finished with a top layer 8mm thick cement plaster 1:4 (1 cement : 4 screened coarse sand) including making of grooves, bands, drip coarse, design etc. as shown in drawing, steel scaffolding, curing, providing & mixing water proofing compound (CICO) in both layers as per manufacturer specification etc. complete as per approved drawing. | C90: SQM | D90: 19200 | E90: 480 | F90: =$D90*E90 -> 9216000 | I90: =J90-H90 -> 0 | N90: =J90/D90 -> 0
A91: 6.4 | B91: Single Layer (Shaft Plaster): Providing and applying 12-15 mm thick external cement plaster in single coat finished with cement plaster 1:4 (1 cement : 4 screened coarse sand) including making of grooves, bands, drip coarse as shown in drawing, steel scaffolding, curing, providing & mixing water proofing compound (CICO) as per manufacturer specification etc. complete as per approved drawing. | C91: SQM | D91: 1000 | E91: 380 | F91: =$D91*E91 -> 380000 | I91: =J91-H91 -> 0 | L91: =M91-K91 -> 0 | M91: =E91*J91 -> 0 | N91: =J91/D91 -> 0
B92: Total of Finishing Work (Plaster) | F92: =SUBTOTAL(9,F81:F91) -> 26427275
A94: 7 | B94: STRUCTURE STEEL
A95: 7.1. | B95: Structural steel work with solid/hollow sections: Providing and fixing M.S. work in built-up section such as staircase railing, balcony railing, grating, MS drain cover, MS mumty door including hold fast/fastener etc. with square/round MS Pipes, MS flats, MS Hollow section etc., as per design electrically welded and fixing in RCC/brick masonry or/and treads of steps with cement concrete 1:2:4 (1 cement : 2 corse sand : 4 grades stone aggregate 20 mm nominal sie), complete in all respect as per drawing & direction of EIC, including a coat of red oxide steel primer. (Basic Rate of Str. Steel - Rs. 60/- Per Kg. F.O.R excluding GST) | C95: KG | D95: 39665 | E95: 110 | F95: =$D95*E95 -> 4363150 | I95: =J95-H95 -> 0 | L95: =M95-K95 -> 0 | M95: =E95*J95 -> 0 | N95: =J95/D95 -> 0
B96: Total of Strutural Steel Work | F96: =SUBTOTAL(9,F95) -> 4363150
A98: 8 | B98: WOOD WORK
A99: 1 | B99: Providing and Fixing seasoned Red Meranti door frame including painting the portion in contact with masonary / R.C.C. with 2 or more coats of Antitermite treatment paint and fixng the frames with suitable 3 Nos. M.S. holdfasts each side made out of 40 x 5 mm flat iron 230 mm long with bolts and nuts/ dash fasteners for RCC surfaces, duly embedded in C.C. Blocks of required size in (1:2:4 ) 1 cement : 2 coarse sand : 4 stone aggregate 20 mm nominal size) including tarring the hold fast etc.all complete as per direction of EIC. (Finished size to be confirmed by client before procurement) (Sample of wood shall be get approved by client before procurement) | C99: CUM | D99: 50 | E99: 79000 | F99: =$D99*E99 -> 3950000 | I99: =J99-H99 -> 0 | L99: =M99-K99 -> 0 | M99: =E99*J99 -> 0 | N99: =J99/D99 -> 0
B100: Total of Wood Work | F100: =SUBTOTAL(9,F99) -> 3950000
A102: 9 | B102: WATERPROOFING
B103: TERRACE WATERPROOFING:
A104: 1 | B104: Providing and laying 120 mm average thickness of brick bat Coba and 65 mm at Khurra on Terrace through an approved agency, approved by the Architect as per steps given. (a) Surface Preparation, Cleaning the mother slab, reapir of joints, Providing and applying URP with cement slurry as primer to fill all the pores etc on mother slab over primer Providing and applying two coats of Fast Flex @ 2kg/Sqm including sandwiching the layer with fiber mesh of 45 GSM between two layers. (It shall also be execute up to 300 mm height of wall) (b) laying cement concrete using broken bricks/ brick bats of size 25 mm to 100 mm size with 50 % of cement mortar 1:5 ( 1 cement : 5 coarse sand) admixed with proprietary water proofing compound conforming to IS:2645 over 20 mm thick layer of cement mortar of mix 1:5 ( 1 cement : 5 coarse sand) admixed with admixed with proprietary water proofing compound conforming to IS:2645 to required slope and treating similarly the adjoining wall upto 300 mm height including rounding of junctions of wall and slabs. (c) After two days of proper curing applying a second coat of cement slurry admixed with proprietary water proofing compound conforming to IS:2645 (d) Finishing the surface with 20 mm thick jointless cement mortar of mix 1:4 (1 cement : 4 coarse sand) admixed with proprietary water proofing compound conforming to IS:2645 and finally finishing the surface with trowel with neat cement slurry and making 300X300 mm square. (e) The whole terrace so finished sshall be looded with water for a minimum period of two weeks for curing and for final test. All above operations to be done in order and as directed and specified by the engineer in charge. With average thickness of 100 mm thickness and minimum thickness at khurra as 65 mm. | C104: SQM | D104: 1000 | E104: 1150 | F104: =$D104*E104 -> 1150000 | I104: =J104-H104 -> 0 | L104: =M104-K104 -> 0 | M104: =E104*J104 -> 0 | N104: =J104/D104 -> 0
B105: Providing gola in 1: 2: 4 cement concrete with 12 mm nominal size stone ballast, finished with cement plaster 1:2 (1 cement: 2 medium sand) laid, cured complete as per design. (Approx. Size 100mm x 100mm) Making khurras 450 x 450 mm with average min. thk. Of 50 mm over PVCsheet of 1m x 1m x 400 micron with cement concrete 1:2:4 (1 cement: 2 coarse sand: 4 graded stone aggregate of 12 mm nominal size) finished with 12 mm cement plaster 1:3 (1 cement: 3 coarse sand) and a coat of neat cement, rounding the edges, making and finishing complete. (Only plan area shall be paid).
B106: Total of Waterproofing Work | F106: =SUBTOTAL(9,F104:F105) -> 1150000
B108: Grand Total (Excluding GST) | F108: =SUBTOTAL(9,F8:F106) -> 162074375 | H108: =SUM(H9:H107) -> 0 | I108: =SUM(I9:I107) -> 1891.7915 | J108: =SUM(J9:J107) -> 1891.7915 | K108: =SUM(K9:K107) -> 0 | L108: =SUM(L9:L107) -> 5824183.5 | M108: =SUM(M9:M107) -> 5824183.5

Sheet EARTH WORK MB
A1: COMPANY- OMAXE PANCHAM REALCON PVT LTD
A2: PROJECT- TOWER-E
A3: LOCATION- NAINI, PRAYAGRAJ
A4: MB SHEET- SOIL SURFACE DRESSING BELOW PLINTH BEAM
A6: S.NO. | B6: DESCRIPTION | C6: UNIT | D6: NOS | E6: NOS | F6: MEASUREMENT | I6: QTY. | J6: REMARKS
F7: L | G7: B | H7: H/T
B8: SOIL DRESSING FOR RAFT PCC
A9: 1 | B9: GRID (22'-43'/A-Q') | C9: SQM | D9: 1 | E9: 1 | F9: =31.935+0.115+0.115+0.1+0.1 -> 32.365 | G9: =36.895+0.115+0.1+0.115+0.1 -> 37.325 | I9: =PRODUCT(D9:H9) -> 1208.0236
A10: 2 | C10: SQM | D10: 1 | E10: 1 | F10: =8.78+0.115+0.115+0.1+0.1 -> 9.21 | G10: 0.515 | I10: =PRODUCT(D10:H10) -> 4.74315
A11: 3 | B11: GRID (22'-26'/M'-Q') | C11: SQM | D11: -1 | E11: 1 | F11: 11.005 | G11: 12.415 | I11: =PRODUCT(D11:H11) -> -136.62707
A12: 4 | B12: GRID (38'-43'/A-E') | C12: SQM | D12: -1 | E12: 1 | F12: 11.09 | G12: 10.285 | I12: =PRODUCT(D12:H12) -> -114.06065
A13: 5 | B13: GRID (22'-30'/A-B') | C13: SQM | D13: -1 | E13: 1 | F13: 11.285 | G13: =1.405+0.815+1.5 -> 3.72 | I13: =PRODUCT(D13:H13) -> -41.9802
A14: 6 | C14: SQM | D14: -1 | E14: 1 | F14: 1.695 | G14: =0.815+1.5 -> 2.315 | I14: =PRODUCT(D14:H14) -> -3.923925
A15: 7 | C15: SQM | D15: -1 | E15: 1 | F15: 3.95 | G15: 1.5 | I15: =PRODUCT(D15:H15) -> -5.925
A16: 8 | C16: SQM | D16: -1 | E16: 1 | F16: 15.8 | G16: =0.115+0.1 -> 0.215 | I16: =PRODUCT(D16:H16) -> -3.397
H18: TOTAL | I18: =SUM(I8:I17) -> 906.85293

Sheet CONCRETE SUMMARY
A2: TOWER-E CONCRETE WORK SUMMARY
D3: QTY | J3: TOTAL
A4: 2 | B4: CONCRETE WORK | D4: 1ST RA | E4: 2ND RA | F4: 3rd RA | G4: 4th RA | H4: 5th RA | I4: 6th RA
B5: Rates for all cement concrete items plain and reinforced described below shall include work from Basement Level to top of last roof including roof of machine room, mumty, over head water tanks and parapets above at all floors and for all heights. The contractor should provide full time sufficient pipes with accessories and pumps based on the site requirement for pumping and laying of concrete as directed by the EIC. The rate inclusive of standard rigid pipe line and its supports, lifting, laying charges, etc., at all heights and levels. No additional payment shall be payable to the contractor on account of using or change in any size of coarse aggregate in PCC/ RCC work at any stage during currency of works. (This section covers cast in situ structural and architectural as well.)
A6: 2.1 | B6: Plain Cement Concrete: Providing and laying plain cement concrete of specified grade as bed concrete under foundation, bases for rafts, underground water tank, building machine equipments, column footing, under floor landings, below road and pathways, cill, coping, screeding at roof to required slope and other locations as called for laid, consolidated and cured etc. complete including finishing the top surface to receive the next course / layer as per specification and drawing. (Shuttering shall be paid in Item No.3.1.1) M10 Grade (Basic Rate of PCC - Rs. 4200/cum) without pump | C6: CUM | D6: ='CONCRETE WORK MB'!I23 -> 56.798193 | J6: =SUM(D6:I6) -> 56.798193
A7: 2.2. | B7: Providing and laying cement concrete 1:2:4 (1 cement : 2 coarse sand : 4 graded stone aggregate 20mm nominal size) for ledge wall below balcony railings, band, mullion, lintel etc. (Shuttering shall be paid separately in respective item) as per drawing and as directed by the Project Manager. | C7: CUM | J7: =SUM(D7:I7) -> 0
A8: 2.3. | B8: Providing and laying damp proof course 40mm thick including shttering with cement concrete 1:2:4 (1 cement : 2 coarse sand : 4 graded stone aggregate 20mm nominal size) including mixing of water proofing compound @ 2% of cement content and applying two layers of bitumen @ 1.70 Kg/Sqm of grade 85/25 and as directed by the Project Manager. | C8: SQM | J8: =SUM(D8:I8) -> 0
A10: 2.4. | B10: RCC WORK
B11: Providing & Laying RMC M-25 Grade as per approved design mix concrete (strictly controlled conditions) with flyash (as per approved design mix) with automatic batching plant machine mixed and machine vibrated RCC with melamine based plasticisers etc., upto any level, including finishing the exposed surface, fixing/ removal of pockets, fixing of sleeves and inserts (sleeves provided by client), curing etc complete, as per drawing (including all size and shape like circular, semi-circular, oval etc.) and as directed for all lead and lift, excluding cost of centering, shuttering and steel reinforcement but including cost of making shear keys and provision of construction / contraction / control joints in various locations. Checking from Client should not be considered as final and any defects arising during or after casting should be borne & bear by contractor at his own cost. This is inclusive of leaving shuttering & centring for pour strip, slab in slope, RCC members in curved, etc., nothing is payable extra on this account. RMC (M-25) Basic Rate - Rs. 5200/cum without pump excluding GST
A12: 2.4.1. | B12: Foundation, column footings, raft slab, raft beams, plinth beam, lift pits, sump pits, pedestals / bases of column, column upto plinth, swimming pool, Retaining wall foundations, grade slab etc. | C12: CUM | D12: ='CONCRETE WORK MB'!I37 -> 748.20967 | J12: =SUM(D12:I12) -> 748.20967
A13: 2.4.2. | B13: Suspended floors, roofs, balconies, shelves/ counters, stair waist slabs, folded plate stairs and landings, swimming pool slab, lintel and floor beams, landing beams, girders (deep beams), RCC bands, swimming pool beam, cantilever projections, coping, cills, slab of tank etc at all levels.
A14: 2.4.2.1. | B14: Stilt Floor level to 7th Floor level | C14: CUM | J14: =SUM(D14:I14) -> 0
A15: 2.4.2.2. | B15: 7th Floor level to to Terrace Including OHT, Mumty, Machine Room, Parapet | C15: CUM | J15: =SUM(D15:I15) -> 0
A16: 2.4.2.3. | B16: All type of Moulding, Bands, Elevation/Architectural Features as per drawing and as directed by EIC. at all level | C16: CUM | J16: =SUM(D16:I16) -> 0
A18: 2.5. | B18: Columns, Wall, pillars, piers, abutments, posts and struts, offset and projection of columns, water tank walls, lift walls, Retaining Wall, swimming pool, Parapets, planters, vertical projection of pergolas, wall and ramp walls etc. at all levels.
A19: 2.5.1. | B19: Stilt Floor level to 7th Floor level | C19: CUM | J19: =SUM(D19:I19) -> 0
A20: 2.5.2. | B20: 7th Floor level to to Terrace Including OHT, Mumty, Machine Room, Parapet | C20: CUM | J20: =SUM(D20:I20) -> 0
A21: 2.5.3. | B21: All type of Moulding, Bands, Elevation/Architectural Features as per drawing and as directed by EIC. at all level | C21: CUM | J21: =SUM(D21:I21) -> 0
A22: 2.5.4. | B22: Finishing vaccum dewatering continuous concrete flooring 100-150 mm thick with specified grade concrete including necessary formwork in required level, vibrating concrete both by poker vibrators / leveling vaccum processing of the concrete and planning the surface by skin powered floater trowels with broom/plain finish including groove cutting & filling etc. complete. (Concrete shall be paid in the respective items above). | C22: SQM | J22: =SUM(D22:I22) -> 0
I24: TOTAL | J24: =SUM(J5:J23) -> 805.00787

Sheet CONCRETE RECO.
B1: RCC SUMMARY : OMAXE TOWER-E
B2: M/s. MARCO ENTERPRISES
A3: S.No. | B3: Item Discription | C3: Grade | D3: Floor Name | E3: NO | F3: Unit Qty. | G3: Quantity | H3: Unit | I3: M10 | J3: M25 | K3: M30 | L3: M35
B4: TOWER-E
A6: 1 | B6: RAFT PCC GRID (A-Q/23-43) | C6: M10 | D6: AS SUB-STRUCTURE | E6: 1 | F6: ='CONCRETE WORK MB'!I23 -> 56.798193 | G6: =E6*F6 -> 56.798193 | H6: Cum | I6: =IF(I$3=$C6,$G6,"-") -> 56.798193 | J6: =IF(J$3=$C6,$G6,"-") -> - | K6: =IF(K$3=$C6,$G6,"-") -> - | L6: =IF(L$3=$C6,$G6,"-") -> -
A7: 2 | B7: RAFT RCC GRID (A-Q/23-43) | C7: M25 | D7: AS SUB-STRUCTURE | E7: =E6 -> 1 | F7: ='CONCRETE WORK MB'!I37 -> 748.20967 | G7: =E7*F7 -> 748.20967 | H7: Cum | I7: =IF(I$3=$C7,$G7,"-") -> - | J7: =IF(J$3=$C7,$G7,"-") -> 748.20967 | K7: =IF(K$3=$C7,$G7,"-") -> - | L7: =IF(L$3=$C7,$G7,"-") -> -
I8: =IF(I$3=$C8,$G8,"-") -> -
B12: TOTAL RCC QTY (THEORITICAL) | G12: =SUM(G4:G11) -> 805.00787 | H12: Cum | I12: =SUM(I4:I11) -> 56.798193 | J12: =SUM(J4:J11) -> 748.20967 | K12: =SUM(K4:K11) -> 0 | L12: =SUM(L4:L11) -> 0
B13: TOTAL RCC QTY (CASTING) | G13: ='PCC & RCC REC.'!Q16 -> 829.2 | H13: Cum | I13: ='PCC & RCC REC.'!D18+'PCC & RCC REC.'!H18+'PCC & RCC REC.'!L18 -> 66.2 | J13: ='PCC & RCC REC.'!E18+'PCC & RCC REC.'!I18+'PCC & RCC REC.'!M18 -> 763 | K13: ='PCC & RCC REC.'!F18+'PCC & RCC REC.'!J18+'PCC & RCC REC.'!N18 -> 0 | L13: ='PCC & RCC REC.'!G18+'PCC & RCC REC.'!K18+'PCC & RCC REC.'!O18 -> 0
B14: DIFFERENCE (WASTAGE) | G14: =G12-G13 -> -24.192134 | H14: Cum | I14: =I12-I13 -> -9.4018075 | J14: =J12-J13 -> -14.790326 | K14: =K12-K13 -> 0 | L14: =L13-L12 -> 0
B15: WASTAGE % | G15: =G14/G12 -> -0.030052046 | I15: =I14/I12 -> -0.16553005 | J15: =J14/J12 -> -0.019767622 | K15: =K14/K12 -> #DIV/0! | L15: =L14/L12 -> #DIV/0!
B17: PREV. BILL RCC QTY (THEORITICAL) | G17: 0 | H17: Cum | J17: 0 | K17: 0 | L17: 0
B18: PREV. BILL RCC QTY (CASTING-ACTUAL) | G18: 0 | H18: Cum | J18: 0 | K18: 0 | L18: 0
B19: DIFFERENCE (WASTAGE) | G19: =G17-G18 -> 0 | H19: Cum | J19: =J17-J18 -> 0 | K19: =K17-K18 -> 0 | L19: =L18-L17 -> 0
B20: WASTAGE % | G20: =G19/G17 -> #DIV/0! | I20: =I19/I17 -> #DIV/0! | J20: =J19/J17 -> #DIV/0! | K20: =K19/K17 -> #DIV/0! | L20: =L19/L17 -> #DIV/0!
B22: THIS BILL RCC QTY (THEORITICAL) | G22: =G12-G17 -> 805.00787 | H22: Cum | I22: =I12-I17 -> 56.798193 | J22: =J12-J17 -> 748.20967 | K22: =K12-K17 -> 0 | L22: =L12-L17 -> 0
B23: THIS BILL RCC QTY (CASTING-ACTUAL) | G23: =G13-G18 -> 829.2 | H23: Cum | I23: =I13-I18 -> 66.2 | J23: =J13-J18 -> 763 | K23: =K13-K18 -> 0 | L23: =L13-L18 -> 0
B24: DIFFERENCE (WASTAGE) | G24: =G22-G23 -> -24.192134 | H24: Cum | I24: =I22-I23 -> -9.4018075 | J24: =J22-J23 -> -14.790326 | K24: =K22-K23 -> 0 | L24: =L23-L22 -> 0
B25: WASTAGE % | G25: =G24/G22 -> -0.030052046 | I25: =I24/I22 -> -0.16553005 | J25: =J24/J22 -> -0.019767622 | K25: =K24/K22 -> #DIV/0! | L25: =L24/L22 -> #DIV/0!

Sheet PCC & RCC REC.
A1: S.NO. | B1: MONTH | C1: DATE | D1: RMC | H1: ELSA | L1: MANUAL | P1: WORK IN PROGRSS | Q1: TOTAL | R1: REMARK
D2: GRADE | H2: GRADE | L2: GRADE
D3: M10 | E3: M25 | F3: M30 | G3: M35 | H3: M10 | I3: M25 | J3: M30 | K3: M35 | L3: M10 | M3: M25 | N3: M30 | O3: M35
A5: 1 | B5: 45778 | C5: 45791 | H5: 3.3 | R5: TOWER-E FOUNDATION PCC CASTING WORK
A6: 2 | C6: 45797 | H6: 5.4 | R6: TOWER-E FOUNDATION PCC CASTING WORK
A7: 3 | C7: 45786 | D7: 40 | R7: TOWER-E RAFT PCC
A8: 4 | C8: 45789 | D8: 17.5 | R8: TOWER-E RAFT PCC
A9: 5 | C9: 45806 | E9: 70 | R9: TOWER-E RAFT RCC
A10: 6 | C10: 45807 | E10: 329 | R10: TOWER-E RAFT RCC
A11: 7 | C11: 45808 | E11: =357+7 -> 364 | R11: TOWER-E RAFT RCC
B16: TOTAL | D16: =SUM(D4:D15) -> 57.5 | E16: =SUM(E4:E15) -> 763 | F16: =SUM(F4:F15) -> 0 | G16: =SUM(G4:G15) -> 0 | H16: =SUM(H4:H15) -> 8.7 | I16: =SUM(I4:I15) -> 0 | J16: =SUM(J4:J15) -> 0 | K16: =SUM(K4:K15) -> 0 | ... P16: =SUM(P4:P15) -> 0 | Q16: =SUM(D16:P16) -> 829.2
B18: GRAND TOTAL | D18: =D16 -> 57.5 | E18: =E16 -> 763 | G18: =G16 -> 0 | H18: =H16 -> 8.7 | I18: =I16 -> 0 | K18: =K16 -> 0 | L18: =L16 -> 0 | M18: =M16 -> 0 | O18: =O16 -> 0 | P18: =P16 -> 0 | Q18: =Q16 -> 829.2
B19: TOTAL RCC BY RMC/ELSA /MANUAL | D19: =D18+E18+G18 -> 820.5 | H19: =H18+I18+K18 -> 8.7 | L19: =L18+M18+O18 -> 0 | P19: =P18 -> 0 | Q19: =D19+H19+P19+L19 -> 829.2
B20: RCC BY RMC + ELSA | D20: =SUM(D19:O19) -> 829.2

Sheet RMC RECEIVING
A1: M/s. MARCO ENTERPRISES : RMC RECEIVING AT OMAXE ANANDA TOWER-E -PRAYAGRAJ
A2: SN | B2: DATE | C2: VEHICLE NO | D2: CHALLAN NO/INVOICE NO. | E2: MATERIAL GRADE | F2: UNIT | G2: RMC PLANT QTY (M 10) | H2: RMC PLANT QTY (M 25) | I2: RMC PLANT QTY (M 30) | J2: RMC PLANT QTY (M 35) | K2: ACTUAL CEMENT WEIGHT BY DESIGN MIX | L2: CEMENT WEIGHT BY RMC PLANT | M2: CEMENT DIFF (IN KG) | N2: IN TIME | O2: OUT TIME | P2: TOWER NO | Q2: TYPE OF WORK | R2: RMC SUPPLIER | S2: REMARKS
A3: 1 | B3: 45786 | C3: UP32VN6145 | D3: 449 | E3: RMC10 | F3: CUM | G3: 7 | K3: =G3*220 -> 1540 | L3: 1096 | M3: =L3-K3 -> -444 | N3: 0.45138889 | O3: 0.51041667 | P3: TOWER-E RAFT PCC | Q3: RAFT PCC | R3: SHUBHAM
A4: 2 | B4: 45786 | C4: UP32WN8332 | D4: 450 | E4: RMC10 | F4: CUM | G4: 7 | K4: =G4*220 -> 1540 | L4: 1096 | M4: =L4-K4 -> -444 | N4: 0.52083333 | O4: 0.56944444 | P4: TOWER-E RAFT PCC | Q4: RAFT PCC | R4: SHUBHAM
A5: 3 | B5: 45786 | C5: UP53HT5034 | D5: 451 | E5: RMC10 | F5: CUM | G5: 7 | K5: =G5*220 -> 1540 | L5: 1096 | M5: =L5-K5 -> -444 | N5: 0.57777778 | O5: 0.61111111 | P5: TOWER-E RAFT PCC | Q5: RAFT PCC | R5: SHUBHAM
A6: 4 | B6: 45786 | C6: UP32VN6145 | D6: 453 | E6: RMC10 | F6: CUM | G6: 7 | K6: =G6*220 -> 1540 | L6: 1096 | M6: =L6-K6 -> -444 | N6: 0.61805556 | O6: 0.66666667 | P6: TOWER-E RAFT PCC | Q6: RAFT PCC | R6: SHUBHAM
A7: 5 | B7: 45786 | C7: UP32WN8334 | D7: 454 | E7: RMC10 | F7: CUM | G7: 6 | K7: =G7*220 -> 1320 | L7: 1096 | M7: =L7-K7 -> -224 | N7: 0.6875 | O7: 0.73958333 | P7: TOWER-E RAFT PCC | Q7: RAFT PCC | R7: SHUBHAM
A8: 6 | B8: 45786 | C8: UP53HT5034 | D8: 457 | E8: RMC10 | F8: CUM | G8: 6 | K8: =G8*220 -> 1320 | L8: 1096 | M8: =L8-K8 -> -224 | N8: 0.77430556 | O8: 0.8125 | P8: TOWER-E RAFT PCC | Q8: RAFT PCC | R8: SHUBHAM
A9: 7 | B9: 45789 | C9: UP32WN8334 | D9: 487 | E9: RMC10 | F9: CUM | G9: 5 | K9: =G9*220 -> 1100 | L9: 1096 | M9: =L9-K9 -> -4 | N9: 0.77430556 | O9: 0.8125 | P9: TOWER-E RAFT PCC | Q9: RAFT PCC | R9: SHUBHAM
A10: 8 | B10: 45789 | C10: UP32WN8334 | D10: 488 | E10: RMC10 | F10: CUM | G10: 5 | K10: =G10*220 -> 1100 | L10: 1096 | M10: =L10-K10 -> -4 | N10: 0.77430556 | O10: 0.8125 | P10: TOWER-E RAFT PCC | Q10: RAFT PCC | R10: SHUBHAM
A11: 9 | B11: 45789 | C11: UP32VN6144 | D11: 490 | E11: RMC10 | F11: CUM | G11: 5.5 | K11: =G11*220 -> 1210 | L11: 1096 | M11: =L11-K11 -> -114 | N11: 0.77430556 | O11: 0.8125 | P11: TOWER-E RAFT PCC | Q11: RAFT PCC | R11: SHUBHAM
A12: 10 | B12: 45789 | C12: UP32VN6144 | D12: 494 | E12: RMC10 | F12: CUM | G12: 2 | K12: =G12*220 -> 440 | L12: 1096 | M12: =L12-K12 -> 656 | N12: 0.77430556 | O12: 0.8125 | P12: TOWER-E RAFT PCC | Q12: RAFT PCC | R12: SHUBHAM
A13: 11 | B13: 29.05.2025 | C13: UP32VN6145 | D13: 721 | E13: RMC 25 | F13: CUM | H13: 7 | K13: =H13*365 -> 2555 | L13: 2563 | M13: =L13-K13 -> 8 | N13: 0.9375 | O13: 0.96388889 | P13: TOWER-E (23-43) | Q13: RAFT | R13: SHUBHAM
A14: 12 | B14: 29.05.2025 | C14: UP32WN8334 | D14: 722 | E14: RMC 25 | F14: CUM | H14: 7 | K14: =H14*365 -> 2555 | L14: 2558 | M14: =L14-K14 -> 3 | N14: 0.96666667 | O14: 0.98125 | P14: TOWER-E (23-43) | Q14: RAFT | R14: SHUBHAM
A15: 13 | B15: 29.05.2025 | C15: UP32WN8333 | D15: 723 | E15: RMC 25 | F15: CUM | H15: 7 | K15: =H15*365 -> 2555 | L15: 2564 | M15: =L15-K15 -> 9 | N15: 0.98541667 | O15: 12:02PM | P15: TOWER-E (23-43) | Q15: RAFT | R15: SHUBHAM
A16: 14 | B16: 29.05.2025 | C16: UP32HT5032 | D16: 724 | E16: RMC 25 | F16: CUM | H16: 7 | K16: =H16*365 -> 2555 | L16: 2574 | M16: =L16-K16 -> 19 | N16: 0.50347222 | O16: 0.013194444 | P16: TOWER-E (23-43) | Q16: RAFT | R16: SHUBHAM
A17: 15 | B17: 29.05.2025 | C17: UP32HT5034 | D17: 725 | E17: RMC 25 | F17: CUM | H17: 5.5 | K17: =H17*365 -> 2007.5 | L17: 2018 | M17: =L17-K17 -> 10.5 | N17: 0.015972222 | O17: 0.029166667 | P17: TOWER-E (23-43) | Q17: RAFT | R17: SHUBHAM
B18: 29.05.2025 | C18: UP32HT5034 | D18: 726 | E18: RMC 25 | F18: CUM | H18: 1.5 | K18: =H18*365 -> 547.5 | L18: 548 | M18: =L18-K18 -> 0.5 | N18: 0.015972222 | O18: 0.029166667 | P18: TOWER-E (23-43) | Q18: RAFT | R18: SHUBHAM
A19: 16 | B19: 29.05.2025 | C19: UP70QT2013 | D19: 905350012 | E19: RMC 25 | F19: CUM | H19: 7 | K19: =H19*365 -> 2555 | L19: 2555 | M19: =L19-K19 -> 0 | N19: 0.9375 | O19: 0.96319444 | P19: TOWER-E (23-43) | Q19: RAFT | R19: ULTRATECH
A20: 17 | B20: 29.05.2025 | C20: UP70QT2341 | D20: 905350013 | E20: RMC 25 | F20: CUM | H20: 7 | K20: =H20*365 -> 2555 | L20: 2555 | M20: =L20-K20 -> 0 | N20: 0.96736111 | O20: 0.98680556 | P20: TOWER-E (23-43) | Q20: RAFT | R20: ULTRATECH
A21: 18 | B21: 29.05.2025 | C21: UP70QT2015 | D21: 905350014 | E21: RMC 25 | F21: CUM | H21: 7 | K21: =H21*365 -> 2555 | L21: 2555 | M21: =L21-K21 -> 0 | N21: 0.98680556 | O21: 1.0083333 | P21: TOWER-E (23-43) | Q21: RAFT | R21: ULTRATECH
A22: 19 | B22: 29.05.2025 | C22: UP70QT2342 | D22: 905350015 | E22: RMC 25 | F22: CUM | H22: 7 | K22: =H22*365 -> 2555 | L22: 2556 | M22: =L22-K22 -> 1 | N22: 0.052777778 | O22: 0.071527778 | P22: TOWER-E (23-43) | Q22: RAFT | R22: ULTRATECH
A23: 20 | B23: 29.05.2025 | C23: UP70QT2014 | D23: 905350016 | E23: RMC 25 | F23: CUM | H23: 7 | K23: =H23*365 -> 2555 | L23: 2555 | M23: =L23-K23 -> 0 | N23: 0.075694444 | O23: 0.086805556 | P23: TOWER-E (23-43) | Q23: RAFT | R23: ULTRATECH
A24: 21 | B24: 30.05.2025 | C24: UP32VN6145 | D24: 727 | E24: RMC 25 | F24: CUM | H24: 7 | K24: =H24*365 -> 2555 | L24: 2561 | M24: =L24-K24 -> 6 | N24: 0.043055556 | O24: 0.076388889 | P24: TOWER-E (23-43) | Q24: RAFT | R24: SHUBHAM
A25: 22 | B25: 30.05.2025 | C25: UP32WN8334 | D25: 728 | E25: RMC 25 | F25: CUM | H25: 7 | K25: =H25*365 -> 2555 | L25: 2551 | M25: =L25-K25 -> -4 | N25: 0.077777778 | O25: 0.09375 | P25: TOWER-E (23-43) | Q25: RAFT | R25: SHUBHAM
A26: 23 | B26: 30.05.2025 | C26: UP32WN8332 | D26: 729 | E26: RMC 25 | F26: CUM | H26: 7 | K26: =H26*365 -> 2555 | L26: 2557 | M26: =L26-K26 -> 2 | N26: 0.096527778 | O26: 0.10625 | P26: TOWER-E (23-43) | Q26: RAFT | R26: SHUBHAM
A27: 24 | B27: 30.05.2025 | C27: UP32WN8333 | D27: 730 | E27: RMC 25 | F27: CUM | H27: 7 | K27: =H27*365 -> 2555 | L27: 2557 | M27: =L27-K27 -> 2 | N27: 0.10763889 | O27: 0.12708333 | P27: TOWER-E (23-43) | Q27: RAFT | R27: SHUBHAM
A28: 25 | B28: 30.05.2025 | C28: UP32VN6144 | D28: 731 | E28: RMC 25 | F28: CUM | H28: 7 | K28: =H28*365 -> 2555 | L28: 2561 | M28: =L28-K28 -> 6 | N28: 0.12708333 | O28: 0.14097222 | P28: TOWER-E (23-43) | Q28: RAFT | R28: SHUBHAM
A29: 26 | B29: 30.05.2025 | C29: UP53HT5032 | D29: 732 | E29: RMC 25 | F29: CUM | H29: 7 | K29: =H29*365 -> 2555 | L29: 2560 | M29: =L29-K29 -> 5 | N29: 0.14305556 | O29: 0.15833333 | P29: TOWER-E (23-43) | Q29: RAFT | R29: SHUBHAM
A30: 27 | B30: 30.05.2025 | C30: UP32VN6145 | D30: 733 | E30: RMC 25 | F30: CUM | H30: 7 | K30: =H30*365 -> 2555 | L30: 2570 | M30: =L30-K30 -> 15 | N30: 0.16180556 | O30: 0.17083333 | P30: TOWER-E (23-43) | Q30: RAFT | R30: SHUBHAM
... A122: 118 | B122: 31.05.2025 | C122: UP70QT2014 | D122: 905350052 | E122: RMC 25 | F122: CUM | H122: 7 | K122: =H122*365 -> 2555 | L122: 2554 | M122: =L122-K122 -> -1 | N122: 0.083333333 | O122: 0.097222222 | P122: TOWER-E (23-43) | Q122: RAFT | R122: ULTRATECH
B124: Total Qty upto date | G124: =SUM(G3:G123) -> 57.5 | H124: =SUM(H3:H123) -> 763 | I124: =SUM(I3:I123) -> 0 | J124: =SUM(J3:J123) -> 0 | K124: =SUM(K3:K123) -> 291145 | L124: =SUM(L3:L123) -> 289936 | M124: =SUM(M3:M123) -> -1209
G125: =SUM(G124:J124) -> 820.5 | K125: =K124/50 -> 5822.9 | L125: =L124/50 -> 5798.72 | M125: BAGS

Sheet CONCRETE WORK MB
A1: COMPANY- OMAXE PANCHAM REALCON PVT LTD
A2: PROJECT- TOWER-E
A3: LOCATION- NAINI, PRAYAGRAJ
A4: MB SHEET- CONCRETE WORK
A6: S.NO. | B6: DESCRIPTION | C6: UNIT | D6: NOS | E6: NOS | F6: MEASUREMENT | I6: QTY. | J6: REMARKS
F7: L | G7: B | H7: H/T
B8: RAFT PCC- M10
A9: 1 | B9: GRID (22'-43'/A-Q') | C9: CUM | D9: 1 | E9: 1 | F9: =31.935+0.115+0.115 -> 32.165 | G9: =36.895+0.115+0.115 -> 37.125 | H9: 0.1 | I9: =PRODUCT(D9:H9) -> 119.41256
A10: 2 | C10: CUM | D10: 1 | E10: 1 | F10: =8.78+0.115+0.115 -> 9.01 | G10: 0.515 | H10: 0.1 | I10: =PRODUCT(D10:H10) -> 0.464015
A11: 3 | B11: GRID (22'-26'/M'-Q') | C11: CUM | D11: -1 | E11: 1 | F11: 11.005 | G11: 12.415 | H11: 0.1 | I11: =PRODUCT(D11:H11) -> -13.662707
A12: 4 | B12: GRID (38'-43'/A-E') | C12: CUM | D12: -1 | E12: 1 | F12: 11.09 | G12: 10.285 | H12: 0.1 | I12: =PRODUCT(D12:H12) -> -11.406065
A13: 5 | B13: GRID (22'-30'/A-B') | C13: CUM | D13: -1 | E13: 1 | F13: 11.285 | G13: 3.72 | H13: 0.1 | I13: =PRODUCT(D13:H13) -> -4.19802
A14: 6 | C14: CUM | D14: -1 | E14: 1 | F14: 1.695 | G14: 2.315 | H14: 0.1 | I14: =PRODUCT(D14:H14) -> -0.3923925
A15: 7 | C15: CUM | D15: -1 | E15: 1 | F15: 3.95 | G15: 1.5 | H15: 0.1 | I15: =PRODUCT(D15:H15) -> -0.5925
D16: -1 | E16: 1 | F16: 15.8 | G16: =0.115 -> 0.115 | H16: 0.1 | I16: =PRODUCT(D16:H16) -> -0.1817
A17: 8 | B17: EXISTING RAFT (DETAILS IN JMR) | C17: CUM | D17: -1 | E17: 1 | F17: 9 | G17: =5.8+0.115 -> 5.915 | H17: 0.1 | I17: =PRODUCT(D17:H17) -> -5.3235
A18: 9 | C18: CUM | D18: -1 | E18: 1 | F18: 19.05 | G18: 10 | H18: 0.1 | I18: =PRODUCT(D18:H18) -> -19.05
A19: 10 | C19: CUM | D19: -1 | E19: 1 | F19: 6.2 | G19: 6.2 | H19: 0.1 | I19: =PRODUCT(D19:H19) -> -3.844
A20: 11 | C20: CUM | D20: -1 | E20: 1 | F20: =11.7-6.2 -> 5.5 | G20: 8.05 | H20: 0.1 | I20: =PRODUCT(D20:H20) -> -4.4275
H23: TOTAL | I23: =SUM(I8:I22) -> 56.798193
A25: S.NO. | B25: DESCRIPTION | C25: UNIT | D25: NOS | E25: NOS | F25: MEASUREMENT | I25: QTY. | J25: REMARKS
F26: L | G26: B | H26: H/T
B27: RAFT RCC- M25
A28: 1 | B28: GRID (22'-43'/A-Q') | C28: CUM | D28: 1 | E28: 1 | F28: =31.935 -> 31.935 | G28: =36.895 -> 36.895 | H28: 0.85 | I28: =PRODUCT(D28:H28) -> 1001.5056
A29: 2 | C29: CUM | D29: 1 | E29: 1 | F29: =8.78 -> 8.78 | G29: 0.515 | H29: 0.85 | I29: =PRODUCT(D29:H29) -> 3.843445
A30: 3 | B30: GRID (22'-26'/M'-Q') | C30: CUM | D30: -1 | E30: 1 | F30: 11.005 | G30: 12.415 | H30: 0.85 | I30: =PRODUCT(D30:H30) -> -116.13301
A31: 4 | B31: GRID (38'-43'/A-E') | C31: CUM | D31: -1 | E31: 1 | F31: 11.09 | G31: 10.285 | H31: 0.85 | I31: =PRODUCT(D31:H31) -> -96.951552
A32: 5 | B32: GRID (22'-30'/A-B') | C32: CUM | D32: -1 | E32: 1 | F32: 11.285 | G32: 3.72 | H32: 0.85 | I32: =PRODUCT(D32:H32) -> -35.68317
A33: 6 | C33: CUM | D33: -1 | E33: 1 | F33: 1.695 | G33: 2.315 | H33: 0.85 | I33: =PRODUCT(D33:H33) -> -3.3353363
A34: 7 | C34: CUM | D34: -1 | E34: 1 | F34: 3.95 | G34: 1.5 | H34: 0.85 | I34: =PRODUCT(D34:H34) -> -5.03625
H37: TOTAL | I37: =SUM(I27:I36) -> 748.20967

Sheet SHUTT. WORK SUMMARY
A1: TOWER-E CENTERING & SHUTTERING WORK SUMMARY
D2: QTY | J2: TOTAL
A3: 3 | B3: CENTRING AND SHUTTERING | D3: 1ST RA | E3: 2ND RA | F3: 3rd RA | G3: 4th RA | H3: 5th RA | I3: 6th RA
B4: Providing and fixing plywood or steel plate shuttering and centring for structural concrete work in locations called for including strutting, propping, bracing, bolting, wedging, casing, striking, removal etc. complete for any size, section, thickness. Props shall consist of well designed steel pipes adequately braced (wooden ballies as props shall not be permitted). The item to include centering and shuttering at all heights and levels. Allow for forming grooves, drip course, chamfers, cut-outs, openings etc. where called for and for dressing with approved shuttering oil to prevent adhesion. Unexposed concrete surfaces subsequently left untreated (in the condition obtained on removal of form work) shall not constitute exposed concrete work and shall be measured under this item only Irregular shapes with sides (like circular, semi-circular, oval etc.) which may not be perpendicular to each other for shapes not conforming to rectangle or square, and circular shuttering shall not be paid separately. Joints of soffits of the slab shall be made clean after concreting and de-shuttering. (quoted rate to include all staging upto 3.50 mtr height). Note:- Contractor shall take necessary precautions such as watertight shuttering. This is inclusive of RCC members, leaving shuttering & centring for pour strip, slab in slope, RCC members in curved (in plan), etc., nothing is payable extra on this account.
A5: 3.1.1. | B5: Foundation, column footings, raft slab, raft beams, plinth beam, lift pits, sump pits, pedestals / bases of column, column up to plinth, swimming pool, Retaining wall foundations, grade slab etc. | C5: SQM | D5: ='SHUTTERING WORK MB'!I37 -> 90.1365 | J5: =SUM(D5:I5) -> 90.1365
A6: 3.1.2. | B6: Suspended floors, roofs, balconies, shelves/ counters, stair waist slabs, folded plate stairs and landings, swimming pool slab, lintel and floor beams, landing beams, girders (deep beams), RCC bands, swimming pool beam, cantilever projections, coping, cills, slab of tank etc at all levels.
A7: 3.1.2.1. | B7: Stilt Floor level to 7th Floor level | C7: SQM | J7: =SUM(D7:I7) -> 0
A8: 3.1.2.2. | B8: 7th Floor level to to Terrace Including OHT, Mumty, Machine Room, Parapet | C8: SQM | J8: =SUM(D8:I8) -> 0
A9: 3.1.2..3 | B9: All type of Moulding, Bands, Elevation/Architectural Features as per drawing and as directed by EIC. at all level | C9: SQM | J9: =SUM(D9:I9) -> 0
A11: 3.2. | B11: Columns, Wall, pillars, piers, abutments, posts and struts, offset and projection of columns, water tank walls, lift walls, Retaining Wall, swimming pool, Parapets, planters, vertical projection of pergolas, wall and ramp walls etc. at all levels.
A12: 3.2.1. | B12: Stilt Floor level to 7th Floor level | C12: SQM | J12: =SUM(D12:I12) -> 0
A13: 3.2.2. | B13: 7th Floor level to to Terrace Including OHT, Mumty, Machine Room, Parapet | C13: SQM | J13: =SUM(D13:I13) -> 0
A14: 3.2.3. | B14: All type of Moulding, Bands, Elevation/Architectural Features as per drawing and as directed by EIC. at all level | C14: SQM | J14: =SUM(D14:I14) -> 0
A16: 3.3. | B16: Extra for additional height in centring, shuttering where ever required with adequate bracing, propping etc. including cost of de-shuttering and decentring at all levels, over and above height of 3.50 mtr (Plan area to be measured and shall be paid proportionately on actual height) – for every 1.0 mtr. height | C16: SQM | J16: =SUM(D16:I16) -> 0
I18: TOTAL | J18: =SUM(J4:J17) -> 90.1365

Sheet SHUTTERING WORK MB
A1: COMPANY- OMAXE PANCHAM REALCON PVT LTD
A2: PROJECT- TOWER-E
A3: LOCATION- NAINI, PRAYAGRAJ
A4: MB SHEET- SHUTTERING BELOW PLINTH BEAM
A6: S.NO. | B6: DESCRIPTION | C6: UNIT | D6: NOS | E6: NOS | F6: MEASUREMENT | I6: QTY. | J6: REMARKS
F7: L | G7: B | H7: H/T
B8: PCC SHUTTERING
A9: 1 | B9: GRID (26'/Q') | C9: SQM | D9: 1 | E9: 1 | F9: 0.7 | H9: 0.1 | I9: =PRODUCT(D9:H9) -> 0.07
A10: 2 | B10: GRID (26'-43'/Q') | C10: SQM | D10: 1 | E10: 1 | F10: =25.89+0.515+0.515 -> 26.92 | H10: 0.1 | I10: =PRODUCT(D10:H10) -> 2.692
A11: 3 | B11: GRID (43'/E'-Q') | C11: SQM | D11: 1 | E11: 1 | F11: 21.65 | H11: 0.1 | I11: =PRODUCT(D11:H11) -> 2.165
A12: 4 | B12: GRID (38'-43'/E') | C12: SQM | D12: 1 | E12: 1 | F12: 11.09 | H12: 0.1 | I12: =PRODUCT(D12:H12) -> 1.109
A13: 5 | B13: GRID (38'/A-E') | C13: SQM | D13: 1 | E13: 1 | F13: 10.285 | H13: 0.1 | I13: =PRODUCT(D13:H13) -> 1.0285
A14: 6 | B14: GRID (30-38'/A) | C14: SQM | D14: 1 | E14: 1 | F14: 8.875 | H14: 0.1 | I14: =PRODUCT(D14:H14) -> 0.8875
A15: 7 | B15: GRID (30/A-A') | C15: SQM | D15: 1 | E15: 1 | F15: 1.5 | H15: 0.1 | I15: =PRODUCT(D15:H15) -> 0.15
A16: 8 | B16: GRID (27'-30/A') | C16: SQM | D16: 1 | E16: 1 | F16: 3.95 | H16: 0.1 | I16: =PRODUCT(D16:H16) -> 0.395
A17: 9 | B17: GRID (27'/A'-B) | C17: SQM | D17: 1 | E17: 1 | F17: 0.815 | H17: 0.1 | I17: =PRODUCT(D17:H17) -> 0.0815
A18: 10 | B18: GRID (26'-27'/B) | C18: SQM | D18: 1 | E18: 1 | F18: 1.695 | H18: 0.1 | I18: =PRODUCT(D18:H18) -> 0.1695
A19: 11 | B19: GRID (26'/B-B') | C19: SQM | D19: 1 | E19: 1 | F19: 1.405 | H19: 0.1 | I19: =PRODUCT(D19:H19) -> 0.1405
A20: 12 | B20: GRID (22'-26'/B') | C20: SQM | D20: 1 | E20: 1 | F20: =11.285-9 -> 2.285 | H20: 0.1 | I20: =PRODUCT(D20:H20) -> 0.2285 | J20: -9mtr as per JMR
B21: RAFT SHUTTERING
A22: 1 | B22: GRID (22'-26'/M') | C22: SQM | D22: 1 | E22: 1 | F22: 11.005 | H22: =0.85-0.3 -> 0.55 | I22: =PRODUCT(D22:H22) -> 6.05275
A23: =+A22+1 -> 2 | B23: GRID (26/M'-Q) | C23: SQM | D23: 1 | E23: 1 | F23: 12.415 | H23: =0.85-0.3 -> 0.55 | I23: =PRODUCT(D23:H23) -> 6.82825
A24: =+A23+1 -> 3 | B24: GRID (26'-43'/Q') | C24: SQM | D24: 1 | E24: 1 | F24: =25.89+0.515+0.515 -> 26.92 | H24: =0.85-0.3 -> 0.55 | I24: =PRODUCT(D24:H24) -> 14.806
A25: =+A24+1 -> 4 | B25: GRID (43'/E'-Q') | C25: SQM | D25: 1 | E25: 1 | F25: 21.65 | H25: =0.85-0.3 -> 0.55 | I25: =PRODUCT(D25:H25) -> 11.9075
A26: =+A25+1 -> 5 | B26: GRID (38'-43'/E') | C26: SQM | D26: 1 | E26: 1 | F26: 11.09 | H26: =0.85-0.3 -> 0.55 | I26: =PRODUCT(D26:H26) -> 6.0995
A27: =+A26+1 -> 6 | B27: GRID (38'/A-E') | C27: SQM | D27: 1 | E27: 1 | F27: 10.285 | H27: =0.85-0.3 -> 0.55 | I27: =PRODUCT(D27:H27) -> 5.65675
A28: =+A27+1 -> 7 | B28: GRID (30-38'/A) | C28: SQM | D28: 1 | E28: 1 | F28: 8.875 | H28: =0.85-0.3 -> 0.55 | I28: =PRODUCT(D28:H28) -> 4.88125
A29: =+A28+1 -> 8 | B29: GRID (30/A-A') | C29: SQM | D29: 1 | E29: 1 | F29: 1.5 | H29: =0.85-0.3 -> 0.55 | I29: =PRODUCT(D29:H29) -> 0.825
A30: =+A29+1 -> 9 | B30: GRID (27'-30/A') | C30: SQM | D30: 1 | E30: 1 | F30: 3.95 | H30: =0.85-0.3 -> 0.55 | I30: =PRODUCT(D30:H30) -> 2.1725
A31: =+A30+1 -> 10 | B31: GRID (27'/A'-B) | C31: SQM | D31: 1 | E31: 1 | F31: 0.815 | H31: =0.85-0.3 -> 0.55 | I31: =PRODUCT(D31:H31) -> 0.44825
A32: =+A31+1 -> 11 | B32: GRID (26'-27'/B) | C32: SQM | D32: 1 | E32: 1 | F32: 1.695 | H32: =0.85-0.3 -> 0.55 | I32: =PRODUCT(D32:H32) -> 0.93225
A33: =+A32+1 -> 12 | B33: GRID (26'/B-B') | C33: SQM | D33: 1 | E33: 1 | F33: 1.405 | H33: =0.85-0.3 -> 0.55 | I33: =PRODUCT(D33:H33) -> 0.77275
A34: =+A33+1 -> 13 | B34: GRID (22'-26'/B') | C34: SQM | D34: 1 | E34: 1 | F34: 11.285 | H34: =0.85-0.3 -> 0.55 | I34: =PRODUCT(D34:H34) -> 6.20675
A35: =+A34+1 -> 14 | B35: GRID (22'-26'/B') | C35: SQM | D35: 1 | E35: 1 | F35: =15.8 -> 15.8 | H35: 0.85 | I35: =PRODUCT(D35:H35) -> 13.43
H37: TOTAL | I37: =SUM(I8:I36) -> 90.1365

Sheet BRICK WORK SUMMARY
A2: TOWER-E BRICK WORK SUMMARY
D3: QTY | J3: TOTAL
A4: 5 | B4: MASONARY WORK | D4: 1ST RA | E4: 2ND RA | F4: 3rd RA | G4: 4th RA | H4: 5th RA | I4: 6th RA
B5: (Quoted Rates are for all heights, all depths, all levels, including basement to roof (mumty) & all leads and lifts, including curved or circular including elevation masonary work) (Basic Rate of Brick @ Rs. 7/No. FOR at site without GST)
A6: 5.1. | B6: Brick work in Sub Structure (Up to Stilt Floor level):
B7: Providing and laying 230mm thick brick masonry using 1st quality burnt clay FPS bricks in Sub-Structure laid in cement mortar 1:6 (1 cement : 6 coarse sand) mix, joints finished, flush/ raked to 6mm depth including scaffolding, curing complete as per specification and drawing or as directed by Project Manager. | C7: CUM | J7: =SUM(D7:I7) -> 0
A8: 5.2. | B8: Brick work in Sub Structure (Up to Stilt Floor level):
B9: Providing and laying of 115 mm thick brick work with 1st quality burnt clay FPS bricks in sub-superstructure laid in cement mortar 1:4 (1 cement : 4 coarse sand) mix, joints finished, including placing hoop iron as per specification at every third course, scaffolding, curing complete in all respect as per direction of EIC. (Hoop iron shall be provided by client free of cost) (Items of RCC bands like shuttering, concrete and reinforcement to be paid in respective items). | C9: SQM | D9: ='BRICK WORK MB'!I24 -> 36.867 | J9: =SUM(D9:I9) -> 36.867
A10: 5.3. | B10: Brick work in Super Structure (Above Stilt FLoor level)
A11: 5.3.1 | B11: Providing and laying 230mm thick brick masonry using 1st quality burnt clay FPS bricks in Super-Structure laid in cement mortar 1:6 (1 cement : 6 coarse sand) mix, joints finished, flush/ raked to 6mm depth including scaffolding, curing complete as per specification and drawing or as directed by Project Manager.
A12: (a) | B12: Stilt Floor level to 7th Floor level | C12: CUM | J12: =SUM(D12:I12) -> 0
A13: (b) | B13: 7th Floor level to to Terrace Including OHT, Mumty, Machine Room, Parapet | C13: CUM | J13: =SUM(D13:I13) -> 0
A14: 5.4. | B14: Brick work in Super Structure (Above Stilt FLoor level)
A15: 5.4.1 | B15: Providing and laying of 115 mm thick brick work with 1st quality burnt clay FPS bricks in Super-Superstructure laid in cement mortar 1:4 (1 cement : 4 coarse sand) mix, joints finished, including placing hoop iron as per specification at every third course, scaffolding, curing complete in all respect as per direction of EIC. (Hoop iron shall be provided by client free of cost) (Items of RCC bands like shuttering, concrete and reinforcement to be paid in respective items).
A16: (a) | B16: Stilt Floor level to 7th Floor level | C16: SQM | J16: =SUM(D16:I16) -> 0
A17: (b) | B17: 7th Floor level to to Terrace Including OHT, Mumty, Machine Room, Parapet | C17: SQM | J17: =SUM(D17:I17) -> 0
A18: 5.8. | B18: Brick work in staircase steps:
B19: Providing and laying and constructing brickwork in staircase steps using 1st quality burnt clay FPS bricks in cement mortar 1:3 (1 cement : 3 coarse sand) at all heights and levels including cutting, chamfering scaffolding, curing, complete as per specification. | C19: CUM | J19: =SUM(D19:I19) -> 0
I21: TOTAL | J21: =SUM(J7:J20) -> 36.867

Sheet BRICK WORK MB
A1: COMPANY- OMAXE PANCHAM REALCON PVT LTD
A2: PROJECT- TOWER-E
A3: LOCATION- NAINI, PRAYAGRAJ
A4: MB SHEET- BRICK WORK BELOW PLINTH BEAM
A6: S.NO. | B6: DESCRIPTION | C6: UNIT | D6: NOS | E6: NOS | F6: MEASUREMENT | I6: QTY. | J6: REMARKS
F7: L | G7: B | H7: H/T
B8: RAFT OUTTER 115MM BRICK WORK
A9: 1 | B9: GRID (22'-26'/M') | C9: SQM | D9: 1 | E9: 1 | F9: 11.005 | H9: 0.3 | I9: =PRODUCT(D9:H9) -> 3.3015
A10: =+A9+1 -> 2 | B10: GRID (26/M'-Q) | C10: SQM | D10: 1 | E10: 1 | F10: 12.415 | H10: 0.3 | I10: =PRODUCT(D10:H10) -> 3.7245
A11: =+A10+1 -> 3 | B11: GRID (26'-43'/Q') | C11: SQM | D11: 1 | E11: 1 | F11: =25.89+0.515+0.515 -> 26.92 | H11: 0.3 | I11: =PRODUCT(D11:H11) -> 8.076
A12: =+A11+1 -> 4 | B12: GRID (43'/E'-Q') | C12: SQM | D12: 1 | E12: 1 | F12: 21.65 | H12: 0.3 | I12: =PRODUCT(D12:H12) -> 6.495
A13: =+A12+1 -> 5 | B13: GRID (38'-43'/E') | C13: SQM | D13: 1 | E13: 1 | F13: 11.09 | H13: 0.3 | I13: =PRODUCT(D13:H13) -> 3.327
A14: =+A13+1 -> 6 | B14: GRID (38'/A-E') | C14: SQM | D14: 1 | E14: 1 | F14: 10.285 | H14: 0.3 | I14: =PRODUCT(D14:H14) -> 3.0855
A15: =+A14+1 -> 7 | B15: GRID (30-38'/A) | C15: SQM | D15: 1 | E15: 1 | F15: 8.875 | H15: 0.3 | I15: =PRODUCT(D15:H15) -> 2.6625
A16: =+A15+1 -> 8 | B16: GRID (30/A-A') | C16: SQM | D16: 1 | E16: 1 | F16: 1.5 | H16: 0.3 | I16: =PRODUCT(D16:H16) -> 0.45
A17: =+A16+1 -> 9 | B17: GRID (27'-30/A') | C17: SQM | D17: 1 | E17: 1 | F17: 3.95 | H17: 0.3 | I17: =PRODUCT(D17:H17) -> 1.185
A18: =+A17+1 -> 10 | B18: GRID (27'/A'-B) | C18: SQM | D18: 1 | E18: 1 | F18: 0.815 | H18: 0.3 | I18: =PRODUCT(D18:H18) -> 0.2445
A19: =+A18+1 -> 11 | B19: GRID (26'-27'/B) | C19: SQM | D19: 1 | E19: 1 | F19: 1.695 | H19: 0.3 | I19: =PRODUCT(D19:H19) -> 0.5085
A20: =+A19+1 -> 12 | B20: GRID (26'/B-B') | C20: SQM | D20: 1 | E20: 1 | F20: 1.405 | H20: 0.3 | I20: =PRODUCT(D20:H20) -> 0.4215
A21: =+A20+1 -> 13 | B21: GRID (22'-26'/B') | C21: SQM | D21: 1 | E21: 1 | F21: 11.285 | H21: 0.3 | I21: =PRODUCT(D21:H21) -> 3.3855
H24: TOTAL | I24: =SUM(I8:I23) -> 36.867

Sheet TMT STEEL RECO.
A1: MARCO ENTERPRISES
A2: TOWER-E
A3: Reconcialation of TMT Steel
A4: S.NO. | B4: Description | C4: Unit | D4: Dia wise | K4: Total
D5: 6mm | E5: 8mm | F5: 10mm | G5: 12mm | H5: 16mm | I5: 20mm | J5: 25mm
A6: A | B6: Total Steel Received upto date | C6: Kg | D6: ='TMT STEEL REC.'!D12 -> 0 | E6: ='TMT STEEL REC.'!E12 -> 9070 | F6: ='TMT STEEL REC.'!F12 -> 6840 | G6: ='TMT STEEL REC.'!G12 -> 7700 | H6: ='TMT STEEL REC.'!H12 -> 67471 | I6: ='TMT STEEL REC.'!I12 -> 29380 | J6: ='TMT STEEL REC.'!J12 -> 15324 | K6: =SUM(E6:J6) -> 135785
A8: B | B8: Consumption Detail
A9: 4.1.1 | B9: Up To Stilt Floor Lvl. | C9: Kg | D9: ='TMT SUMMARY'!F9 -> 0 | E9: ='TMT SUMMARY'!G9 -> 0 | F9: ='TMT SUMMARY'!H9 -> 1205.4389 | G9: ='TMT SUMMARY'!I9 -> 1461.0184 | H9: ='TMT SUMMARY'!J9 -> 25667.402 | I9: ='TMT SUMMARY'!K9 -> 16032.785 | J9: ='TMT SUMMARY'!L9 -> 8560.5934 | K9: =SUM(E9:J9) -> 52927.237
A10: 4.1.2 | B10: Stilt Floor level to to Terrace Including OHT, Mumty, Machine Room, Parapet) | C10: Kg | D10: ='TMT SUMMARY'!F14 -> 0 | E10: ='TMT SUMMARY'!G14 -> 0 | F10: ='TMT SUMMARY'!H14 -> 0 | G10: ='TMT SUMMARY'!I14 -> 0 | H10: ='TMT SUMMARY'!J14 -> 0 | I10: ='TMT SUMMARY'!K14 -> 0 | J10: ='TMT SUMMARY'!L14 -> 0 | K10: =SUM(E10:J10) -> 0
A11: 4.1.3 | B11: All type of Moulding, Bands, Elevation/Architectural Features as per drawing and as directed by EIC. at all level | C11: Kg | D11: ='TMT SUMMARY'!F19 -> 0 | E11: ='TMT SUMMARY'!G19 -> 0 | F11: ='TMT SUMMARY'!H19 -> 0 | G11: ='TMT SUMMARY'!I19 -> 0 | H11: ='TMT SUMMARY'!J19 -> 0 | I11: ='TMT SUMMARY'!K19 -> 0 | J11: ='TMT SUMMARY'!L19 -> 0 | K11: =SUM(E11:J11) -> 0
A13: C | B13: Total consumption | D13: =SUM(D9:D12) -> 0 | E13: =SUM(E9:E12) -> 0 | F13: =SUM(F9:F12) -> 1205.4389 | G13: =SUM(G9:G12) -> 1461.0184 | H13: =SUM(H9:H12) -> 25667.402 | I13: =SUM(I9:I12) -> 16032.785 | J13: =SUM(J9:J12) -> 8560.5934 | K13: =SUM(K9:K12) -> 52927.237
A14: D | B14: Theoretical Balance | C14: Kg | D14: =D6-D13 -> 0 | E14: =E6-E13 -> 9070 | F14: =F6-F13 -> 5634.5611 | G14: =G6-G13 -> 6238.9816 | H14: =H6-H13 -> 41803.598 | I14: =I6-I13 -> 13347.215 | J14: =J6-J13 -> 6763.4066 | K14: =SUM(E14:J14) -> 82857.763
A15: E | B15: Steel available at yard | C15: Kg | E15: 9070 | F15: 5560 | G15: 6180 | H15: 41450 | I15: 13300 | J15: 6650 | K15: =SUM(E15:J15) -> 82210
A16: F | B16: W.I.P. Steel in column lap/lintel/kit Plateform etc | C16: Kg | K16: =SUM(E16:J16) -> 0
K17: =SUM(E17:J17) -> 0
A18: G | B18: Total In Progress | C18: Kg | D18: =SUM(D16:D17) -> 0 | E18: =SUM(E16:E17) -> 0 | F18: =SUM(F16:F17) -> 0 | G18: =SUM(G16:G17) -> 0 | H18: =SUM(H16:H17) -> 0 | I18: =SUM(I16:I17) -> 0 | J18: =SUM(J16:J17) -> 0 | K18: =SUM(E18:J18) -> 0
A21: H | B21: Wastage (D-E-F) | C21: Kg | D21: =D14-D15-D16 -> 0 | E21: =E14-E15-E16 -> 0 | F21: =F14-F15-F16 -> 74.561133 | G21: =G14-G15-G16 -> 58.981592 | H21: =H14-H15-H16 -> 353.59822 | I21: =I14-I15-I16 -> 47.215185 | J21: =J14-J15-J16 -> 113.40664 | K21: =SUM(E21:J21) -> 647.76277 | L21: =+K21/K13 -> 0.012238741
B22: SCRAP SALE | K22: 0
B23: Allowed Wastage 2.5% | C23: Kg | K23: =K13*2.5% -> 1323.1809

Sheet TMT STEEL REC.
A1: (OMAXE TOWER-E, PRAYAGRAJ )
A2: TMT STEEL BAR ISSUE BY OMAXE
A3: S.NO. | B3: DATE | C3: Unit | D3: 6MM Dia. | E3: 8mm Dia. | F3: 10mm Dia. | G3: 12mm Dia. | H3: 16mm Dia. | I3: 20mm Dia. | J3: 25mm Dia. | K3: TOTAL | L3: COMULAT.
A5: 1 | B5: RECEIVED AT 13/5/25 | C5: KG | E5: 9070 | F5: 6840 | I5: 20010 | K5: =SUM(E5:J5) -> 35920 | L5: =K5 -> 35920
A6: 2 | B6: RECEIVED AT 19/5/24 | C6: KG | G6: 7700 | H6: 37621 | I6: 9370 | J6: 5474 | K6: =SUM(E6:J6) -> 60165 | L6: =L5+K6 -> 96085
A7: 3 | B7: RECEIVED AT 24/5/25 | C7: KG | H7: 29850 | J7: 9850 | K7: =SUM(E7:J7) -> 39700 | L7: =L6+K7 -> 135785
K8: =SUM(E8:J8) -> 0 | L8: =L7+K8 -> 135785
K9: =SUM(E9:J9) -> 0 | L9: =L8+K9 -> 135785
B12: TOTAL QTY. | D12: =SUM(D4:D11) -> 0 | E12: =SUM(E4:E11) -> 9070 | F12: =SUM(F4:F11) -> 6840 | G12: =SUM(G4:G11) -> 7700 | H12: =SUM(H4:H11) -> 67471 | I12: =SUM(I4:I11) -> 29380 | J12: =SUM(J4:J11) -> 15324 | K12: =SUM(K4:K11) -> 135785 | L12: KG

Sheet TMT SUMMARY
A1: (OMAXE TOWER-E, PRAYAGRAJ )
A2: STEEL CONSUMPTION SUMMARY
A3: S.NO. | B3: DESCRIPTION | C3: LOCATION | D3: Unit | E3: NOS | F3: 6mm Dia. | G3: 8mm Dia. | H3: 10mm Dia. | I3: 12mm Dia. | J3: 16mm Dia. | K3: 20mm Dia. | L3: 25mm Dia. | M3: TOTAL
B4: 4.1 TMT REINFORCEMENT
A5: 4.1.1. | B5: UPTO STILRT FLOOR LVL
A6: 1 | B6: TOWER-E COLUMN GRID (22-23/A-Q) | C6: UPTO RAFT | D6: KG | E6: 1 | G6: ='COLUMN BBS'!P590*$E$6 -> 0 | H6: ='COLUMN BBS'!Q590*$E$6 -> 631.1908 | I6: ='COLUMN BBS'!R590*$E$6 -> 322.96205 | J6: ='COLUMN BBS'!S590*$E$6 -> 773.44476 | K6: ='COLUMN BBS'!T590*$E$6 -> 656.77869 | L6: ='COLUMN BBS'!U590*$E$6 -> 76.61988 | M6: =SUM(F6:L6) -> 2460.9962
A7: 2 | B7: TOWER-E RAFT GRID (22-23/A-Q) | C7: AS SUB-STRUCTURE | D7: KG | E7: 1 | G7: ='RAFT BBS'!Q786*$E$7 -> 0 | H7: ='RAFT BBS'!R786*$E$7 -> 574.24807 | I7: ='RAFT BBS'!S786*$E$7 -> 1138.0564 | J7: ='RAFT BBS'!T786*$E$7 -> 24893.957 | K7: ='RAFT BBS'!U786*$E$7 -> 15376.006 | L7: ='RAFT BBS'!V786*$E$7 -> 8483.9735 | M7: =SUM(F7:L7) -> 50466.241
F9: =SUM(F6:F8) -> 0 | G9: =SUM(G6:G8) -> 0 | H9: =SUM(H6:H8) -> 1205.4389 | I9: =SUM(I6:I8) -> 1461.0184 | J9: =SUM(J6:J8) -> 25667.402 | K9: =SUM(K6:K8) -> 16032.785 | L9: =SUM(L6:L8) -> 8560.5934 | M9: =SUM(M6:M8) -> 52927.237
A10: 4.1.2. | B10: Stilt Floor level to to Terrace Including OHT, Mumty, Machine Room, Parapet)
A11: 1 | M11: =SUM(F11:L11) -> 0
A12: 2 | M12: =SUM(F12:L12) -> 0
F14: =SUM(F11:F13) -> 0 | G14: =SUM(G11:G13) -> 0 | H14: =SUM(H11:H13) -> 0 | I14: =SUM(I11:I13) -> 0 | J14: =SUM(J11:J13) -> 0 | K14: =SUM(K11:K13) -> 0 | L14: =SUM(L11:L13) -> 0 | M14: =SUM(M11:M13) -> 0
A15: 4.1.3. | B15: All type of Moulding, Bands, Elevation/Architectural Features as per drawing and as directed by EIC. at all level
A16: 1 | M16: =SUM(F16:L16) -> 0
A17: 2 | M17: =SUM(F17:L17) -> 0
F19: =SUM(F16:F18) -> 0 | G19: =SUM(G16:G18) -> 0 | H19: =SUM(H16:H18) -> 0 | I19: =SUM(I16:I18) -> 0 | J19: =SUM(J16:J18) -> 0 | K19: =SUM(K16:K18) -> 0 | L19: =SUM(L16:L18) -> 0 | M19: =SUM(M16:M18) -> 0

Sheet RAFT BBS
A1: TOWER-E RAFT BBS
A3: S.No. | B3: Description | C3: Shape of Bar in mm | G3: Spacing c/c | H3: Dia of Bar | I3: No's of Set | J3: No's of Bar | K3: Actual Length | L3: Lap | M3: No. Of Bend | N3: Deduction In mm | O3: Cut Length | P3: Total Length | Q3: TMT BAR Fe-500D or EQR | W3: Remarks
A4: A | B4: RAFT | Q4: 8mm | R4: 10mm | S4: 12mm | T4: 16mm | U4: 20mm | V4: 25mm
B5: BOTTOM MAIN BAR | Q5: =IF($H5=8,$P5,"") | R5: =IF($H5=10,$P5,"") | S5: =IF($H5=12,$P5,"") | T5: =IF($H5=16,$P5,"") | U5: =IF($H5=20,$P5,"") | V5: =IF($H5=25,$P5,"")
A6: 1 | B6: GRID (39'-43/E'-Q') | Q6: =IF($H6=8,$P6,"") | R6: =IF($H6=10,$P6,"") | S6: =IF($H6=12,$P6,"") | T6: =IF($H6=16,$P6,"") | U6: =IF($H6=20,$P6,"") | V6: =IF($H6=25,$P6,"")
B7: MAIN BAR BOTTOM (ALTH.) | C7: 0.5 | D7: =21.65-2*0.05 -> 21.55 | F7: 0.5 | G7: 0.25 | H7: 16 | I7: 1 | J7: =ROUNDDOWN(8.855/G7/2+1,0) -> 18 | K7: =D7 -> 21.55 | L7: =IF(O7<12,"0",0.049*H7)*2 -> 1.568 | M7: 2 | N7: =M7*2*H7/1000 -> 0.064 | O7: =(D7+C7+F7)-N7 -> 22.486 | P7: =(I7*J7*O7)+L7 -> 406.316 | Q7: =IF($H7=8,$P7,"") | R7: =IF($H7=10,$P7,"") | S7: =IF($H7=12,$P7,"") | T7: =IF($H7=16,$P7,"") -> 406.316 | U7: =IF($H7=20,$P7,"") | V7: =IF($H7=25,$P7,"")
Q8: =IF($H8=8,$P8,"") | R8: =IF($H8=10,$P8,"") | S8: =IF($H8=12,$P8,"") | T8: =IF($H8=16,$P8,"") | U8: =IF($H8=20,$P8,"") | V8: =IF($H8=25,$P8,"")
A9: 1 | B9: GRID (39'-43/E'-Q') | Q9: =IF($H9=8,$P9,"") | R9: =IF($H9=10,$P9,"") | S9: =IF($H9=12,$P9,"") | T9: =IF($H9=16,$P9,"") | U9: =IF($H9=20,$P9,"") | V9: =IF($H9=25,$P9,"")
B10: MAIN BAR BOTTOM (ALTH.) | C10: 0.5 | D10: =21.65-2*0.05 -> 21.55 | F10: 0.5 | G10: 0.25 | H10: 16 | I10: 1 | J10: =ROUNDDOWN(8.855/G10/2,0) -> 17 | K10: =D10 -> 21.55 | L10: =IF(O10<12,"0",0.049*H10) -> 0.784 | M10: 2 | N10: =M10*2*H10/1000 -> 0.064 | O10: =(D10+C10+F10)-N10 -> 22.486 | P10: =(I10*J10*O10)+L10 -> 383.046 | Q10: =IF($H10=8,$P10,"") | R10: =IF($H10=10,$P10,"") | S10: =IF($H10=12,$P10,"") | T10: =IF($H10=16,$P10,"") -> 383.046 | U10: =IF($H10=20,$P10,"") | V10: =IF($H10=25,$P10,"")
Q11: =IF($H11=8,$P11,"") | R11: =IF($H11=10,$P11,"") | S11: =IF($H11=12,$P11,"") | T11: =IF($H11=16,$P11,"") | U11: =IF($H11=20,$P11,"") | V11: =IF($H11=25,$P11,"")
A12: 2 | B12: GRID (38'-39'/E'-Q') | Q12: =IF($H12=8,$P12,"") | R12: =IF($H12=10,$P12,"") | S12: =IF($H12=12,$P12,"") | T12: =IF($H12=16,$P12,"") | U12: =IF($H12=20,$P12,"") | V12: =IF($H12=25,$P12,"")
B13: MAIN BAR BOTTOM (ALTH.) | C13: 0.5 | D13: =21.65+0.515-2*0.05 -> 22.065 | F13: 0.5 | G13: 0.25 | H13: 16 | I13: 1 | J13: =ROUNDDOWN(2.535/G13/2+1,0) -> 6 | K13: =D13 -> 22.065 | L13: =IF(O13<12,"0",0.049*H13)*2 -> 1.568 | M13: 2 | N13: =M13*2*H13/1000 -> 0.064 | O13: =(D13+C13+F13)-N13 -> 23.001 | P13: =(I13*J13*O13)+L13 -> 139.574 | Q13: =IF($H13=8,$P13,"") | R13: =IF($H13=10,$P13,"") | S13: =IF($H13=12,$P13,"") | T13: =IF($H13=16,$P13,"") -> 139.574 | U13: =IF($H13=20,$P13,"") | V13: =IF($H13=25,$P13,"")
Q14: =IF($H14=8,$P14,"") | R14: =IF($H14=10,$P14,"") | S14: =IF($H14=12,$P14,"") | T14: =IF($H14=16,$P14,"") | U14: =IF($H14=20,$P14,"") | V14: =IF($H14=25,$P14,"")
A15: 2 | B15: GRID (38'-39'/E'-Q') | Q15: =IF($H15=8,$P15,"") | R15: =IF($H15=10,$P15,"") | S15: =IF($H15=12,$P15,"") | T15: =IF($H15=16,$P15,"") | U15: =IF($H15=20,$P15,"") | V15: =IF($H15=25,$P15,"")
B16: MAIN BAR BOTTOM (ALTH.) | C16: 0.5 | D16: =21.65+0.515-2*0.05 -> 22.065 | F16: 0.5 | G16: 0.25 | H16: 16 | I16: 1 | J16: =ROUNDDOWN(2.535/G16/2,0) -> 5 | K16: =D16 -> 22.065 | L16: =IF(O16<12,"0",0.049*H16) -> 0.784 | M16: 2 | N16: =M16*2*H16/1000 -> 0.064 | O16: =(D16+C16+F16)-N16 -> 23.001 | P16: =(I16*J16*O16)+L16 -> 115.789 | Q16: =IF($H16=8,$P16,"") | R16: =IF($H16=10,$P16,"") | S16: =IF($H16=12,$P16,"") | T16: =IF($H16=16,$P16,"") -> 115.789 | U16: =IF($H16=20,$P16,"") | V16: =IF($H16=25,$P16,"")
Q17: =IF($H17=8,$P17,"") | R17: =IF($H17=10,$P17,"") | S17: =IF($H17=12,$P17,"") | T17: =IF($H17=16,$P17,"") | U17: =IF($H17=20,$P17,"") | V17: =IF($H17=25,$P17,"")
A18: 3 | B18: GRID (32'-38'/A-Q') | Q18: =IF($H18=8,$P18,"") | R18: =IF($H18=10,$P18,"") | S18: =IF($H18=12,$P18,"") | T18: =IF($H18=16,$P18,"") | U18: =IF($H18=20,$P18,"") | V18: =IF($H18=25,$P18,"")
B19: MAIN BAR BOTTOM (ALTH.) | C19: 0.5 | D19: =32.45-2*0.05 -> 32.35 | F19: 0.5 | G19: 0.25 | H19: 16 | I19: 1 | J19: =ROUND(6.245/G19/2+1,0) -> 13 | K19: =D19 -> 32.35 | L19: =IF(O19<12,"0",0.049*H19)*3 -> 2.352 | M19: 2 | N19: =M19*2*H19/1000 -> 0.064 | O19: =(D19+C19+F19)-N19 -> 33.286 | P19: =(I19*J19*O19)+L19 -> 435.07 | Q19: =IF($H19=8,$P19,"") | R19: =IF($H19=10,$P19,"") | S19: =IF($H19=12,$P19,"") | T19: =IF($H19=16,$P19,"") -> 435.07 | U19: =IF($H19=20,$P19,"") | V19: =IF($H19=25,$P19,"")
Q20: =IF($H20=8,$P20,"") | R20: =IF($H20=10,$P20,"") | S20: =IF($H20=12,$P20,"") | T20: =IF($H20=16,$P20,"") | U20: =IF($H20=20,$P20,"") | V20: =IF($H20=25,$P20,"")
A21: 3 | B21: GRID (32'-38'/A-Q') | Q21: =IF($H21=8,$P21,"") | R21: =IF($H21=10,$P21,"") | S21: =IF($H21=12,$P21,"") | T21: =IF($H21=16,$P21,"") | U21: =IF($H21=20,$P21,"") | V21: =IF($H21=25,$P21,"")
B22: MAIN BAR BOTTOM (ALTH.) | C22: 0.5 | D22: =32.45-2*0.05 -> 32.35 | F22: 0.5 | G22: 0.25 | H22: 16 | I22: 1 | J22: =ROUND(6.245/G22/2+0,0) -> 12 | K22: =D22 -> 32.35 | L22: =IF(O22<12,"0",0.049*H22)*2 -> 1.568 | M22: 2 | N22: =M22*2*H22/1000 -> 0.064 | O22: =(D22+C22+F22)-N22 -> 33.286 | P22: =(I22*J22*O22)+L22 -> 401 | Q22: =IF($H22=8,$P22,"") | R22: =IF($H22=10,$P22,"") | S22: =IF($H22=12,$P22,"") | T22: =IF($H22=16,$P22,"") -> 401 | U22: =IF($H22=20,$P22,"") | V22: =IF($H22=25,$P22,"")
Q23: =IF($H23=8,$P23,"") | R23: =IF($H23=10,$P23,"") | S23: =IF($H23=12,$P23,"") | T23: =IF($H23=16,$P23,"") | U23: =IF($H23=20,$P23,"") | V23: =IF($H23=25,$P23,"")
A24: 4 | B24: GRID (30'-32'/A-Q') | Q24: =IF($H24=8,$P24,"") | R24: =IF($H24=10,$P24,"") | S24: =IF($H24=12,$P24,"") | T24: =IF($H24=16,$P24,"") | U24: =IF($H24=20,$P24,"") | V24: =IF($H24=25,$P24,"")
B25: MAIN BAR BOTTOM (ALTH.) | C25: 0.5 | D25: =31.935-2*0.05 -> 31.835 | F25: 0.5 | G25: 0.25 | H25: 16 | I25: 1 | J25: =ROUND(2.63/G25/2+1,0) -> 6 | K25: =D25 -> 31.835 | L25: =IF(O25<12,"0",0.049*H25)*3 -> 2.352 | M25: 2 | N25: =M25*2*H25/1000 -> 0.064 | O25: =(D25+C25+F25)-N25 -> 32.771 | P25: =(I25*J25*O25)+L25 -> 198.978 | Q25: =IF($H25=8,$P25,"") | R25: =IF($H25=10,$P25,"") | S25: =IF($H25=12,$P25,"") | T25: =IF($H25=16,$P25,"") -> 198.978 | U25: =IF($H25=20,$P25,"") | V25: =IF($H25=25,$P25,"")
Q26: =IF($H26=8,$P26,"") | R26: =IF($H26=10,$P26,"") | S26: =IF($H26=12,$P26,"") | T26: =IF($H26=16,$P26,"") | U26: =IF($H26=20,$P26,"") | V26: =IF($H26=25,$P26,"")
A27: 4 | B27: GRID (30'-32'/A-Q') | Q27: =IF($H27=8,$P27,"") | R27: =IF($H27=10,$P27,"") | S27: =IF($H27=12,$P27,"") | T27: =IF($H27=16,$P27,"") | U27: =IF($H27=20,$P27,"") | V27: =IF($H27=25,$P27,"")
B28: MAIN BAR BOTTOM (ALTH.) | C28: 0.5 | D28: =31.935-2*0.05 -> 31.835 | F28: 0.5 | G28: 0.25 | H28: 16 | I28: 1 | J28: =ROUND(2.63/G28/2,0) -> 5 | K28: =D28 -> 31.835 | L28: =IF(O28<12,"0",0.049*H28)*2 -> 1.568 | M28: 2 | N28: =M28*2*H28/1000 -> 0.064 | O28: =(D28+C28+F28)-N28 -> 32.771 | P28: =(I28*J28*O28)+L28 -> 165.423 | Q28: =IF($H28=8,$P28,"") | R28: =IF($H28=10,$P28,"") | S28: =IF($H28=12,$P28,"") | T28: =IF($H28=16,$P28,"") -> 165.423 | U28: =IF($H28=20,$P28,"") | V28: =IF($H28=25,$P28,"")
Q29: =IF($H29=8,$P29,"") | R29: =IF($H29=10,$P29,"") | S29: =IF($H29=12,$P29,"") | T29: =IF($H29=16,$P29,"") | U29: =IF($H29=20,$P29,"") | V29: =IF($H29=25,$P29,"")
A30: 5 | B30: GRID (27'-30/A-Q') | Q30: =IF($H30=8,$P30,"") | R30: =IF($H30=10,$P30,"") | S30: =IF($H30=12,$P30,"") | T30: =IF($H30=16,$P30,"") | U30: =IF($H30=20,$P30,"") | V30: =IF($H30=25,$P30,"")
B31: MAIN BAR BOTTOM (ALTH.) | C31: 0.5 | D31: =31.95-2*0.05-1.5 -> 30.35 | F31: 0.5 | G31: 0.25 | H31: 16 | I31: 1 | J31: =ROUND(3.95/G31/2+1,0) -> 9 | K31: =D31 -> 30.35 | L31: =IF(O31<12,"0",0.049*H31)*3 -> 2.352 | M31: 2 | N31: =M31*2*H31/1000 -> 0.064 | O31: =(D31+C31+F31)-N31 -> 31.286 | P31: =(I31*J31*O31)+L31 -> 283.926 | Q31: =IF($H31=8,$P31,"") | R31: =IF($H31=10,$P31,"") | S31: =IF($H31=12,$P31,"") | T31: =IF($H31=16,$P31,"") -> 283.926 | U31: =IF($H31=20,$P31,"") | V31: =IF($H31=25,$P31,"")
Q32: =IF($H32=8,$P32,"") | R32: =IF($H32=10,$P32,"") | S32: =IF($H32=12,$P32,"") | T32: =IF($H32=16,$P32,"") | U32: =IF($H32=20,$P32,"") | V32: =IF($H32=25,$P32,"")
A33: 5 | B33: GRID (27'-30/A-Q') | Q33: =IF($H33=8,$P33,"") | R33: =IF($H33=10,$P33,"") | S33: =IF($H33=12,$P33,"") | T33: =IF($H33=16,$P33,"") | U33: =IF($H33=20,$P33,"") | V33: =IF($H33=25,$P33,"")
B34: MAIN BAR BOTTOM (ALTH.) | C34: 0.5 | D34: =31.95-2*0.05-1.5 -> 30.35 | F34: 0.5 | G34: 0.25 | H34: 16 | I34: 1 | J34: =ROUND(3.95/G34/2,0) -> 8 | K34: =D34 -> 30.35 | L34: =IF(O34<12,"0",0.049*H34)*2 -> 1.568 | M34: 2 | N34: =M34*2*H34/1000 -> 0.064 | O34: =(D34+C34+F34)-N34 -> 31.286 | P34: =(I34*J34*O34)+L34 -> 251.856 | Q34: =IF($H34=8,$P34,"") | R34: =IF($H34=10,$P34,"") | S34: =IF($H34=12,$P34,"") | T34: =IF($H34=16,$P34,"") -> 251.856 | U34: =IF($H34=20,$P34,"") | V34: =IF($H34=25,$P34,"")
Q35: =IF($H35=8,$P35,"") | R35: =IF($H35=10,$P35,"") | S35: =IF($H35=12,$P35,"") | T35: =IF($H35=16,$P35,"") | U35: =IF($H35=20,$P35,"") | V35: =IF($H35=25,$P35,"")
A36: 6 | B36: GRID (26'-27'/A'-Q') | Q36: =IF($H36=8,$P36,"") | R36: =IF($H36=10,$P36,"") | S36: =IF($H36=12,$P36,"") | T36: =IF($H36=16,$P36,"") | U36: =IF($H36=20,$P36,"") | V36: =IF($H36=25,$P36,"")
B37: MAIN BAR BOTTOM (ALTH.) | C37: 0.5 | D37: =31.95-2*0.05-1.5-0.815 -> 29.535 | F37: 0.5 | G37: 0.25 | H37: 16 | I37: 1 | J37: =ROUND(1.695/G37/2+1,0) -> 4 | K37: =D37 -> 29.535 | L37: =IF(O37<12,"0",0.049*H37)*3 -> 2.352 | M37: 2 | N37: =M37*2*H37/1000 -> 0.064 | O37: =(D37+C37+F37)-N37 -> 30.471 | P37: =(I37*J37*O37)+L37 -> 124.236 | Q37: =IF($H37=8,$P37,"") | R37: =IF($H37=10,$P37,"") | S37: =IF($H37=12,$P37,"") | T37: =IF($H37=16,$P37,"") -> 124.236 | U37: =IF($H37=20,$P37,"") | V37: =IF($H37=25,$P37,"")
Q38: =IF($H38=8,$P38,"") | R38: =IF($H38=10,$P38,"") | S38: =IF($H38=12,$P38,"") | T38: =IF($H38=16,$P38,"") | U38: =IF($H38=20,$P38,"") | V38: =IF($H38=25,$P38,"")
A39: 6 | B39: GRID (26'-27'/A'-Q') | Q39: =IF($H39=8,$P39,"") | R39: =IF($H39=10,$P39,"") | S39: =IF($H39=12,$P39,"") | T39: =IF($H39=16,$P39,"") | U39: =IF($H39=20,$P39,"") | V39: =IF($H39=25,$P39,"")
B40: MAIN BAR BOTTOM (ALTH.) | C40: 0.5 | D40: =31.95-2*0.05-1.5-0.815 -> 29.535 | F40: 0.5 | G40: 0.25 | H40: 16 | I40: 1 | J40: =ROUND(1.695/G40/2,0) -> 3 | K40: =D40 -> 29.535 | L40: =IF(O40<12,"0",0.049*H40)*2 -> 1.568 | M40: 2 | N40: =M40*2*H40/1000 -> 0.064 | O40: =(D40+C40+F40)-N40 -> 30.471 | P40: =(I40*J40*O40)+L40 -> 92.981 | Q40: =IF($H40=8,$P40,"") | R40: =IF($H40=10,$P40,"") | S40: =IF($H40=12,$P40,"") | T40: =IF($H40=16,$P40,"") -> 92.981 | U40: =IF($H40=20,$P40,"") | V40: =IF($H40=25,$P40,"")
Q41: =IF($H41=8,$P41,"") | R41: =IF($H41=10,$P41,"") | S41: =IF($H41=12,$P41,"") | T41: =IF($H41=16,$P41,"") | U41: =IF($H41=20,$P41,"") | V41: =IF($H41=25,$P41,"")
A42: 7 | B42: GRID (22'-26'/B-Q') | Q42: =IF($H42=8,$P42,"") | R42: =IF($H42=10,$P42,"") | S42: =IF($H42=12,$P42,"") | T42: =IF($H42=16,$P42,"") | U42: =IF($H42=20,$P42,"") | V42: =IF($H42=25,$P42,"")
B43: MAIN BAR BOTTOM (ALTH.) | C43: 0.5 | D43: =15.8-2*0.05 -> 15.7 | F43: 0.5 | G43: 0.25 | H43: 16 | I43: 1 | J43: =ROUND(11.285/G43+1,0) -> 46 | K43: =D43 -> 15.7 | L43: =IF(O43<12,"0",0.049*H43) -> 0.784 | M43: 2 | N43: =M43*2*H43/1000 -> 0.064 | O43: =(D43+C43+F43)-N43 -> 16.636 | P43: =(I43*J43*O43)+L43 -> 766.04 | Q43: =IF($H43=8,$P43,"") | R43: =IF($H43=10,$P43,"") | S43: =IF($H43=12,$P43,"") | T43: =IF($H43=16,$P43,"") -> 766.04 | U43: =IF($H43=20,$P43,"") | V43: =IF($H43=25,$P43,"")
Q44: =IF($H44=8,$P44,"") | R44: =IF($H44=10,$P44,"") | S44: =IF($H44=12,$P44,"") | T44: =IF($H44=16,$P44,"") | U44: =IF($H44=20,$P44,"") | V44: =IF($H44=25,$P44,"")
Q45: =IF($H45=8,$P45,"") | R45: =IF($H45=10,$P45,"") | S45: =IF($H45=12,$P45,"") | T45: =IF($H45=16,$P45,"") | U45: =IF($H45=20,$P45,"") | V45: =IF($H45=25,$P45,"")
B46: BOTTOM DISTRIBUTION BAR | Q46: =IF($H46=8,$P46,"") | R46: =IF($H46=10,$P46,"") | S46: =IF($H46=12,$P46,"") | T46: =IF($H46=16,$P46,"") | U46: =IF($H46=20,$P46,"") | V46: =IF($H46=25,$P46,"")
A47: 1 | B47: GRID (30-38'/A) | Q47: =IF($H47=8,$P47,"") | R47: =IF($H47=10,$P47,"") | S47: =IF($H47=12,$P47,"") | T47: =IF($H47=16,$P47,"") | U47: =IF($H47=20,$P47,"") | V47: =IF($H47=25,$P47,"")
B48: DIST. BAR BOTTOM (ALTH.) | C48: 0.5 | D48: =8.875-2*0.05 -> 8.775 | F48: 0.5 | G48: 0.25 | H48: 16 | I48: 1 | J48: =ROUND(1.5/G48+1,0) -> 7 | K48: =D48 -> 8.775 | L48: =IF(O48<12,"0",0.049*H48) -> 0 | M48: 2 | N48: =M48*2*H48/1000 -> 0.064 | O48: =(D48+C48+F48)-N48 -> 9.711 | P48: =(I48*J48*O48)+L48 -> 67.977 | Q48: =IF($H48=8,$P48,"") | R48: =IF($H48=10,$P48,"") | S48: =IF($H48=12,$P48,"") | T48: =IF($H48=16,$P48,"") -> 67.977 | U48: =IF($H48=20,$P48,"") | V48: =IF($H48=25,$P48,"")
Q49: =IF($H49=8,$P49,"") | R49: =IF($H49=10,$P49,"") | S49: =IF($H49=12,$P49,"") | T49: =IF($H49=16,$P49,"") | U49: =IF($H49=20,$P49,"") | V49: =IF($H49=25,$P49,"")
A50: 2 | B50: GRID (27'-38'/A-B) | Q50: =IF($H50=8,$P50,"") | R50: =IF($H50=10,$P50,"") | S50: =IF($H50=12,$P50,"") | T50: =IF($H50=16,$P50,"") | U50: =IF($H50=20,$P50,"") | V50: =IF($H50=25,$P50,"")
B51: DIST. BAR BOTTOM (ALTH.) | C51: 0.5 | D51: =12.825-2*0.05 -> 12.725 | F51: 0.5 | G51: 0.25 | H51: 16 | I51: 1 | J51: =ROUND(0.815/G51+1,0) -> 4 | K51: =D51 -> 12.725 | L51: =IF(O51<12,"0",0.049*H51) -> 0.784 | M51: 2 | N51: =M51*2*H51/1000 -> 0.064 | O51: =(D51+C51+F51)-N51 -> 13.661 | P51: =(I51*J51*O51)+L51 -> 55.428 | Q51: =IF($H51=8,$P51,"") | R51: =IF($H51=10,$P51,"") | S51: =IF($H51=12,$P51,"") | T51: =IF($H51=16,$P51,"") -> 55.428 | U51: =IF($H51=20,$P51,"") | V51: =IF($H51=25,$P51,"")
Q52: =IF($H52=8,$P52,"") | R52: =IF($H52=10,$P52,"") | S52: =IF($H52=12,$P52,"") | T52: =IF($H52=16,$P52,"") | U52: =IF($H52=20,$P52,"") | V52: =IF($H52=25,$P52,"")
A53: 3 | B53: GRID (26'-38'/B-B') | Q53: =IF($H53=8,$P53,"") | R53: =IF($H53=10,$P53,"") | S53: =IF($H53=12,$P53,"") | T53: =IF($H53=16,$P53,"") | U53: =IF($H53=20,$P53,"") | V53: =IF($H53=25,$P53,"")
B54: DIST. BAR BOTTOM (ALTH.) | C54: 0.5 | D54: =14.52-2*0.05 -> 14.42 | F54: 0.5 | G54: 0.25 | H54: 16 | I54: 1 | J54: =ROUND(1.405/G54+1,0) -> 7 | K54: =D54 -> 14.42 | L54: =IF(O54<12,"0",0.049*H54) -> 0.784 | M54: 2 | N54: =M54*2*H54/1000 -> 0.064 | O54: =(D54+C54+F54)-N54 -> 15.356 | P54: =(I54*J54*O54)+L54 -> 108.276 | Q54: =IF($H54=8,$P54,"") | R54: =IF($H54=10,$P54,"") | S54: =IF($H54=12,$P54,"") | T54: =IF($H54=16,$P54,"") -> 108.276 | U54: =IF($H54=20,$P54,"") | V54: =IF($H54=25,$P54,"")
Q55: =IF($H55=8,$P55,"") | R55: =IF($H55=10,$P55,"") | S55: =IF($H55=12,$P55,"") | T55: =IF($H55=16,$P55,"") | U55: =IF($H55=20,$P55,"") | V55: =IF($H55=25,$P55,"")
A56: 4 | B56: GRID (22'-38'/B'-E') | Q56: =IF($H56=8,$P56,"") | R56: =IF($H56=10,$P56,"") | S56: =IF($H56=12,$P56,"") | T56: =IF($H56=16,$P56,"") | U56: =IF($H56=20,$P56,"") | V56: =IF($H56=25,$P56,"")
B57: DIST. BAR BOTTOM (ALTH.) | D57: =25.805-1*0.05 -> 25.755 | F57: 0.5 | G57: 0.25 | H57: 16 | I57: 1 | J57: =ROUND(6.565/G57+1,0) -> 27 | K57: =D57 -> 25.755 | L57: =IF(O57<12,"0",0.049*H57)*2 -> 1.568 | M57: 1 | N57: =M57*1*H57/1000 -> 0.016 | O57: =(D57+C57+F57)-N57 -> 26.239 | P57: =(I57*J57*O57)+L57 -> 710.021 | Q57: =IF($H57=8,$P57,"") | R57: =IF($H57=10,$P57,"") | S57: =IF($H57=12,$P57,"") | T57: =IF($H57=16,$P57,"") -> 710.021 | U57: =IF($H57=20,$P57,"") | V57: =IF($H57=25,$P57,"")
Q58: =IF($H58=8,$P58,"") | R58: =IF($H58=10,$P58,"") | S58: =IF($H58=12,$P58,"") | T58: =IF($H58=16,$P58,"") | U58: =IF($H58=20,$P58,"") | V58: =IF($H58=25,$P58,"")
A59: 5 | B59: GRID (22'-43'/E'-K) | Q59: =IF($H59=8,$P59,"") | R59: =IF($H59=10,$P59,"") | S59: =IF($H59=12,$P59,"") | T59: =IF($H59=16,$P59,"") | U59: =IF($H59=20,$P59,"") | V59: =IF($H59=25,$P59,"")
B60: DIST. BAR BOTTOM (ALTH.) | D60: =36.89-1*0.05 -> 36.84 | F60: 0.5 | G60: 0.25 | H60: 16 | I60: 1 | J60: =ROUND(9.235/G60+1,0)-8 -> 30 | K60: =D60 -> 36.84 | L60: =IF(O60<12,"0",0.049*H60)*3 -> 2.352 | M60: 1 | N60: =M60*1*H60/1000 -> 0.016 | O60: =(D60+C60+F60)-N60 -> 37.324 | P60: =(I60*J60*O60)+L60 -> 1122.072 | Q60: =IF($H60=8,$P60,"") | R60: =IF($H60=10,$P60,"") | S60: =IF($H60=12,$P60,"") | T60: =IF($H60=16,$P60,"") -> 1122.072 | U60: =IF($H60=20,$P60,"") | V60: =IF($H60=25,$P60,"")
Q61: =IF($H61=8,$P61,"") | R61: =IF($H61=10,$P61,"") | S61: =IF($H61=12,$P61,"") | T61: =IF($H61=16,$P61,"") | U61: =IF($H61=20,$P61,"") | V61: =IF($H61=25,$P61,"")
A62: 6 | B62: GRID (26'-43'/M-Q) | Q62: =IF($H62=8,$P62,"") | R62: =IF($H62=10,$P62,"") | S62: =IF($H62=12,$P62,"") | T62: =IF($H62=16,$P62,"") | U62: =IF($H62=20,$P62,"") | V62: =IF($H62=25,$P62,"")
B63: DIST. BAR BOTTOM (ALTH.) | C63: 0.5 | D63: =25.89-2*0.05 -> 25.79 | F63: 0.5 | G63: 0.25 | H63: 16 | I63: 1 | J63: =ROUND(12.415/G63+1,0) -> 51 | K63: =D63 -> 25.79 | L63: =IF(O63<12,"0",0.049*H63)*2 -> 1.568 | M63: 2 | N63: =M63*2*H63/1000 -> 0.064 | O63: =(D63+C63+F63)-N63 -> 26.726 | P63: =(I63*J63*O63)+L63 -> 1364.594 | Q63: =IF($H63=8,$P63,"") | R63: =IF($H63=10,$P63,"") | S63: =IF($H63=12,$P63,"") | T63: =IF($H63=16,$P63,"") -> 1364.594 | U63: =IF($H63=20,$P63,"") | V63: =IF($H63=25,$P63,"")
Q64: =IF($H64=8,$P64,"") | R64: =IF($H64=10,$P64,"") | S64: =IF($H64=12,$P64,"") | T64: =IF($H64=16,$P64,"") | U64: =IF($H64=20,$P64,"") | V64: =IF($H64=25,$P64,"")
A65: 7 | B65: GRID (33-39/Q') | Q65: =IF($H65=8,$P65,"") | R65: =IF($H65=10,$P65,"") | S65: =IF($H65=12,$P65,"") | T65: =IF($H65=16,$P65,"") | U65: =IF($H65=20,$P65,"") | V65: =IF($H65=25,$P65,"")
B66: DIST. BAR BOTTOM (ALTH.) | C66: 0.5 | D66: =8.78-2*0.05 -> 8.68 | F66: 0.5 | G66: 0.25 | H66: 16 | I66: 1 | J66: =ROUND(0.515/G66+1,0) -> 3 | K66: =D66 -> 8.68 | L66: =IF(O66<12,"0",0.049*H66) -> 0 | M66: 2 | N66: =M66*2*H66/1000 -> 0.064 | O66: =(D66+C66+F66)-N66 -> 9.616 | P66: =(I66*J66*O66)+L66 -> 28.848 | Q66: =IF($H66=8,$P66,"") | R66: =IF($H66=10,$P66,"") | S66: =IF($H66=12,$P66,"") | T66: =IF($H66=16,$P66,"") -> 28.848 | U66: =IF($H66=20,$P66,"") | V66: =IF($H66=25,$P66,"")
Q67: =IF($H67=8,$P67,"") | R67: =IF($H67=10,$P67,"") | S67: =IF($H67=12,$P67,"") | T67: =IF($H67=16,$P67,"") | U67: =IF($H67=20,$P67,"") | V67: =IF($H67=25,$P67,"")
Q68: =IF($H68=8,$P68,"") | R68: =IF($H68=10,$P68,"") | S68: =IF($H68=12,$P68,"") | T68: =IF($H68=16,$P68,"") | U68: =IF($H68=20,$P68,"") | V68: =IF($H68=25,$P68,"")
B69: TOP MAIN BAR | Q69: =IF($H69=8,$P69,"") | R69: =IF($H69=10,$P69,"") | S69: =IF($H69=12,$P69,"") | T69: =IF($H69=16,$P69,"") | U69: =IF($H69=20,$P69,"") | V69: =IF($H69=25,$P69,"")
A70: 1 | B70: GRID (39'-43/E'-Q') | Q70: =IF($H70=8,$P70,"") | R70: =IF($H70=10,$P70,"") | S70: =IF($H70=12,$P70,"") | T70: =IF($H70=16,$P70,"") | U70: =IF($H70=20,$P70,"") | V70: =IF($H70=25,$P70,"")
B71: MAIN BAR BOTTOM (ALTH.) | C71: 0.5 | D71: =21.65-2*0.05 -> 21.55 | F71: 0.5 | G71: 0.25 | H71: 16 | I71: 1 | J71: =ROUND(8.855/G71/2+1,0) -> 19 | K71: =D71 -> 21.55 | L71: =IF(O71<12,"0",0.049*H71)*2 -> 1.568 | M71: 2 | N71: =M71*2*H71/1000 -> 0.064 | O71: =(D71+C71+F71)-N71 -> 22.486 | P71: =(I71*J71*O71)+L71 -> 428.802 | Q71: =IF($H71=8,$P71,"") | R71: =IF($H71=10,$P71,"") | S71: =IF($H71=12,$P71,"") | T71: =IF($H71=16,$P71,"") -> 428.802 | U71: =IF($H71=20,$P71,"") | V71: =IF($H71=25,$P71,"")
Q72: =IF($H72=8,$P72,"") | R72: =IF($H72=10,$P72,"") | S72: =IF($H72=12,$P72,"") | T72: =IF($H72=16,$P72,"") | U72: =IF($H72=20,$P72,"") | V72: =IF($H72=25,$P72,"")
A73: 1 | B73: GRID (39'-43/E'-Q') | Q73: =IF($H73=8,$P73,"") | R73: =IF($H73=10,$P73,"") | S73: =IF($H73=12,$P73,"") | T73: =IF($H73=16,$P73,"") | U73: =IF($H73=20,$P73,"") | V73: =IF($H73=25,$P73,"")
B74: MAIN BAR BOTTOM (ALTH.) | C74: 0.5 | D74: =21.65-2*0.05 -> 21.55 | F74: 0.5 | G74: 0.25 | H74: 16 | I74: 1 | J74: =ROUND(8.855/G74/2,0) -> 18 | K74: =D74 -> 21.55 | L74: =IF(O74<12,"0",0.049*H74) -> 0.784 | M74: 2 | N74: =M74*2*H74/1000 -> 0.064 | O74: =(D74+C74+F74)-N74 -> 22.486 | P74: =(I74*J74*O74)+L74 -> 405.532 | Q74: =IF($H74=8,$P74,"") | R74: =IF($H74=10,$P74,"") | S74: =IF($H74=12,$P74,"") | T74: =IF($H74=16,$P74,"") -> 405.532 | U74: =IF($H74=20,$P74,"") | V74: =IF($H74=25,$P74,"")
Q75: =IF($H75=8,$P75,"") | R75: =IF($H75=10,$P75,"") | S75: =IF($H75=12,$P75,"") | T75: =IF($H75=16,$P75,"") | U75: =IF($H75=20,$P75,"") | V75: =IF($H75=25,$P75,"")
A76: 2 | B76: GRID (38'-39'/E'-Q') | Q76: =IF($H76=8,$P76,"") | R76: =IF($H76=10,$P76,"") | S76: =IF($H76=12,$P76,"") | T76: =IF($H76=16,$P76,"") | U76: =IF($H76=20,$P76,"") | V76: =IF($H76=25,$P76,"")
B77: MAIN BAR BOTTOM (ALTH.) | C77: 0.5 | D77: =21.65+0.515-2*0.05 -> 22.065 | F77: 0.5 | G77: 0.25 | H77: 16 | I77: 1 | J77: =ROUND(2.535/G77/2+1,0) -> 6 | K77: =D77 -> 22.065 | L77: =IF(O77<12,"0",0.049*H77)*2 -> 1.568 | M77: 2 | N77: =M77*2*H77/1000 -> 0.064 | O77: =(D77+C77+F77)-N77 -> 23.001 | P77: =(I77*J77*O77)+L77 -> 139.574 | Q77: =IF($H77=8,$P77,"") | R77: =IF($H77=10,$P77,"") | S77: =IF($H77=12,$P77,"") | T77: =IF($H77=16,$P77,"") -> 139.574 | U77: =IF($H77=20,$P77,"") | V77: =IF($H77=25,$P77,"")
Q78: =IF($H78=8,$P78,"") | R78: =IF($H78=10,$P78,"") | S78: =IF($H78=12,$P78,"") | T78: =IF($H78=16,$P78,"") | U78: =IF($H78=20,$P78,"") | V78: =IF($H78=25,$P78,"")
A79: 2 | B79: GRID (38'-39'/E'-Q') | Q79: =IF($H79=8,$P79,"") | R79: =IF($H79=10,$P79,"") | S79: =IF($H79=12,$P79,"") | T79: =IF($H79=16,$P79,"") | U79: =IF($H79=20,$P79,"") | V79: =IF($H79=25,$P79,"")
B80: MAIN BAR BOTTOM (ALTH.) | C80: 0.5 | D80: =21.65+0.515-2*0.05 -> 22.065 | F80: 0.5 | G80: 0.25 | H80: 16 | I80: 1 | J80: =ROUND(2.535/G80/2,0) -> 5 | K80: =D80 -> 22.065 | L80: =IF(O80<12,"0",0.049*H80) -> 0.784 | M80: 2 | N80: =M80*2*H80/1000 -> 0.064 | O80: =(D80+C80+F80)-N80 -> 23.001 | P80: =(I80*J80*O80)+L80 -> 115.789 | Q80: =IF($H80=8,$P80,"") | R80: =IF($H80=10,$P80,"") | S80: =IF($H80=12,$P80,"") | T80: =IF($H80=16,$P80,"") -> 115.789 | U80: =IF($H80=20,$P80,"") | V80: =IF($H80=25,$P80,"")
Q81: =IF($H81=8,$P81,"") | R81: =IF($H81=10,$P81,"") | S81: =IF($H81=12,$P81,"") | T81: =IF($H81=16,$P81,"") | U81: =IF($H81=20,$P81,"") | V81: =IF($H81=25,$P81,"")
A82: 3 | B82: GRID (32'-38'/A-Q') | Q82: =IF($H82=8,$P82,"") | R82: =IF($H82=10,$P82,"") | S82: =IF($H82=12,$P82,"") | T82: =IF($H82=16,$P82,"") | U82: =IF($H82=20,$P82,"") | V82: =IF($H82=25,$P82,"")
B83: MAIN BAR BOTTOM (ALTH.) | C83: 0.5 | D83: =32.45-2*0.05 -> 32.35 | F83: 0.5 | G83: 0.25 | H83: 16 | I83: 1 | J83: =ROUND(6.245/G83/2+1,0) -> 13 | K83: =D83 -> 32.35 | L83: =IF(O83<12,"0",0.049*H83)*3 -> 2.352 | M83: 2 | N83: =M83*2*H83/1000 -> 0.064 | O83: =(D83+C83+F83)-N83 -> 33.286 | P83: =(I83*J83*O83)+L83 -> 435.07 | Q83: =IF($H83=8,$P83,"") | R83: =IF($H83=10,$P83,"") | S83: =IF($H83=12,$P83,"") | T83: =IF($H83=16,$P83,"") -> 435.07 | U83: =IF($H83=20,$P83,"") | V83: =IF($H83=25,$P83,"")
Q84: =IF($H84=8,$P84,"") | R84: =IF($H84=10,$P84,"") | S84: =IF($H84=12,$P84,"") | T84: =IF($H84=16,$P84,"") | U84: =IF($H84=20,$P84,"") | V84: =IF($H84=25,$P84,"")
A85: 3 | B85: GRID (32'-38'/A-Q') | Q85: =IF($H85=8,$P85,"") | R85: =IF($H85=10,$P85,"") | S85: =IF($H85=12,$P85,"") | T85: =IF($H85=16,$P85,"") | U85: =IF($H85=20,$P85,"") | V85: =IF($H85=25,$P85,"")
B86: MAIN BAR BOTTOM (ALTH.) | C86: 0.5 | D86: =32.45-2*0.05 -> 32.35 | F86: 0.5 | G86: 0.25 | H86: 16 | I86: 1 | J86: =ROUND(6.245/G86/2,0) -> 12 | K86: =D86 -> 32.35 | L86: =IF(O86<12,"0",0.049*H86)*2 -> 1.568 | M86: 2 | N86: =M86*2*H86/1000 -> 0.064 | O86: =(D86+C86+F86)-N86 -> 33.286 | P86: =(I86*J86*O86)+L86 -> 401 | Q86: =IF($H86=8,$P86,"") | R86: =IF($H86=10,$P86,"") | S86: =IF($H86=12,$P86,"") | T86: =IF($H86=16,$P86,"") -> 401 | U86: =IF($H86=20,$P86,"") | V86: =IF($H86=25,$P86,"")
Q87: =IF($H87=8,$P87,"") | R87: =IF($H87=10,$P87,"") | S87: =IF($H87=12,$P87,"") | T87: =IF($H87=16,$P87,"") | U87: =IF($H87=20,$P87,"") | V87: =IF($H87=25,$P87,"")
A88: 4 | B88: GRID (30'-32'/A-Q') | Q88: =IF($H88=8,$P88,"") | R88: =IF($H88=10,$P88,"") | S88: =IF($H88=12,$P88,"") | T88: =IF($H88=16,$P88,"") | U88: =IF($H88=20,$P88,"") | V88: =IF($H88=25,$P88,"")
B89: MAIN BAR BOTTOM (ALTH.) | C89: 0.5 | D89: =31.935-2*0.05 -> 31.835 | F89: 0.5 | G89: 0.25 | H89: 16 | I89: 1 | J89: =ROUND(2.63/G89/2+1,0) -> 6 | K89: =D89 -> 31.835 | L89: =IF(O89<12,"0",0.049*H89)*3 -> 2.352 | M89: 2 | N89: =M89*2*H89/1000 -> 0.064 | O89: =(D89+C89+F89)-N89 -> 32.771 | P89: =(I89*J89*O89)+L89 -> 198.978 | Q89: =IF($H89=8,$P89,"") | R89: =IF($H89=10,$P89,"") | S89: =IF($H89=12,$P89,"") | T89: =IF($H89=16,$P89,"") -> 198.978 | U89: =IF($H89=20,$P89,"") | V89: =IF($H89=25,$P89,"")
Q90: =IF($H90=8,$P90,"") | R90: =IF($H90=10,$P90,"") | S90: =IF($H90=12,$P90,"") | T90: =IF($H90=16,$P90,"") | U90: =IF($H90=20,$P90,"") | V90: =IF($H90=25,$P90,"")
A91: 4 | B91: GRID (30'-32'/A-Q') | Q91: =IF($H91=8,$P91,"") | R91: =IF($H91=10,$P91,"") | S91: =IF($H91=12,$P91,"") | T91: =IF($H91=16,$P91,"") | U91: =IF($H91=20,$P91,"") | V91: =IF($H91=25,$P91,"")
B92: MAIN BAR BOTTOM (ALTH.) | C92: 0.5 | D92: =31.935-2*0.05 -> 31.835 | F92: 0.5 | G92: 0.25 | H92: 16 | I92: 1 | J92: =ROUND(2.63/G92/2,0) -> 5 | K92: =D92 -> 31.835 | L92: =IF(O92<12,"0",0.049*H92)*2 -> 1.568 | M92: 2 | N92: =M92*2*H92/1000 -> 0.064 | O92: =(D92+C92+F92)-N92 -> 32.771 | P92: =(I92*J92*O92)+L92 -> 165.423 | Q92: =IF($H92=8,$P92,"") | R92: =IF($H92=10,$P92,"") | S92: =IF($H92=12,$P92,"") | T92: =IF($H92=16,$P92,"") -> 165.423 | U92: =IF($H92=20,$P92,"") | V92: =IF($H92=25,$P92,"")
Q93: =IF($H93=8,$P93,"") | R93: =IF($H93=10,$P93,"") | S93: =IF($H93=12,$P93,"") | T93: =IF($H93=16,$P93,"") | U93: =IF($H93=20,$P93,"") | V93: =IF($H93=25,$P93,"")
A94: 5 | B94: GRID (27'-30/A-Q') | Q94: =IF($H94=8,$P94,"") | R94: =IF($H94=10,$P94,"") | S94: =IF($H94=12,$P94,"") | T94: =IF($H94=16,$P94,"") | U94: =IF($H94=20,$P94,"") | V94: =IF($H94=25,$P94,"")
B95: MAIN BAR BOTTOM (ALTH.) | C95: 0.5 | D95: =31.95-2*0.05-1.5 -> 30.35 | F95: 0.5 | G95: 0.25 | H95: 16 | I95: 1 | J95: =ROUND(3.95/G95/2+1,0) -> 9 | K95: =D95 -> 30.35 | L95: =IF(O95<12,"0",0.049*H95)*3 -> 2.352 | M95: 2 | N95: =M95*2*H95/1000 -> 0.064 | O95: =(D95+C95+F95)-N95 -> 31.286 | P95: =(I95*J95*O95)+L95 -> 283.926 | Q95: =IF($H95=8,$P95,"") | R95: =IF($H95=10,$P95,"") | S95: =IF($H95=12,$P95,"") | T95: =IF($H95=16,$P95,"") -> 283.926 | U95: =IF($H95=20,$P95,"") | V95: =IF($H95=25,$P95,"")
Q96: =IF($H96=8,$P96,"") | R96: =IF($H96=10,$P96,"") | S96: =IF($H96=12,$P96,"") | T96: =IF($H96=16,$P96,"") | U96: =IF($H96=20,$P96,"") | V96: =IF($H96=25,$P96,"")
A97: 5 | B97: GRID (27'-30/A-Q') | Q97: =IF($H97=8,$P97,"") | R97: =IF($H97=10,$P97,"") | S97: =IF($H97=12,$P97,"") | T97: =IF($H97=16,$P97,"") | U97: =IF($H97=20,$P97,"") | V97: =IF($H97=25,$P97,"")
B98: MAIN BAR BOTTOM (ALTH.) | C98: 0.5 | D98: =31.95-2*0.05-1.5 -> 30.35 | F98: 0.5 | G98: 0.25 | H98: 16 | I98: 1 | J98: =ROUND(3.95/G98/2,0) -> 8 | K98: =D98 -> 30.35 | L98: =IF(O98<12,"0",0.049*H98)*2 -> 1.568 | M98: 2 | N98: =M98*2*H98/1000 -> 0.064 | O98: =(D98+C98+F98)-N98 -> 31.286 | P98: =(I98*J98*O98)+L98 -> 251.856 | Q98: =IF($H98=8,$P98,"") | R98: =IF($H98=10,$P98,"") | S98: =IF($H98=12,$P98,"") | T98: =IF($H98=16,$P98,"") -> 251.856 | U98: =IF($H98=20,$P98,"") | V98: =IF($H98=25,$P98,"")
Q99: =IF($H99=8,$P99,"") | R99: =IF($H99=10,$P99,"") | S99: =IF($H99=12,$P99,"") | T99: =IF($H99=16,$P99,"") | U99: =IF($H99=20,$P99,"") | V99: =IF($H99=25,$P99,"")
A100: 6 | B100: GRID (26'-27'/A'-Q') | Q100: =IF($H100=8,$P100,"") | R100: =IF($H100=10,$P100,"") | S100: =IF($H100=12,$P100,"") | T100: =IF($H100=16,$P100,"") | U100: =IF($H100=20,$P100,"") | V100: =IF($H100=25,$P100,"")
B101: MAIN BAR BOTTOM (ALTH.) | C101: 0.5 | D101: =31.95-2*0.05-1.5-0.815 -> 29.535 | F101: 0.5 | G101: 0.25 | H101: 16 | I101: 1 | J101: =ROUND(1.695/G101/2+1,0) -> 4 | K101: =D101 -> 29.535 | L101: =IF(O101<12,"0",0.049*H101)*3 -> 2.352 | M101: 2 | N101: =M101*2*H101/1000 -> 0.064 | O101: =(D101+C101+F101)-N101 -> 30.471 | P101: =(I101*J101*O101)+L101 -> 124.236 | Q101: =IF($H101=8,$P101,"") | R101: =IF($H101=10,$P101,"") | S101: =IF($H101=12,$P101,"") | T101: =IF($H101=16,$P101,"") -> 124.236 | U101: =IF($H101=20,$P101,"") | V101: =IF($H101=25,$P101,"")
...

Sheet COLUMN BBS
A1: TOWER-E COLUMN FOUNDATION BBS (BELOW PLINTH BEAM)
A3: S.No. | B3: Description | C3: Shape of Bar in mm | F3: Spacing c/c | G3: Dia of Bar | H3: Nos of Columns | I3: Nos of Bar | J3: Actual Length | K3: Lap | L3: No. Of Bend | M3: Deduction | N3: Cut Length | O3: Total Length | P3: TMT BAR Fe-500D or EQR | V3: Remarks
P4: 8mm | Q4: 10mm | R4: 12mm | S4: 16mm | T4: 20mm | U4: 25mm
P5: =IF($G5=8,$O5,"") | Q5: =IF($G5=10,$O5,"") | R5: =IF($G5=12,$O5,"") | S5: =IF($G5=16,$O5,"") | T5: =IF($G5=20,$O5,"") | U5: =IF($G5=25,$O5,"")
A6: 1 | B6: Column C1 (300x600) | P6: =IF($G6=8,$O6,"") | Q6: =IF($G6=10,$O6,"") | R6: =IF($G6=12,$O6,"") | S6: =IF($G6=16,$O6,"") | T6: =IF($G6=20,$O6,"") | U6: =IF($G6=25,$O6,"")
B7: VERTICAL BARS A | D7: =0.85-0.075-2*0.016 -> 0.743 | G7: 16 | H7: 16 | I7: 4 | J7: =D7 -> 0.743 | K7: =IF(N7<12,"0",0.049*G7) -> 0 | L7: 1 | M7: =2*G7*L7/1000 -> 0.032 | N7: =J7+E9-M7 -> 1.011 | O7: =H7*I7*N7 -> 64.704 | P7: =IF($G7=8,$O7,"") | Q7: =IF($G7=10,$O7,"") | R7: =IF($G7=12,$O7,"") | S7: =IF($G7=16,$O7,"") -> 64.704 | T7: =IF($G7=20,$O7,"") | U7: =IF($G7=25,$O7,"")
B8: VERTICAL BARS B | G8: 12 | H8: 16 | I8: 2 | J8: =D7 -> 0.743 | K8: =IF(N8<12,"0",0.049*G8) -> 0 | L8: 1 | M8: =2*G8*L8/1000 -> 0.024 | N8: =J8+E9-M8 -> 1.019 | O8: =H8*I8*N8 -> 32.608 | P8: =IF($G8=8,$O8,"") | Q8: =IF($G8=10,$O8,"") | R8: =IF($G8=12,$O8,"") -> 32.608 | S8: =IF($G8=16,$O8,"") | T8: =IF($G8=20,$O8,"") | U8: =IF($G8=25,$O8,"")
B9: VERTICAL BARS C | E9: 0.3 | G9: 16 | H9: 16 | I9: 4 | J9: =D7 -> 0.743 | K9: =IF(N9<12,"0",0.049*G9) -> 0 | L9: 1 | M9: =2*G9*L9/1000 -> 0.032 | N9: =J9+E9-M9 -> 1.011 | O9: =H9*I9*N9 -> 64.704 | P9: =IF($G9=8,$O9,"") | Q9: =IF($G9=10,$O9,"") | R9: =IF($G9=12,$O9,"") | S9: =IF($G9=16,$O9,"") -> 64.704 | T9: =IF($G9=20,$O9,"") | U9: =IF($G9=25,$O9,"")
B10: VERTICAL BARS D | G10: 12 | H10: 16 | I10: 4 | J10: =D7 -> 0.743 | K10: =IF(N10<12,"0",0.049*G10) -> 0 | L10: 1 | M10: =2*G10*L10/1000 -> 0.024 | N10: =J10+E9-M10 -> 1.019 | O10: =H10*I10*N10 -> 65.216 | P10: =IF($G10=8,$O10,"") | Q10: =IF($G10=10,$O10,"") | R10: =IF($G10=12,$O10,"") -> 65.216 | S10: =IF($G10=16,$O10,"") | T10: =IF($G10=20,$O10,"") | U10: =IF($G10=25,$O10,"")
P11: =IF($G11=8,$O11,"") | Q11: =IF($G11=10,$O11,"") | R11: =IF($G11=12,$O11,"") | S11: =IF($G11=16,$O11,"") | T11: =IF($G11=20,$O11,"") | U11: =IF($G11=25,$O11,"")
C12: 0.08 | P12: =IF($G12=8,$O12,"") | Q12: =IF($G12=10,$O12,"") | R12: =IF($G12=12,$O12,"") | S12: =IF($G12=16,$O12,"") | T12: =IF($G12=20,$O12,"") | U12: =IF($G12=25,$O12,"")
B13: Stirupps a | E13: =0.6-0.08 -> 0.52 | G13: 10 | H13: 16 | I13: 4 | J13: =2*(D15+E13)+2*8*G13/1000 -> 1.64 | L13: 5 | M13: =2*G13*L13/1000 -> 0.1 | N13: =(J13+K13-M13)+0.02 -> 1.56 | O13: =(H13*I13*N13) -> 99.84 | P13: =IF($G13=8,$O13,"") | Q13: =IF($G13=10,$O13,"") -> 99.84 | R13: =IF($G13=12,$O13,"") | S13: =IF($G13=16,$O13,"") | T13: =IF($G13=20,$O13,"") | U13: =IF($G13=25,$O13,"")
P14: =IF($G14=8,$O14,"") | Q14: =IF($G14=10,$O14,"") | R14: =IF($G14=12,$O14,"") | S14: =IF($G14=16,$O14,"") | T14: =IF($G14=20,$O14,"") | U14: =IF($G14=25,$O14,"")
D15: =0.3-0.08 -> 0.22 | P15: =IF($G15=8,$O15,"") | Q15: =IF($G15=10,$O15,"") | R15: =IF($G15=12,$O15,"") | S15: =IF($G15=16,$O15,"") | T15: =IF($G15=20,$O15,"") | U15: =IF($G15=25,$O15,"")
P16: =IF($G16=8,$O16,"") | Q16: =IF($G16=10,$O16,"") | R16: =IF($G16=12,$O16,"") | S16: =IF($G16=16,$O16,"") | T16: =IF($G16=20,$O16,"") | U16: =IF($G16=25,$O16,"")
C17: 0.08 | P17: =IF($G17=8,$O17,"") | Q17: =IF($G17=10,$O17,"") | R17: =IF($G17=12,$O17,"") | S17: =IF($G17=16,$O17,"") | T17: =IF($G17=20,$O17,"") | U17: =IF($G17=25,$O17,"")
B18: Stirupps b | E18: =((0.6-0.08-0.016)/5)+0.012+0.02 -> 0.1328 | G18: 10 | H18: 16 | I18: 1 | J18: =2*(D20+E18)+2*8*G18/1000 -> 0.8656 | L18: 5 | M18: =2*G18*L18/1000 -> 0.1 | N18: =(J18+K18-M18)+0.02 -> 0.7856 | O18: =(H18*I18*N18) -> 12.5696 | P18: =IF($G18=8,$O18,"") | Q18: =IF($G18=10,$O18,"") -> 12.5696 | R18: =IF($G18=12,$O18,"") | S18: =IF($G18=16,$O18,"") | T18: =IF($G18=20,$O18,"") | U18: =IF($G18=25,$O18,"")
P19: =IF($G19=8,$O19,"") | Q19: =IF($G19=10,$O19,"") | R19: =IF($G19=12,$O19,"") | S19: =IF($G19=16,$O19,"") | T19: =IF($G19=20,$O19,"") | U19: =IF($G19=25,$O19,"")
D20: =0.3-0.08 -> 0.22 | P20: =IF($G20=8,$O20,"") | Q20: =IF($G20=10,$O20,"") | R20: =IF($G20=12,$O20,"") | S20: =IF($G20=16,$O20,"") | T20: =IF($G20=20,$O20,"") | U20: =IF($G20=25,$O20,"")
P21: =IF($G21=8,$O21,"") | Q21: =IF($G21=10,$O21,"") | R21: =IF($G21=12,$O21,"") | S21: =IF($G21=16,$O21,"") | T21: =IF($G21=20,$O21,"") | U21: =IF($G21=25,$O21,"")
B22: Stirupps c | G22: 10 | H22: 16 | I22: 1 | J22: =C23+D25+E23+2*8*G22/1000 -> 0.73 | L22: 4 | M22: =2*G22*L22/1000 -> 0.08 | N22: =(J22+K22-M22) -> 0.65 | O22: =(H22*I22*N22) -> 10.4 | P22: =IF($G22=8,$O22,"") | Q22: =IF($G22=10,$O22,"") -> 10.4 | R22: =IF($G22=12,$O22,"") | S22: =IF($G22=16,$O22,"") | T22: =IF($G22=20,$O22,"") | U22: =IF($G22=25,$O22,"")
C23: 0.175 | E23: 0.175 | P23: =IF($G23=8,$O23,"") | Q23: =IF($G23=10,$O23,"") | R23: =IF($G23=12,$O23,"") | S23: =IF($G23=16,$O23,"") | T23: =IF($G23=20,$O23,"") | U23: =IF($G23=25,$O23,"")
P24: =IF($G24=8,$O24,"") | Q24: =IF($G24=10,$O24,"") | R24: =IF($G24=12,$O24,"") | S24: =IF($G24=16,$O24,"") | T24: =IF($G24=20,$O24,"") | U24: =IF($G24=25,$O24,"")
D25: =0.3-0.08 -> 0.22 | P25: =IF($G25=8,$O25,"") | Q25: =IF($G25=10,$O25,"") | R25: =IF($G25=12,$O25,"") | S25: =IF($G25=16,$O25,"") | T25: =IF($G25=20,$O25,"") | U25: =IF($G25=25,$O25,"")
P26: =IF($G26=8,$O26,"") | Q26: =IF($G26=10,$O26,"") | R26: =IF($G26=12,$O26,"") | S26: =IF($G26=16,$O26,"") | T26: =IF($G26=20,$O26,"") | U26: =IF($G26=25,$O26,"")
B27: Stirupps d | G27: 10 | H27: 16 | I27: 1 | J27: =C28+D30+E28+2*8*G27/1000 -> 0.73 | L27: 4 | M27: =2*G27*L27/1000 -> 0.08 | N27: =(J27+K27-M27) -> 0.65 | O27: =(H27*I27*N27) -> 10.4 | P27: =IF($G27=8,$O27,"") | Q27: =IF($G27=10,$O27,"") -> 10.4 | R27: =IF($G27=12,$O27,"") | S27: =IF($G27=16,$O27,"") | T27: =IF($G27=20,$O27,"") | U27: =IF($G27=25,$O27,"")
C28: 0.175 | E28: 0.175 | P28: =IF($G28=8,$O28,"") | Q28: =IF($G28=10,$O28,"") | R28: =IF($G28=12,$O28,"") | S28: =IF($G28=16,$O28,"") | T28: =IF($G28=20,$O28,"") | U28: =IF($G28=25,$O28,"")
P29: =IF($G29=8,$O29,"") | Q29: =IF($G29=10,$O29,"") | R29: =IF($G29=12,$O29,"") | S29: =IF($G29=16,$O29,"") | T29: =IF($G29=20,$O29,"") | U29: =IF($G29=25,$O29,"")
D30: =0.3-0.08 -> 0.22 | P30: =IF($G30=8,$O30,"") | Q30: =IF($G30=10,$O30,"") | R30: =IF($G30=12,$O30,"") | S30: =IF($G30=16,$O30,"") | T30: =IF($G30=20,$O30,"") | U30: =IF($G30=25,$O30,"")
P31: =IF($G31=8,$O31,"") | Q31: =IF($G31=10,$O31,"") | R31: =IF($G31=12,$O31,"") | S31: =IF($G31=16,$O31,"") | T31: =IF($G31=20,$O31,"") | U31: =IF($G31=25,$O31,"")
A32: 2 | B32: Column C2 (300x600) | P32: =IF($G32=8,$O32,"") | Q32: =IF($G32=10,$O32,"") | R32: =IF($G32=12,$O32,"") | S32: =IF($G32=16,$O32,"") | T32: =IF($G32=20,$O32,"") | U32: =IF($G32=25,$O32,"")
B33: VERTICAL BARS A | D33: =0.85-0.075-2*0.016 -> 0.743 | G33: 20 | H33: 11 | I33: 4 | J33: =D33 -> 0.743 | K33: =IF(N33<12,"0",0.049*G33) -> 0 | L33: 1 | M33: =2*G33*L33/1000 -> 0.04 | N33: =J33+E35-M33 -> 1.003 | O33: =H33*I33*N33 -> 44.132 | P33: =IF($G33=8,$O33,"") | Q33: =IF($G33=10,$O33,"") | R33: =IF($G33=12,$O33,"") | S33: =IF($G33=16,$O33,"") | T33: =IF($G33=20,$O33,"") -> 44.132 | U33: =IF($G33=25,$O33,"")
B34: VERTICAL BARS B | G34: 20 | H34: 11 | I34: 2 | J34: =D33 -> 0.743 | K34: =IF(N34<12,"0",0.049*G34) -> 0 | L34: 1 | M34: =2*G34*L34/1000 -> 0.04 | N34: =J34+E35-M34 -> 1.003 | O34: =H34*I34*N34 -> 22.066 | P34: =IF($G34=8,$O34,"") | Q34: =IF($G34=10,$O34,"") | R34: =IF($G34=12,$O34,"") | S34: =IF($G34=16,$O34,"") | T34: =IF($G34=20,$O34,"") -> 22.066 | U34: =IF($G34=25,$O34,"")
B35: VERTICAL BARS C | E35: 0.3 | G35: 16 | H35: 11 | I35: 4 | J35: =D33 -> 0.743 | K35: =IF(N35<12,"0",0.049*G35) -> 0 | L35: 1 | M35: =2*G35*L35/1000 -> 0.032 | N35: =J35+E35-M35 -> 1.011 | O35: =H35*I35*N35 -> 44.484 | P35: =IF($G35=8,$O35,"") | Q35: =IF($G35=10,$O35,"") | R35: =IF($G35=12,$O35,"") | S35: =IF($G35=16,$O35,"") -> 44.484 | T35: =IF($G35=20,$O35,"") | U35: =IF($G35=25,$O35,"")
B36: VERTICAL BARS D | G36: 16 | H36: 11 | I36: 4 | J36: =D33 -> 0.743 | K36: =IF(N36<12,"0",0.049*G36) -> 0 | L36: 1 | M36: =2*G36*L36/1000 -> 0.032 | N36: =J36+E35-M36 -> 1.011 | O36: =H36*I36*N36 -> 44.484 | P36: =IF($G36=8,$O36,"") | Q36: =IF($G36=10,$O36,"") | R36: =IF($G36=12,$O36,"") | S36: =IF($G36=16,$O36,"") -> 44.484 | T36: =IF($G36=20,$O36,"") | U36: =IF($G36=25,$O36,"")
P37: =IF($G37=8,$O37,"") | Q37: =IF($G37=10,$O37,"") | R37: =IF($G37=12,$O37,"") | S37: =IF($G37=16,$O37,"") | T37: =IF($G37=20,$O37,"") | U37: =IF($G37=25,$O37,"")
C38: 0.08 | P38: =IF($G38=8,$O38,"") | Q38: =IF($G38=10,$O38,"") | R38: =IF($G38=12,$O38,"") | S38: =IF($G38=16,$O38,"") | T38: =IF($G38=20,$O38,"") | U38: =IF($G38=25,$O38,"")
B39: Stirupps a | E39: =0.6-0.08 -> 0.52 | G39: 10 | H39: 11 | I39: 4 | J39: =2*(D41+E39)+2*8*G39/1000 -> 1.64 | L39: 5 | M39: =2*G39*L39/1000 -> 0.1 | N39: =(J39+K39-M39) -> 1.54 | O39: =(H39*I39*N39) -> 67.76 | P39: =IF($G39=8,$O39,"") | Q39: =IF($G39=10,$O39,"") -> 67.76 | R39: =IF($G39=12,$O39,"") | S39: =IF($G39=16,$O39,"") | T39: =IF($G39=20,$O39,"") | U39: =IF($G39=25,$O39,"")
P40: =IF($G40=8,$O40,"") | Q40: =IF($G40=10,$O40,"") | R40: =IF($G40=12,$O40,"") | S40: =IF($G40=16,$O40,"") | T40: =IF($G40=20,$O40,"") | U40: =IF($G40=25,$O40,"")
D41: =0.3-0.08 -> 0.22 | P41: =IF($G41=8,$O41,"") | Q41: =IF($G41=10,$O41,"") | R41: =IF($G41=12,$O41,"") | S41: =IF($G41=16,$O41,"") | T41: =IF($G41=20,$O41,"") | U41: =IF($G41=25,$O41,"")
P42: =IF($G42=8,$O42,"") | Q42: =IF($G42=10,$O42,"") | R42: =IF($G42=12,$O42,"") | S42: =IF($G42=16,$O42,"") | T42: =IF($G42=20,$O42,"") | U42: =IF($G42=25,$O42,"")
C43: 0.08 | P43: =IF($G43=8,$O43,"") | Q43: =IF($G43=10,$O43,"") | R43: =IF($G43=12,$O43,"") | S43: =IF($G43=16,$O43,"") | T43: =IF($G43=20,$O43,"") | U43: =IF($G43=25,$O43,"")
B44: Stirupps b | E44: =((0.6-0.08-0.016)/5)+0.012+0.02 -> 0.1328 | G44: 10 | H44: 11 | I44: 1 | J44: =2*(D46+E44)+2*8*G44/1000 -> 0.8656 | L44: 5 | M44: =2*G44*L44/1000 -> 0.1 | N44: =(J44+K44-M44) -> 0.7656 | O44: =(H44*I44*N44) -> 8.4216 | P44: =IF($G44=8,$O44,"") | Q44: =IF($G44=10,$O44,"") -> 8.4216 | R44: =IF($G44=12,$O44,"") | S44: =IF($G44=16,$O44,"") | T44: =IF($G44=20,$O44,"") | U44: =IF($G44=25,$O44,"")
P45: =IF($G45=8,$O45,"") | Q45: =IF($G45=10,$O45,"") | R45: =IF($G45=12,$O45,"") | S45: =IF($G45=16,$O45,"") | T45: =IF($G45=20,$O45,"") | U45: =IF($G45=25,$O45,"")
D46: =0.3-0.08 -> 0.22 | P46: =IF($G46=8,$O46,"") | Q46: =IF($G46=10,$O46,"") | R46: =IF($G46=12,$O46,"") | S46: =IF($G46=16,$O46,"") | T46: =IF($G46=20,$O46,"") | U46: =IF($G46=25,$O46,"")
P47: =IF($G47=8,$O47,"") | Q47: =IF($G47=10,$O47,"") | R47: =IF($G47=12,$O47,"") | S47: =IF($G47=16,$O47,"") | T47: =IF($G47=20,$O47,"") | U47: =IF($G47=25,$O47,"")
B48: Stirupps c | G48: 10 | H48: 11 | I48: 1 | J48: =C49+D51+E49+2*8*G48/1000 -> 0.73 | L48: 4 | M48: =2*G48*L48/1000 -> 0.08 | N48: =(J48+K48-M48) -> 0.65 | O48: =(H48*I48*N48) -> 7.15 | P48: =IF($G48=8,$O48,"") | Q48: =IF($G48=10,$O48,"") -> 7.15 | R48: =IF($G48=12,$O48,"") | S48: =IF($G48=16,$O48,"") | T48: =IF($G48=20,$O48,"") | U48: =IF($G48=25,$O48,"")
C49: 0.175 | E49: 0.175 | P49: =IF($G49=8,$O49,"") | Q49: =IF($G49=10,$O49,"") | R49: =IF($G49=12,$O49,"") | S49: =IF($G49=16,$O49,"") | T49: =IF($G49=20,$O49,"") | U49: =IF($G49=25,$O49,"")
P50: =IF($G50=8,$O50,"") | Q50: =IF($G50=10,$O50,"") | R50: =IF($G50=12,$O50,"") | S50: =IF($G50=16,$O50,"") | T50: =IF($G50=20,$O50,"") | U50: =IF($G50=25,$O50,"")
D51: =0.3-0.08 -> 0.22 | P51: =IF($G51=8,$O51,"") | Q51: =IF($G51=10,$O51,"") | R51: =IF($G51=12,$O51,"") | S51: =IF($G51=16,$O51,"") | T51: =IF($G51=20,$O51,"") | U51: =IF($G51=25,$O51,"")
P52: =IF($G52=8,$O52,"") | Q52: =IF($G52=10,$O52,"") | R52: =IF($G52=12,$O52,"") | S52: =IF($G52=16,$O52,"") | T52: =IF($G52=20,$O52,"") | U52: =IF($G52=25,$O52,"")
B53: Stirupps d | G53: 10 | H53: 11 | I53: 1 | J53: =C54+D56+E54+2*8*G53/1000 -> 0.73 | L53: 4 | M53: =2*G53*L53/1000 -> 0.08 | N53: =(J53+K53-M53) -> 0.65 | O53: =(H53*I53*N53) -> 7.15 | P53: =IF($G53=8,$O53,"") | Q53: =IF($G53=10,$O53,"") -> 7.15 | R53: =IF($G53=12,$O53,"") | S53: =IF($G53=16,$O53,"") | T53: =IF($G53=20,$O53,"") | U53: =IF($G53=25,$O53,"")
C54: 0.175 | E54: 0.175 | P54: =IF($G54=8,$O54,"") | Q54: =IF($G54=10,$O54,"") | R54: =IF($G54=12,$O54,"") | S54: =IF($G54=16,$O54,"") | T54: =IF($G54=20,$O54,"") | U54: =IF($G54=25,$O54,"")
P55: =IF($G55=8,$O55,"") | Q55: =IF($G55=10,$O55,"") | R55: =IF($G55=12,$O55,"") | S55: =IF($G55=16,$O55,"") | T55: =IF($G55=20,$O55,"") | U55: =IF($G55=25,$O55,"")
D56: =0.3-0.08 -> 0.22 | P56: =IF($G56=8,$O56,"") | Q56: =IF($G56=10,$O56,"") | R56: =IF($G56=12,$O56,"") | S56: =IF($G56=16,$O56,"") | T56: =IF($G56=20,$O56,"") | U56: =IF($G56=25,$O56,"")
P57: =IF($G57=8,$O57,"") | Q57: =IF($G57=10,$O57,"") | R57: =IF($G57=12,$O57,"") | S57: =IF($G57=16,$O57,"") | T57: =IF($G57=20,$O57,"") | U57: =IF($G57=25,$O57,"")
A58: 3 | B58: Column C3 (300x600) | P58: =IF($G58=8,$O58,"") | Q58: =IF($G58=10,$O58,"") | R58: =IF($G58=12,$O58,"") | S58: =IF($G58=16,$O58,"") | T58: =IF($G58=20,$O58,"") | U58: =IF($G58=25,$O58,"")
B59: VERTICAL BARS A | D59: =0.85-0.075-2*0.016 -> 0.743 | G59: 25 | H59: 2 | I59: 4 | J59: =D59 -> 0.743 | K59: =IF(N59<12,"0",0.049*G59) -> 0 | L59: 1 | M59: =2*G59*L59/1000 -> 0.05 | N59: =J59+E61-M59 -> 0.993 | O59: =H59*I59*N59 -> 7.944 | P59: =IF($G59=8,$O59,"") | Q59: =IF($G59=10,$O59,"") | R59: =IF($G59=12,$O59,"") | S59: =IF($G59=16,$O59,"") | T59: =IF($G59=20,$O59,"") | U59: =IF($G59=25,$O59,"") -> 7.944
B60: VERTICAL BARS B | G60: 25 | H60: 2 | I60: 2 | J60: =D59 -> 0.743 | K60: =IF(N60<12,"0",0.049*G60) -> 0 | L60: 1 | M60: =2*G60*L60/1000 -> 0.05 | N60: =J60+E61-M60 -> 0.993 | O60: =H60*I60*N60 -> 3.972 | P60: =IF($G60=8,$O60,"") | Q60: =IF($G60=10,$O60,"") | R60: =IF($G60=12,$O60,"") | S60: =IF($G60=16,$O60,"") | T60: =IF($G60=20,$O60,"") | U60: =IF($G60=25,$O60,"") -> 3.972
B61: VERTICAL BARS C | E61: 0.3 | G61: 25 | H61: 2 | I61: 4 | J61: =D59 -> 0.743 | K61: =IF(N61<12,"0",0.049*G61) -> 0 | L61: 1 | M61: =2*G61*L61/1000 -> 0.05 | N61: =J61+E61-M61 -> 0.993 | O61: =H61*I61*N61 -> 7.944 | P61: =IF($G61=8,$O61,"") | Q61: =IF($G61=10,$O61,"") | R61: =IF($G61=12,$O61,"") | S61: =IF($G61=16,$O61,"") | T61: =IF($G61=20,$O61,"") | U61: =IF($G61=25,$O61,"") -> 7.944
B62: VERTICAL BARS D | G62: 20 | H62: 2 | I62: 4 | J62: =D59 -> 0.743 | K62: =IF(N62<12,"0",0.049*G62) -> 0 | L62: 1 | M62: =2*G62*L62/1000 -> 0.04 | N62: =J62+E61-M62 -> 1.003 | O62: =H62*I62*N62 -> 8.024 | P62: =IF($G62=8,$O62,"") | Q62: =IF($G62=10,$O62,"") | R62: =IF($G62=12,$O62,"") | S62: =IF($G62=16,$O62,"") | T62: =IF($G62=20,$O62,"") -> 8.024 | U62: =IF($G62=25,$O62,"")
P63: =IF($G63=8,$O63,"") | Q63: =IF($G63=10,$O63,"") | R63: =IF($G63=12,$O63,"") | S63: =IF($G63=16,$O63,"") | T63: =IF($G63=20,$O63,"") | U63: =IF($G63=25,$O63,"")
C64: 0.08 | P64: =IF($G64=8,$O64,"") | Q64: =IF($G64=10,$O64,"") | R64: =IF($G64=12,$O64,"") | S64: =IF($G64=16,$O64,"") | T64: =IF($G64=20,$O64,"") | U64: =IF($G64=25,$O64,"")
B65: Stirupps a | E65: =0.6-0.08 -> 0.52 | G65: 10 | H65: 2 | I65: 4 | J65: =2*(D67+E65)+2*8*G65/1000 -> 1.64 | L65: 5 | M65: =2*G65*L65/1000 -> 0.1 | N65: =(J65+K65-M65) -> 1.54 | O65: =(H65*I65*N65) -> 12.32 | P65: =IF($G65=8,$O65,"") | Q65: =IF($G65=10,$O65,"") -> 12.32 | R65: =IF($G65=12,$O65,"") | S65: =IF($G65=16,$O65,"") | T65: =IF($G65=20,$O65,"") | U65: =IF($G65=25,$O65,"")
P66: =IF($G66=8,$O66,"") | Q66: =IF($G66=10,$O66,"") | R66: =IF($G66=12,$O66,"") | S66: =IF($G66=16,$O66,"") | T66: =IF($G66=20,$O66,"") | U66: =IF($G66=25,$O66,"")
D67: =0.3-0.08 -> 0.22 | P67: =IF($G67=8,$O67,"") | Q67: =IF($G67=10,$O67,"") | R67: =IF($G67=12,$O67,"") | S67: =IF($G67=16,$O67,"") | T67: =IF($G67=20,$O67,"") | U67: =IF($G67=25,$O67,"")
P68: =IF($G68=8,$O68,"") | Q68: =IF($G68=10,$O68,"") | R68: =IF($G68=12,$O68,"") | S68: =IF($G68=16,$O68,"") | T68: =IF($G68=20,$O68,"") | U68: =IF($G68=25,$O68,"")
C69: 0.08 | P69: =IF($G69=8,$O69,"") | Q69: =IF($G69=10,$O69,"") | R69: =IF($G69=12,$O69,"") | S69: =IF($G69=16,$O69,"") | T69: =IF($G69=20,$O69,"") | U69: =IF($G69=25,$O69,"")
B70: Stirupps b | E70: =((0.6-0.08-0.016)/5)+0.012+0.02 -> 0.1328 | G70: 10 | H70: 2 | I70: 1 | J70: =2*(D72+E70)+2*8*G70/1000 -> 0.8656 | L70: 5 | M70: =2*G70*L70/1000 -> 0.1 | N70: =(J70+K70-M70) -> 0.7656 | O70: =(H70*I70*N70) -> 1.5312 | P70: =IF($G70=8,$O70,"") | Q70: =IF($G70=10,$O70,"") -> 1.5312 | R70: =IF($G70=12,$O70,"") | S70: =IF($G70=16,$O70,"") | T70: =IF($G70=20,$O70,"") | U70: =IF($G70=25,$O70,"")
P71: =IF($G71=8,$O71,"") | Q71: =IF($G71=10,$O71,"") | R71: =IF($G71=12,$O71,"") | S71: =IF($G71=16,$O71,"") | T71: =IF($G71=20,$O71,"") | U71: =IF($G71=25,$O71,"")
D72: =0.3-0.08 -> 0.22 | P72: =IF($G72=8,$O72,"") | Q72: =IF($G72=10,$O72,"") | R72: =IF($G72=12,$O72,"") | S72: =IF($G72=16,$O72,"") | T72: =IF($G72=20,$O72,"") | U72: =IF($G72=25,$O72,"")
P73: =IF($G73=8,$O73,"") | Q73: =IF($G73=10,$O73,"") | R73: =IF($G73=12,$O73,"") | S73: =IF($G73=16,$O73,"") | T73: =IF($G73=20,$O73,"") | U73: =IF($G73=25,$O73,"")
B74: Stirupps c | G74: 10 | H74: 2 | I74: 1 | J74: =C75+D77+E75+2*8*G74/1000 -> 0.73 | L74: 4 | M74: =2*G74*L74/1000 -> 0.08 | N74: =(J74+K74-M74) -> 0.65 | O74: =(H74*I74*N74) -> 1.3 | P74: =IF($G74=8,$O74,"") | Q74: =IF($G74=10,$O74,"") -> 1.3 | R74: =IF($G74=12,$O74,"") | S74: =IF($G74=16,$O74,"") | T74: =IF($G74=20,$O74,"") | U74: =IF($G74=25,$O74,"")
C75: 0.175 | E75: 0.175 | P75: =IF($G75=8,$O75,"") | Q75: =IF($G75=10,$O75,"") | R75: =IF($G75=12,$O75,"") | S75: =IF($G75=16,$O75,"") | T75: =IF($G75=20,$O75,"") | U75: =IF($G75=25,$O75,"")
P76: =IF($G76=8,$O76,"") | Q76: =IF($G76=10,$O76,"") | R76: =IF($G76=12,$O76,"") | S76: =IF($G76=16,$O76,"") | T76: =IF($G76=20,$O76,"") | U76: =IF($G76=25,$O76,"")
D77: =0.3-0.08 -> 0.22 | P77: =IF($G77=8,$O77,"") | Q77: =IF($G77=10,$O77,"") | R77: =IF($G77=12,$O77,"") | S77: =IF($G77=16,$O77,"") | T77: =IF($G77=20,$O77,"") | U77: =IF($G77=25,$O77,"")
P78: =IF($G78=8,$O78,"") | Q78: =IF($G78=10,$O78,"") | R78: =IF($G78=12,$O78,"") | S78: =IF($G78=16,$O78,"") | T78: =IF($G78=20,$O78,"") | U78: =IF($G78=25,$O78,"")
B79: Stirupps d | G79: 10 | H79: 2 | I79: 1 | J79: =C80+D82+E80+2*8*G79/1000 -> 0.73 | L79: 4 | M79: =2*G79*L79/1000 -> 0.08 | N79: =(J79+K79-M79) -> 0.65 | O79: =(H79*I79*N79) -> 1.3 | P79: =IF($G79=8,$O79,"") | Q79: =IF($G79=10,$O79,"") -> 1.3 | R79: =IF($G79=12,$O79,"") | S79: =IF($G79=16,$O79,"") | T79: =IF($G79=20,$O79,"") | U79: =IF($G79=25,$O79,"")
C80: 0.175 | E80: 0.175 | P80: =IF($G80=8,$O80,"") | Q80: =IF($G80=10,$O80,"") | R80: =IF($G80=12,$O80,"") | S80: =IF($G80=16,$O80,"") | T80: =IF($G80=20,$O80,"") | U80: =IF($G80=25,$O80,"")
P81: =IF($G81=8,$O81,"") | Q81: =IF($G81=10,$O81,"") | R81: =IF($G81=12,$O81,"") | S81: =IF($G81=16,$O81,"") | T81: =IF($G81=20,$O81,"") | U81: =IF($G81=25,$O81,"")
D82: =0.3-0.08 -> 0.22 | P82: =IF($G82=8,$O82,"") | Q82: =IF($G82=10,$O82,"") | R82: =IF($G82=12,$O82,"") | S82: =IF($G82=16,$O82,"") | T82: =IF($G82=20,$O82,"") | U82: =IF($G82=25,$O82,"")
P83: =IF($G83=8,$O83,"") | Q83: =IF($G83=10,$O83,"") | R83: =IF($G83=12,$O83,"") | S83: =IF($G83=16,$O83,"") | T83: =IF($G83=20,$O83,"") | U83: =IF($G83=25,$O83,"")
A84: 4 | B84: Column C4 (300x750) | P84: =IF($G84=8,$O84,"") | Q84: =IF($G84=10,$O84,"") | R84: =IF($G84=12,$O84,"") | S84: =IF($G84=16,$O84,"") | T84: =IF($G84=20,$O84,"") | U84: =IF($G84=25,$O84,"")
B85: VERTICAL BARS A | D85: =0.85-0.075-2*0.016 -> 0.743 | G85: 20 | H85: 8 | I85: 4 | J85: =D85 -> 0.743 | K85: =IF(N85<12,"0",0.049*G85) -> 0 | L85: 1 | M85: =2*G85*L85/1000 -> 0.04 | N85: =J85+E87-M85 -> 1.003 | O85: =H85*I85*N85 -> 32.096 | P85: =IF($G85=8,$O85,"") | Q85: =IF($G85=10,$O85,"") | R85: =IF($G85=12,$O85,"") | S85: =IF($G85=16,$O85,"") | T85: =IF($G85=20,$O85,"") -> 32.096 | U85: =IF($G85=25,$O85,"")
B86: VERTICAL BARS B | G86: 20 | H86: 8 | I86: 2 | J86: =D85 -> 0.743 | K86: =IF(N86<12,"0",0.049*G86) -> 0 | L86: 1 | M86: =2*G86*L86/1000 -> 0.04 | N86: =J86+E87-M86 -> 1.003 | O86: =H86*I86*N86 -> 16.048 | P86: =IF($G86=8,$O86,"") | Q86: =IF($G86=10,$O86,"") | R86: =IF($G86=12,$O86,"") | S86: =IF($G86=16,$O86,"") | T86: =IF($G86=20,$O86,"") -> 16.048 | U86: =IF($G86=25,$O86,"")
B87: VERTICAL BARS C | E87: 0.3 | G87: 20 | H87: 8 | I87: 4 | J87: =D85 -> 0.743 | K87: =IF(N87<12,"0",0.049*G87) -> 0 | L87: 1 | M87: =2*G87*L87/1000 -> 0.04 | N87: =J87+E87-M87 -> 1.003 | O87: =H87*I87*N87 -> 32.096 | P87: =IF($G87=8,$O87,"") | Q87: =IF($G87=10,$O87,"") | R87: =IF($G87=12,$O87,"") | S87: =IF($G87=16,$O87,"") | T87: =IF($G87=20,$O87,"") -> 32.096 | U87: =IF($G87=25,$O87,"")
B88: VERTICAL BARS D | G88: 20 | H88: 8 | I88: 4 | J88: =D85 -> 0.743 | K88: =IF(N88<12,"0",0.049*G88) -> 0 | L88: 1 | M88: =2*G88*L88/1000 -> 0.04 | N88: =J88+E87-M88 -> 1.003 | O88: =H88*I88*N88 -> 32.096 | P88: =IF($G88=8,$O88,"") | Q88: =IF($G88=10,$O88,"") | R88: =IF($G88=12,$O88,"") | S88: =IF($G88=16,$O88,"") | T88: =IF($G88=20,$O88,"") -> 32.096 | U88: =IF($G88=25,$O88,"")
B89: VERTICAL BARS E | G89: 20 | H89: 8 | I89: 2 | J89: =D85 -> 0.743 | K89: =IF(N89<12,"0",0.049*G89) -> 0 | L89: 1 | M89: =2*G89*L89/1000 -> 0.04 | N89: =J89+E88-M89 -> 0.703 | O89: =H89*I89*N89 -> 11.248 | P89: =IF($G89=8,$O89,"") | Q89: =IF($G89=10,$O89,"") | R89: =IF($G89=12,$O89,"") | S89: =IF($G89=16,$O89,"") | T89: =IF($G89=20,$O89,"") -> 11.248 | U89: =IF($G89=25,$O89,"")
P90: =IF($G90=8,$O90,"") | Q90: =IF($G90=10,$O90,"") | R90: =IF($G90=12,$O90,"") | S90: =IF($G90=16,$O90,"") | T90: =IF($G90=20,$O90,"") | U90: =IF($G90=25,$O90,"")
C91: 0.08 | P91: =IF($G91=8,$O91,"") | Q91: =IF($G91=10,$O91,"") | R91: =IF($G91=12,$O91,"") | S91: =IF($G91=16,$O91,"") | T91: =IF($G91=20,$O91,"") | U91: =IF($G91=25,$O91,"")
B92: Stirupps a | E92: =0.75-0.08 -> 0.67 | G92: 10 | H92: 8 | I92: 4 | J92: =2*(D94+E92)+2*8*G92/1000 -> 1.94 | L92: 5 | M92: =2*G92*L92/1000 -> 0.1 | N92: =(J92+K92-M92) -> 1.84 | O92: =(H92*I92*N92) -> 58.88 | P92: =IF($G92=8,$O92,"") | Q92: =IF($G92=10,$O92,"") -> 58.88 | R92: =IF($G92=12,$O92,"") | S92: =IF($G92=16,$O92,"") | T92: =IF($G92=20,$O92,"") | U92: =IF($G92=25,$O92,"")
P93: =IF($G93=8,$O93,"") | Q93: =IF($G93=10,$O93,"") | R93: =IF($G93=12,$O93,"") | S93: =IF($G93=16,$O93,"") | T93: =IF($G93=20,$O93,"") | U93: =IF($G93=25,$O93,"")
D94: =0.3-0.08 -> 0.22 | P94: =IF($G94=8,$O94,"") | Q94: =IF($G94=10,$O94,"") | R94: =IF($G94=12,$O94,"") | S94: =IF($G94=16,$O94,"") | T94: =IF($G94=20,$O94,"") | U94: =IF($G94=25,$O94,"")
P95: =IF($G95=8,$O95,"") | Q95: =IF($G95=10,$O95,"") | R95: =IF($G95=12,$O95,"") | S95: =IF($G95=16,$O95,"") | T95: =IF($G95=20,$O95,"") | U95: =IF($G95=25,$O95,"")
C96: 0.08 | P96: =IF($G96=8,$O96,"") | Q96: =IF($G96=10,$O96,"") | R96: =IF($G96=12,$O96,"") | S96: =IF($G96=16,$O96,"") | T96: =IF($G96=20,$O96,"") | U96: =IF($G96=25,$O96,"")
B97: Stirupps b | E97: =(2*((0.75-0.08-0.016)/6))+0.012+0.02 -> 0.25 | G97: 10 | H97: 8 | I97: 1 | J97: =2*(D99+E97)+2*8*G97/1000 -> 1.1 | L97: 5 | M97: =2*G97*L97/1000 -> 0.1 | N97: =(J97+K97-M97) -> 1 | O97: =(H97*I97*N97) -> 8 | P97: =IF($G97=8,$O97,"") | Q97: =IF($G97=10,$O97,"") -> 8 | R97: =IF($G97=12,$O97,"") | S97: =IF($G97=16,$O97,"") | T97: =IF($G97=20,$O97,"") | U97: =IF($G97=25,$O97,"")
P98: =IF($G98=8,$O98,"") | Q98: =IF($G98=10,$O98,"") | R98: =IF($G98=12,$O98,"") | S98: =IF($G98=16,$O98,"") | T98: =IF($G98=20,$O98,"") | U98: =IF($G98=25,$O98,"")
D99: =0.3-0.08 -> 0.22 | P99: =IF($G99=8,$O99,"") | Q99: =IF($G99=10,$O99,"") | R99: =IF($G99=12,$O99,"") | S99: =IF($G99=16,$O99,"") | T99: =IF($G99=20,$O99,"") | U99: =IF($G99=25,$O99,"")
P100: =IF($G100=8,$O100,"") | Q100: =IF($G100=10,$O100,"") | R100: =IF($G100=12,$O100,"") | S100: =IF($G100=16,$O100,"") | T100: =IF($G100=20,$O100,"") | U100: =IF($G100=25,$O100,"")
B101: Stirupps c | G101: 10 | H101: 8 | I101: 1 | J101: =C102+D104+E102+2*8*G101/1000 -> 0.73 | L101: 4 | M101: =2*G101*L101/1000 -> 0.08 | N101: =(J101+K101-M101) -> 0.65 | O101: =(H101*I101*N101) -> 5.2 | P101: =IF($G101=8,$O101,"") | Q101: =IF($G101=10,$O101,"") -> 5.2 | R101: =IF($G101=12,$O101,"") | S101: =IF($G101=16,$O101,"") | T101: =IF($G101=20,$O101,"") | U101: =IF($G101=25,$O101,"")
...
